Workbook

Sheet Summary
A1: Township Green Loop – Executive Summary
A3: SDP University Hackathon 2026 · Theme: Planet · We run the platform; township developers pay to use it; residents invest in three green pools.
A5: Vendor (us, the platform)
A6: Vendor ROI (5-yr) | C6: Vendor net profit (5-yr) | E6: Vendor NPV
A7: =ROI!C16 -> 1.171918 | C7: =ROI!H10 -> 1434165.2 | E7: =ROI!E31 -> 778498.7
A9: Customer (township developers, all clients)
A10: Customer ROI (5-yr) | C10: Customer net profit (5-yr) | E10: Customer NPV
A11: =ROI!C17 -> 2.3525179 | C11: =ROI!H13 -> 4258510.4 | E11: =ROI!C39 -> 2478279.8
A13: ="Discount rate "&TEXT(Assumptions!$B$58,"0%")&" · ROI = (gain − cost) ÷ cost · Customer = benefit to developers minus what they pay us (Customer_ROI has SDP alone)." -> Discount rate 15% · ROI = (gain − cost) ÷ cost · Customer = benefit to developers minus what they pay us (Customer_ROI has SDP alone).
A15: Investor (resident) view: see the Investor_View sheet (minimum and maximum investment for each pool).
A17: Key takeaways
A18: • SDP gains from Year 1 even on cash alone: Year 1 costs only a RM20,000 set-up instalment, and the JV passes a 1% fee on residents' solar money to SDP. Half of the community saving is guaranteed in the contract.
A19: • Residents earn from Year 1 on solar and upgrades; EV is variable with a minimum-usage top-up.
A20: • We lose money in Year 1 (covered by a RM120,000 grant) and earn from Year 2, even if only one new developer signs that year. See Conservative_Test.
A22: Core prices
A23: ="Set-up fee RM"&TEXT(Assumptions!$B$38,"#,##0")&" (RM"&TEXT(Assumptions!$B$60,"#,##0")&" in Year 1, RM"&TEXT(Assumptions!$B$61,"#,##0")&" in Year 2) · Platform fee RM"&TEXT(Assumptions!$B$39,"#,##0")&" a year from Year 2 · Success fee "&TEXT(Assumptions!$B$40,"0.00%")&" (waived in Year 1) · "&TEXT(Assumptions!$B$41,"0.0%")&" a year on money invested · "&TEXT(Assumptions!$B$42,"0%")&" on mall redemptions · smaller developers pay pro rata" -> Set-up fee RM50,000 (RM20,000 in Year 1, RM30,000 in Year 2) · Platform fee RM72,000 a year from Year 2 · Success fee 0.75% (waived in Year 1) · 0.5% a year on money invested · 2% on mall redemptions · smaller developers pay pro rata
A25: Normal vs conservative (live, from Conservative_Test)
A26: Check | C26: Normal | E26: Conservative | G26: Normal | H26: Conservative
A27: 1. Customer (SDP) net gain, Year 1 | C27: =Conservative_Test!B26 -> 137144.65 | E27: =Conservative_Test!C26 -> 22856.606 | G27: =Conservative_Test!E26 -> PASS | H27: =Conservative_Test!F26 -> PASS
A28: 2. Customer cash-only net gain, Year 1 (no community saving) | C28: =Conservative_Test!B27 -> 33144.65 | E28: =Conservative_Test!C27 -> 22856.606 | G28: =Conservative_Test!E27 -> PASS | H28: =Conservative_Test!F27 -> PASS
A29: 2b. New developer net gain, its Year 1 | C29: =Conservative_Test!B28 -> 82286.79 | E29: =Conservative_Test!C28 -> 9142.6423 | G29: =Conservative_Test!E28 -> PASS | H29: =Conservative_Test!F28 -> PASS
A30: 3. Residents' profit, Year 1 (all pools, SDP) | C30: =Conservative_Test!B29 -> 82163.299 | E30: =Conservative_Test!C29 -> 50465.897 | G30: =Conservative_Test!E29 -> PASS | H30: =Conservative_Test!F29 -> PASS
A31: 4a. Solar investor return, Year 1 | C31: =Conservative_Test!B30 -> 0.04547563 | E31: =Conservative_Test!C30 -> 0.04547563 | G31: =Conservative_Test!E30 -> PASS | H31: =Conservative_Test!F30 -> PASS
A32: 4b. Upgrade investor return, Year 1 | C32: =Conservative_Test!B31 -> 0.05484129 | E32: =Conservative_Test!C31 -> 0.012947272 | G32: =Conservative_Test!E31 -> PASS | H32: =Conservative_Test!F31 -> PASS
A33: 4c. EV investor loss over the 7-year payback period | C33: =Conservative_Test!B32 -> 0 | E33: =Conservative_Test!C32 -> 0.4 | G33: =Conservative_Test!E32 -> PASS | H33: =Conservative_Test!F32 -> PASS
A34: 5. Our net profit, Year 2 | C34: =Conservative_Test!B33 -> 92228.355 | E34: =Conservative_Test!C33 -> 5033.9555 | G34: =Conservative_Test!E33 -> PASS | H34: =Conservative_Test!F33 -> PASS
A35: 6. Our net profit, 5 years | C35: =Conservative_Test!B34 -> 1434165.2 | E35: =Conservative_Test!C34 -> 131171.91 | G35: =Conservative_Test!E34 -> PASS | H35: =Conservative_Test!F34 -> PASS
A36: 7. NPV of our cash flows | C36: =Conservative_Test!B35 -> 778498.7 | E36: =Conservative_Test!C35 -> 22817.907 | G36: =Conservative_Test!E35 -> PASS | H36: =Conservative_Test!F35 -> PASS
A37: 8. Lowest cash balance in 5 years (with grant) | C37: =Conservative_Test!B36 -> 33918.505 | E37: =Conservative_Test!C36 -> 12403.716 | G37: =Conservative_Test!E36 -> PASS | H37: =Conservative_Test!F36 -> PASS
A38: 9. Our lowest yearly net profit, Years 2–5 | C38: =Conservative_Test!B37 -> 92228.355 | E38: =Conservative_Test!C37 -> 5033.9555 | G38: =Conservative_Test!E37 -> PASS | H38: =Conservative_Test!F37 -> PASS
A39: All checks | G39: =Conservative_Test!E38 -> ALL PASS | H39: =Conservative_Test!F38 -> ALL PASS

Sheet Investor_View
A1: Investor_View – what a resident gets from each pool, at the minimum and maximum investment
A2: All numbers link to Investor_ROI and Assumptions. Change the limits in Assumptions rows 96–101.
A4: Per resident | B4: Solar pool (low risk) | D4: Upgrade pool (medium risk) | F4: EV pool (high risk)
B5: Minimum | C5: Maximum | D5: Minimum | E5: Maximum | F5: Minimum | G5: Maximum
A6: Invest | B6: =Assumptions!$B$96 -> 100 | C6: =Assumptions!$B$97 -> 5000 | D6: =Assumptions!$B$98 -> 100 | E6: =Assumptions!$B$99 -> 3000 | F6: =Assumptions!$B$100 -> 100 | G6: =Assumptions!$B$101 -> 1000
A7: Investment rate (per year) | B7: =Investor_ROI!B6 -> 0.05 | C7: =Investor_ROI!B6 -> 0.05 | D7: =Investor_ROI!B15 -> 0.065 | E7: =Investor_ROI!B15 -> 0.065 | F7: =Investor_ROI!B57 -> 0.066187268 | G7: =Investor_ROI!B57 -> 0.066187268
A8: Rate type | B8: Fixed payout backed by tenant power payments (not roof leasing); minimum 4.5% | C8: Fixed payout backed by tenant power payments (not roof leasing); minimum 4.5% | D8: Fixed; installer guarantees shop savings | E8: Fixed; installer guarantees shop savings | F8: Variable, not guaranteed; partners top up to 60 kWh/day (capped) | G8: Variable, not guaranteed; partners top up to 60 kWh/day (capped)
A9: Money paid back over | B9: =Assumptions!$B$20&" years, monthly" -> 5 years, monthly | C9: =Assumptions!$B$20&" years, monthly" -> 5 years, monthly | D9: =Assumptions!$B$27&" years, monthly" -> 3 years, monthly | E9: =Assumptions!$B$27&" years, monthly" -> 3 years, monthly | F9: =Investor_ROI!B30&" years, from charging income" -> 7 years, from charging income | G9: =Investor_ROI!B30&" years, from charging income" -> 7 years, from charging income
A10: Normal case
A11: Total received | B11: =B6*(Investor_ROI!B46)/Investor_ROI!B45 -> 113.2274 | C11: =C6*(Investor_ROI!B46)/Investor_ROI!B45 -> 5661.3701 | D11: =D6*((Investor_ROI!B50-Investor_ROI!B51))/Investor_ROI!B45 -> 110.33641 | E11: =E6*((Investor_ROI!B50-Investor_ROI!B51))/Investor_ROI!B45 -> 3310.0923 | F11: =F6*(Investor_ROI!B55)/Investor_ROI!B45 -> 128.70961 | G11: =G6*(Investor_ROI!B55)/Investor_ROI!B45 -> 1287.0961
A12: Return over the payback period (RM) | B12: =B6*(Investor_ROI!B46)/Investor_ROI!B45-B6 -> 13.227402 | C12: =C6*(Investor_ROI!B46)/Investor_ROI!B45-C6 -> 661.37009 | D12: =D6*((Investor_ROI!B50-Investor_ROI!B51))/Investor_ROI!B45-D6 -> 10.33641 | E12: =E6*((Investor_ROI!B50-Investor_ROI!B51))/Investor_ROI!B45-E6 -> 310.09231 | F12: =F6*(Investor_ROI!B55)/Investor_ROI!B45-F6 -> 28.709607 | G12: =G6*(Investor_ROI!B55)/Investor_ROI!B45-G6 -> 287.09607
A13: Return over the payback period (%) | B13: =(Investor_ROI!B46)/Investor_ROI!B45-1 -> 0.13227402 | C13: =(Investor_ROI!B46)/Investor_ROI!B45-1 -> 0.13227402 | D13: =((Investor_ROI!B50-Investor_ROI!B51))/Investor_ROI!B45-1 -> 0.1033641 | E13: =((Investor_ROI!B50-Investor_ROI!B51))/Investor_ROI!B45-1 -> 0.1033641 | F13: =(Investor_ROI!B55)/Investor_ROI!B45-1 -> 0.28709607 | G13: =(Investor_ROI!B55)/Investor_ROI!B45-1 -> 0.28709607
A14: Conservative case (Scenarios sheet)
A15: Effective rate (per year) | B15: =Investor_ROI!C8 -> 0.05 | C15: =Investor_ROI!C8 -> 0.05 | D15: =Investor_ROI!C53 -> 0.032304876 | E15: =Investor_ROI!C53 -> 0.032304876 | F15: =Investor_ROI!C57 -> -0.11351477 | G15: =Investor_ROI!C57 -> -0.11351477
A16: Total received | B16: =B6*(Investor_ROI!C46)/Investor_ROI!C45 -> 113.2274 | C16: =C6*(Investor_ROI!C46)/Investor_ROI!C45 -> 5661.3701 | D16: =D6*((Investor_ROI!C50-Investor_ROI!C51))/Investor_ROI!C45 -> 105.05843 | E16: =E6*((Investor_ROI!C50-Investor_ROI!C51))/Investor_ROI!C45 -> 3151.7528 | F16: =F6*(Investor_ROI!C55)/Investor_ROI!C45 -> 60 | G16: =G6*(Investor_ROI!C55)/Investor_ROI!C45 -> 600
A17: Return over the payback period (RM) | B17: =B6*(Investor_ROI!C46)/Investor_ROI!C45-B6 -> 13.227402 | C17: =C6*(Investor_ROI!C46)/Investor_ROI!C45-C6 -> 661.37009 | D17: =D6*((Investor_ROI!C50-Investor_ROI!C51))/Investor_ROI!C45-D6 -> 5.0584278 | E17: =E6*((Investor_ROI!C50-Investor_ROI!C51))/Investor_ROI!C45-E6 -> 151.75283 | F17: =F6*(Investor_ROI!C55)/Investor_ROI!C45-F6 -> -40 | G17: =G6*(Investor_ROI!C55)/Investor_ROI!C45-G6 -> -400
A18: Return over the payback period (%) | B18: =(Investor_ROI!C46)/Investor_ROI!C45-1 -> 0.13227402 | C18: =(Investor_ROI!C46)/Investor_ROI!C45-1 -> 0.13227402 | D18: =((Investor_ROI!C50-Investor_ROI!C51))/Investor_ROI!C45-1 -> 0.050584278 | E18: =((Investor_ROI!C50-Investor_ROI!C51))/Investor_ROI!C45-1 -> 0.050584278 | F18: =(Investor_ROI!C55)/Investor_ROI!C45-1 -> -0.4 | G18: =(Investor_ROI!C55)/Investor_ROI!C45-1 -> -0.4
A20: ="Most one resident can put in across all three pools: RM"&TEXT(Assumptions!$B$97+Assumptions!$B$99+Assumptions!$B$101,"#,##0")&". Smallest start: RM"&TEXT(MIN(Assumptions!$B$96,Assumptions!$B$98,Assumptions!$B$100),"#,##0")&" in any one pool." -> Most one resident can put in across all three pools: RM9,000. Smallest start: RM100 in any one pool.
A21: • Payback period: solar 5 years, upgrades 3 years, EV 7 years. Returns are over each pool's own payback period. The return % is the same at the minimum and the maximum; only the RM amount changes.
A22: • Solar: residents are funders, not roof landlords. The developer/JV owns and runs the panels; tenants, malls and factories pay for the power, and residents' payouts are paid first. Different from SDP's CREAM roof-leasing project in Elmina.
A23: • Upgrades: paid back monthly over 3 years. Totals are after expected shop defaults and the bad-debt reserve.
A24: • EV: the thinnest pool. A licensed charge point operator (CPO) co-invests half and runs the chargers. Payouts come only from charging profit; the developer and platform take their 10% shares only after residents get their money back. If usage falls below 60 kWh/day, partners top up (capped at RM3,000 per charger a year). Price wars, cost rises and a refused government grant are NOT covered: in the conservative case residents get back only about 60% of their money.
A25: • Risk disclosure: none of the pools is a deposit and none is covered by PIDM. Money is held by a licensed platform, never by us. The maximum per pool stays within the RM5,000-per-company limit for retail investors [R24].

Sheet Assumptions
A1: Township Green Loop – Business Plan Assumptions
A2: Blue = input you can change · Yellow = key assumption to check · Black = formula · Green sections (rows 59–101) were added in v2; rows 102+ were added in v3 (EV rework, solar positioning). All money in RM.
A4: Input | B4: Value | C4: Unit | D4: Source / note
A5: General
A6: Model Year 1 (calendar year) | B6: 2027 | C6: year | D6: Platform goes live after the hackathon pilot.
A7: Average investment per resident | B7: 500 | C7: RM | D7: Assumption. Each pool has its own minimum and maximum (Assumptions rows 96–101).
A8: Share of resident payouts spent at the developer's malls | B8: 0.3 | C8: % | D8: Assumption. Not survey-validated.
A9: Mall redemption bonus (paid by participating shops as a promotion) | B9: 0.1 | C9: % | D9: Design choice. Shops fund it, so it costs the developer nothing.
A10: Turnover rent the mall earns on extra shop sales | B10: 0.01 | C10: % of sales | D10: Example rate of 1% of gross sales on top of base rent: D&H law firm [R13].
A11: Average electricity tariff | B11: 0.454 | C11: RM/kWh | D11: Average base tariff 45.4 sen/kWh from July 2025 (HLIB via Business Today) [R8].
A12: Grid emission factor, Peninsular Malaysia 2024 | B12: 0.74 | C12: tCO2e/MWh | D12: Energy Commission, GEF 2022–2024 (provisional) [R9].
A13: SDP yearly spend on community programmes and spaces | B13: 20800000 | C13: RM/yr | D13: SDP Integrated Report 2024 key highlights: 70,000+ beneficiaries, RM20.8 million total economic spend [R12].
A14: Share of solar funding saving kept by the developer | B14: 0.5 | C14: % | D14: Assumption. Solar assets sit in the SDP × GSPARX JV [R1]; the JV split was not found in public sources, so 50% is used.
A15: Pool 1 – Rooftop solar (residents fund it; the developer/JV owns and runs it – not roof leasing)
A16: Installed solar cost | B16: 3200 | C16: RM/kWp | D16: v3: 2,800 → 3,200 (commercial system incl. SST, structure and grid works). Prudent: one installer lists commercial 50–100 kWp from RM2,400/kWp before SST [R38]; the RM3,500–4,000 range in the brief was not confirmed.
A17: Solar output per kWp | B17: 1250 | C17: kWh/kWp/yr | D17: 100 kWp commercial roof gives about 120,000–140,000 kWh a year (Trexon) [R5].
A18: Share of each solar asset funded by residents | B18: =Assumptions!$B$111 -> 0.3 | C18: % | D18: v3: links to row 111 (normal 30%); conservative uses row 112 (20%) through Scenarios. Team solar model: at 30%, tenant payments cover payouts 1.83 times [R20].
A19: Payout rate to residents (solar) | B19: 0.05 | C19: % a year | D19: Team solar model. 12-month FD is about 1.9% (ABM, Aug 2026) [R11].
A20: Solar payout tenure | B20: 5 | C20: years | D20: Team solar model.
A21: Return the JV would otherwise need on its own money | B21: 0.085 | C21: % a year | D21: Team solar model project IRR 8.5%; The Edge: mid to high single-digit IRR for solar PPAs [R6].
A22: Pool 2 – Shop energy upgrades
A23: Upgrade cost per shop | B23: 20000 | C23: RM | D23: Assumption (efficient air-con, fridges, LED). Get supplier quotes.
A24: Bill saving per shop | B24: 1000 | C24: RM/month | D24: Assumption: about 25% of a RM4,000 bill. Sunway Pyramid's chiller retrofit beat a 30% energy-cut target [R14].
A25: Share of savings used to repay residents | B25: 0.8 | C25: % | D25: Malaysian ESCO shared-savings cases use 80:20 and 75:25 (MAESCO) [R7].
A26: Payout rate to residents (upgrades) | B26: 0.065 | C26: % a year | D26: Design choice: higher than solar to reflect shop default risk.
A27: Upgrade payout tenure | B27: 3 | C27: years | D27: Design choice.
A28: Developer's share of the monthly safety margin | B28: 0.5 | C28: % | D28: Design choice. Other half kept as a bad-debt reserve.
A29: Pool 3 – EV charging (v3: DC 60 kW + AC 22 kW mix, run by a licensed charge point operator (CPO))
A30: Installed cost per charger, blended DC/AC mix (before grant) | B30: =Assumptions!$B$115*Assumptions!$B$116+(1-Assumptions!$B$115)*Assumptions!$B$117 -> 62500 | C30: RM | D30: v3: formula = DC share × DC cost + AC share × AC cost (rows 115–117). Was 70,000 for one DC charger [R4].
A31: Share of each charger's net cost funded by residents | B31: 0.5 | C31: % | D31: Design choice. v3: the CPO partner co-invests the other 50% and runs the chargers (operations, maintenance, SLA, customer service).
A32: DC 60 kW standard charging price | B32: 1.4 | C32: RM/kWh | D32: v3: 1.29 → 1.40. ChargEV AEON Mall Cheras Selatan: 60 kW DC RM1.40, 22 kW AC RM1.00, 180 kW DC RM1.60 (Jul 2026) [R25]. The brief cited AEON Rawang; the confirmed source is the Cheras Selatan site.
A33: Payment and app costs | B33: 0.03 | C33: % of charging revenue | D33: v3: 10% → 3%. Payment gateway about 1.5–3% plus 1–2% app share (brief; typical gateway range, not separately sourced).
A34: DC 60 kW maintenance and CPO service fee | B34: 10000 | C34: RM/yr | D34: v3: 5,000 → 10,000. US benchmark about US$1,800 a year for a DC fast charger (≈RM7,900) [R32]; 10,000 adds the CPO's SLA and customer service. The brief's '30% of capital a year' is not supported (10,000 is 10% of 100,000).
A35: Energy sold per charger per day | B35: =Assumptions!$B$105*Assumptions!$B$106 -> 60 | C35: kWh/day | D35: v3: 100 → formula = sessions × kWh per session (rows 105–106) = 60. Biggest EV risk: public chargers are mostly AC and utilisation is low [R31].
A36: Developer's share of residents' charging profit (site host) | B36: 0.1 | C36: % | D36: v3: value kept at 10%, but the split is now residents 70% (row 132), developer 10%, platform 10% (row 133), O&M reserve 10% (row 134). Developer and platform shares wait until residents recover their money (row 135).
A37: Vendor pricing (what we charge each developer)
A38: Set-up fee (total, billed over client Years 1 and 2) | B38: =Assumptions!$B$60+Assumptions!$B$61 -> 50000 | C38: RM | D38: v2: formula = Year 1 instalment + Year 2 instalment (rows 60–61).
A39: Annual platform fee (from client's second year) | B39: 72000 | C39: RM/yr | D39: Our price for an SDP-size client (RM6,000 a month, billed monthly). Waived in the first year as a pilot. v2: smaller clients pay pro rata to size.
A40: Success fee on money raised through the platform | B40: 0.0075 | C40: % of raised | D40: Our price. Crowdfunding platforms also charge a success fee on amounts raised (pitchIN) [R15]. v2: waived in client Year 1 (row 62).
A41: Yearly fee on residents' money still invested | B41: 0.005 | C41: % a year | D41: Our price, from client's second year.
A42: Fee on mall redemptions (paid by shops) | B42: 0.02 | C42: % of redemptions | D42: Our price.
A43: Vendor costs
A44: Founders on payroll | B44: 2 | C44: people | D44: Lean team: product/tech lead + business lead.
A45: Founder salary | B45: 4000 | C45: RM/month | D45: Junior developer range RM3,000–5,500 a month (SecondTalent, Aug 2026) [R16].
A46: Employer EPF + SOCSO + EIS | B46: 0.1495 | C46: % of salary | D46: 13% + 1.75% + 0.2% for wages up to RM5,000 (AJobThing, 2026) [R17].
A47: Contract developer, Year 1 | B47: 6 | C47: months | D47: Help build the first version.
A48: Contract / extra developer pay | B48: 7000 | C48: RM/month | D48: Mid-level range RM5,500–9,000 a month [R16].
A49: Supabase Pro per client | B49: 25 | C49: USD/month | D49: US$25 per project a month (Automation Atlas, 2026) [R18].
A50: Vercel Pro per seat | B50: 20 | C50: USD/month | D50: US$20 per seat a month (MakerKit, 2026) [R19].
A51: Vercel seats | B51: 2 | C51: seats
A52: USD to RM | B52: 4.4 | C52: RM per USD | D52: Approximate rate; check before use.
A53: Security testing, Year 1 | B53: 15000 | C53: RM | D53: Assumption (penetration test before handling investor data).
A54: Security testing, later years | B54: 8000 | C54: RM/yr | D54: Assumption.
A55: Legal, PDPA and partner agreements, Year 1 | B55: 15000 | C55: RM | D55: Assumption (licensed platform and developer contracts).
A56: Legal and compliance, later years | B56: 5000 | C56: RM/yr | D56: Assumption.
A57: Sales and onboarding per new client | B57: 8000 | C57: RM | D57: Assumption. v2: used for Year 1 only; later years use row 82.
A58: Discount rate for NPV | B58: 0.15 | C58: % a year | D58: Common range for early-stage tech ventures is 15–20%.
A59: v2 – Launch terms (customer must gain in Year 1)
A60: Set-up fee, Year 1 instalment (50% at signing) | B60: 20000 | C60: RM | D60: v2. Split set-up fee so the client pays less in Year 1. Price for an SDP-size client; smaller clients pay pro rata.
A61: Set-up fee, Year 2 instalment (at go-live of full rollout) | B61: 30000 | C61: RM | D61: v2.
A62: Success-fee discount in client Year 1 | B62: 1 | C62: % off | D62: v2. 100% = waived in Year 1, in exchange for a signed Year 2 platform-fee commitment.
A63: v2 – Community-saving guarantee (makes benefit E contractual)
A64: Community saving actually achieved (vs expected) | B64: 1 | C64: % | D64: v2. Normal case 100%. Conservative test sets this to 0%.
A65: Saving we guarantee in the contract (share of expected) | B65: 0.5 | C65: % | D65: v2. We only promise half of the expected saving.
A66: Share of any shortfall we credit back to the developer | B66: 0.5 | C66: % | D66: v2. Credit against our fees.
A67: Credit cap in client Year 1 (share of that year's fees) | B67: 1 | C67: % | D67: v2. In Year 1 the credit can cancel all fees.
A68: Credit cap from client Year 2 (share of that year's fees) | B68: 0.25 | C68: % | D68: v2. Limits our downside.
A69: v2 – Investor protection
A70: JV arrangement fee passed to the developer | B70: 0.01 | C70: % a year of residents' solar money | D70: v2. JV shares part of its funding saving (8.5% − 5% = 3.5%) with the developer that brings the residents. To negotiate.
A71: Solar minimum payout rate (floor) | B71: 0.045 | C71: % a year | D71: v2. Backed by the JV saving above; contract rate stays 5%.
A72: Guaranteed minimum saving per shop (installer contract) | B72: 800 | C72: RM/month | D72: v2. ESCO contracts can include a minimum-savings clause where the ESCO covers the shortfall (Trexon ESCO guide) [R21].
A73: Shop default rate | B73: 0.02 | C73: % a year | D73: v2. Assumption. Conservative test uses 10%.
A74: Loss when a shop defaults (after deposit and equipment recovery) | B74: 0.5 | C74: % of upgrade cost | D74: v2. Assumption: SDP holds tenant deposits.
A75: EV minimum usage topped up to | B75: 60 | C75: kWh/day/charger | D75: v3: 80 → 60 (= normal usage, so no top-up in the normal case). If a charger sells less, partners pay residents for the missing kWh at the normal contract margin, up to the yearly cap (row 140).
A76: Share of the top-up paid by the developer | B76: 0.33 | C76: % | D76: v3: 100% → 33%. Platform pays 33% (row 138), CPO pays 34% (row 139, it also covers its own downtime).
A77: v2 – New income lines (paid by shops or from certificate sales, not by the developer)
A78: Renewable energy certificate (REC) price | B78: 3.45 | C78: USD/MWh | D78: v2. Malaysian solar I-REC, US$3.45/MWh, 24 Apr 2026 (S&P Global Platts) [R22].
A79: Our REC registration and sales service fee | B79: 0.1 | C79: % of REC sales | D79: v2. Our price.
A80: Shops buying featured offers in the rewards catalogue | B80: 10 | C80: shops per SDP-size client | D80: v2. Assumption.
A81: Featured-offer fee | B81: 200 | C81: RM/month per shop | D81: v2. Our price.
A82: Energy dashboard subscription for upgraded shops | B82: 50 | C82: RM/month per shop | D82: v2. Our price. Shops track their savings.
A83: v2 – Our cost and cash plan
A84: Founders' pay taken in cash in Year 1 | B84: 0.5 | C84: % of salary | D84: v2. Rest taken as equity (non-cash).
A85: Contract developer paid in cash | B85: 0.7 | C85: % of pay | D85: v2. Rest paid in equity.
A86: Onboarding per new client after Year 1 (standardised) | B86: 5000 | C86: RM | D86: v2. Standard playbook lowers the cost.
A87: Year 1 grant / pre-seed funding | B87: 120000 | C87: RM | D87: v2. Covers the Year 1 loss. Cradle CIP Spark offers up to RM150,000 (conditional grant) [R23].
A88: v2 – Solar cover check (from team solar model)
A89: Tenant's avoided grid rate | B89: 0.4 | C89: RM/kWh | D89: Team solar model [R20].
A90: PPA discount vs grid | B90: 0.15 | C90: % | D90: About 15% cheaper than tariffs (The Edge) [R6].
A91: Solar O&M | B91: 0.01 | C91: % of capex a year | D91: Team solar model [R20].
A92: Solar insurance | B92: 0.003 | C92: % of capex a year | D92: Team solar model [R20].
A93: Asset management fee on solar revenue | B93: 0.05 | C93: % of revenue | D93: Team solar model [R20].
A94: v2 – Investment example and limits per resident
A95: Example investment per resident (Investor_ROI 5-year view) | B95: 1000 | C95: RM | D95: Illustration only.
A96: Solar pool: minimum investment | B96: 100 | C96: RM | D96: Low entry so more residents can join (inclusivity).
A97: Solar pool: maximum investment | B97: 5000 | C97: RM | D97: Retail investors may put up to RM5,000 into one issuer under SC equity crowdfunding rules [R24]; each pool is a separate issuer.
A98: Upgrade pool: minimum investment | B98: 100 | C98: RM | D98: Same entry level for all pools.
A99: Upgrade pool: maximum investment | B99: 3000 | C99: RM | D99: Assumption: lower than solar because shop default risk is higher.
A100: EV pool: minimum investment | B100: 100 | C100: RM | D100: Same entry level for all pools.
A101: EV pool: maximum investment | B101: 1000 | C101: RM | D101: Assumption: smallest cap because capital is not guaranteed and the expected return is the lowest for its risk (see EV_Pilot).
...

Sheet Yearly_Inputs
A1: Yearly inputs
A2: Blue = input · Yellow = key assumption. Pool numbers are per client, by the client's year on the platform.
A4: Input | B4: Y1 | C4: Y2 | D4: Y3 | E4: Y4 | F4: Y5 | G4: Unit | H4: Source / note
A5: New solar capacity with a resident share, per client | B5: 3 | C5: 3 | D5: 4 | E5: 5 | F5: 5 | G5: MW | H5: By the client's year on the platform. Reaches 20 MW in 5 years, in line with the SDP × GSPARX JV target of 20 MW in 5 years [R1].
A6: New shops upgraded, per client | B6: 15 | C6: 25 | D6: 10 | E6: 10 | F6: 10 | G6: shops | H6: By the client's year. SDP's 3 malls have about 380 outlets [R2][R3]; only high-energy, low-risk shops qualify (v2: highest-saving shops first).
A7: New EV chargers, per client | B7: 1 | C7: 2 | D7: 2 | E7: 2 | F7: 2 | G7: chargers | H7: By the client's year. v3: 2,4,4,4,4 → 1,2,2,2,2. Start with a 1–2 charger pilot and expand only after 12 months of usage data. High-traffic sites only.
A8: Community-programme saving from digital sign-ups, QR check-ins and auto reports | B8: 0.005 | C8: 0.01 | D8: 0.01 | E8: 0.01 | F8: 0.01 | G8: % of programme spend | H8: Assumption, half in the first year. v2: half of this is guaranteed in the contract (Assumptions rows 64–68).
A9: New developer clients signed (calendar year) | B9: 1 | C9: 2 | D9: 2 | E9: 2 | F9: 2 | G9: clients | H9: Y1 = SDP. Later: other township developers. v2: sign letters of intent in Year 1 for Year 2 clients.
A10: Size of clients joining this year vs SDP | B10: 1 | C10: 0.6 | D10: 0.6 | E10: 0.6 | F10: 0.6 | G10: x SDP | H10: Assumption: later clients are 60% of SDP's size.
A11: Extra developers on payroll (calendar year) | B11: 0 | C11: 0 | D11: 1 | E11: 1 | F11: 2 | G11: people | H11: Hire only once revenue allows.
A12: Part-time support and operations (calendar year) | B12: 0 | C12: 18000 | D12: 36000 | E12: 36000 | F12: 48000 | G12: RM/yr | H12: Assumption.

Sheet Scenarios
A1: Scenarios – conservative stress inputs
A2: Normal values link to Assumptions / Yearly_Inputs. Change the blue Conservative values to re-run the C_ sheets and Conservative_Test.
A4: Stressed input | B4: Normal | C4: Conservative | D4: Change | E4: Why
A5: Community saving actually achieved | B5: =Assumptions!$B$64 -> 1 | C5: 0 | D5: =IF(B5=0,"",C5/B5-1) -> -1 | E5: Benefit E fails completely.
A6: EV energy sold per charger per day (kWh) = sessions × kWh per session | B6: =Assumptions!$B$35 -> 60 | C6: =C15*C16 -> 30 | D6: =IF(B6=0,"",C6/B6-1) -> -0.5 | E6: v3: 30 kWh/day (was 50). Formula from rows 15–16.
A7: Bill saving per shop (RM/month) | B7: =Assumptions!$B$24 -> 1000 | C7: 500 | D7: =IF(B7=0,"",C7/B7-1) -> -0.5 | E7: Upgrades save half as much.
A8: New developer clients signed in Year 2 | B8: =Yearly_Inputs!$C$9 -> 2 | C8: 1 | D8: =IF(B8=0,"",C8/B8-1) -> -0.5 | E8: Only one new client in Year 2.
A9: Developer's share of solar funding saving | B9: =Assumptions!$B$14 -> 0.5 | C9: 0.3 | D9: =IF(B9=0,"",C9/B9-1) -> -0.4 | E9: Weaker JV terms.
A10: Discount rate for NPV | B10: =Assumptions!$B$58 -> 0.15 | C10: 0.2 | D10: =IF(B10=0,"",C10/B10-1) -> 0.33333333 | E10: Higher required return.
A11: Competitor price drop (all charging prices) | B11: =0 -> 0 | C11: 0.2 | D11: =IF(B11=0,"",C11/B11-1) | E11: v3: 10% → 20%. Price war.
A12: Size of new clients vs SDP (Years 2–5) | B12: =Yearly_Inputs!$C$10 -> 0.6 | C12: 0.4 | D12: =IF(B12=0,"",C12/B12-1) -> -0.33333333 | E12: Smaller developers sign up.
A13: Shop default rate (a year) | B13: =Assumptions!$B$73 -> 0.02 | C13: 0.1 | D13: =IF(B13=0,"",C13/B13-1) -> 4 | E13: Five times more shop defaults.
A14: Extra developers hired in Year 3 (our response, not a stress) | B14: =Yearly_Inputs!$D$11 -> 1 | C14: 0 | D14: =IF(B14=0,"",C14/B14-1) -> -1 | E14: Delay the hire when fewer clients sign.
A15: v3 EV: charging sessions per charger per day | B15: =Assumptions!$B$105 -> 2 | C15: 1.5 | D15: =IF(B15=0,"",C15/B15-1) -> -0.25 | E15: Brief said 1 session × 20 kWh, but also 30 kWh/day; 1.5 × 20 keeps both the 20 kWh and the 30 kWh/day.
A16: v3 EV: average kWh per session | B16: =Assumptions!$B$106 -> 30 | C16: 20 | D16: =IF(B16=0,"",C16/B16-1) -> -0.33333333 | E16: Smaller top-ups.
A17: v3 EV: electricity cost increase | B17: =0 -> 0 | C17: 0.2 | D17: =IF(B17=0,"",C17/B17-1) | E17: Tariff or AFA surcharge up 20%.
A18: v3 EV: maintenance cost increase | B18: =0 -> 0 | C18: 0.5 | D18: =IF(B18=0,"",C18/B18-1) | E18: Repairs and parts 50% dearer.
A19: v3 EV: charger downtime | B19: =0 -> 0 | C19: 0.1 | D19: =IF(B19=0,"",C19/B19-1) | E19: Chargers out of service 10% of the time.
A20: v3 EV: MARii grant approved (1 = yes, 0 = no) | B20: =1 -> 1 | C20: 0 | D20: =IF(B20=0,"",C20/B20-1) -> -1 | E20: Grant not approved; residents and CPO fund the full DC cost.
A21: v3 EV: billed idle minutes per charger per day | B21: =Assumptions!$B$124 -> 10 | C21: 5 | D21: =IF(B21=0,"",C21/B21-1) -> -0.5 | E21: Half the idle-fee income.
A22: v3 EV: paying members per charger | B22: =Assumptions!$B$126 -> 10 | C22: 5 | D22: =IF(B22=0,"",C22/B22-1) -> -0.5 | E22: Half the membership income.
A23: v3 Solar: residents' share of each solar asset | B23: =Assumptions!$B$111 -> 0.3 | C23: =Assumptions!$B$112 -> 0.2 | D23: =IF(B23=0,"",C23/B23-1) -> -0.33333333 | E23: Assumptions row 112.
A24: Charging price after drop (RM/kWh) | B24: =Assumptions!$B$32 -> 1.4 | C24: =Assumptions!$B$32*(1-Scenarios!$C$11) -> 1.12

Sheet Pools
A1: Pools – what happens inside one client (SDP size), by the client's year on the platform
A2: Money raised from residents, money still invested, payouts and impact for the three pools. Other clients are scaled from this.
A4: Item | B4: Unit | C4: Year 1 | D4: Year 2 | E4: Year 3 | F4: Year 4 | G4: Year 5
A5: Timing factors (money is raised mid-year on average)
A6: Year since money was raised | C6: 1 | D6: 2 | E6: 3 | F6: 4 | G6: 5
A7: Solar: share of money still owed at year end | C7: =((1+Assumptions!$B$19)^Assumptions!$B$20-(1+Assumptions!$B$19)^C6)/((1+Assumptions!$B$19)^Assumptions!$B$20-1) -> 0.8190252 | D7: =((1+Assumptions!$B$19)^Assumptions!$B$20-(1+Assumptions!$B$19)^D6)/((1+Assumptions!$B$19)^Assumptions!$B$20-1) -> 0.62900166 | E7: =((1+Assumptions!$B$19)^Assumptions!$B$20-(1+Assumptions!$B$19)^E6)/((1+Assumptions!$B$19)^Assumptions!$B$20-1) -> 0.42947695 | F7: =((1+Assumptions!$B$19)^Assumptions!$B$20-(1+Assumptions!$B$19)^F6)/((1+Assumptions!$B$19)^Assumptions!$B$20-1) -> 0.219976 | G7: =((1+Assumptions!$B$19)^Assumptions!$B$20-(1+Assumptions!$B$19)^G6)/((1+Assumptions!$B$19)^Assumptions!$B$20-1) -> 0
A8: Solar: average share still invested | C8: =0.5 -> 0.5 | D8: =(1+C7)/2 -> 0.9095126 | E8: =(C7+D7)/2 -> 0.72401343 | F8: =(D7+E7)/2 -> 0.52923931 | G8: =(E7+F7)/2 -> 0.32472647
A9: Payout timing (half year in first year) | C9: =0.5 -> 0.5 | D9: =1 -> 1 | E9: =1 -> 1 | F9: =1 -> 1 | G9: =1 -> 1
A10: Upgrades: share still owed at year end | C10: =MAX(0,((1+Assumptions!$B$26)^Assumptions!$B$27-(1+Assumptions!$B$26)^C6)/((1+Assumptions!$B$26)^Assumptions!$B$27-1)) -> 0.6874243 | D10: =MAX(0,((1+Assumptions!$B$26)^Assumptions!$B$27-(1+Assumptions!$B$26)^D6)/((1+Assumptions!$B$26)^Assumptions!$B$27-1)) -> 0.35453118 | E10: =MAX(0,((1+Assumptions!$B$26)^Assumptions!$B$27-(1+Assumptions!$B$26)^E6)/((1+Assumptions!$B$26)^Assumptions!$B$27-1)) -> 0 | F10: =MAX(0,((1+Assumptions!$B$26)^Assumptions!$B$27-(1+Assumptions!$B$26)^F6)/((1+Assumptions!$B$26)^Assumptions!$B$27-1)) -> 0 | G10: =MAX(0,((1+Assumptions!$B$26)^Assumptions!$B$27-(1+Assumptions!$B$26)^G6)/((1+Assumptions!$B$26)^Assumptions!$B$27-1)) -> 0
A11: Upgrades: average share still invested | C11: =0.5 -> 0.5 | D11: =(1+C10)/2 -> 0.84371215 | E11: =(C10+D10)/2 -> 0.52097774 | F11: =(D10+E10)/2 -> 0.17726559 | G11: =(E10+F10)/2 -> 0
A12: Upgrades: share of year a shop is repaying | C12: =0.5 -> 0.5 | D12: =1 -> 1 | E12: =1 -> 1 | F12: =0.5 -> 0.5 | G12: =0 -> 0
A13: EV: average share still invested (paid back evenly over the EV payback period) | C13: =0.5*(1+(1-0.5/Assumptions!$B$137))/2 -> 0.48214286 | D13: =MAX(0,1-1/Assumptions!$B$137) -> 0.85714286 | E13: =MAX(0,1-2/Assumptions!$B$137) -> 0.71428571 | F13: =MAX(0,1-3/Assumptions!$B$137) -> 0.57142857 | G13: =MAX(0,1-4/Assumptions!$B$137) -> 0.42857143
A14: EV: share of money paid back in the year | C14: =0.5/Assumptions!$B$137 -> 0.071428571 | D14: =IF(2-0.5<=Assumptions!$B$137,1/Assumptions!$B$137,0) -> 0.14285714 | E14: =IF(3-0.5<=Assumptions!$B$137,1/Assumptions!$B$137,0) -> 0.14285714 | F14: =IF(4-0.5<=Assumptions!$B$137,1/Assumptions!$B$137,0) -> 0.14285714 | G14: =IF(5-0.5<=Assumptions!$B$137,1/Assumptions!$B$137,0) -> 0.14285714
A15: Pool 1 – Rooftop solar
A16: New solar capacity with resident share | B16: MW | C16: =Yearly_Inputs!$B$5 -> 3 | D16: =Yearly_Inputs!$C$5 -> 3 | E16: =Yearly_Inputs!$D$5 -> 4 | F16: =Yearly_Inputs!$E$5 -> 5 | G16: =Yearly_Inputs!$F$5 -> 5
A17: Money raised from residents | B17: RM | C17: =C16*1000*Assumptions!$B$16*Assumptions!$B$18 -> 2880000 | D17: =D16*1000*Assumptions!$B$16*Assumptions!$B$18 -> 2880000 | E17: =E16*1000*Assumptions!$B$16*Assumptions!$B$18 -> 3840000 | F17: =F16*1000*Assumptions!$B$16*Assumptions!$B$18 -> 4800000 | G17: =G16*1000*Assumptions!$B$16*Assumptions!$B$18 -> 4800000
A18: Residents' money still invested (average) | B18: RM | C18: =C17*C8 -> 1440000 | D18: =C17*D8+D17*C8 -> 4059396.3 | E18: =C17*E8+D17*D8+E17*C8 -> 6624555 | F18: =C17*F8+D17*E8+E17*D8+F17*C8 -> 9501896.3 | G18: =C17*G8+D17*F8+E17*E8+F17*D8+G17*C8 -> 12005294
A19: Yearly payment per RM1 raised | B19: factor | C19: =PMT(Assumptions!$B$19,Assumptions!$B$20,-1) -> 0.2309748 | D19: =PMT(Assumptions!$B$19,Assumptions!$B$20,-1) -> 0.2309748 | E19: =PMT(Assumptions!$B$19,Assumptions!$B$20,-1) -> 0.2309748 | F19: =PMT(Assumptions!$B$19,Assumptions!$B$20,-1) -> 0.2309748 | G19: =PMT(Assumptions!$B$19,Assumptions!$B$20,-1) -> 0.2309748
A20: Payouts to residents | B20: RM | C20: =(C17*C9)*C19 -> 332603.71 | D20: =(C17*D9+D17*C9)*D19 -> 997811.13 | E20: =(C17*E9+D17*D9+E17*C9)*E19 -> 1773886.4 | F20: =(C17*F9+D17*E9+E17*D9+F17*C9)*F19 -> 2771697.6 | G20: =(C17*G9+D17*F9+E17*E9+F17*D9+G17*C9)*G19 -> 3880376.6
A21: Solar capacity running (average) | B21: MW | C21: =C16*C9 -> 1.5 | D21: =C16*D9+D16*C9 -> 4.5 | E21: =C16*E9+D16*D9+E16*C9 -> 8 | F21: =C16*F9+D16*E9+E16*D9+F16*C9 -> 12.5 | G21: =C16*G9+D16*F9+E16*E9+F16*D9+G16*C9 -> 17.5
A22: Solar power produced | B22: MWh | C22: =C21*Assumptions!$B$17 -> 1875 | D22: =D21*Assumptions!$B$17 -> 5625 | E22: =E21*Assumptions!$B$17 -> 10000 | F22: =F21*Assumptions!$B$17 -> 15625 | G22: =G21*Assumptions!$B$17 -> 21875
A23: CO2 avoided by solar | B23: tCO2e | C23: =C22*Assumptions!$B$12 -> 1387.5 | D23: =D22*Assumptions!$B$12 -> 4162.5 | E23: =E22*Assumptions!$B$12 -> 7400 | F23: =F22*Assumptions!$B$12 -> 11562.5 | G23: =G22*Assumptions!$B$12 -> 16187.5
A24: Pool 2 – Shop energy upgrades
A25: New shops upgraded | B25: shops | C25: =Yearly_Inputs!$B$6 -> 15 | D25: =Yearly_Inputs!$C$6 -> 25 | E25: =Yearly_Inputs!$D$6 -> 10 | F25: =Yearly_Inputs!$E$6 -> 10 | G25: =Yearly_Inputs!$F$6 -> 10
A26: Money raised from residents | B26: RM | C26: =C25*Assumptions!$B$23 -> 300000 | D26: =D25*Assumptions!$B$23 -> 500000 | E26: =E25*Assumptions!$B$23 -> 200000 | F26: =F25*Assumptions!$B$23 -> 200000 | G26: =G25*Assumptions!$B$23 -> 200000
A27: Residents' money still invested (average) | B27: RM | C27: =C26*C11 -> 150000 | D27: =C26*D11+D26*C11 -> 503113.64 | E27: =C26*E11+D26*D11+E26*C11 -> 678149.4 | F27: =C26*F11+D26*E11+E26*D11+F26*C11 -> 582410.97 | G27: =C26*G11+D26*F11+E26*E11+F26*D11+G26*C11 -> 461570.77
A28: Shops repaying (shop-years) | B28: shop-yrs | C28: =C25*C12 -> 7.5 | D28: =C25*D12+D25*C12 -> 27.5 | E28: =C25*E12+D25*D12+E25*C12 -> 45 | F28: =C25*F12+D25*E12+E25*D12+F25*C12 -> 47.5 | G28: =C25*G12+D25*F12+E25*E12+F25*D12+G25*C12 -> 37.5
A29: Yearly payout per shop to residents | B29: RM | C29: =PMT(Assumptions!$B$26/12,Assumptions!$B$27*12,-Assumptions!$B$23)*12 -> 7355.7607 | D29: =PMT(Assumptions!$B$26/12,Assumptions!$B$27*12,-Assumptions!$B$23)*12 -> 7355.7607 | E29: =PMT(Assumptions!$B$26/12,Assumptions!$B$27*12,-Assumptions!$B$23)*12 -> 7355.7607 | F29: =PMT(Assumptions!$B$26/12,Assumptions!$B$27*12,-Assumptions!$B$23)*12 -> 7355.7607 | G29: =PMT(Assumptions!$B$26/12,Assumptions!$B$27*12,-Assumptions!$B$23)*12 -> 7355.7607
A30: Payouts to residents | B30: RM | C30: =C28*C29 -> 55168.205 | D30: =D28*D29 -> 202283.42 | E30: =E28*E29 -> 331009.23 | F30: =F28*F29 -> 349398.63 | G30: =G28*G29 -> 275841.03
A31: Safety margin per shop-year (repayment counted − payout) | B31: RM | C31: =C56*12-C29 -> 2244.2393 | D31: =D56*12-D29 -> 2244.2393 | E31: =E56*12-E29 -> 2244.2393 | F31: =F56*12-F29 -> 2244.2393 | G31: =G56*12-G29 -> 2244.2393
A32: Savings shops keep | B32: RM | C32: =C28*Assumptions!$B$24*12*(1-Assumptions!$B$25) -> 18000 | D32: =D28*Assumptions!$B$24*12*(1-Assumptions!$B$25) -> 66000 | E32: =E28*Assumptions!$B$24*12*(1-Assumptions!$B$25) -> 108000 | F32: =F28*Assumptions!$B$24*12*(1-Assumptions!$B$25) -> 114000 | G32: =G28*Assumptions!$B$24*12*(1-Assumptions!$B$25) -> 90000
A33: Electricity saved | B33: MWh | C33: =C28*Assumptions!$B$24*12/Assumptions!$B$11/1000 -> 198.23789 | D33: =D28*Assumptions!$B$24*12/Assumptions!$B$11/1000 -> 726.87225 | E33: =E28*Assumptions!$B$24*12/Assumptions!$B$11/1000 -> 1189.4273 | F33: =F28*Assumptions!$B$24*12/Assumptions!$B$11/1000 -> 1255.5066 | G33: =G28*Assumptions!$B$24*12/Assumptions!$B$11/1000 -> 991.18943
A34: CO2 avoided by upgrades | B34: tCO2e | C34: =C33*Assumptions!$B$12 -> 146.69604 | D34: =D33*Assumptions!$B$12 -> 537.88546 | E34: =E33*Assumptions!$B$12 -> 880.17621 | F34: =F33*Assumptions!$B$12 -> 929.07489 | G34: =G33*Assumptions!$B$12 -> 733.48018
A35: Pool 3 – EV charging
A36: New EV chargers | B36: chargers | C36: =Yearly_Inputs!$B$7 -> 1 | D36: =Yearly_Inputs!$C$7 -> 2 | E36: =Yearly_Inputs!$D$7 -> 2 | F36: =Yearly_Inputs!$E$7 -> 2 | G36: =Yearly_Inputs!$F$7 -> 2
A37: Money raised from residents (net cost after grant × residents' share) | B37: RM | C37: =C36*EV_Pilot!$B$46*Assumptions!$B$31 -> 22500 | D37: =D36*EV_Pilot!$B$46*Assumptions!$B$31 -> 45000 | E37: =E36*EV_Pilot!$B$46*Assumptions!$B$31 -> 45000 | F37: =F36*EV_Pilot!$B$46*Assumptions!$B$31 -> 45000 | G37: =G36*EV_Pilot!$B$46*Assumptions!$B$31 -> 45000
A38: Residents' money still invested (average) | B38: RM | C38: =C37*C13 -> 10848.214 | D38: =C37*D13+D37*C13 -> 40982.143 | E38: =C37*E13+D37*D13+E37*C13 -> 76339.286 | F38: =C37*F13+D37*E13+E37*D13+F37*C13 -> 105267.86 | G38: =C37*G13+D37*F13+E37*E13+F37*D13+G37*C13 -> 127767.86
A39: Chargers running (charger-years) | B39: chg-yrs | C39: =C36*C9 -> 0.5 | D39: =C36*D9+D36*C9 -> 2 | E39: =C36*E9+D36*D9+E36*C9 -> 4 | F39: =C36*F9+D36*E9+E36*D9+F36*C9 -> 6 | G39: =C36*G9+D36*F9+E36*E9+F36*D9+G36*C9 -> 8
A40: Net charging profit per charger-year (blended DC/AC, from EV_Pilot) | B40: RM | C40: =EV_Pilot!$B$50 -> 8979.74 | D40: =EV_Pilot!$B$50 -> 8979.74 | E40: =EV_Pilot!$B$50 -> 8979.74 | F40: =EV_Pilot!$B$50 -> 8979.74 | G40: =EV_Pilot!$B$50 -> 8979.74
A41: Residents' share of charging profit (their 50%, before the 70/10/10/10 split) | B41: RM | C41: =C39*EV_Pilot!$B$54 -> 2244.935 | D41: =D39*EV_Pilot!$B$54 -> 8979.74 | E41: =E39*EV_Pilot!$B$54 -> 17959.48 | F41: =F39*EV_Pilot!$B$54 -> 26939.22 | G41: =G39*EV_Pilot!$B$54 -> 35918.96
A42: Payouts to residents (incl. usage top-up) | B42: RM | C42: =C68*EV_Pilot!$B$56+C69*EV_Pilot!$B$57+C39*EV_Pilot!$B$65 -> 2020.4415 | D42: =D68*EV_Pilot!$B$56+D69*EV_Pilot!$B$57+D39*EV_Pilot!$B$65 -> 8081.766 | E42: =E68*EV_Pilot!$B$56+E69*EV_Pilot!$B$57+E39*EV_Pilot!$B$65 -> 16163.532 | F42: =F68*EV_Pilot!$B$56+F69*EV_Pilot!$B$57+F39*EV_Pilot!$B$65 -> 24245.298 | G42: =G68*EV_Pilot!$B$56+G69*EV_Pilot!$B$57+G39*EV_Pilot!$B$65 -> 32327.064
A43: Residents' EV money paid back | B43: RM | C43: =C37*C14 -> 1607.1429 | D43: =C37*D14+D37*C14 -> 6428.5714 | E43: =C37*E14+D37*D14+E37*C14 -> 12857.143 | F43: =C37*F14+D37*E14+E37*D14+F37*C14 -> 19285.714 | G43: =C37*G14+D37*F14+E37*E14+F37*D14+G37*C14 -> 25714.286
A44: All pools – totals for one SDP-size client
A45: Money raised from residents | B45: RM | C45: =C17+C26+C37 -> 3202500 | D45: =D17+D26+D37 -> 3425000 | E45: =E17+E26+E37 -> 4085000 | F45: =F17+F26+F37 -> 5045000 | G45: =G17+G26+G37 -> 5045000
A46: Residents' money still invested (average) | B46: RM | C46: =C18+C27+C38 -> 1600848.2 | D46: =D18+D27+D38 -> 4603492.1 | E46: =E18+E27+E38 -> 7379043.7 | F46: =F18+F27+F38 -> 10189575 | G46: =G18+G27+G38 -> 12594632
A47: Payouts to residents | B47: RM | C47: =C20+C30+C42 -> 389792.36 | D47: =D20+D30+D42 -> 1208176.3 | E47: =E20+E30+E42 -> 2121059.2 | F47: =F20+F30+F42 -> 3145341.5 | G47: =G20+G30+G42 -> 4188544.7
A48: Spent at the developer's malls (incl. bonus) | B48: RM | C48: =C47*Assumptions!$B$8*(1+Assumptions!$B$9) -> 128631.48 | D48: =D47*Assumptions!$B$8*(1+Assumptions!$B$9) -> 398698.18 | E48: =E47*Assumptions!$B$8*(1+Assumptions!$B$9) -> 699949.54 | F48: =F47*Assumptions!$B$8*(1+Assumptions!$B$9) -> 1037962.7 | G48: =G47*Assumptions!$B$8*(1+Assumptions!$B$9) -> 1382219.8
A49: Resident investments made (count, at average ticket) | B49: count | C49: =C45/Assumptions!$B$7 -> 6405 | D49: =D45/Assumptions!$B$7 -> 6850 | E49: =E45/Assumptions!$B$7 -> 8170 | F49: =F45/Assumptions!$B$7 -> 10090 | G49: =G45/Assumptions!$B$7 -> 10090
A50: Residents' profit earned (after expected shop losses) | B50: RM | C50: =C18*Assumptions!$B$19+C27*Assumptions!$B$26-C59+C42-C43 -> 82163.299 | D50: =D18*Assumptions!$B$19+D27*Assumptions!$B$26-D59+D42-D43 -> 237325.4 | E50: =E18*Assumptions!$B$19+E27*Assumptions!$B$26-E59+E42-E43 -> 378613.85 | F50: =F18*Assumptions!$B$19+F27*Assumptions!$B$26-F59+F42-F43 -> 517911.11 | G50: =G18*Assumptions!$B$19+G27*Assumptions!$B$26-G59+G42-G43 -> 636879.55
A51: CO2 avoided by assets residents co-fund (solar + upgrades) | B51: tCO2e | C51: =C23+C34 -> 1534.196 | D51: =D23+D34 -> 4700.3855 | E51: =E23+E34 -> 8280.1762 | F51: =F23+F34 -> 12491.575 | G51: =G23+G34 -> 16920.98
A53: Note: timing factors are simple approximations (money raised mid-year; solar and upgrades repaid monthly; EV money returned from charging profit, not guaranteed).
A55: v2 – Guarantees, expected losses and certificates
A56: Repayment counted per shop-month (higher of actual or guaranteed saving × repay share) | B56: RM | C56: =MAX(Assumptions!$B$24,Assumptions!$B$72)*Assumptions!$B$25 -> 800 | D56: =MAX(Assumptions!$B$24,Assumptions!$B$72)*Assumptions!$B$25 -> 800 | E56: =MAX(Assumptions!$B$24,Assumptions!$B$72)*Assumptions!$B$25 -> 800 | F56: =MAX(Assumptions!$B$24,Assumptions!$B$72)*Assumptions!$B$25 -> 800 | G56: =MAX(Assumptions!$B$24,Assumptions!$B$72)*Assumptions!$B$25 -> 800
A57: Expected default loss per shop-year | B57: RM | C57: =Assumptions!$B$23*Assumptions!$B$73*Assumptions!$B$74 -> 200 | D57: =Assumptions!$B$23*Assumptions!$B$73*Assumptions!$B$74 -> 200 | E57: =Assumptions!$B$23*Assumptions!$B$73*Assumptions!$B$74 -> 200 | F57: =Assumptions!$B$23*Assumptions!$B$73*Assumptions!$B$74 -> 200 | G57: =Assumptions!$B$23*Assumptions!$B$73*Assumptions!$B$74 -> 200
A58: Bad-debt reserve per shop-year (unused half of margin) | B58: RM | C58: =MAX(0,C31)*(1-Assumptions!$B$28) -> 1122.1197 | D58: =MAX(0,D31)*(1-Assumptions!$B$28) -> 1122.1197 | E58: =MAX(0,E31)*(1-Assumptions!$B$28) -> 1122.1197 | F58: =MAX(0,F31)*(1-Assumptions!$B$28) -> 1122.1197 | G58: =MAX(0,G31)*(1-Assumptions!$B$28) -> 1122.1197
A59: Residents' uncovered loss on upgrades | B59: RM | C59: =C28*(MAX(0,C57-C58)+MAX(0,-C31)) -> 0 | D59: =D28*(MAX(0,D57-D58)+MAX(0,-D31)) -> 0 | E59: =E28*(MAX(0,E57-E58)+MAX(0,-E31)) -> 0 | F59: =F28*(MAX(0,F57-F58)+MAX(0,-F31)) -> 0 | G59: =G28*(MAX(0,G57-G58)+MAX(0,-G31)) -> 0
A60: v3: kWh sold per charger-day (after downtime) | B60: kWh | C60: =EV_Pilot!$B$9 -> 60 | D60: =EV_Pilot!$B$9 -> 60 | E60: =EV_Pilot!$B$9 -> 60 | F60: =EV_Pilot!$B$9 -> 60 | G60: =EV_Pilot!$B$9 -> 60
A61: v3: usage top-up per charger-year (after cap) | B61: RM | C61: =EV_Pilot!$B$65 -> 0 | D61: =EV_Pilot!$B$65 -> 0 | E61: =EV_Pilot!$B$65 -> 0 | F61: =EV_Pilot!$B$65 -> 0 | G61: =EV_Pilot!$B$65 -> 0
A62: v3: usage top-up paid to residents (developer + platform + CPO) | B62: RM | C62: =C39*C61 -> 0 | D62: =D39*D61 -> 0 | E62: =E39*E61 -> 0 | F62: =F39*F61 -> 0 | G62: =G39*G61 -> 0
A63: Solar MWh from the residents' share (for certificates) | B63: MWh | C63: =C22*Assumptions!$B$18 -> 562.5 | D63: =D22*Assumptions!$B$18 -> 1687.5 | E63: =E22*Assumptions!$B$18 -> 3000 | F63: =F22*Assumptions!$B$18 -> 4687.5 | G63: =G22*Assumptions!$B$18 -> 6562.5
A65: v3 – EV: who is paid while residents recover their money
A66: EV: charger-year factor while residents recover (by age) | C66: =C9*IF(C6-0.5<EV_Pilot!$B$73,1,0) -> 0.5 | D66: =D9*IF(D6-0.5<EV_Pilot!$B$73,1,0) -> 1 | E66: =E9*IF(E6-0.5<EV_Pilot!$B$73,1,0) -> 1 | F66: =F9*IF(F6-0.5<EV_Pilot!$B$73,1,0) -> 1 | G66: =G9*IF(G6-0.5<EV_Pilot!$B$73,1,0) -> 1
A67: EV: charger-year factor after residents recover (by age) | C67: =C9-C66 -> 0 | D67: =D9-D66 -> 0 | E67: =E9-E66 -> 0 | F67: =F9-F66 -> 0 | G67: =G9-G66 -> 0
A68: EV charger-years while residents recover | B68: chg-yrs | C68: =C36*C66 -> 0.5 | D68: =C36*D66+D36*C66 -> 2 | E68: =C36*E66+D36*D66+E36*C66 -> 4 | F68: =C36*F66+D36*E66+E36*D66+F36*C66 -> 6 | G68: =C36*G66+D36*F66+E36*E66+F36*D66+G36*C66 -> 8
A69: EV charger-years after residents recover | B69: chg-yrs | C69: =C36*C67 -> 0 | D69: =C36*D67+D36*C67 -> 0 | E69: =C36*E67+D36*D67+E36*C67 -> 0 | F69: =C36*F67+D36*E67+E36*D67+F36*C67 -> 0 | G69: =C36*G67+D36*F67+E36*E67+F36*D67+G36*C67 -> 0
A70: Developer's 10% share of residents' EV profit (paid after recovery if deferral is on) | B70: RM | C70: =IF(Assumptions!$B$135=1,C69,C39)*EV_Pilot!$B$58 -> 0 | D70: =IF(Assumptions!$B$135=1,D69,D39)*EV_Pilot!$B$58 -> 0 | E70: =IF(Assumptions!$B$135=1,E69,E39)*EV_Pilot!$B$58 -> 0 | F70: =IF(Assumptions!$B$135=1,F69,F39)*EV_Pilot!$B$58 -> 0 | G70: =IF(Assumptions!$B$135=1,G69,G39)*EV_Pilot!$B$58 -> 0
A71: Developer's part of the usage top-up | B71: RM | C71: =C39*EV_Pilot!$B$66 -> 0 | D71: =D39*EV_Pilot!$B$66 -> 0 | E71: =E39*EV_Pilot!$B$66 -> 0 | F71: =F39*EV_Pilot!$B$66 -> 0 | G71: =G39*EV_Pilot!$B$66 -> 0
A72: Platform's 10% share of residents' EV profit (paid after recovery if deferral is on) | B72: RM | C72: =IF(Assumptions!$B$135=1,C69,C39)*EV_Pilot!$B$59 -> 0 | D72: =IF(Assumptions!$B$135=1,D69,D39)*EV_Pilot!$B$59 -> 0 | E72: =IF(Assumptions!$B$135=1,E69,E39)*EV_Pilot!$B$59 -> 0 | F72: =IF(Assumptions!$B$135=1,F69,F39)*EV_Pilot!$B$59 -> 0 | G72: =IF(Assumptions!$B$135=1,G69,G39)*EV_Pilot!$B$59 -> 0
A73: Platform's part of the usage top-up | B73: RM | C73: =C39*EV_Pilot!$B$67 -> 0 | D73: =D39*EV_Pilot!$B$67 -> 0 | E73: =E39*EV_Pilot!$B$67 -> 0 | F73: =F39*EV_Pilot!$B$67 -> 0 | G73: =G39*EV_Pilot!$B$67 -> 0

Sheet EV_Pilot
A1: EV_Pilot – one charger's economics, who gets the money, and stress tests
A2: Each column is a case. B = normal, C = conservative (all stresses together, from Scenarios). D–K change ONE thing from normal. L and M switch off a protection. Every cell is a formula.
A4: Item | B4: Normal | C4: Conservative (all stresses) | D4: Tariff +20% | E4: Maintenance +50% | F4: Downtime 10% | G4: Price −20% | H4: Grant not approved | I4: Usage 30 kWh/day | J4: No idle or membership fees | K4: Mall MV demand charge | L4: Normal, no deferral (70% split from day 1) | M4: Conservative, no top-up | N4: Unit / how
A5: Usage and prices
A6: Charging sessions per charger per day | B6: =Assumptions!$B$105 -> 2 | C6: =Scenarios!$C$15 -> 1.5 | D6: =Assumptions!$B$105 -> 2 | E6: =Assumptions!$B$105 -> 2 | F6: =Assumptions!$B$105 -> 2 | G6: =Assumptions!$B$105 -> 2 | H6: =Assumptions!$B$105 -> 2 | I6: =Scenarios!$C$15 -> 1.5 | J6: =Assumptions!$B$105 -> 2 | K6: =Assumptions!$B$105 -> 2 | L6: =Assumptions!$B$105 -> 2 | M6: =Scenarios!$C$15 -> 1.5 | N6: sessions
A7: Energy per session | B7: =Assumptions!$B$106 -> 30 | C7: =Scenarios!$C$16 -> 20 | D7: =Assumptions!$B$106 -> 30 | E7: =Assumptions!$B$106 -> 30 | F7: =Assumptions!$B$106 -> 30 | G7: =Assumptions!$B$106 -> 30 | H7: =Assumptions!$B$106 -> 30 | I7: =Scenarios!$C$16 -> 20 | J7: =Assumptions!$B$106 -> 30 | K7: =Assumptions!$B$106 -> 30 | L7: =Assumptions!$B$106 -> 30 | M7: =Scenarios!$C$16 -> 20 | N7: kWh
A8: Downtime | B8: =0 -> 0 | C8: =Scenarios!$C$19 -> 0.1 | D8: =0 -> 0 | E8: =0 -> 0 | F8: =Scenarios!$C$19 -> 0.1 | G8: =0 -> 0 | H8: =0 -> 0 | I8: =0 -> 0 | J8: =0 -> 0 | K8: =0 -> 0 | L8: =0 -> 0 | M8: =Scenarios!$C$19 -> 0.1 | N8: % of time
A9: Energy sold per charger per day | B9: =B6*B7*(1-B8) -> 60 | C9: =C6*C7*(1-C8) -> 27 | D9: =D6*D7*(1-D8) -> 60 | E9: =E6*E7*(1-E8) -> 60 | F9: =F6*F7*(1-F8) -> 54 | G9: =G6*G7*(1-G8) -> 60 | H9: =H6*H7*(1-H8) -> 60 | I9: =I6*I7*(1-I8) -> 30 | ... M9: =M6*M7*(1-M8) -> 27 | N9: kWh/day
A10: Price level (1 − competitor price drop) | B10: =1-0 -> 1 | C10: =1-Scenarios!$C$11 -> 0.8 | D10: =1-0 -> 1 | E10: =1-0 -> 1 | F10: =1-0 -> 1 | G10: =1-Scenarios!$C$11 -> 0.8 | H10: =1-0 -> 1 | I10: =1-0 -> 1 | J10: =1-0 -> 1 | K10: =1-0 -> 1 | L10: =1-0 -> 1 | M10: =1-Scenarios!$C$11 -> 0.8
A11: DC average price (standard + peak) | B11: =(Assumptions!$B$32*(1-Assumptions!$B$120)+Assumptions!$B$119*Assumptions!$B$120)*B10 -> 1.49 | C11: =(Assumptions!$B$32*(1-Assumptions!$B$120)+Assumptions!$B$119*Assumptions!$B$120)*C10 -> 1.192 | D11: =(Assumptions!$B$32*(1-Assumptions!$B$120)+Assumptions!$B$119*Assumptions!$B$120)*D10 -> 1.49 | E11: =(Assumptions!$B$32*(1-Assumptions!$B$120)+Assumptions!$B$119*Assumptions!$B$120)*E10 -> 1.49 | F11: =(Assumptions!$B$32*(1-Assumptions!$B$120)+Assumptions!$B$119*Assumptions!$B$120)*F10 -> 1.49 | G11: =(Assumptions!$B$32*(1-Assumptions!$B$120)+Assumptions!$B$119*Assumptions!$B$120)*G10 -> 1.192 | H11: =(Assumptions!$B$32*(1-Assumptions!$B$120)+Assumptions!$B$119*Assumptions!$B$120)*H10 -> 1.49 | I11: =(Assumptions!$B$32*(1-Assumptions!$B$120)+Assumptions!$B$119*Assumptions!$B$120)*I10 -> 1.49 | ... M11: =(Assumptions!$B$32*(1-Assumptions!$B$120)+Assumptions!$B$119*Assumptions!$B$120)*M10 -> 1.192 | N11: RM/kWh
A12: AC average price (standard + off-peak) | B12: =(Assumptions!$B$118*(1-Assumptions!$B$122)+Assumptions!$B$121*Assumptions!$B$122)*B10 -> 0.95 | C12: =(Assumptions!$B$118*(1-Assumptions!$B$122)+Assumptions!$B$121*Assumptions!$B$122)*C10 -> 0.76 | D12: =(Assumptions!$B$118*(1-Assumptions!$B$122)+Assumptions!$B$121*Assumptions!$B$122)*D10 -> 0.95 | E12: =(Assumptions!$B$118*(1-Assumptions!$B$122)+Assumptions!$B$121*Assumptions!$B$122)*E10 -> 0.95 | F12: =(Assumptions!$B$118*(1-Assumptions!$B$122)+Assumptions!$B$121*Assumptions!$B$122)*F10 -> 0.95 | G12: =(Assumptions!$B$118*(1-Assumptions!$B$122)+Assumptions!$B$121*Assumptions!$B$122)*G10 -> 0.76 | H12: =(Assumptions!$B$118*(1-Assumptions!$B$122)+Assumptions!$B$121*Assumptions!$B$122)*H10 -> 0.95 | I12: =(Assumptions!$B$118*(1-Assumptions!$B$122)+Assumptions!$B$121*Assumptions!$B$122)*I10 -> 0.95 | ... M12: =(Assumptions!$B$118*(1-Assumptions!$B$122)+Assumptions!$B$121*Assumptions!$B$122)*M10 -> 0.76 | N12: RM/kWh
A13: Electricity cost per kWh (energy + capacity + network) | B13: =Assumptions!$B$102*(1+0) -> 0.5068 | C13: =Assumptions!$B$102*(1+Scenarios!$C$17) -> 0.60816 | D13: =Assumptions!$B$102*(1+Scenarios!$C$17) -> 0.60816 | E13: =Assumptions!$B$102*(1+0) -> 0.5068 | F13: =Assumptions!$B$102*(1+0) -> 0.5068 | G13: =Assumptions!$B$102*(1+0) -> 0.5068 | H13: =Assumptions!$B$102*(1+0) -> 0.5068 | I13: =Assumptions!$B$102*(1+0) -> 0.5068 | J13: =Assumptions!$B$102*(1+0) -> 0.5068 | K13: =Assumptions!$B$102*(1+0) -> 0.5068 | L13: =Assumptions!$B$102*(1+0) -> 0.5068 | M13: =Assumptions!$B$102*(1+Scenarios!$C$17) -> 0.60816 | N13: RM/kWh
A14: of which capacity charge | B14: =Assumptions!$B$103*(1+0) -> 0.0883 | C14: =Assumptions!$B$103*(1+Scenarios!$C$17) -> 0.10596 | D14: =Assumptions!$B$103*(1+Scenarios!$C$17) -> 0.10596 | E14: =Assumptions!$B$103*(1+0) -> 0.0883 | F14: =Assumptions!$B$103*(1+0) -> 0.0883 | G14: =Assumptions!$B$103*(1+0) -> 0.0883 | H14: =Assumptions!$B$103*(1+0) -> 0.0883 | I14: =Assumptions!$B$103*(1+0) -> 0.0883 | J14: =Assumptions!$B$103*(1+0) -> 0.0883 | K14: =Assumptions!$B$103*(1+0) -> 0.0883 | L14: =Assumptions!$B$103*(1+0) -> 0.0883 | M14: =Assumptions!$B$103*(1+Scenarios!$C$17) -> 0.10596 | N14: RM/kWh
A15: Maximum-demand charge per kW (only if the site is on the MV tariff) | B15: =0*Assumptions!$B$141 -> 0 | C15: =0*Assumptions!$B$141 -> 0 | D15: =0*Assumptions!$B$141 -> 0 | E15: =0*Assumptions!$B$141 -> 0 | F15: =0*Assumptions!$B$141 -> 0 | G15: =0*Assumptions!$B$141 -> 0 | H15: =0*Assumptions!$B$141 -> 0 | I15: =0*Assumptions!$B$141 -> 0 | J15: =0*Assumptions!$B$141 -> 0 | K15: =1*Assumptions!$B$141 -> 89.27 | L15: =0*Assumptions!$B$141 -> 0 | M15: =0*Assumptions!$B$141 -> 0 | N15: RM/kW/month
A16: DC 60 kW charger (per year)
A17: Installed cost | B17: =Assumptions!$B$116 -> 100000 | C17: =Assumptions!$B$116 -> 100000 | D17: =Assumptions!$B$116 -> 100000 | E17: =Assumptions!$B$116 -> 100000 | F17: =Assumptions!$B$116 -> 100000 | G17: =Assumptions!$B$116 -> 100000 | H17: =Assumptions!$B$116 -> 100000 | I17: =Assumptions!$B$116 -> 100000 | ... M17: =Assumptions!$B$116 -> 100000 | N17: RM
A18: MARii grant (if approved) | B18: =MIN(Assumptions!$B$116*Assumptions!$B$104,Assumptions!$B$129)*1 -> 50000 | C18: =MIN(Assumptions!$B$116*Assumptions!$B$104,Assumptions!$B$129)*Scenarios!$C$20 -> 0 | D18: =MIN(Assumptions!$B$116*Assumptions!$B$104,Assumptions!$B$129)*1 -> 50000 | E18: =MIN(Assumptions!$B$116*Assumptions!$B$104,Assumptions!$B$129)*1 -> 50000 | F18: =MIN(Assumptions!$B$116*Assumptions!$B$104,Assumptions!$B$129)*1 -> 50000 | G18: =MIN(Assumptions!$B$116*Assumptions!$B$104,Assumptions!$B$129)*1 -> 50000 | H18: =MIN(Assumptions!$B$116*Assumptions!$B$104,Assumptions!$B$129)*Scenarios!$C$20 -> 0 | I18: =MIN(Assumptions!$B$116*Assumptions!$B$104,Assumptions!$B$129)*1 -> 50000 | J18: =MIN(Assumptions!$B$116*Assumptions!$B$104,Assumptions!$B$129)*1 -> 50000 | K18: =MIN(Assumptions!$B$116*Assumptions!$B$104,Assumptions!$B$129)*1 -> 50000 | L18: =MIN(Assumptions!$B$116*Assumptions!$B$104,Assumptions!$B$129)*1 -> 50000 | M18: =MIN(Assumptions!$B$116*Assumptions!$B$104,Assumptions!$B$129)*Scenarios!$C$20 -> 0 | N18: RM
A19: Compliance cost share (per site ÷ chargers per site) | B19: =Assumptions!$B$107/Assumptions!$B$128 -> 7500 | C19: =Assumptions!$B$107/Assumptions!$B$128 -> 7500 | D19: =Assumptions!$B$107/Assumptions!$B$128 -> 7500 | E19: =Assumptions!$B$107/Assumptions!$B$128 -> 7500 | F19: =Assumptions!$B$107/Assumptions!$B$128 -> 7500 | G19: =Assumptions!$B$107/Assumptions!$B$128 -> 7500 | H19: =Assumptions!$B$107/Assumptions!$B$128 -> 7500 | I19: =Assumptions!$B$107/Assumptions!$B$128 -> 7500 | ... M19: =Assumptions!$B$107/Assumptions!$B$128 -> 7500 | N19: RM
A20: Net installed cost | B20: =B17-B18+B19 -> 57500 | C20: =C17-C18+C19 -> 107500 | D20: =D17-D18+D19 -> 57500 | E20: =E17-E18+E19 -> 57500 | F20: =F17-F18+F19 -> 57500 | G20: =G17-G18+G19 -> 57500 | H20: =H17-H18+H19 -> 107500 | I20: =I17-I18+I19 -> 57500 | ... M20: =M17-M18+M19 -> 107500 | N20: RM
A21: Charging revenue | B21: =365*B9*B11 -> 32631 | C21: =365*C9*C11 -> 11747.16 | D21: =365*D9*D11 -> 32631 | E21: =365*E9*E11 -> 32631 | F21: =365*F9*F11 -> 29367.9 | G21: =365*G9*G11 -> 26104.8 | H21: =365*H9*H11 -> 32631 | I21: =365*I9*I11 -> 16315.5 | ... M21: =365*M9*M11 -> 11747.16 | N21: RM/yr
A22: Idle (occupancy) fees | B22: =365*Assumptions!$B$124*Assumptions!$B$123*(1-B8) -> 1460 | C22: =365*Scenarios!$C$21*Assumptions!$B$123*(1-C8) -> 657 | D22: =365*Assumptions!$B$124*Assumptions!$B$123*(1-D8) -> 1460 | E22: =365*Assumptions!$B$124*Assumptions!$B$123*(1-E8) -> 1460 | F22: =365*Assumptions!$B$124*Assumptions!$B$123*(1-F8) -> 1314 | G22: =365*Assumptions!$B$124*Assumptions!$B$123*(1-G8) -> 1460 | H22: =365*Assumptions!$B$124*Assumptions!$B$123*(1-H8) -> 1460 | I22: =365*Assumptions!$B$124*Assumptions!$B$123*(1-I8) -> 1460 | J22: =365*0*Assumptions!$B$123*(1-J8) -> 0 | K22: =365*Assumptions!$B$124*Assumptions!$B$123*(1-K8) -> 1460 | L22: =365*Assumptions!$B$124*Assumptions!$B$123*(1-L8) -> 1460 | M22: =365*Scenarios!$C$21*Assumptions!$B$123*(1-M8) -> 657 | N22: RM/yr
A23: Membership fees | B23: =Assumptions!$B$126*Assumptions!$B$125*12 -> 1800 | C23: =Scenarios!$C$22*Assumptions!$B$125*12 -> 900 | D23: =Assumptions!$B$126*Assumptions!$B$125*12 -> 1800 | E23: =Assumptions!$B$126*Assumptions!$B$125*12 -> 1800 | F23: =Assumptions!$B$126*Assumptions!$B$125*12 -> 1800 | G23: =Assumptions!$B$126*Assumptions!$B$125*12 -> 1800 | H23: =Assumptions!$B$126*Assumptions!$B$125*12 -> 1800 | I23: =Assumptions!$B$126*Assumptions!$B$125*12 -> 1800 | J23: =0*Assumptions!$B$125*12 -> 0 | K23: =Assumptions!$B$126*Assumptions!$B$125*12 -> 1800 | L23: =Assumptions!$B$126*Assumptions!$B$125*12 -> 1800 | M23: =Scenarios!$C$22*Assumptions!$B$125*12 -> 900 | N23: RM/yr
A24: Payment and app costs | B24: =-Assumptions!$B$33*(B21+B22+B23) -> -1076.73 | C24: =-Assumptions!$B$33*(C21+C22+C23) -> -399.1248 | D24: =-Assumptions!$B$33*(D21+D22+D23) -> -1076.73 | E24: =-Assumptions!$B$33*(E21+E22+E23) -> -1076.73 | F24: =-Assumptions!$B$33*(F21+F22+F23) -> -974.457 | G24: =-Assumptions!$B$33*(G21+G22+G23) -> -880.944 | H24: =-Assumptions!$B$33*(H21+H22+H23) -> -1076.73 | I24: =-Assumptions!$B$33*(I21+I22+I23) -> -587.265 | ... M24: =-Assumptions!$B$33*(M21+M22+M23) -> -399.1248 | N24: RM/yr
A25: Electricity (incl. capacity and network charges) | B25: =-365*B9*B13 -> -11098.92 | C25: =-365*C9*C13 -> -5993.4168 | D25: =-365*D9*D13 -> -13318.704 | E25: =-365*E9*E13 -> -11098.92 | F25: =-365*F9*F13 -> -9989.028 | G25: =-365*G9*G13 -> -11098.92 | H25: =-365*H9*H13 -> -11098.92 | I25: =-365*I9*I13 -> -5549.46 | ... M25: =-365*M9*M13 -> -5993.4168 | N25: RM/yr
A26: Maximum-demand charge (MV sites only) | B26: =-B15*Assumptions!$B$142*1*12 -> 0 | C26: =-C15*Assumptions!$B$142*1*12 -> 0 | D26: =-D15*Assumptions!$B$142*1*12 -> 0 | E26: =-E15*Assumptions!$B$142*1*12 -> 0 | F26: =-F15*Assumptions!$B$142*1*12 -> 0 | G26: =-G15*Assumptions!$B$142*1*12 -> 0 | H26: =-H15*Assumptions!$B$142*1*12 -> 0 | I26: =-I15*Assumptions!$B$142*1*12 -> 0 | ... M26: =-M15*Assumptions!$B$142*1*12 -> 0 | N26: RM/yr
A27: Maintenance and CPO service fee | B27: =-Assumptions!$B$34*(1+0) -> -10000 | C27: =-Assumptions!$B$34*(1+Scenarios!$C$18) -> -15000 | D27: =-Assumptions!$B$34*(1+0) -> -10000 | E27: =-Assumptions!$B$34*(1+Scenarios!$C$18) -> -15000 | F27: =-Assumptions!$B$34*(1+0) -> -10000 | G27: =-Assumptions!$B$34*(1+0) -> -10000 | H27: =-Assumptions!$B$34*(1+0) -> -10000 | I27: =-Assumptions!$B$34*(1+0) -> -10000 | J27: =-Assumptions!$B$34*(1+0) -> -10000 | K27: =-Assumptions!$B$34*(1+0) -> -10000 | L27: =-Assumptions!$B$34*(1+0) -> -10000 | M27: =-Assumptions!$B$34*(1+Scenarios!$C$18) -> -15000 | N27: RM/yr
A28: Compliance audit share | B28: =-Assumptions!$B$108/Assumptions!$B$128 -> -2500 | C28: =-Assumptions!$B$108/Assumptions!$B$128 -> -2500 | D28: =-Assumptions!$B$108/Assumptions!$B$128 -> -2500 | E28: =-Assumptions!$B$108/Assumptions!$B$128 -> -2500 | F28: =-Assumptions!$B$108/Assumptions!$B$128 -> -2500 | G28: =-Assumptions!$B$108/Assumptions!$B$128 -> -2500 | H28: =-Assumptions!$B$108/Assumptions!$B$128 -> -2500 | I28: =-Assumptions!$B$108/Assumptions!$B$128 -> -2500 | ... M28: =-Assumptions!$B$108/Assumptions!$B$128 -> -2500 | N28: RM/yr
A29: Net charging profit | B29: =SUM(B21:B28) -> 11215.35 | C29: =SUM(C21:C28) -> -10588.382 | D29: =SUM(D21:D28) -> 8995.566 | E29: =SUM(E21:E28) -> 6215.35 | F29: =SUM(F21:F28) -> 9018.415 | G29: =SUM(G21:G28) -> 4884.936 | H29: =SUM(H21:H28) -> 11215.35 | I29: =SUM(I21:I28) -> 938.775 | ... M29: =SUM(M21:M28) -> -10588.382 | N29: RM/yr
A30: Revenue per charger per day | B30: =(B21+B22+B23)/365 -> 98.331507 | C30: =(C21+C22+C23)/365 -> 36.449753 | D30: =(D21+D22+D23)/365 -> 98.331507 | E30: =(E21+E22+E23)/365 -> 98.331507 | F30: =(F21+F22+F23)/365 -> 88.991507 | G30: =(G21+G22+G23)/365 -> 80.451507 | H30: =(H21+H22+H23)/365 -> 98.331507 | I30: =(I21+I22+I23)/365 -> 53.631507 | ... M30: =(M21+M22+M23)/365 -> 36.449753 | N30: RM/day
A31: AC 22 kW charger (per year)
A32: Installed cost | B32: =Assumptions!$B$117 -> 25000 | C32: =Assumptions!$B$117 -> 25000 | D32: =Assumptions!$B$117 -> 25000 | E32: =Assumptions!$B$117 -> 25000 | F32: =Assumptions!$B$117 -> 25000 | G32: =Assumptions!$B$117 -> 25000 | H32: =Assumptions!$B$117 -> 25000 | I32: =Assumptions!$B$117 -> 25000 | ... M32: =Assumptions!$B$117 -> 25000 | N32: RM
A33: Compliance cost share (per site ÷ chargers per site) | B33: =Assumptions!$B$107/Assumptions!$B$128 -> 7500 | C33: =Assumptions!$B$107/Assumptions!$B$128 -> 7500 | D33: =Assumptions!$B$107/Assumptions!$B$128 -> 7500 | E33: =Assumptions!$B$107/Assumptions!$B$128 -> 7500 | F33: =Assumptions!$B$107/Assumptions!$B$128 -> 7500 | G33: =Assumptions!$B$107/Assumptions!$B$128 -> 7500 | H33: =Assumptions!$B$107/Assumptions!$B$128 -> 7500 | I33: =Assumptions!$B$107/Assumptions!$B$128 -> 7500 | ... M33: =Assumptions!$B$107/Assumptions!$B$128 -> 7500 | N33: RM
A34: Net installed cost | B34: =B32+B33 -> 32500 | C34: =C32+C33 -> 32500 | D34: =D32+D33 -> 32500 | E34: =E32+E33 -> 32500 | F34: =F32+F33 -> 32500 | G34: =G32+G33 -> 32500 | H34: =H32+H33 -> 32500 | I34: =I32+I33 -> 32500 | ... M34: =M32+M33 -> 32500 | N34: RM
A35: Charging revenue | B35: =365*B9*B12 -> 20805 | C35: =365*C9*C12 -> 7489.8 | D35: =365*D9*D12 -> 20805 | E35: =365*E9*E12 -> 20805 | F35: =365*F9*F12 -> 18724.5 | G35: =365*G9*G12 -> 16644 | H35: =365*H9*H12 -> 20805 | I35: =365*I9*I12 -> 10402.5 | ... M35: =365*M9*M12 -> 7489.8 | N35: RM/yr
A36: Idle (occupancy) fees | B36: =365*Assumptions!$B$124*Assumptions!$B$123*(1-B8) -> 1460 | C36: =365*Scenarios!$C$21*Assumptions!$B$123*(1-C8) -> 657 | D36: =365*Assumptions!$B$124*Assumptions!$B$123*(1-D8) -> 1460 | E36: =365*Assumptions!$B$124*Assumptions!$B$123*(1-E8) -> 1460 | F36: =365*Assumptions!$B$124*Assumptions!$B$123*(1-F8) -> 1314 | G36: =365*Assumptions!$B$124*Assumptions!$B$123*(1-G8) -> 1460 | H36: =365*Assumptions!$B$124*Assumptions!$B$123*(1-H8) -> 1460 | I36: =365*Assumptions!$B$124*Assumptions!$B$123*(1-I8) -> 1460 | J36: =365*0*Assumptions!$B$123*(1-J8) -> 0 | K36: =365*Assumptions!$B$124*Assumptions!$B$123*(1-K8) -> 1460 | L36: =365*Assumptions!$B$124*Assumptions!$B$123*(1-L8) -> 1460 | M36: =365*Scenarios!$C$21*Assumptions!$B$123*(1-M8) -> 657 | N36: RM/yr
A37: Membership fees | B37: =Assumptions!$B$126*Assumptions!$B$125*12 -> 1800 | C37: =Scenarios!$C$22*Assumptions!$B$125*12 -> 900 | D37: =Assumptions!$B$126*Assumptions!$B$125*12 -> 1800 | E37: =Assumptions!$B$126*Assumptions!$B$125*12 -> 1800 | F37: =Assumptions!$B$126*Assumptions!$B$125*12 -> 1800 | G37: =Assumptions!$B$126*Assumptions!$B$125*12 -> 1800 | H37: =Assumptions!$B$126*Assumptions!$B$125*12 -> 1800 | I37: =Assumptions!$B$126*Assumptions!$B$125*12 -> 1800 | J37: =0*Assumptions!$B$125*12 -> 0 | K37: =Assumptions!$B$126*Assumptions!$B$125*12 -> 1800 | L37: =Assumptions!$B$126*Assumptions!$B$125*12 -> 1800 | M37: =Scenarios!$C$22*Assumptions!$B$125*12 -> 900 | N37: RM/yr
A38: Payment and app costs | B38: =-Assumptions!$B$33*(B35+B36+B37) -> -721.95 | C38: =-Assumptions!$B$33*(C35+C36+C37) -> -271.404 | D38: =-Assumptions!$B$33*(D35+D36+D37) -> -721.95 | E38: =-Assumptions!$B$33*(E35+E36+E37) -> -721.95 | F38: =-Assumptions!$B$33*(F35+F36+F37) -> -655.155 | G38: =-Assumptions!$B$33*(G35+G36+G37) -> -597.12 | H38: =-Assumptions!$B$33*(H35+H36+H37) -> -721.95 | I38: =-Assumptions!$B$33*(I35+I36+I37) -> -409.875 | ... M38: =-Assumptions!$B$33*(M35+M36+M37) -> -271.404 | N38: RM/yr
A39: Electricity (incl. capacity and network charges) | B39: =-365*B9*B13 -> -11098.92 | C39: =-365*C9*C13 -> -5993.4168 | D39: =-365*D9*D13 -> -13318.704 | E39: =-365*E9*E13 -> -11098.92 | F39: =-365*F9*F13 -> -9989.028 | G39: =-365*G9*G13 -> -11098.92 | H39: =-365*H9*H13 -> -11098.92 | I39: =-365*I9*I13 -> -5549.46 | ... M39: =-365*M9*M13 -> -5993.4168 | N39: RM/yr
A40: Maximum-demand charge (MV sites only) | B40: =-B15*Assumptions!$B$142*22/60*12 -> 0 | C40: =-C15*Assumptions!$B$142*22/60*12 -> 0 | D40: =-D15*Assumptions!$B$142*22/60*12 -> 0 | E40: =-E15*Assumptions!$B$142*22/60*12 -> 0 | F40: =-F15*Assumptions!$B$142*22/60*12 -> 0 | G40: =-G15*Assumptions!$B$142*22/60*12 -> 0 | H40: =-H15*Assumptions!$B$142*22/60*12 -> 0 | I40: =-I15*Assumptions!$B$142*22/60*12 -> 0 | ... M40: =-M15*Assumptions!$B$142*22/60*12 -> 0 | N40: RM/yr
A41: Maintenance and CPO service fee | B41: =-Assumptions!$B$127*(1+0) -> -3000 | C41: =-Assumptions!$B$127*(1+Scenarios!$C$18) -> -4500 | D41: =-Assumptions!$B$127*(1+0) -> -3000 | E41: =-Assumptions!$B$127*(1+Scenarios!$C$18) -> -4500 | F41: =-Assumptions!$B$127*(1+0) -> -3000 | G41: =-Assumptions!$B$127*(1+0) -> -3000 | H41: =-Assumptions!$B$127*(1+0) -> -3000 | I41: =-Assumptions!$B$127*(1+0) -> -3000 | J41: =-Assumptions!$B$127*(1+0) -> -3000 | K41: =-Assumptions!$B$127*(1+0) -> -3000 | L41: =-Assumptions!$B$127*(1+0) -> -3000 | M41: =-Assumptions!$B$127*(1+Scenarios!$C$18) -> -4500 | N41: RM/yr
A42: Compliance audit share | B42: =-Assumptions!$B$108/Assumptions!$B$128 -> -2500 | C42: =-Assumptions!$B$108/Assumptions!$B$128 -> -2500 | D42: =-Assumptions!$B$108/Assumptions!$B$128 -> -2500 | E42: =-Assumptions!$B$108/Assumptions!$B$128 -> -2500 | F42: =-Assumptions!$B$108/Assumptions!$B$128 -> -2500 | G42: =-Assumptions!$B$108/Assumptions!$B$128 -> -2500 | H42: =-Assumptions!$B$108/Assumptions!$B$128 -> -2500 | I42: =-Assumptions!$B$108/Assumptions!$B$128 -> -2500 | ... M42: =-Assumptions!$B$108/Assumptions!$B$128 -> -2500 | N42: RM/yr
A43: Net charging profit | B43: =SUM(B35:B42) -> 6744.13 | C43: =SUM(C35:C42) -> -4218.0208 | D43: =SUM(D35:D42) -> 4524.346 | E43: =SUM(E35:E42) -> 5244.13 | F43: =SUM(F35:F42) -> 5694.317 | G43: =SUM(G35:G42) -> 2707.96 | H43: =SUM(H35:H42) -> 6744.13 | I43: =SUM(I35:I42) -> 2203.165 | ... M43: =SUM(M35:M42) -> -4218.0208 | N43: RM/yr
A44: Revenue per charger per day | B44: =(B35+B36+B37)/365 -> 65.931507 | C44: =(C35+C36+C37)/365 -> 24.785753 | D44: =(D35+D36+D37)/365 -> 65.931507 | E44: =(E35+E36+E37)/365 -> 65.931507 | F44: =(F35+F36+F37)/365 -> 59.831507 | G44: =(G35+G36+G37)/365 -> 54.531507 | H44: =(H35+H36+H37)/365 -> 65.931507 | I44: =(I35+I36+I37)/365 -> 37.431507 | ... M44: =(M35+M36+M37)/365 -> 24.785753 | N44: RM/day
A45: Blended charger (DC share × DC + AC share × AC)
A46: Net installed cost after grant | B46: =Assumptions!$B$115*B20+(1-Assumptions!$B$115)*B34 -> 45000 | C46: =Assumptions!$B$115*C20+(1-Assumptions!$B$115)*C34 -> 70000 | D46: =Assumptions!$B$115*D20+(1-Assumptions!$B$115)*D34 -> 45000 | E46: =Assumptions!$B$115*E20+(1-Assumptions!$B$115)*E34 -> 45000 | F46: =Assumptions!$B$115*F20+(1-Assumptions!$B$115)*F34 -> 45000 | G46: =Assumptions!$B$115*G20+(1-Assumptions!$B$115)*G34 -> 45000 | H46: =Assumptions!$B$115*H20+(1-Assumptions!$B$115)*H34 -> 70000 | I46: =Assumptions!$B$115*I20+(1-Assumptions!$B$115)*I34 -> 45000 | ... M46: =Assumptions!$B$115*M20+(1-Assumptions!$B$115)*M34 -> 70000 | N46: RM
A47: Government grant received | B47: =Assumptions!$B$115*B18 -> 25000 | C47: =Assumptions!$B$115*C18 -> 0 | D47: =Assumptions!$B$115*D18 -> 25000 | E47: =Assumptions!$B$115*E18 -> 25000 | F47: =Assumptions!$B$115*F18 -> 25000 | G47: =Assumptions!$B$115*G18 -> 25000 | H47: =Assumptions!$B$115*H18 -> 0 | I47: =Assumptions!$B$115*I18 -> 25000 | ... M47: =Assumptions!$B$115*M18 -> 0 | N47: RM
A48: Revenue per charger per day | B48: =Assumptions!$B$115*B30+(1-Assumptions!$B$115)*B44 -> 82.131507 | C48: =Assumptions!$B$115*C30+(1-Assumptions!$B$115)*C44 -> 30.617753 | D48: =Assumptions!$B$115*D30+(1-Assumptions!$B$115)*D44 -> 82.131507 | E48: =Assumptions!$B$115*E30+(1-Assumptions!$B$115)*E44 -> 82.131507 | F48: =Assumptions!$B$115*F30+(1-Assumptions!$B$115)*F44 -> 74.411507 | G48: =Assumptions!$B$115*G30+(1-Assumptions!$B$115)*G44 -> 67.491507 | H48: =Assumptions!$B$115*H30+(1-Assumptions!$B$115)*H44 -> 82.131507 | I48: =Assumptions!$B$115*I30+(1-Assumptions!$B$115)*I44 -> 45.531507 | ... M48: =Assumptions!$B$115*M30+(1-Assumptions!$B$115)*M44 -> 30.617753 | N48: RM/day
A49: Electricity cost per charger per day (incl. capacity charge and any MV demand charge) | B49: =-(Assumptions!$B$115*(B25+B26)+(1-Assumptions!$B$115)*(B39+B40))/365 -> 30.408 | C49: =-(Assumptions!$B$115*(C25+C26)+(1-Assumptions!$B$115)*(C39+C40))/365 -> 16.42032 | D49: =-(Assumptions!$B$115*(D25+D26)+(1-Assumptions!$B$115)*(D39+D40))/365 -> 36.4896 | E49: =-(Assumptions!$B$115*(E25+E26)+(1-Assumptions!$B$115)*(E39+E40))/365 -> 30.408 | F49: =-(Assumptions!$B$115*(F25+F26)+(1-Assumptions!$B$115)*(F39+F40))/365 -> 27.3672 | G49: =-(Assumptions!$B$115*(G25+G26)+(1-Assumptions!$B$115)*(G39+G40))/365 -> 30.408 | H49: =-(Assumptions!$B$115*(H25+H26)+(1-Assumptions!$B$115)*(H39+H40))/365 -> 30.408 | I49: =-(Assumptions!$B$115*(I25+I26)+(1-Assumptions!$B$115)*(I39+I40))/365 -> 15.204 | ... M49: =-(Assumptions!$B$115*(M25+M26)+(1-Assumptions!$B$115)*(M39+M40))/365 -> 16.42032 | N49: RM/day
A50: Net charging profit per charger | B50: =Assumptions!$B$115*B29+(1-Assumptions!$B$115)*B43 -> 8979.74 | C50: =Assumptions!$B$115*C29+(1-Assumptions!$B$115)*C43 -> -7403.2012 | D50: =Assumptions!$B$115*D29+(1-Assumptions!$B$115)*D43 -> 6759.956 | E50: =Assumptions!$B$115*E29+(1-Assumptions!$B$115)*E43 -> 5729.74 | F50: =Assumptions!$B$115*F29+(1-Assumptions!$B$115)*F43 -> 7356.366 | G50: =Assumptions!$B$115*G29+(1-Assumptions!$B$115)*G43 -> 3796.448 | H50: =Assumptions!$B$115*H29+(1-Assumptions!$B$115)*H43 -> 8979.74 | I50: =Assumptions!$B$115*I29+(1-Assumptions!$B$115)*I43 -> 1570.97 | ... M50: =Assumptions!$B$115*M29+(1-Assumptions!$B$115)*M43 -> -7403.2012 | N50: RM/yr
A51: Whole-charger payback | B51: =IF(B50<=0,"Never",B46/B50) -> 5.011281 | C51: =IF(C50<=0,"Never",C46/C50) -> Never | D51: =IF(D50<=0,"Never",D46/D50) -> 6.6568481 | E51: =IF(E50<=0,"Never",E46/E50) -> 7.8537595 | F51: =IF(F50<=0,"Never",F46/F50) -> 6.1171508 | G51: =IF(G50<=0,"Never",G46/G50) -> 11.853185 | H51: =IF(H50<=0,"Never",H46/H50) -> 7.7953259 | I51: =IF(I50<=0,"Never",I46/I50) -> 28.644723 | ... M51: =IF(M50<=0,"Never",M46/M50) -> Never | N51: years
A52: Who gets the profit (per charger per year)
A53: Residents' money in one charger | B53: =B46*Assumptions!$B$31 -> 22500 | C53: =C46*Assumptions!$B$31 -> 35000 | D53: =D46*Assumptions!$B$31 -> 22500 | E53: =E46*Assumptions!$B$31 -> 22500 | F53: =F46*Assumptions!$B$31 -> 22500 | G53: =G46*Assumptions!$B$31 -> 22500 | H53: =H46*Assumptions!$B$31 -> 35000 | I53: =I46*Assumptions!$B$31 -> 22500 | ... M53: =M46*Assumptions!$B$31 -> 35000 | N53: RM
A54: Residents' share of profit (their 50%) | B54: =MAX(0,B50)*Assumptions!$B$31 -> 4489.87 | C54: =MAX(0,C50)*Assumptions!$B$31 -> 0 | D54: =MAX(0,D50)*Assumptions!$B$31 -> 3379.978 | E54: =MAX(0,E50)*Assumptions!$B$31 -> 2864.87 | F54: =MAX(0,F50)*Assumptions!$B$31 -> 3678.183 | G54: =MAX(0,G50)*Assumptions!$B$31 -> 1898.224 | H54: =MAX(0,H50)*Assumptions!$B$31 -> 4489.87 | I54: =MAX(0,I50)*Assumptions!$B$31 -> 785.485 | ... M54: =MAX(0,M50)*Assumptions!$B$31 -> 0 | N54: RM/yr
A55: CPO's share of profit (its 50%; it also earns the service fee) | B55: =B50*(1-Assumptions!$B$31) -> 4489.87 | C55: =C50*(1-Assumptions!$B$31) -> -3701.6006 | D55: =D50*(1-Assumptions!$B$31) -> 3379.978 | E55: =E50*(1-Assumptions!$B$31) -> 2864.87 | F55: =F50*(1-Assumptions!$B$31) -> 3678.183 | G55: =G50*(1-Assumptions!$B$31) -> 1898.224 | H55: =H50*(1-Assumptions!$B$31) -> 4489.87 | I55: =I50*(1-Assumptions!$B$31) -> 785.485 | ... M55: =M50*(1-Assumptions!$B$31) -> -3701.6006 | N55: RM/yr
A56: To residents while they recover their money | B56: =B54*(Assumptions!$B$132+Assumptions!$B$135*(Assumptions!$B$36+Assumptions!$B$133)) -> 4040.883 | C56: =C54*(Assumptions!$B$132+Assumptions!$B$135*(Assumptions!$B$36+Assumptions!$B$133)) -> 0 | D56: =D54*(Assumptions!$B$132+Assumptions!$B$135*(Assumptions!$B$36+Assumptions!$B$133)) -> 3041.9802 | E56: =E54*(Assumptions!$B$132+Assumptions!$B$135*(Assumptions!$B$36+Assumptions!$B$133)) -> 2578.383 | F56: =F54*(Assumptions!$B$132+Assumptions!$B$135*(Assumptions!$B$36+Assumptions!$B$133)) -> 3310.3647 | G56: =G54*(Assumptions!$B$132+Assumptions!$B$135*(Assumptions!$B$36+Assumptions!$B$133)) -> 1708.4016 | H56: =H54*(Assumptions!$B$132+Assumptions!$B$135*(Assumptions!$B$36+Assumptions!$B$133)) -> 4040.883 | I56: =I54*(Assumptions!$B$132+Assumptions!$B$135*(Assumptions!$B$36+Assumptions!$B$133)) -> 706.9365 | ... K56: =K54*(Assumptions!$B$132+Assumptions!$B$135*(Assumptions!$B$36+Assumptions!$B$133)) -> 746.82 | L56: =L54*(Assumptions!$B$132+0*(Assumptions!$B$36+Assumptions!$B$133)) -> 3142.909 | M56: =M54*(Assumptions!$B$132+Assumptions!$B$135*(Assumptions!$B$36+Assumptions!$B$133)) -> 0 | N56: RM/yr
A57: To residents after they recover their money | B57: =B54*Assumptions!$B$132 -> 3142.909 | C57: =C54*Assumptions!$B$132 -> 0 | D57: =D54*Assumptions!$B$132 -> 2365.9846 | E57: =E54*Assumptions!$B$132 -> 2005.409 | F57: =F54*Assumptions!$B$132 -> 2574.7281 | G57: =G54*Assumptions!$B$132 -> 1328.7568 | H57: =H54*Assumptions!$B$132 -> 3142.909 | I57: =I54*Assumptions!$B$132 -> 549.8395 | ... M57: =M54*Assumptions!$B$132 -> 0 | N57: RM/yr
A58: Developer share (paid after recovery if deferral is on) | B58: =B54*Assumptions!$B$36 -> 448.987 | C58: =C54*Assumptions!$B$36 -> 0 | D58: =D54*Assumptions!$B$36 -> 337.9978 | E58: =E54*Assumptions!$B$36 -> 286.487 | F58: =F54*Assumptions!$B$36 -> 367.8183 | G58: =G54*Assumptions!$B$36 -> 189.8224 | H58: =H54*Assumptions!$B$36 -> 448.987 | I58: =I54*Assumptions!$B$36 -> 78.5485 | ... M58: =M54*Assumptions!$B$36 -> 0 | N58: RM/yr
A59: Platform share (paid after recovery if deferral is on) | B59: =B54*Assumptions!$B$133 -> 448.987 | C59: =C54*Assumptions!$B$133 -> 0 | D59: =D54*Assumptions!$B$133 -> 337.9978 | E59: =E54*Assumptions!$B$133 -> 286.487 | F59: =F54*Assumptions!$B$133 -> 367.8183 | G59: =G54*Assumptions!$B$133 -> 189.8224 | H59: =H54*Assumptions!$B$133 -> 448.987 | I59: =I54*Assumptions!$B$133 -> 78.5485 | ... M59: =M54*Assumptions!$B$133 -> 0 | N59: RM/yr
A60: O&M reserve | B60: =B54*Assumptions!$B$134 -> 448.987 | C60: =C54*Assumptions!$B$134 -> 0 | D60: =D54*Assumptions!$B$134 -> 337.9978 | E60: =E54*Assumptions!$B$134 -> 286.487 | F60: =F54*Assumptions!$B$134 -> 367.8183 | G60: =G54*Assumptions!$B$134 -> 189.8224 | H60: =H54*Assumptions!$B$134 -> 448.987 | I60: =I54*Assumptions!$B$134 -> 78.5485 | ... M60: =M54*Assumptions!$B$134 -> 0 | N60: RM/yr
A61: Usage top-up (partners pay for missing kWh below the minimum, up to a cap)
A62: Missing kWh per day below the minimum | B62: =MAX(0,Assumptions!$B$75-B9) -> 0 | C62: =MAX(0,Assumptions!$B$75-C9) -> 33 | D62: =MAX(0,Assumptions!$B$75-D9) -> 0 | E62: =MAX(0,Assumptions!$B$75-E9) -> 0 | F62: =MAX(0,Assumptions!$B$75-F9) -> 6 | G62: =MAX(0,Assumptions!$B$75-G9) -> 0 | H62: =MAX(0,Assumptions!$B$75-H9) -> 0 | I62: =MAX(0,Assumptions!$B$75-I9) -> 30 | ... M62: =MAX(0,Assumptions!$B$75-M9) -> 33 | N62: kWh/day
A63: Contract top-up rate (normal margin per kWh, fixed in contract) | B63: =Assumptions!$B$115*(($B$11)*(1-Assumptions!$B$33)-$B$13)+(1-Assumptions!$B$115)*(($B$12)*(1-Assumptions!$B$33)-$B$13) -> 0.6766 | C63: =Assumptions!$B$115*(($B$11)*(1-Assumptions!$B$33)-$B$13)+(1-Assumptions!$B$115)*(($B$12)*(1-Assumptions!$B$33)-$B$13) -> 0.6766 | D63: =Assumptions!$B$115*(($B$11)*(1-Assumptions!$B$33)-$B$13)+(1-Assumptions!$B$115)*(($B$12)*(1-Assumptions!$B$33)-$B$13) -> 0.6766 | E63: =Assumptions!$B$115*(($B$11)*(1-Assumptions!$B$33)-$B$13)+(1-Assumptions!$B$115)*(($B$12)*(1-Assumptions!$B$33)-$B$13) -> 0.6766 | F63: =Assumptions!$B$115*(($B$11)*(1-Assumptions!$B$33)-$B$13)+(1-Assumptions!$B$115)*(($B$12)*(1-Assumptions!$B$33)-$B$13) -> 0.6766 | G63: =Assumptions!$B$115*(($B$11)*(1-Assumptions!$B$33)-$B$13)+(1-Assumptions!$B$115)*(($B$12)*(1-Assumptions!$B$33)-$B$13) -> 0.6766 | H63: =Assumptions!$B$115*(($B$11)*(1-Assumptions!$B$33)-$B$13)+(1-Assumptions!$B$115)*(($B$12)*(1-Assumptions!$B$33)-$B$13) -> 0.6766 | I63: =Assumptions!$B$115*(($B$11)*(1-Assumptions!$B$33)-$B$13)+(1-Assumptions!$B$115)*(($B$12)*(1-Assumptions!$B$33)-$B$13) -> 0.6766 | ... M63: =Assumptions!$B$115*(($B$11)*(1-Assumptions!$B$33)-$B$13)+(1-Assumptions!$B$115)*(($B$12)*(1-Assumptions!$B$33)-$B$13) -> 0.6766 | N63: RM/kWh
A64: Top-up before cap (residents' part) | B64: =365*B62*B63*Assumptions!$B$31*(Assumptions!$B$132+Assumptions!$B$135*(Assumptions!$B$36+Assumptions!$B$133))*1 -> 0 | C64: =365*C62*C63*Assumptions!$B$31*(Assumptions!$B$132+Assumptions!$B$135*(Assumptions!$B$36+Assumptions!$B$133))*1 -> 3667.3412 | D64: =365*D62*D63*Assumptions!$B$31*(Assumptions!$B$132+Assumptions!$B$135*(Assumptions!$B$36+Assumptions!$B$133))*1 -> 0 | E64: =365*E62*E63*Assumptions!$B$31*(Assumptions!$B$132+Assumptions!$B$135*(Assumptions!$B$36+Assumptions!$B$133))*1 -> 0 | F64: =365*F62*F63*Assumptions!$B$31*(Assumptions!$B$132+Assumptions!$B$135*(Assumptions!$B$36+Assumptions!$B$133))*1 -> 666.7893 | G64: =365*G62*G63*Assumptions!$B$31*(Assumptions!$B$132+Assumptions!$B$135*(Assumptions!$B$36+Assumptions!$B$133))*1 -> 0 | H64: =365*H62*H63*Assumptions!$B$31*(Assumptions!$B$132+Assumptions!$B$135*(Assumptions!$B$36+Assumptions!$B$133))*1 -> 0 | I64: =365*I62*I63*Assumptions!$B$31*(Assumptions!$B$132+Assumptions!$B$135*(Assumptions!$B$36+Assumptions!$B$133))*1 -> 3333.9465 | ... K64: =365*K62*K63*Assumptions!$B$31*(Assumptions!$B$132+Assumptions!$B$135*(Assumptions!$B$36+Assumptions!$B$133))*1 -> 0 | L64: =365*L62*L63*Assumptions!$B$31*(Assumptions!$B$132+0*(Assumptions!$B$36+Assumptions!$B$133))*1 -> 0 | M64: =365*M62*M63*Assumptions!$B$31*(Assumptions!$B$132+Assumptions!$B$135*(Assumptions!$B$36+Assumptions!$B$133))*0 -> 0 | N64: RM/yr
A65: Top-up paid (after cap) | B65: =MIN(Assumptions!$B$140,B64) -> 0 | C65: =MIN(Assumptions!$B$140,C64) -> 3000 | D65: =MIN(Assumptions!$B$140,D64) -> 0 | E65: =MIN(Assumptions!$B$140,E64) -> 0 | F65: =MIN(Assumptions!$B$140,F64) -> 666.7893 | G65: =MIN(Assumptions!$B$140,G64) -> 0 | H65: =MIN(Assumptions!$B$140,H64) -> 0 | I65: =MIN(Assumptions!$B$140,I64) -> 3000 | ... M65: =MIN(Assumptions!$B$140,M64) -> 0 | N65: RM/yr
A66: paid by developer | B66: =B65*Assumptions!$B$76 -> 0 | C66: =C65*Assumptions!$B$76 -> 990 | D66: =D65*Assumptions!$B$76 -> 0 | E66: =E65*Assumptions!$B$76 -> 0 | F66: =F65*Assumptions!$B$76 -> 220.04047 | G66: =G65*Assumptions!$B$76 -> 0 | H66: =H65*Assumptions!$B$76 -> 0 | I66: =I65*Assumptions!$B$76 -> 990 | ... M66: =M65*Assumptions!$B$76 -> 0 | N66: RM/yr
A67: paid by platform (us) | B67: =B65*Assumptions!$B$138 -> 0 | C67: =C65*Assumptions!$B$138 -> 990 | D67: =D65*Assumptions!$B$138 -> 0 | E67: =E65*Assumptions!$B$138 -> 0 | F67: =F65*Assumptions!$B$138 -> 220.04047 | G67: =G65*Assumptions!$B$138 -> 0 | H67: =H65*Assumptions!$B$138 -> 0 | I67: =I65*Assumptions!$B$138 -> 990 | ... M67: =M65*Assumptions!$B$138 -> 0 | N67: RM/yr
A68: paid by CPO | B68: =B65*Assumptions!$B$139 -> 0 | C68: =C65*Assumptions!$B$139 -> 1020 | D68: =D65*Assumptions!$B$139 -> 0 | E68: =E65*Assumptions!$B$139 -> 0 | F68: =F65*Assumptions!$B$139 -> 226.70836 | G68: =G65*Assumptions!$B$139 -> 0 | H68: =H65*Assumptions!$B$139 -> 0 | I68: =I65*Assumptions!$B$139 -> 1020 | ... M68: =M65*Assumptions!$B$139 -> 0 | N68: RM/yr
A69: Residents: cash for every RM1,000 invested
A70: Cash a year while recovering money (incl. top-up) | B70: =(B56+B65)/B53*1000 -> 179.5948 | C70: =(C56+C65)/C53*1000 -> 85.714286 | D70: =(D56+D65)/D53*1000 -> 135.19912 | E70: =(E56+E65)/E53*1000 -> 114.5948 | F70: =(F56+F65)/F53*1000 -> 176.7624 | G70: =(G56+G65)/G53*1000 -> 75.92896 | H70: =(H56+H65)/H53*1000 -> 115.4538 | I70: =(I56+I65)/I53*1000 -> 164.75273 | ... M70: =(M56+M65)/M53*1000 -> 0 | N70: RM/yr
A71: Cash a year after recovering money (incl. top-up) | B71: =(B57+B65)/B53*1000 -> 139.68484 | C71: =(C57+C65)/C53*1000 -> 85.714286 | D71: =(D57+D65)/D53*1000 -> 105.15487 | E71: =(E57+E65)/E53*1000 -> 89.129289 | F71: =(F57+F65)/F53*1000 -> 144.06744 | G71: =(G57+G65)/G53*1000 -> 59.055858 | H71: =(H57+H65)/H53*1000 -> 89.7974 | I71: =(I57+I65)/I53*1000 -> 157.77064 | ... M71: =(M57+M65)/M53*1000 -> 0 | N71: RM/yr
A72: Reserve returned at the end | B72: =B60*Assumptions!$B$137*Assumptions!$B$136/B53*1000 -> 69.842422 | C72: =C60*Assumptions!$B$137*Assumptions!$B$136/C53*1000 -> 0 | D72: =D60*Assumptions!$B$137*Assumptions!$B$136/D53*1000 -> 52.577436 | E72: =E60*Assumptions!$B$137*Assumptions!$B$136/E53*1000 -> 44.564644 | F72: =F60*Assumptions!$B$137*Assumptions!$B$136/F53*1000 -> 57.21618 | G72: =G60*Assumptions!$B$137*Assumptions!$B$136/G53*1000 -> 29.527929 | H72: =H60*Assumptions!$B$137*Assumptions!$B$136/H53*1000 -> 44.8987 | I72: =I60*Assumptions!$B$137*Assumptions!$B$136/I53*1000 -> 12.218656 | ... M72: =M60*Assumptions!$B$137*Assumptions!$B$136/M53*1000 -> 0 | N72: RM
A73: Years to recover money | B73: =IF(B70<=0,99,1000/B70) -> 5.5680899 | C73: =IF(C70<=0,99,1000/C70) -> 11.666667 | D73: =IF(D70<=0,99,1000/D70) -> 7.3964978 | E73: =IF(E70<=0,99,1000/E70) -> 8.7263995 | F73: =IF(F70<=0,99,1000/F70) -> 5.6573117 | G73: =IF(G70<=0,99,1000/G70) -> 13.170205 | H73: =IF(H70<=0,99,1000/H70) -> 8.6614732 | I73: =IF(I70<=0,99,1000/I70) -> 6.069702 | ... M73: =IF(M70<=0,99,1000/M70) -> 99 | N73: years
A74: Year 0 (invest) | B74: =-1000 -> -1000 | C74: =-1000 -> -1000 | D74: =-1000 -> -1000 | E74: =-1000 -> -1000 | F74: =-1000 -> -1000 | G74: =-1000 -> -1000 | H74: =-1000 -> -1000 | I74: =-1000 -> -1000 | ... M74: =-1000 -> -1000
A75: Year 1 | B75: =IF(1>Assumptions!$B$137,0,IF(0<1000,B70,B71)+IF(1=Assumptions!$B$137,B72,0)) -> 179.5948 | C75: =IF(1>Assumptions!$B$137,0,IF(0<1000,C70,C71)+IF(1=Assumptions!$B$137,C72,0)) -> 85.714286 | D75: =IF(1>Assumptions!$B$137,0,IF(0<1000,D70,D71)+IF(1=Assumptions!$B$137,D72,0)) -> 135.19912 | E75: =IF(1>Assumptions!$B$137,0,IF(0<1000,E70,E71)+IF(1=Assumptions!$B$137,E72,0)) -> 114.5948 | F75: =IF(1>Assumptions!$B$137,0,IF(0<1000,F70,F71)+IF(1=Assumptions!$B$137,F72,0)) -> 176.7624 | G75: =IF(1>Assumptions!$B$137,0,IF(0<1000,G70,G71)+IF(1=Assumptions!$B$137,G72,0)) -> 75.92896 | H75: =IF(1>Assumptions!$B$137,0,IF(0<1000,H70,H71)+IF(1=Assumptions!$B$137,H72,0)) -> 115.4538 | I75: =IF(1>Assumptions!$B$137,0,IF(0<1000,I70,I71)+IF(1=Assumptions!$B$137,I72,0)) -> 164.75273 | ... M75: =IF(1>Assumptions!$B$137,0,IF(0<1000,M70,M71)+IF(1=Assumptions!$B$137,M72,0)) -> 0
A76: Year 2 | B76: =IF(2>Assumptions!$B$137,0,IF(SUM(B75:B75)<1000,B70,B71)+IF(2=Assumptions!$B$137,B72,0)) -> 179.5948 | C76: =IF(2>Assumptions!$B$137,0,IF(SUM(C75:C75)<1000,C70,C71)+IF(2=Assumptions!$B$137,C72,0)) -> 85.714286 | D76: =IF(2>Assumptions!$B$137,0,IF(SUM(D75:D75)<1000,D70,D71)+IF(2=Assumptions!$B$137,D72,0)) -> 135.19912 | E76: =IF(2>Assumptions!$B$137,0,IF(SUM(E75:E75)<1000,E70,E71)+IF(2=Assumptions!$B$137,E72,0)) -> 114.5948 | F76: =IF(2>Assumptions!$B$137,0,IF(SUM(F75:F75)<1000,F70,F71)+IF(2=Assumptions!$B$137,F72,0)) -> 176.7624 | G76: =IF(2>Assumptions!$B$137,0,IF(SUM(G75:G75)<1000,G70,G71)+IF(2=Assumptions!$B$137,G72,0)) -> 75.92896 | H76: =IF(2>Assumptions!$B$137,0,IF(SUM(H75:H75)<1000,H70,H71)+IF(2=Assumptions!$B$137,H72,0)) -> 115.4538 | I76: =IF(2>Assumptions!$B$137,0,IF(SUM(I75:I75)<1000,I70,I71)+IF(2=Assumptions!$B$137,I72,0)) -> 164.75273 | ... M76: =IF(2>Assumptions!$B$137,0,IF(SUM(M75:M75)<1000,M70,M71)+IF(2=Assumptions!$B$137,M72,0)) -> 0
A77: Year 3 | B77: =IF(3>Assumptions!$B$137,0,IF(SUM(B75:B76)<1000,B70,B71)+IF(3=Assumptions!$B$137,B72,0)) -> 179.5948 | C77: =IF(3>Assumptions!$B$137,0,IF(SUM(C75:C76)<1000,C70,C71)+IF(3=Assumptions!$B$137,C72,0)) -> 85.714286 | D77: =IF(3>Assumptions!$B$137,0,IF(SUM(D75:D76)<1000,D70,D71)+IF(3=Assumptions!$B$137,D72,0)) -> 135.19912 | E77: =IF(3>Assumptions!$B$137,0,IF(SUM(E75:E76)<1000,E70,E71)+IF(3=Assumptions!$B$137,E72,0)) -> 114.5948 | F77: =IF(3>Assumptions!$B$137,0,IF(SUM(F75:F76)<1000,F70,F71)+IF(3=Assumptions!$B$137,F72,0)) -> 176.7624 | G77: =IF(3>Assumptions!$B$137,0,IF(SUM(G75:G76)<1000,G70,G71)+IF(3=Assumptions!$B$137,G72,0)) -> 75.92896 | H77: =IF(3>Assumptions!$B$137,0,IF(SUM(H75:H76)<1000,H70,H71)+IF(3=Assumptions!$B$137,H72,0)) -> 115.4538 | I77: =IF(3>Assumptions!$B$137,0,IF(SUM(I75:I76)<1000,I70,I71)+IF(3=Assumptions!$B$137,I72,0)) -> 164.75273 | ... M77: =IF(3>Assumptions!$B$137,0,IF(SUM(M75:M76)<1000,M70,M71)+IF(3=Assumptions!$B$137,M72,0)) -> 0
A78: Year 4 | B78: =IF(4>Assumptions!$B$137,0,IF(SUM(B75:B77)<1000,B70,B71)+IF(4=Assumptions!$B$137,B72,0)) -> 179.5948 | C78: =IF(4>Assumptions!$B$137,0,IF(SUM(C75:C77)<1000,C70,C71)+IF(4=Assumptions!$B$137,C72,0)) -> 85.714286 | D78: =IF(4>Assumptions!$B$137,0,IF(SUM(D75:D77)<1000,D70,D71)+IF(4=Assumptions!$B$137,D72,0)) -> 135.19912 | E78: =IF(4>Assumptions!$B$137,0,IF(SUM(E75:E77)<1000,E70,E71)+IF(4=Assumptions!$B$137,E72,0)) -> 114.5948 | F78: =IF(4>Assumptions!$B$137,0,IF(SUM(F75:F77)<1000,F70,F71)+IF(4=Assumptions!$B$137,F72,0)) -> 176.7624 | G78: =IF(4>Assumptions!$B$137,0,IF(SUM(G75:G77)<1000,G70,G71)+IF(4=Assumptions!$B$137,G72,0)) -> 75.92896 | H78: =IF(4>Assumptions!$B$137,0,IF(SUM(H75:H77)<1000,H70,H71)+IF(4=Assumptions!$B$137,H72,0)) -> 115.4538 | I78: =IF(4>Assumptions!$B$137,0,IF(SUM(I75:I77)<1000,I70,I71)+IF(4=Assumptions!$B$137,I72,0)) -> 164.75273 | ... M78: =IF(4>Assumptions!$B$137,0,IF(SUM(M75:M77)<1000,M70,M71)+IF(4=Assumptions!$B$137,M72,0)) -> 0
A79: Year 5 | B79: =IF(5>Assumptions!$B$137,0,IF(SUM(B75:B78)<1000,B70,B71)+IF(5=Assumptions!$B$137,B72,0)) -> 179.5948 | C79: =IF(5>Assumptions!$B$137,0,IF(SUM(C75:C78)<1000,C70,C71)+IF(5=Assumptions!$B$137,C72,0)) -> 85.714286 | D79: =IF(5>Assumptions!$B$137,0,IF(SUM(D75:D78)<1000,D70,D71)+IF(5=Assumptions!$B$137,D72,0)) -> 135.19912 | E79: =IF(5>Assumptions!$B$137,0,IF(SUM(E75:E78)<1000,E70,E71)+IF(5=Assumptions!$B$137,E72,0)) -> 114.5948 | F79: =IF(5>Assumptions!$B$137,0,IF(SUM(F75:F78)<1000,F70,F71)+IF(5=Assumptions!$B$137,F72,0)) -> 176.7624 | G79: =IF(5>Assumptions!$B$137,0,IF(SUM(G75:G78)<1000,G70,G71)+IF(5=Assumptions!$B$137,G72,0)) -> 75.92896 | H79: =IF(5>Assumptions!$B$137,0,IF(SUM(H75:H78)<1000,H70,H71)+IF(5=Assumptions!$B$137,H72,0)) -> 115.4538 | I79: =IF(5>Assumptions!$B$137,0,IF(SUM(I75:I78)<1000,I70,I71)+IF(5=Assumptions!$B$137,I72,0)) -> 164.75273 | ... M79: =IF(5>Assumptions!$B$137,0,IF(SUM(M75:M78)<1000,M70,M71)+IF(5=Assumptions!$B$137,M72,0)) -> 0
A80: Year 6 | B80: =IF(6>Assumptions!$B$137,0,IF(SUM(B75:B79)<1000,B70,B71)+IF(6=Assumptions!$B$137,B72,0)) -> 179.5948 | C80: =IF(6>Assumptions!$B$137,0,IF(SUM(C75:C79)<1000,C70,C71)+IF(6=Assumptions!$B$137,C72,0)) -> 85.714286 | D80: =IF(6>Assumptions!$B$137,0,IF(SUM(D75:D79)<1000,D70,D71)+IF(6=Assumptions!$B$137,D72,0)) -> 135.19912 | E80: =IF(6>Assumptions!$B$137,0,IF(SUM(E75:E79)<1000,E70,E71)+IF(6=Assumptions!$B$137,E72,0)) -> 114.5948 | F80: =IF(6>Assumptions!$B$137,0,IF(SUM(F75:F79)<1000,F70,F71)+IF(6=Assumptions!$B$137,F72,0)) -> 176.7624 | G80: =IF(6>Assumptions!$B$137,0,IF(SUM(G75:G79)<1000,G70,G71)+IF(6=Assumptions!$B$137,G72,0)) -> 75.92896 | H80: =IF(6>Assumptions!$B$137,0,IF(SUM(H75:H79)<1000,H70,H71)+IF(6=Assumptions!$B$137,H72,0)) -> 115.4538 | I80: =IF(6>Assumptions!$B$137,0,IF(SUM(I75:I79)<1000,I70,I71)+IF(6=Assumptions!$B$137,I72,0)) -> 164.75273 | ... M80: =IF(6>Assumptions!$B$137,0,IF(SUM(M75:M79)<1000,M70,M71)+IF(6=Assumptions!$B$137,M72,0)) -> 0
A81: Year 7 | B81: =IF(7>Assumptions!$B$137,0,IF(SUM(B75:B80)<1000,B70,B71)+IF(7=Assumptions!$B$137,B72,0)) -> 209.52727 | C81: =IF(7>Assumptions!$B$137,0,IF(SUM(C75:C80)<1000,C70,C71)+IF(7=Assumptions!$B$137,C72,0)) -> 85.714286 | D81: =IF(7>Assumptions!$B$137,0,IF(SUM(D75:D80)<1000,D70,D71)+IF(7=Assumptions!$B$137,D72,0)) -> 187.77656 | E81: =IF(7>Assumptions!$B$137,0,IF(SUM(E75:E80)<1000,E70,E71)+IF(7=Assumptions!$B$137,E72,0)) -> 159.15944 | F81: =IF(7>Assumptions!$B$137,0,IF(SUM(F75:F80)<1000,F70,F71)+IF(7=Assumptions!$B$137,F72,0)) -> 201.28362 | G81: =IF(7>Assumptions!$B$137,0,IF(SUM(G75:G80)<1000,G70,G71)+IF(7=Assumptions!$B$137,G72,0)) -> 105.45689 | H81: =IF(7>Assumptions!$B$137,0,IF(SUM(H75:H80)<1000,H70,H71)+IF(7=Assumptions!$B$137,H72,0)) -> 160.3525 | I81: =IF(7>Assumptions!$B$137,0,IF(SUM(I75:I80)<1000,I70,I71)+IF(7=Assumptions!$B$137,I72,0)) -> 176.97139 | ... M81: =IF(7>Assumptions!$B$137,0,IF(SUM(M75:M80)<1000,M70,M71)+IF(7=Assumptions!$B$137,M72,0)) -> 0
A82: Year 8 | B82: =IF(8>Assumptions!$B$137,0,IF(SUM(B75:B81)<1000,B70,B71)+IF(8=Assumptions!$B$137,B72,0)) -> 0 | C82: =IF(8>Assumptions!$B$137,0,IF(SUM(C75:C81)<1000,C70,C71)+IF(8=Assumptions!$B$137,C72,0)) -> 0 | D82: =IF(8>Assumptions!$B$137,0,IF(SUM(D75:D81)<1000,D70,D71)+IF(8=Assumptions!$B$137,D72,0)) -> 0 | E82: =IF(8>Assumptions!$B$137,0,IF(SUM(E75:E81)<1000,E70,E71)+IF(8=Assumptions!$B$137,E72,0)) -> 0 | F82: =IF(8>Assumptions!$B$137,0,IF(SUM(F75:F81)<1000,F70,F71)+IF(8=Assumptions!$B$137,F72,0)) -> 0 | G82: =IF(8>Assumptions!$B$137,0,IF(SUM(G75:G81)<1000,G70,G71)+IF(8=Assumptions!$B$137,G72,0)) -> 0 | H82: =IF(8>Assumptions!$B$137,0,IF(SUM(H75:H81)<1000,H70,H71)+IF(8=Assumptions!$B$137,H72,0)) -> 0 | I82: =IF(8>Assumptions!$B$137,0,IF(SUM(I75:I81)<1000,I70,I71)+IF(8=Assumptions!$B$137,I72,0)) -> 0 | ... M82: =IF(8>Assumptions!$B$137,0,IF(SUM(M75:M81)<1000,M70,M71)+IF(8=Assumptions!$B$137,M72,0)) -> 0
A83: Year 9 | B83: =IF(9>Assumptions!$B$137,0,IF(SUM(B75:B82)<1000,B70,B71)+IF(9=Assumptions!$B$137,B72,0)) -> 0 | C83: =IF(9>Assumptions!$B$137,0,IF(SUM(C75:C82)<1000,C70,C71)+IF(9=Assumptions!$B$137,C72,0)) -> 0 | D83: =IF(9>Assumptions!$B$137,0,IF(SUM(D75:D82)<1000,D70,D71)+IF(9=Assumptions!$B$137,D72,0)) -> 0 | E83: =IF(9>Assumptions!$B$137,0,IF(SUM(E75:E82)<1000,E70,E71)+IF(9=Assumptions!$B$137,E72,0)) -> 0 | F83: =IF(9>Assumptions!$B$137,0,IF(SUM(F75:F82)<1000,F70,F71)+IF(9=Assumptions!$B$137,F72,0)) -> 0 | G83: =IF(9>Assumptions!$B$137,0,IF(SUM(G75:G82)<1000,G70,G71)+IF(9=Assumptions!$B$137,G72,0)) -> 0 | H83: =IF(9>Assumptions!$B$137,0,IF(SUM(H75:H82)<1000,H70,H71)+IF(9=Assumptions!$B$137,H72,0)) -> 0 | I83: =IF(9>Assumptions!$B$137,0,IF(SUM(I75:I82)<1000,I70,I71)+IF(9=Assumptions!$B$137,I72,0)) -> 0 | ... M83: =IF(9>Assumptions!$B$137,0,IF(SUM(M75:M82)<1000,M70,M71)+IF(9=Assumptions!$B$137,M72,0)) -> 0
A84: Year 10 | B84: =IF(10>Assumptions!$B$137,0,IF(SUM(B75:B83)<1000,B70,B71)+IF(10=Assumptions!$B$137,B72,0)) -> 0 | C84: =IF(10>Assumptions!$B$137,0,IF(SUM(C75:C83)<1000,C70,C71)+IF(10=Assumptions!$B$137,C72,0)) -> 0 | D84: =IF(10>Assumptions!$B$137,0,IF(SUM(D75:D83)<1000,D70,D71)+IF(10=Assumptions!$B$137,D72,0)) -> 0 | E84: =IF(10>Assumptions!$B$137,0,IF(SUM(E75:E83)<1000,E70,E71)+IF(10=Assumptions!$B$137,E72,0)) -> 0 | F84: =IF(10>Assumptions!$B$137,0,IF(SUM(F75:F83)<1000,F70,F71)+IF(10=Assumptions!$B$137,F72,0)) -> 0 | G84: =IF(10>Assumptions!$B$137,0,IF(SUM(G75:G83)<1000,G70,G71)+IF(10=Assumptions!$B$137,G72,0)) -> 0 | H84: =IF(10>Assumptions!$B$137,0,IF(SUM(H75:H83)<1000,H70,H71)+IF(10=Assumptions!$B$137,H72,0)) -> 0 | I84: =IF(10>Assumptions!$B$137,0,IF(SUM(I75:I83)<1000,I70,I71)+IF(10=Assumptions!$B$137,I72,0)) -> 0 | ... M84: =IF(10>Assumptions!$B$137,0,IF(SUM(M75:M83)<1000,M70,M71)+IF(10=Assumptions!$B$137,M72,0)) -> 0
A85: Total received over the payback period | B85: =SUM(B75:B84) -> 1287.0961 | C85: =SUM(C75:C84) -> 600 | D85: =SUM(D75:D84) -> 998.97128 | E85: =SUM(E75:E84) -> 846.72824 | F85: =SUM(F75:F84) -> 1261.858 | G85: =SUM(G75:G84) -> 561.03065 | H85: =SUM(H75:H84) -> 853.0753 | I85: =SUM(I75:I84) -> 1165.4878 | ... M85: =SUM(M75:M84) -> 0 | N85: RM
A86: Money back (share of what was invested) | B86: =B85/1000 -> 1.2870961 | C86: =C85/1000 -> 0.6 | D86: =D85/1000 -> 0.99897128 | E86: =E85/1000 -> 0.84672824 | F86: =F85/1000 -> 1.261858 | G86: =G85/1000 -> 0.56103065 | H86: =H85/1000 -> 0.8530753 | I86: =I85/1000 -> 1.1654878 | ... M86: =M85/1000 -> 0
A87: Loss over the payback period (target: no worse than 50%) | B87: =MAX(0,1-B86) -> 0 | C87: =MAX(0,1-C86) -> 0.4 | D87: =MAX(0,1-D86) -> 0.0010287244 | E87: =MAX(0,1-E86) -> 0.15327176 | F87: =MAX(0,1-F86) -> 0 | G87: =MAX(0,1-G86) -> 0.43896935 | H87: =MAX(0,1-H86) -> 0.1469247 | I87: =MAX(0,1-I86) -> 0 | ... M87: =MAX(0,1-M86) -> 1
A88: Residents' return a year (IRR) | B88: =IFERROR(IRR(B74:B84),-1) -> 0.066187268 | C88: =IFERROR(IRR(C74:C84),-1) -> -0.11351477 | D88: =IFERROR(IRR(D74:D84),-1) -> -0.00024748024 | E88: =IFERROR(IRR(E74:E84),-1) -> -0.038472292 | F88: =IFERROR(IRR(F74:F84),-1) -> 0.060849358 | G88: =IFERROR(IRR(G74:G84),-1) -> -0.12230207 | H88: =IFERROR(IRR(H74:H84),-1) -> -0.036808596 | I88: =IFERROR(IRR(I74:I84),-1) -> 0.039500305 | ... M88: =IFERROR(IRR(M74:M84),-1) -> -1
A89: Year-1 cash return (cash ÷ invested) | B89: =B70/1000 -> 0.1795948 | C89: =C70/1000 -> 0.085714286 | D89: =D70/1000 -> 0.13519912 | E89: =E70/1000 -> 0.1145948 | F89: =F70/1000 -> 0.1767624 | G89: =G70/1000 -> 0.07592896 | H89: =H70/1000 -> 0.1154538 | I89: =I70/1000 -> 0.16475273 | ... M89: =M70/1000 -> 0
A90: Developer, platform and CPO (per charger per year)
A91: Developer net while residents recover (share − top-up) | B91: =(1-Assumptions!$B$135)*B58-B66 -> 0 | C91: =(1-Assumptions!$B$135)*C58-C66 -> -990 | D91: =(1-Assumptions!$B$135)*D58-D66 -> 0 | E91: =(1-Assumptions!$B$135)*E58-E66 -> 0 | F91: =(1-Assumptions!$B$135)*F58-F66 -> -220.04047 | G91: =(1-Assumptions!$B$135)*G58-G66 -> 0 | H91: =(1-Assumptions!$B$135)*H58-H66 -> 0 | I91: =(1-Assumptions!$B$135)*I58-I66 -> -990 | ... K91: =(1-Assumptions!$B$135)*K58-K66 -> 0 | L91: =(1-0)*L58-L66 -> 448.987 | M91: =(1-Assumptions!$B$135)*M58-M66 -> 0 | N91: RM/yr
A92: Developer net after residents recover | B92: =B58-B66 -> 448.987 | C92: =C58-C66 -> -990 | D92: =D58-D66 -> 337.9978 | E92: =E58-E66 -> 286.487 | F92: =F58-F66 -> 147.77783 | G92: =G58-G66 -> 189.8224 | H92: =H58-H66 -> 448.987 | I92: =I58-I66 -> -911.4515 | ... M92: =M58-M66 -> 0 | N92: RM/yr
A93: Platform net while residents recover (share − top-up) | B93: =(1-Assumptions!$B$135)*B59-B67 -> 0 | C93: =(1-Assumptions!$B$135)*C59-C67 -> -990 | D93: =(1-Assumptions!$B$135)*D59-D67 -> 0 | E93: =(1-Assumptions!$B$135)*E59-E67 -> 0 | F93: =(1-Assumptions!$B$135)*F59-F67 -> -220.04047 | G93: =(1-Assumptions!$B$135)*G59-G67 -> 0 | H93: =(1-Assumptions!$B$135)*H59-H67 -> 0 | I93: =(1-Assumptions!$B$135)*I59-I67 -> -990 | ... K93: =(1-Assumptions!$B$135)*K59-K67 -> 0 | L93: =(1-0)*L59-L67 -> 448.987 | M93: =(1-Assumptions!$B$135)*M59-M67 -> 0 | N93: RM/yr
A94: Platform net after residents recover | B94: =B59-B67 -> 448.987 | C94: =C59-C67 -> -990 | D94: =D59-D67 -> 337.9978 | E94: =E59-E67 -> 286.487 | F94: =F59-F67 -> 147.77783 | G94: =G59-G67 -> 189.8224 | H94: =H59-H67 -> 448.987 | I94: =I59-I67 -> -911.4515 | ... M94: =M59-M67 -> 0 | N94: RM/yr
A95: CPO: profit share + service fee − top-up | B95: =B55+Assumptions!$B$115*Assumptions!$B$34*(1+0)+(1-Assumptions!$B$115)*Assumptions!$B$127*(1+0)-B68 -> 10989.87 | C95: =C55+Assumptions!$B$115*Assumptions!$B$34*(1+Scenarios!$C$18)+(1-Assumptions!$B$115)*Assumptions!$B$127*(1+Scenarios!$C$18)-C68 -> 5028.3994 | D95: =D55+Assumptions!$B$115*Assumptions!$B$34*(1+0)+(1-Assumptions!$B$115)*Assumptions!$B$127*(1+0)-D68 -> 9879.978 | E95: =E55+Assumptions!$B$115*Assumptions!$B$34*(1+Scenarios!$C$18)+(1-Assumptions!$B$115)*Assumptions!$B$127*(1+Scenarios!$C$18)-E68 -> 12614.87 | F95: =F55+Assumptions!$B$115*Assumptions!$B$34*(1+0)+(1-Assumptions!$B$115)*Assumptions!$B$127*(1+0)-F68 -> 9951.4746 | G95: =G55+Assumptions!$B$115*Assumptions!$B$34*(1+0)+(1-Assumptions!$B$115)*Assumptions!$B$127*(1+0)-G68 -> 8398.224 | H95: =H55+Assumptions!$B$115*Assumptions!$B$34*(1+0)+(1-Assumptions!$B$115)*Assumptions!$B$127*(1+0)-H68 -> 10989.87 | I95: =I55+Assumptions!$B$115*Assumptions!$B$34*(1+0)+(1-Assumptions!$B$115)*Assumptions!$B$127*(1+0)-I68 -> 6265.485 | J95: =J55+Assumptions!$B$115*Assumptions!$B$34*(1+0)+(1-Assumptions!$B$115)*Assumptions!$B$127*(1+0)-J68 -> 9408.77 | K95: =K55+Assumptions!$B$115*Assumptions!$B$34*(1+0)+(1-Assumptions!$B$115)*Assumptions!$B$127*(1+0)-K68 -> 7329.8 | L95: =L55+Assumptions!$B$115*Assumptions!$B$34*(1+0)+(1-Assumptions!$B$115)*Assumptions!$B$127*(1+0)-L68 -> 10989.87 | M95: =M55+Assumptions!$B$115*Assumptions!$B$34*(1+Scenarios!$C$18)+(1-Assumptions!$B$115)*Assumptions!$B$127*(1+Scenarios!$C$18)-M68 -> 6048.3994 | N95: RM/yr
A96: CPO earns the service fee to cover its own crews and parts; shown for context | B96: ="" | C96: ="" | D96: ="" | E96: ="" | F96: ="" | G96: ="" | H96: ="" | I96: ="" | ... M96: =""
A98: How to read: a charger costs about RM45,000 after the grant; residents fund half and the CPO funds half. Profit is shared 50/50 by funding, then residents' half is split 70/10/10/10.
A99: Normal: the whole charger pays back in about 5 years, so a 7-year resident payback gives a single-digit return. EV is the thinnest pool: keep it small (RM1,000 cap per resident, 1–2 chargers a year).
A100: Top-up: if a charger sells less than 60 kWh/day, the developer (33%), platform (33%) and CPO (34%) pay residents for the missing kWh at the normal contract margin, capped at RM3,000 per charger a year. It does not cover price wars or cost rises.
A101: Losses: payouts never go below zero. Operating losses stay with the asset; a charger that keeps losing money should be moved or switched off by the CPO.
A102: The 'Mall MV demand charge' column assumes each charger adds 10 kW to the mall's peak with no load management. The CPO's load management must prevent this.

Sheet Benefits
A1: 1) Benefits – value created for the developer (customer)
A2: Top: one SDP-size client by its year on the platform. Bottom: all clients together by calendar year.
A4: Benefit | B4: How it is worked out | C4: Year 1 | D4: Year 2 | E4: Year 3 | F4: Year 4 | G4: Year 5
A5: One SDP-size client (by client's year)
A6: A. Cheaper money for solar | B6: Residents' solar money × ((8.5% − 5%) × developer's JV share + JV arrangement fee) | C6: =Pools!C18*((Assumptions!$B$21-Assumptions!$B$19)*Assumptions!$B$14+Assumptions!$B$70) -> 39600 | D6: =Pools!D18*((Assumptions!$B$21-Assumptions!$B$19)*Assumptions!$B$14+Assumptions!$B$70) -> 111633.4 | E6: =Pools!E18*((Assumptions!$B$21-Assumptions!$B$19)*Assumptions!$B$14+Assumptions!$B$70) -> 182175.26 | F6: =Pools!F18*((Assumptions!$B$21-Assumptions!$B$19)*Assumptions!$B$14+Assumptions!$B$70) -> 261302.15 | G6: =Pools!G18*((Assumptions!$B$21-Assumptions!$B$19)*Assumptions!$B$14+Assumptions!$B$70) -> 330145.57
A7: B. Fee from shop upgrades | B7: Shop-years × positive safety margin × developer's share | C7: =Pools!C28*MAX(0,Pools!C31)*Assumptions!$B$28 -> 8415.8974 | D7: =Pools!D28*MAX(0,Pools!D31)*Assumptions!$B$28 -> 30858.291 | E7: =Pools!E28*MAX(0,Pools!E31)*Assumptions!$B$28 -> 50495.384 | F7: =Pools!F28*MAX(0,Pools!F31)*Assumptions!$B$28 -> 53300.684 | G7: =Pools!G28*MAX(0,Pools!G31)*Assumptions!$B$28 -> 42079.487
A8: C. Developer's EV share, less its part of the usage top-up | B8: v3: 10% of residents' EV profit (paid after residents recover) − developer's 33% of any top-up | C8: =Pools!C70-Pools!C71 -> 0 | D8: =Pools!D70-Pools!D71 -> 0 | E8: =Pools!E70-Pools!E71 -> 0 | F8: =Pools!F70-Pools!F71 -> 0 | G8: =Pools!G70-Pools!G71 -> 0
A9: D. Extra mall rent | B9: Money spent at malls × turnover rent | C9: =Pools!C48*Assumptions!$B$10 -> 1286.3148 | D9: =Pools!D48*Assumptions!$B$10 -> 3986.9818 | E9: =Pools!E48*Assumptions!$B$10 -> 6999.4954 | F9: =Pools!F48*Assumptions!$B$10 -> 10379.627 | G9: =Pools!G48*Assumptions!$B$10 -> 13822.198
A10: Cash benefits (A to D, plus F) | C10: =SUM(C6:C9)+C31 -> 53144.65 | D10: =SUM(D6:D9)+D31 -> 158005.98 | E10: =SUM(E6:E9)+E31 -> 260163.14 | F10: =SUM(F6:F9)+F31 -> 357002.77 | G10: =SUM(G6:G9)+G31 -> 430875.69
A11: E. Community-programme saving (actually achieved) | B11: Programme spend × saving rate × share achieved | C11: =Assumptions!$B$13*Yearly_Inputs!$B$8*Assumptions!$B$64 -> 104000 | D11: =Assumptions!$B$13*Yearly_Inputs!$C$8*Assumptions!$B$64 -> 208000 | E11: =Assumptions!$B$13*Yearly_Inputs!$D$8*Assumptions!$B$64 -> 208000 | F11: =Assumptions!$B$13*Yearly_Inputs!$E$8*Assumptions!$B$64 -> 208000 | G11: =Assumptions!$B$13*Yearly_Inputs!$F$8*Assumptions!$B$64 -> 208000
A12: Total benefit for one SDP-size client | C12: =C10+C11 -> 157144.65 | D12: =D10+D11 -> 366005.98 | E12: =E10+E11 -> 468163.14 | F12: =F10+F11 -> 565002.77 | G12: =G10+G11 -> 638875.69
A14: Value to residents and shops (one SDP-size client, not counted in developer ROI)
A15: Residents' profit earned | B15: Payout profit on money invested, after expected shop losses | C15: =Pools!C50 -> 82163.299 | D15: =Pools!D50 -> 237325.4 | E15: =Pools!E50 -> 378613.85 | F15: =Pools!F50 -> 517911.11 | G15: =Pools!G50 -> 636879.55
A16: Savings shops keep | B16: 20% of savings during repayment | C16: =Pools!C32 -> 18000 | D16: =Pools!D32 -> 66000 | E16: =Pools!E32 -> 108000 | F16: =Pools!F32 -> 114000 | G16: =Pools!G32 -> 90000
A17: CO2 avoided (tCO2e) | B17: Solar + upgrades | C17: =Pools!C51 -> 1534.196 | D17: =Pools!D51 -> 4700.3855 | E17: =Pools!E51 -> 8280.1762 | F17: =Pools!F51 -> 12491.575 | G17: =Pools!G51 -> 16920.98
A19: All clients together (by calendar year)
A20: Developer clients on the platform | B20: Cumulative clients signed | C20: =Yearly_Inputs!$B$9 -> 1 | D20: =Yearly_Inputs!$B$9+Yearly_Inputs!$C$9 -> 3 | E20: =Yearly_Inputs!$B$9+Yearly_Inputs!$C$9+Yearly_Inputs!$D$9 -> 5 | F20: =Yearly_Inputs!$B$9+Yearly_Inputs!$C$9+Yearly_Inputs!$D$9+Yearly_Inputs!$E$9 -> 7 | G20: =Yearly_Inputs!$B$9+Yearly_Inputs!$C$9+Yearly_Inputs!$D$9+Yearly_Inputs!$E$9+Yearly_Inputs!$F$9 -> 9
A21: Cash benefits (A to D, plus F), all clients | C21: =Yearly_Inputs!$B$9*Yearly_Inputs!$B$10*C10 -> 53144.65 | D21: =Yearly_Inputs!$B$9*Yearly_Inputs!$B$10*D10+Yearly_Inputs!$C$9*Yearly_Inputs!$C$10*C10 -> 221779.56 | E21: =Yearly_Inputs!$B$9*Yearly_Inputs!$B$10*E10+Yearly_Inputs!$C$9*Yearly_Inputs!$C$10*D10+Yearly_Inputs!$D$9*Yearly_Inputs!$D$10*C10 -> 513543.9 | F21: =Yearly_Inputs!$B$9*Yearly_Inputs!$B$10*F10+Yearly_Inputs!$C$9*Yearly_Inputs!$C$10*E10+Yearly_Inputs!$D$9*Yearly_Inputs!$D$10*D10+Yearly_Inputs!$E$9*Yearly_Inputs!$E$10*C10 -> 922579.3 | G21: =Yearly_Inputs!$B$9*Yearly_Inputs!$B$10*G10+Yearly_Inputs!$C$9*Yearly_Inputs!$C$10*F10+Yearly_Inputs!$D$9*Yearly_Inputs!$D$10*E10+Yearly_Inputs!$E$9*Yearly_Inputs!$E$10*D10+Yearly_Inputs!$F$9*Yearly_Inputs!$F$10*C10 -> 1424855.5
A22: Community-programme saving, all clients | C22: =Yearly_Inputs!$B$9*Yearly_Inputs!$B$10*C11 -> 104000 | D22: =Yearly_Inputs!$B$9*Yearly_Inputs!$B$10*D11+Yearly_Inputs!$C$9*Yearly_Inputs!$C$10*C11 -> 332800 | E22: =Yearly_Inputs!$B$9*Yearly_Inputs!$B$10*E11+Yearly_Inputs!$C$9*Yearly_Inputs!$C$10*D11+Yearly_Inputs!$D$9*Yearly_Inputs!$D$10*C11 -> 582400 | F22: =Yearly_Inputs!$B$9*Yearly_Inputs!$B$10*F11+Yearly_Inputs!$C$9*Yearly_Inputs!$C$10*E11+Yearly_Inputs!$D$9*Yearly_Inputs!$D$10*D11+Yearly_Inputs!$E$9*Yearly_Inputs!$E$10*C11 -> 832000 | G22: =Yearly_Inputs!$B$9*Yearly_Inputs!$B$10*G11+Yearly_Inputs!$C$9*Yearly_Inputs!$C$10*F11+Yearly_Inputs!$D$9*Yearly_Inputs!$D$10*E11+Yearly_Inputs!$E$9*Yearly_Inputs!$E$10*D11+Yearly_Inputs!$F$9*Yearly_Inputs!$F$10*C11 -> 1081600
A23: Total benefits, all clients | C23: =C21+C22 -> 157144.65 | D23: =D21+D22 -> 554579.56 | E23: =E21+E22 -> 1095943.9 | F23: =F21+F22 -> 1754579.3 | G23: =G21+G22 -> 2506455.5
A24: Money raised from residents, all clients | C24: =Yearly_Inputs!$B$9*Yearly_Inputs!$B$10*Pools!C45 -> 3202500 | D24: =Yearly_Inputs!$B$9*Yearly_Inputs!$B$10*Pools!D45+Yearly_Inputs!$C$9*Yearly_Inputs!$C$10*Pools!C45 -> 7268000 | E24: =Yearly_Inputs!$B$9*Yearly_Inputs!$B$10*Pools!E45+Yearly_Inputs!$C$9*Yearly_Inputs!$C$10*Pools!D45+Yearly_Inputs!$D$9*Yearly_Inputs!$D$10*Pools!C45 -> 12038000 | F24: =Yearly_Inputs!$B$9*Yearly_Inputs!$B$10*Pools!F45+Yearly_Inputs!$C$9*Yearly_Inputs!$C$10*Pools!E45+Yearly_Inputs!$D$9*Yearly_Inputs!$D$10*Pools!D45+Yearly_Inputs!$E$9*Yearly_Inputs!$E$10*Pools!C45 -> 17900000 | G24: =Yearly_Inputs!$B$9*Yearly_Inputs!$B$10*Pools!G45+Yearly_Inputs!$C$9*Yearly_Inputs!$C$10*Pools!F45+Yearly_Inputs!$D$9*Yearly_Inputs!$D$10*Pools!E45+Yearly_Inputs!$E$9*Yearly_Inputs!$E$10*Pools!D45+Yearly_Inputs!$F$9*Yearly_Inputs!$F$10*Pools!C45 -> 23954000
A25: Resident investments made, all clients (count) | B25: count | C25: =Yearly_Inputs!$B$9*Yearly_Inputs!$B$10*Pools!C49 -> 6405 | D25: =Yearly_Inputs!$B$9*Yearly_Inputs!$B$10*Pools!D49+Yearly_Inputs!$C$9*Yearly_Inputs!$C$10*Pools!C49 -> 14536 | E25: =Yearly_Inputs!$B$9*Yearly_Inputs!$B$10*Pools!E49+Yearly_Inputs!$C$9*Yearly_Inputs!$C$10*Pools!D49+Yearly_Inputs!$D$9*Yearly_Inputs!$D$10*Pools!C49 -> 24076 | F25: =Yearly_Inputs!$B$9*Yearly_Inputs!$B$10*Pools!F49+Yearly_Inputs!$C$9*Yearly_Inputs!$C$10*Pools!E49+Yearly_Inputs!$D$9*Yearly_Inputs!$D$10*Pools!D49+Yearly_Inputs!$E$9*Yearly_Inputs!$E$10*Pools!C49 -> 35800 | G25: =Yearly_Inputs!$B$9*Yearly_Inputs!$B$10*Pools!G49+Yearly_Inputs!$C$9*Yearly_Inputs!$C$10*Pools!F49+Yearly_Inputs!$D$9*Yearly_Inputs!$D$10*Pools!E49+Yearly_Inputs!$E$9*Yearly_Inputs!$E$10*Pools!D49+Yearly_Inputs!$F$9*Yearly_Inputs!$F$10*Pools!C49 -> 47908
A26: Residents' profit, all clients | C26: =Yearly_Inputs!$B$9*Yearly_Inputs!$B$10*Pools!C50 -> 82163.299 | D26: =Yearly_Inputs!$B$9*Yearly_Inputs!$B$10*Pools!D50+Yearly_Inputs!$C$9*Yearly_Inputs!$C$10*Pools!C50 -> 335921.35 | E26: =Yearly_Inputs!$B$9*Yearly_Inputs!$B$10*Pools!E50+Yearly_Inputs!$C$9*Yearly_Inputs!$C$10*Pools!D50+Yearly_Inputs!$D$9*Yearly_Inputs!$D$10*Pools!C50 -> 762000.28 | F26: =Yearly_Inputs!$B$9*Yearly_Inputs!$B$10*Pools!F50+Yearly_Inputs!$C$9*Yearly_Inputs!$C$10*Pools!E50+Yearly_Inputs!$D$9*Yearly_Inputs!$D$10*Pools!D50+Yearly_Inputs!$E$9*Yearly_Inputs!$E$10*Pools!C50 -> 1355634.2 | G26: =Yearly_Inputs!$B$9*Yearly_Inputs!$B$10*Pools!G50+Yearly_Inputs!$C$9*Yearly_Inputs!$C$10*Pools!F50+Yearly_Inputs!$D$9*Yearly_Inputs!$D$10*Pools!E50+Yearly_Inputs!$E$9*Yearly_Inputs!$E$10*Pools!D50+Yearly_Inputs!$F$9*Yearly_Inputs!$F$10*Pools!C50 -> 2096095.9
A27: CO2 avoided, all clients (tCO2e) | C27: =Yearly_Inputs!$B$9*Yearly_Inputs!$B$10*Pools!C51 -> 1534.196 | D27: =Yearly_Inputs!$B$9*Yearly_Inputs!$B$10*Pools!D51+Yearly_Inputs!$C$9*Yearly_Inputs!$C$10*Pools!C51 -> 6541.4207 | E27: =Yearly_Inputs!$B$9*Yearly_Inputs!$B$10*Pools!E51+Yearly_Inputs!$C$9*Yearly_Inputs!$C$10*Pools!D51+Yearly_Inputs!$D$9*Yearly_Inputs!$D$10*Pools!C51 -> 15761.674 | F27: =Yearly_Inputs!$B$9*Yearly_Inputs!$B$10*Pools!F51+Yearly_Inputs!$C$9*Yearly_Inputs!$C$10*Pools!E51+Yearly_Inputs!$D$9*Yearly_Inputs!$D$10*Pools!D51+Yearly_Inputs!$E$9*Yearly_Inputs!$E$10*Pools!C51 -> 29909.284 | G27: =Yearly_Inputs!$B$9*Yearly_Inputs!$B$10*Pools!G51+Yearly_Inputs!$C$9*Yearly_Inputs!$C$10*Pools!F51+Yearly_Inputs!$D$9*Yearly_Inputs!$D$10*Pools!E51+Yearly_Inputs!$E$9*Yearly_Inputs!$E$10*Pools!D51+Yearly_Inputs!$F$9*Yearly_Inputs!$F$10*Pools!C51 -> 49328.579
A28: Benefit A only counts the residents' share of each solar asset and only the developer's assumed share of the JV. Benefit E is the least certain; v2 guarantees half of it in the contract (see Pricing_Income credit rows).
A30: v2 – Certificates and the community-saving guarantee (one SDP-size client)
A31: F. Renewable energy certificate (REC) sales, developer's share | B31: Residents' share of solar MWh × REC price × USD rate × JV share × (1 − our service fee) | C31: =Pools!C63*Assumptions!$B$78*Assumptions!$B$52*Assumptions!$B$14*(1-Assumptions!$B$79) -> 3842.4375 | D31: =Pools!D63*Assumptions!$B$78*Assumptions!$B$52*Assumptions!$B$14*(1-Assumptions!$B$79) -> 11527.312 | E31: =Pools!E63*Assumptions!$B$78*Assumptions!$B$52*Assumptions!$B$14*(1-Assumptions!$B$79) -> 20493 | F31: =Pools!F63*Assumptions!$B$78*Assumptions!$B$52*Assumptions!$B$14*(1-Assumptions!$B$79) -> 32020.312 | G31: =Pools!G63*Assumptions!$B$78*Assumptions!$B$52*Assumptions!$B$14*(1-Assumptions!$B$79) -> 44828.438
A32: Community saving we guarantee in the contract | B32: Programme spend × saving rate × guaranteed share | C32: =Assumptions!$B$13*Yearly_Inputs!$B$8*Assumptions!$B$65 -> 52000 | D32: =Assumptions!$B$13*Yearly_Inputs!$C$8*Assumptions!$B$65 -> 104000 | E32: =Assumptions!$B$13*Yearly_Inputs!$D$8*Assumptions!$B$65 -> 104000 | F32: =Assumptions!$B$13*Yearly_Inputs!$E$8*Assumptions!$B$65 -> 104000 | G32: =Assumptions!$B$13*Yearly_Inputs!$F$8*Assumptions!$B$65 -> 104000
A33: Shortfall vs guarantee | B33: Guaranteed − achieved (if positive) | C33: =MAX(0,C32-C11) -> 0 | D33: =MAX(0,D32-D11) -> 0 | E33: =MAX(0,E32-E11) -> 0 | F33: =MAX(0,F32-F11) -> 0 | G33: =MAX(0,G32-G11) -> 0

Sheet Pricing_Income
A1: 2) Pricing / Income – what clients pay = what we earn
A2: Top: one client by its year on the platform. Bottom: all clients by calendar year. v2 credits refund part of our fees if the community saving falls short.
A4: Income line | B4: Who pays | C4: Year 1 | D4: Year 2 | E4: Year 3 | F4: Year 4 | G4: Year 5
A5: One client (by client's year). Fixed fees are the same for every client; usage fees scale with client size.
A6: Set-up fee (v2: split into Year 1 and Year 2 instalments) | B6: Developer | C6: =Assumptions!$B$60 -> 20000 | D6: =Assumptions!$B$61 -> 30000 | E6: =0 -> 0 | F6: =0 -> 0 | G6: =0 -> 0
A7: Platform fee (waived in Year 1 pilot; billed monthly) | B7: Developer | C7: =0 -> 0 | D7: =Assumptions!$B$39 -> 72000 | E7: =Assumptions!$B$39 -> 72000 | F7: =Assumptions!$B$39 -> 72000 | G7: =Assumptions!$B$39 -> 72000
A8: Fixed fees | C8: =C6+C7 -> 20000 | D8: =D6+D7 -> 102000 | E8: =E6+E7 -> 72000 | F8: =F6+F7 -> 72000 | G8: =G6+G7 -> 72000
A9: Success fee on money raised (v2: discounted in Year 1) | B9: Developer (from pool) | C9: =Pools!C45*Assumptions!$B$40*(1-Assumptions!$B$62) -> 0 | D9: =Pools!D45*Assumptions!$B$40 -> 25687.5 | E9: =Pools!E45*Assumptions!$B$40 -> 30637.5 | F9: =Pools!F45*Assumptions!$B$40 -> 37837.5 | G9: =Pools!G45*Assumptions!$B$40 -> 37837.5
A10: Fee on money still invested (from Year 2) | B10: Developer (from pool) | C10: =0 -> 0 | D10: =Pools!D46*Assumptions!$B$41 -> 23017.46 | E10: =Pools!E46*Assumptions!$B$41 -> 36895.218 | F10: =Pools!F46*Assumptions!$B$41 -> 50947.876 | G10: =Pools!G46*Assumptions!$B$41 -> 62973.161
A11: Usage fees paid by developer (SDP size) | C11: =C9+C10 -> 0 | D11: =D9+D10 -> 48704.96 | E11: =E9+E10 -> 67532.718 | F11: =F9+F10 -> 88785.376 | G11: =G9+G10 -> 100810.66
A12: Fee on mall redemptions (SDP size) | B12: Mall shops | C12: =Pools!C48*Assumptions!$B$42 -> 2572.6295 | D12: =Pools!D48*Assumptions!$B$42 -> 7973.9637 | E12: =Pools!E48*Assumptions!$B$42 -> 13998.991 | F12: =Pools!F48*Assumptions!$B$42 -> 20759.254 | G12: =Pools!G48*Assumptions!$B$42 -> 27644.395
A13: SDP pays us (fixed + usage − guarantee credit) | C13: =C8+C11-C25 -> 20000 | D13: =D8+D11-D25 -> 150704.96 | E13: =E8+E11-E25 -> 139532.72 | F13: =F8+F11-F25 -> 160785.38 | G13: =G8+G11-G25 -> 172810.66
A15: All clients (by calendar year)
A16: Fixed fees (set-up + platform, pro rata to client size) | B16: Developers | C16: =Yearly_Inputs!$B$9*Yearly_Inputs!$B$10*C8 -> 20000 | D16: =Yearly_Inputs!$B$9*Yearly_Inputs!$B$10*D8+Yearly_Inputs!$C$9*Yearly_Inputs!$C$10*C8 -> 126000 | E16: =Yearly_Inputs!$B$9*Yearly_Inputs!$B$10*E8+Yearly_Inputs!$C$9*Yearly_Inputs!$C$10*D8+Yearly_Inputs!$D$9*Yearly_Inputs!$D$10*C8 -> 218400 | F16: =Yearly_Inputs!$B$9*Yearly_Inputs!$B$10*F8+Yearly_Inputs!$C$9*Yearly_Inputs!$C$10*E8+Yearly_Inputs!$D$9*Yearly_Inputs!$D$10*D8+Yearly_Inputs!$E$9*Yearly_Inputs!$E$10*C8 -> 304800 | G16: =Yearly_Inputs!$B$9*Yearly_Inputs!$B$10*G8+Yearly_Inputs!$C$9*Yearly_Inputs!$C$10*F8+Yearly_Inputs!$D$9*Yearly_Inputs!$D$10*E8+Yearly_Inputs!$E$9*Yearly_Inputs!$E$10*D8+Yearly_Inputs!$F$9*Yearly_Inputs!$F$10*C8 -> 391200
A17: Usage fees (success + invested money) | B17: Developers | C17: =Yearly_Inputs!$B$9*Yearly_Inputs!$B$10*C11 -> 0 | D17: =Yearly_Inputs!$B$9*Yearly_Inputs!$B$10*D11+Yearly_Inputs!$C$9*Yearly_Inputs!$C$10*C11 -> 48704.96 | E17: =Yearly_Inputs!$B$9*Yearly_Inputs!$B$10*E11+Yearly_Inputs!$C$9*Yearly_Inputs!$C$10*D11+Yearly_Inputs!$D$9*Yearly_Inputs!$D$10*C11 -> 125978.67 | F17: =Yearly_Inputs!$B$9*Yearly_Inputs!$B$10*F11+Yearly_Inputs!$C$9*Yearly_Inputs!$C$10*E11+Yearly_Inputs!$D$9*Yearly_Inputs!$D$10*D11+Yearly_Inputs!$E$9*Yearly_Inputs!$E$10*C11 -> 228270.59 | G17: =Yearly_Inputs!$B$9*Yearly_Inputs!$B$10*G11+Yearly_Inputs!$C$9*Yearly_Inputs!$C$10*F11+Yearly_Inputs!$D$9*Yearly_Inputs!$D$10*E11+Yearly_Inputs!$E$9*Yearly_Inputs!$E$10*D11+Yearly_Inputs!$F$9*Yearly_Inputs!$F$10*C11 -> 346838.33
A18: Paid by developers (after guarantee credits) | C18: =C16+C17-C37 -> 20000 | D18: =D16+D17-D37 -> 174704.96 | E18: =E16+E17-E37 -> 344378.67 | F18: =F16+F17-F37 -> 533070.59 | G18: =G16+G17-G37 -> 738038.33
A19: Redemption fees | B19: Mall shops | C19: =Yearly_Inputs!$B$9*Yearly_Inputs!$B$10*C12 -> 2572.6295 | D19: =Yearly_Inputs!$B$9*Yearly_Inputs!$B$10*D12+Yearly_Inputs!$C$9*Yearly_Inputs!$C$10*C12 -> 11061.119 | E19: =Yearly_Inputs!$B$9*Yearly_Inputs!$B$10*E12+Yearly_Inputs!$C$9*Yearly_Inputs!$C$10*D12+Yearly_Inputs!$D$9*Yearly_Inputs!$D$10*C12 -> 26654.903 | F19: =Yearly_Inputs!$B$9*Yearly_Inputs!$B$10*F12+Yearly_Inputs!$C$9*Yearly_Inputs!$C$10*E12+Yearly_Inputs!$D$9*Yearly_Inputs!$D$10*D12+Yearly_Inputs!$E$9*Yearly_Inputs!$E$10*C12 -> 50213.955 | G19: =Yearly_Inputs!$B$9*Yearly_Inputs!$B$10*G12+Yearly_Inputs!$C$9*Yearly_Inputs!$C$10*F12+Yearly_Inputs!$D$9*Yearly_Inputs!$D$10*E12+Yearly_Inputs!$E$9*Yearly_Inputs!$E$10*D12+Yearly_Inputs!$F$9*Yearly_Inputs!$F$10*C12 -> 82010.201
A20: Total income (incl. v2 and v3 income lines) | C20: =C18+C19+C38+C39+C40+C46 -> 39926.505 | D20: =D18+D19+D38+D39+D40+D46 -> 249652.35 | E20: =E18+E19+E38+E39+E40+E46 -> 499086.17 | F20: =F18+F19+F38+F39+F40+F46 -> 782063.57 | G20: =G18+G19+G38+G39+G40+G46 -> 1087212.6
A23: v2 – Guarantee credits and new income lines (one client, by client's year)
A24: Credit cap (share of that year's developer fees) | C24: =Assumptions!$B$67 -> 1 | D24: =Assumptions!$B$68 -> 0.25 | E24: =Assumptions!$B$68 -> 0.25 | F24: =Assumptions!$B$68 -> 0.25 | G24: =Assumptions!$B$68 -> 0.25
A25: Guarantee credit to an SDP-size client | B25: Credit to developer | C25: =MIN(Assumptions!$B$66*Benefits!C33,C24*(C8+C11)) -> 0 | D25: =MIN(Assumptions!$B$66*Benefits!D33,D24*(D8+D11)) -> 0 | E25: =MIN(Assumptions!$B$66*Benefits!E33,E24*(E8+E11)) -> 0 | F25: =MIN(Assumptions!$B$66*Benefits!F33,F24*(F8+F11)) -> 0 | G25: =MIN(Assumptions!$B$66*Benefits!G33,G24*(G8+G11)) -> 0
A26: Guarantee credit to a typical new client | B26: Credit to developer | C26: =MIN(Assumptions!$B$66*Yearly_Inputs!$C$10*Benefits!C33,C24*Yearly_Inputs!$C$10*(C8+C11)) -> 0 | D26: =MIN(Assumptions!$B$66*Yearly_Inputs!$C$10*Benefits!D33,D24*Yearly_Inputs!$C$10*(D8+D11)) -> 0 | E26: =MIN(Assumptions!$B$66*Yearly_Inputs!$C$10*Benefits!E33,E24*Yearly_Inputs!$C$10*(E8+E11)) -> 0 | F26: =MIN(Assumptions!$B$66*Yearly_Inputs!$C$10*Benefits!F33,F24*Yearly_Inputs!$C$10*(F8+F11)) -> 0 | G26: =MIN(Assumptions!$B$66*Yearly_Inputs!$C$10*Benefits!G33,G24*Yearly_Inputs!$C$10*(G8+G11)) -> 0
A27: Featured offers in rewards catalogue (SDP size) | B27: Mall shops | C27: =Assumptions!$B$80*Assumptions!$B$81*12*Pools!C9 -> 12000 | D27: =Assumptions!$B$80*Assumptions!$B$81*12*Pools!D9 -> 24000 | E27: =Assumptions!$B$80*Assumptions!$B$81*12*Pools!E9 -> 24000 | F27: =Assumptions!$B$80*Assumptions!$B$81*12*Pools!F9 -> 24000 | G27: =Assumptions!$B$80*Assumptions!$B$81*12*Pools!G9 -> 24000
A28: Energy dashboard subscriptions (SDP size) | B28: Upgraded shops | C28: =Pools!C28*Assumptions!$B$82*12 -> 4500 | D28: =Pools!D28*Assumptions!$B$82*12 -> 16500 | E28: =Pools!E28*Assumptions!$B$82*12 -> 27000 | F28: =Pools!F28*Assumptions!$B$82*12 -> 28500 | G28: =Pools!G28*Assumptions!$B$82*12 -> 22500
A29: REC registration and sales service (SDP size) | B29: From REC proceeds | C29: =Pools!C63*Assumptions!$B$78*Assumptions!$B$52*Assumptions!$B$79 -> 853.875 | D29: =Pools!D63*Assumptions!$B$78*Assumptions!$B$52*Assumptions!$B$79 -> 2561.625 | E29: =Pools!E63*Assumptions!$B$78*Assumptions!$B$52*Assumptions!$B$79 -> 4554 | F29: =Pools!F63*Assumptions!$B$78*Assumptions!$B$52*Assumptions!$B$79 -> 7115.625 | G29: =Pools!G63*Assumptions!$B$78*Assumptions!$B$52*Assumptions!$B$79 -> 9961.875
A31: v2 – All clients (by calendar year)
A32: Guarantee credits – clients signed in Y1 | B32: Credit to developers | C32: =Yearly_Inputs!$B$9*MIN(Assumptions!$B$66*Yearly_Inputs!$B$10*Benefits!C33,C24*Yearly_Inputs!$B$10*(C8+C11)) -> 0 | D32: =Yearly_Inputs!$B$9*MIN(Assumptions!$B$66*Yearly_Inputs!$B$10*Benefits!D33,D24*Yearly_Inputs!$B$10*(D8+D11)) -> 0 | E32: =Yearly_Inputs!$B$9*MIN(Assumptions!$B$66*Yearly_Inputs!$B$10*Benefits!E33,E24*Yearly_Inputs!$B$10*(E8+E11)) -> 0 | F32: =Yearly_Inputs!$B$9*MIN(Assumptions!$B$66*Yearly_Inputs!$B$10*Benefits!F33,F24*Yearly_Inputs!$B$10*(F8+F11)) -> 0 | G32: =Yearly_Inputs!$B$9*MIN(Assumptions!$B$66*Yearly_Inputs!$B$10*Benefits!G33,G24*Yearly_Inputs!$B$10*(G8+G11)) -> 0
A33: Guarantee credits – clients signed in Y2 | B33: Credit to developers | C33: =0 -> 0 | D33: =Yearly_Inputs!$C$9*MIN(Assumptions!$B$66*Yearly_Inputs!$C$10*Benefits!C33,C24*Yearly_Inputs!$C$10*(C8+C11)) -> 0 | E33: =Yearly_Inputs!$C$9*MIN(Assumptions!$B$66*Yearly_Inputs!$C$10*Benefits!D33,D24*Yearly_Inputs!$C$10*(D8+D11)) -> 0 | F33: =Yearly_Inputs!$C$9*MIN(Assumptions!$B$66*Yearly_Inputs!$C$10*Benefits!E33,E24*Yearly_Inputs!$C$10*(E8+E11)) -> 0 | G33: =Yearly_Inputs!$C$9*MIN(Assumptions!$B$66*Yearly_Inputs!$C$10*Benefits!F33,F24*Yearly_Inputs!$C$10*(F8+F11)) -> 0
A34: Guarantee credits – clients signed in Y3 | B34: Credit to developers | C34: =0 -> 0 | D34: =0 -> 0 | E34: =Yearly_Inputs!$D$9*MIN(Assumptions!$B$66*Yearly_Inputs!$D$10*Benefits!C33,C24*Yearly_Inputs!$D$10*(C8+C11)) -> 0 | F34: =Yearly_Inputs!$D$9*MIN(Assumptions!$B$66*Yearly_Inputs!$D$10*Benefits!D33,D24*Yearly_Inputs!$D$10*(D8+D11)) -> 0 | G34: =Yearly_Inputs!$D$9*MIN(Assumptions!$B$66*Yearly_Inputs!$D$10*Benefits!E33,E24*Yearly_Inputs!$D$10*(E8+E11)) -> 0
A35: Guarantee credits – clients signed in Y4 | B35: Credit to developers | C35: =0 -> 0 | D35: =0 -> 0 | E35: =0 -> 0 | F35: =Yearly_Inputs!$E$9*MIN(Assumptions!$B$66*Yearly_Inputs!$E$10*Benefits!C33,C24*Yearly_Inputs!$E$10*(C8+C11)) -> 0 | G35: =Yearly_Inputs!$E$9*MIN(Assumptions!$B$66*Yearly_Inputs!$E$10*Benefits!D33,D24*Yearly_Inputs!$E$10*(D8+D11)) -> 0
A36: Guarantee credits – clients signed in Y5 | B36: Credit to developers | C36: =0 -> 0 | D36: =0 -> 0 | E36: =0 -> 0 | F36: =0 -> 0 | G36: =Yearly_Inputs!$F$9*MIN(Assumptions!$B$66*Yearly_Inputs!$F$10*Benefits!C33,C24*Yearly_Inputs!$F$10*(C8+C11)) -> 0
A37: Guarantee credits, all clients | B37: Credit to developers | C37: =SUM(C32:C36) -> 0 | D37: =SUM(D32:D36) -> 0 | E37: =SUM(E32:E36) -> 0 | F37: =SUM(F32:F36) -> 0 | G37: =SUM(G32:G36) -> 0
A38: Featured offers, all clients | B38: Mall shops | C38: =Yearly_Inputs!$B$9*Yearly_Inputs!$B$10*C27 -> 12000 | D38: =Yearly_Inputs!$B$9*Yearly_Inputs!$B$10*D27+Yearly_Inputs!$C$9*Yearly_Inputs!$C$10*C27 -> 38400 | E38: =Yearly_Inputs!$B$9*Yearly_Inputs!$B$10*E27+Yearly_Inputs!$C$9*Yearly_Inputs!$C$10*D27+Yearly_Inputs!$D$9*Yearly_Inputs!$D$10*C27 -> 67200 | F38: =Yearly_Inputs!$B$9*Yearly_Inputs!$B$10*F27+Yearly_Inputs!$C$9*Yearly_Inputs!$C$10*E27+Yearly_Inputs!$D$9*Yearly_Inputs!$D$10*D27+Yearly_Inputs!$E$9*Yearly_Inputs!$E$10*C27 -> 96000 | G38: =Yearly_Inputs!$B$9*Yearly_Inputs!$B$10*G27+Yearly_Inputs!$C$9*Yearly_Inputs!$C$10*F27+Yearly_Inputs!$D$9*Yearly_Inputs!$D$10*E27+Yearly_Inputs!$E$9*Yearly_Inputs!$E$10*D27+Yearly_Inputs!$F$9*Yearly_Inputs!$F$10*C27 -> 124800
A39: Energy dashboards, all clients | B39: Upgraded shops | C39: =Yearly_Inputs!$B$9*Yearly_Inputs!$B$10*C28 -> 4500 | D39: =Yearly_Inputs!$B$9*Yearly_Inputs!$B$10*D28+Yearly_Inputs!$C$9*Yearly_Inputs!$C$10*C28 -> 21900 | E39: =Yearly_Inputs!$B$9*Yearly_Inputs!$B$10*E28+Yearly_Inputs!$C$9*Yearly_Inputs!$C$10*D28+Yearly_Inputs!$D$9*Yearly_Inputs!$D$10*C28 -> 52200 | F39: =Yearly_Inputs!$B$9*Yearly_Inputs!$B$10*F28+Yearly_Inputs!$C$9*Yearly_Inputs!$C$10*E28+Yearly_Inputs!$D$9*Yearly_Inputs!$D$10*D28+Yearly_Inputs!$E$9*Yearly_Inputs!$E$10*C28 -> 86100 | G39: =Yearly_Inputs!$B$9*Yearly_Inputs!$B$10*G28+Yearly_Inputs!$C$9*Yearly_Inputs!$C$10*F28+Yearly_Inputs!$D$9*Yearly_Inputs!$D$10*E28+Yearly_Inputs!$E$9*Yearly_Inputs!$E$10*D28+Yearly_Inputs!$F$9*Yearly_Inputs!$F$10*C28 -> 114300
A40: REC service fees, all clients | B40: From REC proceeds | C40: =Yearly_Inputs!$B$9*Yearly_Inputs!$B$10*C29 -> 853.875 | D40: =Yearly_Inputs!$B$9*Yearly_Inputs!$B$10*D29+Yearly_Inputs!$C$9*Yearly_Inputs!$C$10*C29 -> 3586.275 | E40: =Yearly_Inputs!$B$9*Yearly_Inputs!$B$10*E29+Yearly_Inputs!$C$9*Yearly_Inputs!$C$10*D29+Yearly_Inputs!$D$9*Yearly_Inputs!$D$10*C29 -> 8652.6 | F40: =Yearly_Inputs!$B$9*Yearly_Inputs!$B$10*F29+Yearly_Inputs!$C$9*Yearly_Inputs!$C$10*E29+Yearly_Inputs!$D$9*Yearly_Inputs!$D$10*D29+Yearly_Inputs!$E$9*Yearly_Inputs!$E$10*C29 -> 16679.025 | G40: =Yearly_Inputs!$B$9*Yearly_Inputs!$B$10*G29+Yearly_Inputs!$C$9*Yearly_Inputs!$C$10*F29+Yearly_Inputs!$D$9*Yearly_Inputs!$D$10*E29+Yearly_Inputs!$E$9*Yearly_Inputs!$E$10*D29+Yearly_Inputs!$F$9*Yearly_Inputs!$F$10*C29 -> 28064.025
A42: v3 – EV: our 10% share and our part of the usage top-up
A43: EV: our 10% share of residents' charging profit (SDP size; after residents recover) | B43: From EV pool | C43: =Pools!C72 -> 0 | D43: =Pools!D72 -> 0 | E43: =Pools!E72 -> 0 | F43: =Pools!F72 -> 0 | G43: =Pools!G72 -> 0
A44: EV: our 33% part of the usage top-up (cost, SDP size) | B44: We pay | C44: =-Pools!C73 -> 0 | D44: =-Pools!D73 -> 0 | E44: =-Pools!E73 -> 0 | F44: =-Pools!F73 -> 0 | G44: =-Pools!G73 -> 0
A45: EV: net (SDP size) | C45: =C43+C44 -> 0 | D45: =D43+D44 -> 0 | E45: =E43+E44 -> 0 | F45: =F43+F44 -> 0 | G45: =G43+G44 -> 0
A46: EV: net, all clients (can be negative) | C46: =Yearly_Inputs!$B$9*Yearly_Inputs!$B$10*C45 -> 0 | D46: =Yearly_Inputs!$B$9*Yearly_Inputs!$B$10*D45+Yearly_Inputs!$C$9*Yearly_Inputs!$C$10*C45 -> 0 | E46: =Yearly_Inputs!$B$9*Yearly_Inputs!$B$10*E45+Yearly_Inputs!$C$9*Yearly_Inputs!$C$10*D45+Yearly_Inputs!$D$9*Yearly_Inputs!$D$10*C45 -> 0 | F46: =Yearly_Inputs!$B$9*Yearly_Inputs!$B$10*F45+Yearly_Inputs!$C$9*Yearly_Inputs!$C$10*E45+Yearly_Inputs!$D$9*Yearly_Inputs!$D$10*D45+Yearly_Inputs!$E$9*Yearly_Inputs!$E$10*C45 -> 0 | G46: =Yearly_Inputs!$B$9*Yearly_Inputs!$B$10*G45+Yearly_Inputs!$C$9*Yearly_Inputs!$C$10*F45+Yearly_Inputs!$D$9*Yearly_Inputs!$D$10*E45+Yearly_Inputs!$E$9*Yearly_Inputs!$E$10*D45+Yearly_Inputs!$F$9*Yearly_Inputs!$F$10*C45 -> 0

Sheet Customer_ROI
A1: Does the customer make money from Year 1?
A2: Developer's benefit minus what the developer pays us (after any guarantee credit). Shops' fees are not counted (shops pay them).
A4: Item | C4: Year 1 | D4: Year 2 | E4: Year 3 | F4: Year 4 | G4: Year 5
A5: Sime Darby Property (first client, full size)
A6: Total benefit | C6: =Benefits!C12 -> 157144.65 | D6: =Benefits!D12 -> 366005.98 | E6: =Benefits!E12 -> 468163.14 | F6: =Benefits!F12 -> 565002.77 | G6: =Benefits!G12 -> 638875.69
A7: Paid to us (after guarantee credit) | C7: =Pricing_Income!C13 -> 20000 | D7: =Pricing_Income!D13 -> 150704.96 | E7: =Pricing_Income!E13 -> 139532.72 | F7: =Pricing_Income!F13 -> 160785.38 | G7: =Pricing_Income!G13 -> 172810.66
A8: Net gain | C8: =C6-C7 -> 137144.65 | D8: =D6-D7 -> 215301.02 | E8: =E6-E7 -> 328630.42 | F8: =F6-F7 -> 404217.4 | G8: =G6-G7 -> 466065.03
A9: Cumulative net gain | C9: =C8 -> 137144.65 | D9: =C9+D8 -> 352445.67 | E9: =D9+E8 -> 681076.1 | F9: =E9+F8 -> 1085293.5 | G9: =F9+G8 -> 1551358.5
A10: Net gain WITHOUT community-programme saving (cash only, after any credit) | C10: =Benefits!C10-C7 -> 33144.65 | D10: =Benefits!D10-D7 -> 7301.0224 | E10: =Benefits!E10-E7 -> 120630.42 | F10: =Benefits!F10-F7 -> 196217.4 | G10: =Benefits!G10-G7 -> 258065.03
A11: Return on what SDP pays (benefit ÷ paid) | C11: =IF(C7<=0,"n/a",C6/C7) -> 7.8572325 | D11: =IF(D7<=0,"n/a",D6/D7) -> 2.428626 | E11: =IF(E7<=0,"n/a",E6/E7) -> 3.3552213 | F11: =IF(F7<=0,"n/a",F6/F7) -> 3.5140184 | G11: =IF(G7<=0,"n/a",G6/G7) -> 3.6969692
A13: A typical new developer (smaller client)
A14: Total benefit | C14: =Benefits!C12*Yearly_Inputs!$C$10 -> 94286.79 | D14: =Benefits!D12*Yearly_Inputs!$C$10 -> 219603.59 | E14: =Benefits!E12*Yearly_Inputs!$C$10 -> 280897.89 | F14: =Benefits!F12*Yearly_Inputs!$C$10 -> 339001.66 | G14: =Benefits!G12*Yearly_Inputs!$C$10 -> 383325.42
A15: Paid to us (after guarantee credit) | C15: =(Pricing_Income!C8+Pricing_Income!C11)*Yearly_Inputs!$C$10-Pricing_Income!C26 -> 12000 | D15: =(Pricing_Income!D8+Pricing_Income!D11)*Yearly_Inputs!$C$10-Pricing_Income!D26 -> 90422.976 | E15: =(Pricing_Income!E8+Pricing_Income!E11)*Yearly_Inputs!$C$10-Pricing_Income!E26 -> 83719.631 | F15: =(Pricing_Income!F8+Pricing_Income!F11)*Yearly_Inputs!$C$10-Pricing_Income!F26 -> 96471.225 | G15: =(Pricing_Income!G8+Pricing_Income!G11)*Yearly_Inputs!$C$10-Pricing_Income!G26 -> 103686.4
A16: Net gain | C16: =C14-C15 -> 82286.79 | D16: =D14-D15 -> 129180.61 | E16: =E14-E15 -> 197178.25 | F16: =F14-F15 -> 242530.44 | G16: =G14-G15 -> 279639.02
A17: Net gain WITHOUT community-programme saving (cash only, after any credit) | C17: =Benefits!C10*Yearly_Inputs!$C$10-C15 -> 19886.79 | D17: =Benefits!D10*Yearly_Inputs!$C$10-D15 -> 4380.6135 | E17: =Benefits!E10*Yearly_Inputs!$C$10-E15 -> 72378.254 | F17: =Benefits!F10*Yearly_Inputs!$C$10-F15 -> 117730.44 | G17: =Benefits!G10*Yearly_Inputs!$C$10-G15 -> 154839.02
A19: Checks
A20: SDP gains in Year 1? | C20: =IF(C8>0,"YES","NO") -> YES
A21: New developer gains in its Year 1? | C21: =IF(C16>0,"YES","NO") -> YES
A23: v2 – Contract view and extra checks
A24: Guarantee credit SDP receives | C24: =Pricing_Income!C25 -> 0 | D24: =Pricing_Income!D25 -> 0 | E24: =Pricing_Income!E25 -> 0 | F24: =Pricing_Income!F25 -> 0 | G24: =Pricing_Income!G25 -> 0
A25: Net gain if community saving only reaches the guaranteed level | C25: =Benefits!C10+MIN(Benefits!C11,Benefits!C32)-C7 -> 85144.65 | D25: =Benefits!D10+MIN(Benefits!D11,Benefits!D32)-D7 -> 111301.02 | E25: =Benefits!E10+MIN(Benefits!E11,Benefits!E32)-E7 -> 224630.42 | F25: =Benefits!F10+MIN(Benefits!F11,Benefits!F32)-F7 -> 300217.4 | G25: =Benefits!G10+MIN(Benefits!G11,Benefits!G32)-G7 -> 362065.03
A26: Guarantee credit a new client receives | C26: =Pricing_Income!C26 -> 0 | D26: =Pricing_Income!D26 -> 0 | E26: =Pricing_Income!E26 -> 0 | F26: =Pricing_Income!F26 -> 0 | G26: =Pricing_Income!G26 -> 0
A27: SDP cash-only net gain > 0 in Year 1? | C27: =IF(C10>0,"YES","NO") -> YES
A28: New developer cash-only net gain > 0 in its Year 1? | C28: =IF(C17>0,"YES","NO") -> YES

Sheet Investor_ROI
A1: Investor_ROI – what one resident gets in Year 1, per RM1,000 invested
A2: Normal uses Assumptions; Conservative uses the Scenarios sheet. Money is held by a licensed platform, never by us. Payouts are monthly.
A4: Item | B4: Normal | C4: Conservative | D4: Note
A5: Pool 1 – Rooftop solar (low risk): fixed payout backed by tenant power payments, not roof leasing
A6: Contract payout rate | B6: =Assumptions!$B$19 -> 0.05 | C6: =Assumptions!$B$19 -> 0.05
A7: Minimum payout rate (floor, backed by JV saving) | B7: =Assumptions!$B$71 -> 0.045 | C7: =Assumptions!$B$71 -> 0.045
A8: Rate paid in Year 1 | B8: =MAX(B6,B7) -> 0.05 | C8: =MAX(C6,C7) -> 0.05
A9: Average share of money still invested in first 12 months | B9: =(1+((1+Assumptions!$B$19)^Assumptions!$B$20-(1+Assumptions!$B$19))/((1+Assumptions!$B$19)^Assumptions!$B$20-1))/2 -> 0.9095126 | C9: =(1+((1+Assumptions!$B$19)^Assumptions!$B$20-(1+Assumptions!$B$19))/((1+Assumptions!$B$19)^Assumptions!$B$20-1))/2 -> 0.9095126 | D9: Money is paid back monthly, so less is invested by year end.
A10: Year-1 profit per RM1,000 | B10: =1000*B8*B9 -> 45.47563 | C10: =1000*C8*C9 -> 45.47563
A11: Year-1 return | B11: =B10/1000 -> 0.04547563 | C11: =C10/1000 -> 0.04547563
A12: Solar cover: tenant power payments ÷ payouts to residents | B12: =(Assumptions!$B$17*1000*Assumptions!$B$89*(1-Assumptions!$B$90)*(1-Assumptions!$B$93)-Assumptions!$B$16*1000*(Assumptions!$B$91+Assumptions!$B$92))/(Assumptions!$B$16*1000*Assumptions!$B$18*PMT(Assumptions!$B$19,Assumptions!$B$20,-1)) -> 1.63325 | C12: =(Assumptions!$B$17*1000*Assumptions!$B$89*(1-Assumptions!$B$90)*(1-Assumptions!$B$93)-Assumptions!$B$16*1000*(Assumptions!$B$91+Assumptions!$B$92))/(Assumptions!$B$16*1000*Scenarios!$C$23*PMT(Assumptions!$B$19,Assumptions!$B$20,-1)) -> 2.449875 | D12: Above 1.3x is comfortable. Per MW, first year.
A14: Pool 2 – Shop energy upgrades (medium risk)
A15: Contract payout rate | B15: =Assumptions!$B$26 -> 0.065 | C15: =Assumptions!$B$26 -> 0.065
A16: Average share of money still invested in first 12 months | B16: =(1+((1+Assumptions!$B$26)^Assumptions!$B$27-(1+Assumptions!$B$26))/((1+Assumptions!$B$26)^Assumptions!$B$27-1))/2 -> 0.84371215 | C16: =(1+((1+Assumptions!$B$26)^Assumptions!$B$27-(1+Assumptions!$B$26))/((1+Assumptions!$B$26)^Assumptions!$B$27-1))/2 -> 0.84371215
A17: Year-1 profit per RM1,000 before losses | B17: =1000*B15*B16 -> 54.84129 | C17: =1000*C15*C16 -> 54.84129
A18: Repayment counted per shop-month (higher of actual or guaranteed saving × 80%) | B18: =MAX(Assumptions!$B$24,Assumptions!$B$72)*Assumptions!$B$25 -> 800 | C18: =MAX(Scenarios!$C$7,Assumptions!$B$72)*Assumptions!$B$25 -> 640 | D18: Installer guarantees a minimum saving.
A19: Payout due per shop-year | B19: =PMT(Assumptions!$B$26/12,Assumptions!$B$27*12,-Assumptions!$B$23)*12 -> 7355.7607 | C19: =PMT(Assumptions!$B$26/12,Assumptions!$B$27*12,-Assumptions!$B$23)*12 -> 7355.7607
A20: Safety margin per shop-year | B20: =B18*12-B19 -> 2244.2393 | C20: =C18*12-C19 -> 324.23931
A21: Bad-debt reserve per shop-year | B21: =MAX(0,B20)*(1-Assumptions!$B$28) -> 1122.1197 | C21: =MAX(0,C20)*(1-Assumptions!$B$28) -> 162.11965
A22: Expected default loss per shop-year | B22: =Assumptions!$B$23*Assumptions!$B$73*Assumptions!$B$74 -> 200 | C22: =Assumptions!$B$23*Scenarios!$C$13*Assumptions!$B$74 -> 1000
A23: Uncovered loss per RM1,000 | B23: =(MAX(0,B22-B21)+MAX(0,-B20))/Assumptions!$B$23*1000 -> 0 | C23: =(MAX(0,C22-C21)+MAX(0,-C20))/Assumptions!$B$23*1000 -> 41.894017
A24: Year-1 profit per RM1,000 after expected losses | B24: =B17-B23 -> 54.84129 | C24: =C17-C23 -> 12.947272
A25: Year-1 return | B25: =B24/1000 -> 0.05484129 | C25: =C24/1000 -> 0.012947272
A27: Pool 3 – EV charging (high risk, not capital-guaranteed; CPO partner runs the chargers)
A28: kWh sold per charger per day (after downtime) | B28: =EV_Pilot!B9 -> 60 | C28: =EV_Pilot!C9 -> 27
A29: Usage top-up per charger per year (after cap) | B29: =EV_Pilot!B65 -> 0 | C29: =EV_Pilot!C65 -> 3000 | D29: Developer 33%, platform 33%, CPO 34%; cap RM3,000.
A30: EV payback period | B30: =Assumptions!$B$137 -> 7 | C30: =Assumptions!$B$137 -> 7 | D30: v3: 5 → 7 years.
A31: Cash per RM1,000 a year WITHOUT top-up (while recovering money) | B31: =EV_Pilot!B56/EV_Pilot!B53*1000 -> 179.5948 | C31: =EV_Pilot!C56/EV_Pilot!C53*1000 -> 0 | D31: Shown for transparency.
A32: Cash per RM1,000 a year WITH top-up (while recovering money) | B32: =EV_Pilot!B70 -> 179.5948 | C32: =EV_Pilot!C70 -> 85.714286
A33: Year-1 profit per RM1,000 (cash − money paid back) | B33: =B32-1000/B30 -> 36.737657 | C33: =C32-1000/C30 -> -57.142857
A34: Year-1 return | B34: =B33/1000 -> 0.036737657 | C34: =C33/1000 -> -0.057142857
A35: Money back over the payback period (share of RM invested) | B35: =EV_Pilot!B86 -> 1.2870961 | C35: =EV_Pilot!C86 -> 0.6
A36: Loss over the payback period (if any) | B36: =MAX(0,1-B35) -> 0 | C36: =MAX(0,1-C35) -> 0.4
A37: Money back without the protection (B: no deferral; C: no top-up) | B37: =EV_Pilot!L86 -> 1.0476363 | C37: =EV_Pilot!M86 -> 0 | D37: Shows what the v3 protections are worth.
A39: Checks
A40: Solar Year-1 return > 0? | B40: =IF(B11>0,"YES","NO") -> YES | C40: =IF(C11>0,"YES","NO") -> YES
A41: Upgrades Year-1 return > 0? | B41: =IF(B25>0,"YES","NO") -> YES | C41: =IF(C25>0,"YES","NO") -> YES
A42: EV loss over the payback period no worse than 50%? | B42: =IF(B36<=0.5,"YES","NO") -> YES | C42: =IF(C36<=0.5,"YES","NO") -> YES
A44: 5-year view per example investment (used on Summary)
A45: Example investment | B45: =Assumptions!$B$95 -> 1000 | C45: =Assumptions!$B$95 -> 1000
A46: Solar: total received over tenure | B46: =PMT(Assumptions!$B$19/12,Assumptions!$B$20*12,-Assumptions!$B$95)*Assumptions!$B$20*12 -> 1132.274 | C46: =PMT(Assumptions!$B$19/12,Assumptions!$B$20*12,-Assumptions!$B$95)*Assumptions!$B$20*12 -> 1132.274
A47: Solar: 5-year profit | B47: =B46-B45 -> 132.27402 | C47: =C46-C45 -> 132.27402
A48: Upgrades: share still owed after year 1 | B48: =((1+Assumptions!$B$26)^Assumptions!$B$27-(1+Assumptions!$B$26))/((1+Assumptions!$B$26)^Assumptions!$B$27-1) -> 0.6874243 | C48: =((1+Assumptions!$B$26)^Assumptions!$B$27-(1+Assumptions!$B$26))/((1+Assumptions!$B$26)^Assumptions!$B$27-1) -> 0.6874243
A49: Upgrades: share still owed after year 2 | B49: =MAX(0,((1+Assumptions!$B$26)^Assumptions!$B$27-(1+Assumptions!$B$26)^2)/((1+Assumptions!$B$26)^Assumptions!$B$27-1)) -> 0.35453118 | C49: =MAX(0,((1+Assumptions!$B$26)^Assumptions!$B$27-(1+Assumptions!$B$26)^2)/((1+Assumptions!$B$26)^Assumptions!$B$27-1)) -> 0.35453118
A50: Upgrades: total received over tenure | B50: =PMT(Assumptions!$B$26/12,Assumptions!$B$27*12,-Assumptions!$B$95)*Assumptions!$B$27*12 -> 1103.3641 | C50: =PMT(Assumptions!$B$26/12,Assumptions!$B$27*12,-Assumptions!$B$95)*Assumptions!$B$27*12 -> 1103.3641
A51: Upgrades: expected uncovered loss over tenure | B51: =MAX(0,B45*Assumptions!$B$73*Assumptions!$B$74*(0.5+B48+B49)-B45/Assumptions!$B$23*B21*Assumptions!$B$27)+MAX(0,-B20)/Assumptions!$B$23*B45*Assumptions!$B$27 -> 0 | C51: =MAX(0,C45*Scenarios!$C$13*Assumptions!$B$74*(0.5+C48+C49)-C45/Assumptions!$B$23*C21*Assumptions!$B$27)+MAX(0,-C20)/Assumptions!$B$23*C45*Assumptions!$B$27 -> 52.779825 | D51: Defaults on money still owed, after the bad-debt reserve.
A52: Upgrades: 5-year profit after expected losses | B52: =B50-B45-B51 -> 103.3641 | C52: =C50-C45-C51 -> 50.584278
A53: Upgrades: rate after expected losses | B53: =RATE(Assumptions!$B$27*12,(B50-B51)/(Assumptions!$B$27*12),-B45)*12 -> 0.065 | C53: =RATE(Assumptions!$B$27*12,(C50-C51)/(Assumptions!$B$27*12),-C45)*12 -> 0.032304876
A54: EV: cash received in Year 1 (with top-up) | B54: =B32*B45/1000 -> 179.5948 | C54: =C32*C45/1000 -> 85.714286
A55: EV: total received over the payback period (7 years) | B55: =EV_Pilot!B85*B45/1000 -> 1287.0961 | C55: =EV_Pilot!C85*C45/1000 -> 600
A56: EV: profit / (loss) over the payback period | B56: =B55-B45 -> 287.09607 | C56: =C55-C45 -> -400
A57: EV: expected rate (IRR, from EV_Pilot) | B57: =EV_Pilot!B88 -> 0.066187268 | C57: =EV_Pilot!C88 -> -0.11351477 | D57: Variable, not guaranteed.

Sheet Spendings
A1: 3) Spendings – our own cost to build and run the platform (calendar year)
A2: Lean team; cloud cost grows with each client. v2: part of Year 1 pay taken as equity.
A4: Cost line | B4: How it is worked out | C4: Year 1 | D4: Year 2 | E4: Year 3 | F4: Year 4 | G4: Year 5
A5: Clients on the platform | B5: From Benefits | C5: =Benefits!C20 -> 1 | D5: =Benefits!D20 -> 3 | E5: =Benefits!E20 -> 5 | F5: =Benefits!F20 -> 7 | G5: =Benefits!G20 -> 9
A6: Founders' pay (cash) | B6: People × salary × 12 × (1 + on-cost); Year 1 × cash share | C6: =Assumptions!$B$44*Assumptions!$B$45*12*(1+Assumptions!$B$46)*Assumptions!$B$84 -> 55176 | D6: =Assumptions!$B$44*Assumptions!$B$45*12*(1+Assumptions!$B$46) -> 110352 | E6: =Assumptions!$B$44*Assumptions!$B$45*12*(1+Assumptions!$B$46) -> 110352 | F6: =Assumptions!$B$44*Assumptions!$B$45*12*(1+Assumptions!$B$46) -> 110352 | G6: =Assumptions!$B$44*Assumptions!$B$45*12*(1+Assumptions!$B$46) -> 110352
A7: Contract developer (build Year 1, cash part) | B7: Months × monthly rate × cash share | C7: =Assumptions!$B$47*Assumptions!$B$48*Assumptions!$B$85 -> 29400 | D7: =0 -> 0 | E7: =0 -> 0 | F7: =0 -> 0 | G7: =0 -> 0
A8: Extra developers | B8: People × pay × 12 × (1 + on-cost) | C8: =Yearly_Inputs!$B$11*Assumptions!$B$48*12*(1+Assumptions!$B$46) -> 0 | D8: =Yearly_Inputs!$C$11*Assumptions!$B$48*12*(1+Assumptions!$B$46) -> 0 | E8: =Yearly_Inputs!$D$11*Assumptions!$B$48*12*(1+Assumptions!$B$46) -> 96558 | F8: =Yearly_Inputs!$E$11*Assumptions!$B$48*12*(1+Assumptions!$B$46) -> 96558 | G8: =Yearly_Inputs!$F$11*Assumptions!$B$48*12*(1+Assumptions!$B$46) -> 193116
A9: Part-time support and operations | B9: From Yearly_Inputs | C9: =Yearly_Inputs!$B$12 -> 0 | D9: =Yearly_Inputs!$C$12 -> 18000 | E9: =Yearly_Inputs!$D$12 -> 36000 | F9: =Yearly_Inputs!$E$12 -> 36000 | G9: =Yearly_Inputs!$F$12 -> 48000
A10: Cloud (Supabase + Vercel) | B10: (Clients × Supabase + seats × Vercel) × 12 × USD rate | C10: =(C5*Assumptions!$B$49+Assumptions!$B$51*Assumptions!$B$50)*12*Assumptions!$B$52 -> 3432 | D10: =(D5*Assumptions!$B$49+Assumptions!$B$51*Assumptions!$B$50)*12*Assumptions!$B$52 -> 6072 | E10: =(E5*Assumptions!$B$49+Assumptions!$B$51*Assumptions!$B$50)*12*Assumptions!$B$52 -> 8712 | F10: =(F5*Assumptions!$B$49+Assumptions!$B$51*Assumptions!$B$50)*12*Assumptions!$B$52 -> 11352 | G10: =(G5*Assumptions!$B$49+Assumptions!$B$51*Assumptions!$B$50)*12*Assumptions!$B$52 -> 13992
A11: Security testing | B11: Year 1 full test, then yearly retest | C11: =Assumptions!$B$53 -> 15000 | D11: =Assumptions!$B$54 -> 8000 | E11: =Assumptions!$B$54 -> 8000 | F11: =Assumptions!$B$54 -> 8000 | G11: =Assumptions!$B$54 -> 8000
A12: Legal, PDPA and partner agreements | B12: Year 1 set-up, then yearly | C12: =Assumptions!$B$55 -> 15000 | D12: =Assumptions!$B$56 -> 5000 | E12: =Assumptions!$B$56 -> 5000 | F12: =Assumptions!$B$56 -> 5000 | G12: =Assumptions!$B$56 -> 5000
A13: Sales and onboarding | B13: New clients × cost per client (standardised from Year 2) | C13: =Yearly_Inputs!$B$9*Assumptions!$B$57 -> 8000 | D13: =Yearly_Inputs!$C$9*Assumptions!$B$86 -> 10000 | E13: =Yearly_Inputs!$D$9*Assumptions!$B$86 -> 10000 | F13: =Yearly_Inputs!$E$9*Assumptions!$B$86 -> 10000 | G13: =Yearly_Inputs!$F$9*Assumptions!$B$86 -> 10000
A14: Total spend | C14: =SUM(C6:C13) -> 126008 | D14: =SUM(D6:D13) -> 157424 | E14: =SUM(E6:E13) -> 274622 | F14: =SUM(F6:F13) -> 277262 | G14: =SUM(G6:G13) -> 388460
A16: v2 – Non-cash pay taken as equity (not in total spend)
A17: Founders' pay taken as equity | B17: Year 1 salary × (1 − cash share) | C17: =Assumptions!$B$44*Assumptions!$B$45*12*(1-Assumptions!$B$84) -> 48000 | D17: =0 -> 0 | E17: =0 -> 0 | F17: =0 -> 0 | G17: =0 -> 0
A18: Contract pay taken as equity | B18: Contract pay × (1 − cash share) | C18: =Assumptions!$B$47*Assumptions!$B$48*(1-Assumptions!$B$85) -> 12600 | D18: =0 -> 0 | E18: =0 -> 0 | F18: =0 -> 0 | G18: =0 -> 0

Sheet ROI
A1: ROI – year by year and 5-year summary (calendar years, all clients)
A4: Item | C4: Y1 | D4: Y2 | E4: Y3 | F4: Y4 | G4: Y5 | H4: 5-year total
A5: Developer clients | C5: =Benefits!C20 -> 1 | D5: =Benefits!D20 -> 3 | E5: =Benefits!E20 -> 5 | F5: =Benefits!F20 -> 7 | G5: =Benefits!G20 -> 9
A6: Total benefits for developers | C6: =Benefits!C23 -> 157144.65 | D6: =Benefits!D23 -> 554579.56 | E6: =Benefits!E23 -> 1095943.9 | F6: =Benefits!F23 -> 1754579.3 | G6: =Benefits!G23 -> 2506455.5 | H6: =SUM(C6:G6) -> 6068703
A7: Paid by developers to us (after credits) | C7: =Pricing_Income!C18 -> 20000 | D7: =Pricing_Income!D18 -> 174704.96 | E7: =Pricing_Income!E18 -> 344378.67 | F7: =Pricing_Income!F18 -> 533070.59 | G7: =Pricing_Income!G18 -> 738038.33 | H7: =SUM(C7:G7) -> 1810192.5
A8: Our total income (incl. shop and REC fees) | C8: =Pricing_Income!C20 -> 39926.505 | D8: =Pricing_Income!D20 -> 249652.35 | E8: =Pricing_Income!E20 -> 499086.17 | F8: =Pricing_Income!F20 -> 782063.57 | G8: =Pricing_Income!G20 -> 1087212.6 | H8: =SUM(C8:G8) -> 2657941.2
A9: Our total spend | C9: =Spendings!C14 -> 126008 | D9: =Spendings!D14 -> 157424 | E9: =Spendings!E14 -> 274622 | F9: =Spendings!F14 -> 277262 | G9: =Spendings!G14 -> 388460 | H9: =SUM(C9:G9) -> 1223776
A10: Our net profit / (loss) | C10: =C8-C9 -> -86081.495 | D10: =D8-D9 -> 92228.355 | E10: =E8-E9 -> 224464.17 | F10: =F8-F9 -> 504801.57 | G10: =G8-G9 -> 698752.55 | H10: =SUM(C10:G10) -> 1434165.2
A11: Our cumulative net | C11: =C10 -> -86081.495 | D11: =C11+D10 -> 6146.8591 | E11: =D11+E10 -> 230611.03 | F11: =E11+F10 -> 735412.6 | G11: =F11+G10 -> 1434165.2
A12: Our profit margin | C12: =IF(C8<=0,"n/a",C10/C8) -> -2.1559988 | D12: =IF(D8<=0,"n/a",D10/D8) -> 0.36942714 | E12: =IF(E8<=0,"n/a",E10/E8) -> 0.44975033 | F12: =IF(F8<=0,"n/a",F10/F8) -> 0.64547383 | G12: =IF(G8<=0,"n/a",G10/G8) -> 0.64270096
A13: Developers' net gain (benefit − paid) | C13: =C6-C7 -> 137144.65 | D13: =D6-D7 -> 379874.6 | E13: =E6-E7 -> 751565.23 | F13: =F6-F7 -> 1221508.7 | G13: =G6-G7 -> 1768417.2 | H13: =SUM(C13:G13) -> 4258510.4
A15: 5-year summary
A16: Our ROI = (income − spend) ÷ spend | C16: =(H8-H9)/H9 -> 1.171918 | D16: Our return on every RM spent over 5 years.
A17: Developer ROI = (benefit − paid) ÷ paid | C17: =(H6-H7)/H7 -> 2.3525179 | D17: What developers get back for every RM paid to us.
A18: First profitable year | C18: =IF(C10>0,"Y1",IF(D10>0,"Y2",IF(E10>0,"Y3",IF(F10>0,"Y4",IF(G10>0,"Y5","Not in 5 yrs"))))) -> Y2
A19: Year cumulative net turns positive | C19: =IF(C11>0,"Y1",IF(D11>0,"Y2",IF(E11>0,"Y3",IF(F11>0,"Y4",IF(G11>0,"Y5","Not in 5 yrs"))))) -> Y2
A20: Target: we lose money in Y1? | C20: =IF(C10<0,"YES","NO") -> YES
A21: Target: we make money from Y2? | C21: =IF(AND(D10>0,E10>0,F10>0,G10>0),"YES","NO") -> YES
A22: Target: SDP gains in its Y1? | C22: =Customer_ROI!C20 -> YES
A24: Net present value (NPV) of our cash flows
A25: Year | C25: Net cash flow | D25: Discount factor | E25: Present value
A26: Y1 | C26: =C10 -> -86081.495 | D26: =1/(1+Assumptions!$B$58)^1 -> 0.86956522 | E26: =C26*D26 -> -74853.474
A27: Y2 | C27: =D10 -> 92228.355 | D27: =1/(1+Assumptions!$B$58)^2 -> 0.75614367 | E27: =C27*D27 -> 69737.886
A28: Y3 | C28: =E10 -> 224464.17 | D28: =1/(1+Assumptions!$B$58)^3 -> 0.65751623 | E28: =C28*D28 -> 147588.84
A29: Y4 | C29: =F10 -> 504801.57 | D29: =1/(1+Assumptions!$B$58)^4 -> 0.57175325 | E29: =C29*D29 -> 288621.94
A30: Y5 | C30: =G10 -> 698752.55 | D30: =1/(1+Assumptions!$B$58)^5 -> 0.49717674 | E30: =C30*D30 -> 347403.51
A31: NPV | E31: =SUM(E26:E30) -> 778498.7
A33: NPV brings each year's profit or loss back to today's value using the discount rate on Assumptions (Scenarios for the conservative copy).
A35: v2 – Cash plan (grant covers the Year 1 loss)
A36: Grant / pre-seed funding received | C36: =Assumptions!$B$87 -> 120000 | D36: =0 -> 0 | E36: =0 -> 0 | F36: =0 -> 0 | G36: =0 -> 0 | H36: =SUM(C36:G36) -> 120000
A37: Cash balance at year end | C37: =C10+C36 -> 33918.505 | D37: =C37+D10+D36 -> 126146.86 | E37: =D37+E10+E36 -> 350611.03 | F37: =E37+F10+F36 -> 855412.6 | G37: =F37+G10+G36 -> 1554165.2
A38: Cash stays positive in all 5 years? | C38: =IF(MIN(C37:G37)>=0,"YES","NO") -> YES
A39: Developers' NPV of net gain (all clients) | C39: =NPV(Assumptions!$B$58,C13:G13) -> 2478279.8 | D39: Same discount rate as our NPV.

Sheet Conservative_Test
A1: Conservative_Test – do the three targets hold under stress?
A2: Normal = original sheets. Conservative = C_ sheets, driven by the Scenarios sheet. Every number is a live formula.
A4: Stressed input | B4: Normal | C4: Conservative
A5: Community saving actually achieved | B5: =Scenarios!B5 -> 1 | C5: =Scenarios!C5 -> 0
A6: EV energy sold per charger per day (kWh) = sessions × kWh per session | B6: =Scenarios!B6 -> 60 | C6: =Scenarios!C6 -> 30
A7: Bill saving per shop (RM/month) | B7: =Scenarios!B7 -> 1000 | C7: =Scenarios!C7 -> 500
A8: New developer clients signed in Year 2 | B8: =Scenarios!B8 -> 2 | C8: =Scenarios!C8 -> 1
A9: Developer's share of solar funding saving | B9: =Scenarios!B9 -> 0.5 | C9: =Scenarios!C9 -> 0.3
A10: Discount rate for NPV | B10: =Scenarios!B10 -> 0.15 | C10: =Scenarios!C10 -> 0.2
A11: Competitor price drop (all charging prices) | B11: =Scenarios!B11 -> 0 | C11: =Scenarios!C11 -> 0.2
A12: Size of new clients vs SDP (Years 2–5) | B12: =Scenarios!B12 -> 0.6 | C12: =Scenarios!C12 -> 0.4
A13: Shop default rate (a year) | B13: =Scenarios!B13 -> 0.02 | C13: =Scenarios!C13 -> 0.1
A14: Extra developers hired in Year 3 (our response, not a stress) | B14: =Scenarios!B14 -> 1 | C14: =Scenarios!C14 -> 0
A15: v3 EV: charging sessions per charger per day | B15: =Scenarios!B15 -> 2 | C15: =Scenarios!C15 -> 1.5
A16: v3 EV: average kWh per session | B16: =Scenarios!B16 -> 30 | C16: =Scenarios!C16 -> 20
... A23: v3 Solar: residents' share of each solar asset | B23: =Scenarios!B23 -> 0.3 | C23: =Scenarios!C23 -> 0.2
A25: Check | B25: Normal | C25: Conservative | D25: Target | E25: Pass (normal) | F25: Pass (conservative)
A26: 1. Customer (SDP) net gain, Year 1 | B26: =Customer_ROI!C8 -> 137144.65 | C26: =C_Customer_ROI!C8 -> 22856.606 | D26: >0 | E26: =IF(B26>0,"PASS","FAIL") -> PASS | F26: =IF(C26>0,"PASS","FAIL") -> PASS
A27: 2. Customer cash-only net gain, Year 1 (no community saving) | B27: =Customer_ROI!C10 -> 33144.65 | C27: =C_Customer_ROI!C10 -> 22856.606 | D27: >0 | E27: =IF(B27>0,"PASS","FAIL") -> PASS | F27: =IF(C27>0,"PASS","FAIL") -> PASS
A28: 2b. New developer net gain, its Year 1 | B28: =Customer_ROI!C16 -> 82286.79 | C28: =C_Customer_ROI!C16 -> 9142.6423 | D28: >0 | E28: =IF(B28>0,"PASS","FAIL") -> PASS | F28: =IF(C28>0,"PASS","FAIL") -> PASS
A29: 3. Residents' profit, Year 1 (all pools, SDP) | B29: =Pools!C50 -> 82163.299 | C29: =C_Pools!C50 -> 50465.897 | D29: >0 | E29: =IF(B29>0,"PASS","FAIL") -> PASS | F29: =IF(C29>0,"PASS","FAIL") -> PASS
A30: 4a. Solar investor return, Year 1 | B30: =Investor_ROI!B11 -> 0.04547563 | C30: =Investor_ROI!C11 -> 0.04547563 | D30: >0 | E30: =IF(B30>0,"PASS","FAIL") -> PASS | F30: =IF(C30>0,"PASS","FAIL") -> PASS
A31: 4b. Upgrade investor return, Year 1 | B31: =Investor_ROI!B25 -> 0.05484129 | C31: =Investor_ROI!C25 -> 0.012947272 | D31: >0 | E31: =IF(B31>0,"PASS","FAIL") -> PASS | F31: =IF(C31>0,"PASS","FAIL") -> PASS
A32: 4c. EV investor loss over the 7-year payback period | B32: =Investor_ROI!B36 -> 0 | C32: =Investor_ROI!C36 -> 0.4 | D32: <=50% | E32: =IF(B32<=0.5,"PASS","FAIL") -> PASS | F32: =IF(C32<=0.5,"PASS","FAIL") -> PASS
A33: 5. Our net profit, Year 2 | B33: =ROI!D10 -> 92228.355 | C33: =C_ROI!D10 -> 5033.9555 | D33: >0 | E33: =IF(B33>0,"PASS","FAIL") -> PASS | F33: =IF(C33>0,"PASS","FAIL") -> PASS
A34: 6. Our net profit, 5 years | B34: =ROI!H10 -> 1434165.2 | C34: =C_ROI!H10 -> 131171.91 | D34: >0 | E34: =IF(B34>0,"PASS","FAIL") -> PASS | F34: =IF(C34>0,"PASS","FAIL") -> PASS
A35: 7. NPV of our cash flows | B35: =ROI!E31 -> 778498.7 | C35: =C_ROI!E31 -> 22817.907 | D35: >0 | E35: =IF(B35>0,"PASS","FAIL") -> PASS | F35: =IF(C35>0,"PASS","FAIL") -> PASS
A36: 8. Lowest cash balance in 5 years (with grant) | B36: =MIN(ROI!C37:G37) -> 33918.505 | C36: =MIN(C_ROI!C37:G37) -> 12403.716 | D36: >=0 | E36: =IF(B36>=0,"PASS","FAIL") -> PASS | F36: =IF(C36>=0,"PASS","FAIL") -> PASS
A37: 9. Our lowest yearly net profit, Years 2–5 | B37: =MIN(ROI!D10:G10) -> 92228.355 | C37: =MIN(C_ROI!D10:G10) -> 5033.9555 | D37: >0 | E37: =IF(B37>0,"PASS","FAIL") -> PASS | F37: =IF(C37>0,"PASS","FAIL") -> PASS
A38: All checks pass? | E38: =IF(COUNTIF(E26:E37,"FAIL")=0,"ALL PASS","SOME FAIL") -> ALL PASS | F38: =IF(COUNTIF(F26:F37,"FAIL")=0,"ALL PASS","SOME FAIL") -> ALL PASS
A40: Minimum changes that make the conservative case pass (already built into v2 inputs):
A41: • Year 1: set-up fee RM20,000 only; success fee waived; platform fee waived (Assumptions rows 38–40, 60–62).
A42: • Community saving made contractual: we guarantee 50% of the expected saving and credit back 50% of any shortfall (cap 100% of fees in Year 1, 25% later).
A43: • JV passes a 1% a year arrangement fee to the developer on residents' solar money (row 70).
A44: • Shop upgrades need an installer contract with a minimum-savings clause (RM800 a month) (row 72).
A45: • v3 EV: partners top up to 60 kWh/day (developer 33%, platform 33%, CPO 34%), capped at RM3,000 per charger a year (Assumptions rows 75–76, 138–140).
A46: • v3 EV: developer and platform 10% shares wait until residents recover their money (row 135); without this the normal EV return is about 1% a year.
A47: • v3 EV: start with 1–2 chargers a year and an RM1,000 cap per resident, so a weak EV pool cannot hurt the customer or vendor targets.
A48: • New shop-paid income: featured offers and energy dashboards; REC service fee. None is paid by the developer.
A49: • Our Year 1 cost: founders take half pay in cash, contract developer 70% cash; a RM120,000 grant covers the Year 1 loss (RM100,000 leaves conservative cash slightly negative).
A50: • Clients: sign letters of intent in Year 1 so at least one new client starts in Year 2 (two is the safety margin).
A51: • If only one new client signs in Year 2, delay the Year 3 developer hire by a year (Scenarios row 14).
A52: • Fixed fees are pro rata to client size, so smaller developers are not priced out.

Sheet Dashboard
A1: Township Green Loop – 5-Year Financial Projection
A2: Charts link to ROI, C_ROI and Customer_ROI and update when inputs change.
A3: Year | B3: Our income | C3: Our spend | D3: Our cumulative net | E3: SDP benefit | F3: SDP pays us | G3: Our net (normal) | H3: Our net (conservative)
A4: Y1 | B4: =ROI!C8 -> 39926.505 | C4: =ROI!C9 -> 126008 | D4: =ROI!C11 -> -86081.495 | E4: =Customer_ROI!C6 -> 157144.65 | F4: =Customer_ROI!C7 -> 20000 | G4: =ROI!C10 -> -86081.495 | H4: =C_ROI!C10 -> -107596.28
A5: Y2 | B5: =ROI!D8 -> 249652.35 | C5: =ROI!D9 -> 157424 | D5: =ROI!D11 -> 6146.8591 | E5: =Customer_ROI!D6 -> 366005.98 | F5: =Customer_ROI!D7 -> 150704.96 | G5: =ROI!D10 -> 92228.355 | H5: =C_ROI!D10 -> 5033.9555
A6: Y3 | B6: =ROI!E8 -> 499086.17 | C6: =ROI!E9 -> 274622 | D6: =ROI!E11 -> 230611.03 | E6: =Customer_ROI!E6 -> 468163.14 | F6: =Customer_ROI!E7 -> 139532.72 | G6: =ROI!E10 -> 224464.17 | H6: =C_ROI!E10 -> 47108.152
A7: Y4 | B7: =ROI!F8 -> 782063.57 | C7: =ROI!F9 -> 277262 | D7: =ROI!F11 -> 735412.6 | E7: =Customer_ROI!F6 -> 565002.77 | F7: =Customer_ROI!F7 -> 160785.38 | G7: =ROI!F10 -> 504801.57 | H7: =C_ROI!F10 -> 83647.022
A8: Y5 | B8: =ROI!G8 -> 1087212.6 | C8: =ROI!G9 -> 388460 | D8: =ROI!G11 -> 1434165.2 | E8: =Customer_ROI!G6 -> 638875.69 | F8: =Customer_ROI!G7 -> 172810.66 | G8: =ROI!G10 -> 698752.55 | H8: =C_ROI!G10 -> 102979.07

Sheet C_Pools
A1: Pools – what happens inside one client (SDP size), by the client's year on the platform – CONSERVATIVE scenario (inputs from Scenarios sheet)
A2: Money raised from residents, money still invested, payouts and impact for the three pools. Other clients are scaled from this.
A4: Item | B4: Unit | C4: Year 1 | D4: Year 2 | E4: Year 3 | F4: Year 4 | G4: Year 5
A5: Timing factors (money is raised mid-year on average)
A6: Year since money was raised | C6: 1 | D6: 2 | E6: 3 | F6: 4 | G6: 5
A7: Solar: share of money still owed at year end | C7: =((1+Assumptions!$B$19)^Assumptions!$B$20-(1+Assumptions!$B$19)^C6)/((1+Assumptions!$B$19)^Assumptions!$B$20-1) -> 0.8190252 | D7: =((1+Assumptions!$B$19)^Assumptions!$B$20-(1+Assumptions!$B$19)^D6)/((1+Assumptions!$B$19)^Assumptions!$B$20-1) -> 0.62900166 | E7: =((1+Assumptions!$B$19)^Assumptions!$B$20-(1+Assumptions!$B$19)^E6)/((1+Assumptions!$B$19)^Assumptions!$B$20-1) -> 0.42947695 | F7: =((1+Assumptions!$B$19)^Assumptions!$B$20-(1+Assumptions!$B$19)^F6)/((1+Assumptions!$B$19)^Assumptions!$B$20-1) -> 0.219976 | G7: =((1+Assumptions!$B$19)^Assumptions!$B$20-(1+Assumptions!$B$19)^G6)/((1+Assumptions!$B$19)^Assumptions!$B$20-1) -> 0
A8: Solar: average share still invested | C8: =0.5 -> 0.5 | D8: =(1+C7)/2 -> 0.9095126 | E8: =(C7+D7)/2 -> 0.72401343 | F8: =(D7+E7)/2 -> 0.52923931 | G8: =(E7+F7)/2 -> 0.32472647
A9: Payout timing (half year in first year) | C9: =0.5 -> 0.5 | D9: =1 -> 1 | E9: =1 -> 1 | F9: =1 -> 1 | G9: =1 -> 1
A10: Upgrades: share still owed at year end | C10: =MAX(0,((1+Assumptions!$B$26)^Assumptions!$B$27-(1+Assumptions!$B$26)^C6)/((1+Assumptions!$B$26)^Assumptions!$B$27-1)) -> 0.6874243 | D10: =MAX(0,((1+Assumptions!$B$26)^Assumptions!$B$27-(1+Assumptions!$B$26)^D6)/((1+Assumptions!$B$26)^Assumptions!$B$27-1)) -> 0.35453118 | E10: =MAX(0,((1+Assumptions!$B$26)^Assumptions!$B$27-(1+Assumptions!$B$26)^E6)/((1+Assumptions!$B$26)^Assumptions!$B$27-1)) -> 0 | F10: =MAX(0,((1+Assumptions!$B$26)^Assumptions!$B$27-(1+Assumptions!$B$26)^F6)/((1+Assumptions!$B$26)^Assumptions!$B$27-1)) -> 0 | G10: =MAX(0,((1+Assumptions!$B$26)^Assumptions!$B$27-(1+Assumptions!$B$26)^G6)/((1+Assumptions!$B$26)^Assumptions!$B$27-1)) -> 0
A11: Upgrades: average share still invested | C11: =0.5 -> 0.5 | D11: =(1+C10)/2 -> 0.84371215 | E11: =(C10+D10)/2 -> 0.52097774 | F11: =(D10+E10)/2 -> 0.17726559 | G11: =(E10+F10)/2 -> 0
A12: Upgrades: share of year a shop is repaying | C12: =0.5 -> 0.5 | D12: =1 -> 1 | E12: =1 -> 1 | F12: =0.5 -> 0.5 | G12: =0 -> 0
A13: EV: average share still invested (paid back evenly over the EV payback period) | C13: =0.5*(1+(1-0.5/Assumptions!$B$137))/2 -> 0.48214286 | D13: =MAX(0,1-1/Assumptions!$B$137) -> 0.85714286 | E13: =MAX(0,1-2/Assumptions!$B$137) -> 0.71428571 | F13: =MAX(0,1-3/Assumptions!$B$137) -> 0.57142857 | G13: =MAX(0,1-4/Assumptions!$B$137) -> 0.42857143
A14: EV: share of money paid back in the year | C14: =0.5/Assumptions!$B$137 -> 0.071428571 | D14: =IF(2-0.5<=Assumptions!$B$137,1/Assumptions!$B$137,0) -> 0.14285714 | E14: =IF(3-0.5<=Assumptions!$B$137,1/Assumptions!$B$137,0) -> 0.14285714 | F14: =IF(4-0.5<=Assumptions!$B$137,1/Assumptions!$B$137,0) -> 0.14285714 | G14: =IF(5-0.5<=Assumptions!$B$137,1/Assumptions!$B$137,0) -> 0.14285714
A15: Pool 1 – Rooftop solar
A16: New solar capacity with resident share | B16: MW | C16: =Yearly_Inputs!$B$5 -> 3 | D16: =Yearly_Inputs!$C$5 -> 3 | E16: =Yearly_Inputs!$D$5 -> 4 | F16: =Yearly_Inputs!$E$5 -> 5 | G16: =Yearly_Inputs!$F$5 -> 5
A17: Money raised from residents | B17: RM | C17: =C16*1000*Assumptions!$B$16*Scenarios!$C$23 -> 1920000 | D17: =D16*1000*Assumptions!$B$16*Scenarios!$C$23 -> 1920000 | E17: =E16*1000*Assumptions!$B$16*Scenarios!$C$23 -> 2560000 | F17: =F16*1000*Assumptions!$B$16*Scenarios!$C$23 -> 3200000 | G17: =G16*1000*Assumptions!$B$16*Scenarios!$C$23 -> 3200000
A18: Residents' money still invested (average) | B18: RM | C18: =C17*C8 -> 960000 | D18: =C17*D8+D17*C8 -> 2706264.2 | E18: =C17*E8+D17*D8+E17*C8 -> 4416370 | F18: =C17*F8+D17*E8+E17*D8+F17*C8 -> 6334597.5 | G18: =C17*G8+D17*F8+E17*E8+F17*D8+G17*C8 -> 8003529
A19: Yearly payment per RM1 raised | B19: factor | C19: =PMT(Assumptions!$B$19,Assumptions!$B$20,-1) -> 0.2309748 | D19: =PMT(Assumptions!$B$19,Assumptions!$B$20,-1) -> 0.2309748 | E19: =PMT(Assumptions!$B$19,Assumptions!$B$20,-1) -> 0.2309748 | F19: =PMT(Assumptions!$B$19,Assumptions!$B$20,-1) -> 0.2309748 | G19: =PMT(Assumptions!$B$19,Assumptions!$B$20,-1) -> 0.2309748
A20: Payouts to residents | B20: RM | C20: =(C17*C9)*C19 -> 221735.81 | D20: =(C17*D9+D17*C9)*D19 -> 665207.42 | E20: =(C17*E9+D17*D9+E17*C9)*E19 -> 1182591 | F20: =(C17*F9+D17*E9+E17*D9+F17*C9)*F19 -> 1847798.4 | G20: =(C17*G9+D17*F9+E17*E9+F17*D9+G17*C9)*G19 -> 2586917.7
A21: Solar capacity running (average) | B21: MW | C21: =C16*C9 -> 1.5 | D21: =C16*D9+D16*C9 -> 4.5 | E21: =C16*E9+D16*D9+E16*C9 -> 8 | F21: =C16*F9+D16*E9+E16*D9+F16*C9 -> 12.5 | G21: =C16*G9+D16*F9+E16*E9+F16*D9+G16*C9 -> 17.5
A22: Solar power produced | B22: MWh | C22: =C21*Assumptions!$B$17 -> 1875 | D22: =D21*Assumptions!$B$17 -> 5625 | E22: =E21*Assumptions!$B$17 -> 10000 | F22: =F21*Assumptions!$B$17 -> 15625 | G22: =G21*Assumptions!$B$17 -> 21875
A23: CO2 avoided by solar | B23: tCO2e | C23: =C22*Assumptions!$B$12 -> 1387.5 | D23: =D22*Assumptions!$B$12 -> 4162.5 | E23: =E22*Assumptions!$B$12 -> 7400 | F23: =F22*Assumptions!$B$12 -> 11562.5 | G23: =G22*Assumptions!$B$12 -> 16187.5
A24: Pool 2 – Shop energy upgrades
A25: New shops upgraded | B25: shops | C25: =Yearly_Inputs!$B$6 -> 15 | D25: =Yearly_Inputs!$C$6 -> 25 | E25: =Yearly_Inputs!$D$6 -> 10 | F25: =Yearly_Inputs!$E$6 -> 10 | G25: =Yearly_Inputs!$F$6 -> 10
A26: Money raised from residents | B26: RM | C26: =C25*Assumptions!$B$23 -> 300000 | D26: =D25*Assumptions!$B$23 -> 500000 | E26: =E25*Assumptions!$B$23 -> 200000 | F26: =F25*Assumptions!$B$23 -> 200000 | G26: =G25*Assumptions!$B$23 -> 200000
A27: Residents' money still invested (average) | B27: RM | C27: =C26*C11 -> 150000 | D27: =C26*D11+D26*C11 -> 503113.64 | E27: =C26*E11+D26*D11+E26*C11 -> 678149.4 | F27: =C26*F11+D26*E11+E26*D11+F26*C11 -> 582410.97 | G27: =C26*G11+D26*F11+E26*E11+F26*D11+G26*C11 -> 461570.77
A28: Shops repaying (shop-years) | B28: shop-yrs | C28: =C25*C12 -> 7.5 | D28: =C25*D12+D25*C12 -> 27.5 | E28: =C25*E12+D25*D12+E25*C12 -> 45 | F28: =C25*F12+D25*E12+E25*D12+F25*C12 -> 47.5 | G28: =C25*G12+D25*F12+E25*E12+F25*D12+G25*C12 -> 37.5
A29: Yearly payout per shop to residents | B29: RM | C29: =PMT(Assumptions!$B$26/12,Assumptions!$B$27*12,-Assumptions!$B$23)*12 -> 7355.7607 | D29: =PMT(Assumptions!$B$26/12,Assumptions!$B$27*12,-Assumptions!$B$23)*12 -> 7355.7607 | E29: =PMT(Assumptions!$B$26/12,Assumptions!$B$27*12,-Assumptions!$B$23)*12 -> 7355.7607 | F29: =PMT(Assumptions!$B$26/12,Assumptions!$B$27*12,-Assumptions!$B$23)*12 -> 7355.7607 | G29: =PMT(Assumptions!$B$26/12,Assumptions!$B$27*12,-Assumptions!$B$23)*12 -> 7355.7607
A30: Payouts to residents | B30: RM | C30: =C28*C29 -> 55168.205 | D30: =D28*D29 -> 202283.42 | E30: =E28*E29 -> 331009.23 | F30: =F28*F29 -> 349398.63 | G30: =G28*G29 -> 275841.03
A31: Safety margin per shop-year (repayment counted − payout) | B31: RM | C31: =C56*12-C29 -> 324.23931 | D31: =D56*12-D29 -> 324.23931 | E31: =E56*12-E29 -> 324.23931 | F31: =F56*12-F29 -> 324.23931 | G31: =G56*12-G29 -> 324.23931
A32: Savings shops keep | B32: RM | C32: =C28*Scenarios!$C$7*12*(1-Assumptions!$B$25) -> 9000 | D32: =D28*Scenarios!$C$7*12*(1-Assumptions!$B$25) -> 33000 | E32: =E28*Scenarios!$C$7*12*(1-Assumptions!$B$25) -> 54000 | F32: =F28*Scenarios!$C$7*12*(1-Assumptions!$B$25) -> 57000 | G32: =G28*Scenarios!$C$7*12*(1-Assumptions!$B$25) -> 45000
A33: Electricity saved | B33: MWh | C33: =C28*Scenarios!$C$7*12/Assumptions!$B$11/1000 -> 99.118943 | D33: =D28*Scenarios!$C$7*12/Assumptions!$B$11/1000 -> 363.43612 | E33: =E28*Scenarios!$C$7*12/Assumptions!$B$11/1000 -> 594.71366 | F33: =F28*Scenarios!$C$7*12/Assumptions!$B$11/1000 -> 627.7533 | G33: =G28*Scenarios!$C$7*12/Assumptions!$B$11/1000 -> 495.59471
A34: CO2 avoided by upgrades | B34: tCO2e | C34: =C33*Assumptions!$B$12 -> 73.348018 | D34: =D33*Assumptions!$B$12 -> 268.94273 | E34: =E33*Assumptions!$B$12 -> 440.08811 | F34: =F33*Assumptions!$B$12 -> 464.53744 | G34: =G33*Assumptions!$B$12 -> 366.74009
A35: Pool 3 – EV charging
A36: New EV chargers | B36: chargers | C36: =Yearly_Inputs!$B$7 -> 1 | D36: =Yearly_Inputs!$C$7 -> 2 | E36: =Yearly_Inputs!$D$7 -> 2 | F36: =Yearly_Inputs!$E$7 -> 2 | G36: =Yearly_Inputs!$F$7 -> 2
A37: Money raised from residents (net cost after grant × residents' share) | B37: RM | C37: =C36*EV_Pilot!$C$46*Assumptions!$B$31 -> 35000 | D37: =D36*EV_Pilot!$C$46*Assumptions!$B$31 -> 70000 | E37: =E36*EV_Pilot!$C$46*Assumptions!$B$31 -> 70000 | F37: =F36*EV_Pilot!$C$46*Assumptions!$B$31 -> 70000 | G37: =G36*EV_Pilot!$C$46*Assumptions!$B$31 -> 70000
A38: Residents' money still invested (average) | B38: RM | C38: =C37*C13 -> 16875 | D38: =C37*D13+D37*C13 -> 63750 | E38: =C37*E13+D37*D13+E37*C13 -> 118750 | F38: =C37*F13+D37*E13+E37*D13+F37*C13 -> 163750 | G38: =C37*G13+D37*F13+E37*E13+F37*D13+G37*C13 -> 198750
A39: Chargers running (charger-years) | B39: chg-yrs | C39: =C36*C9 -> 0.5 | D39: =C36*D9+D36*C9 -> 2 | E39: =C36*E9+D36*D9+E36*C9 -> 4 | F39: =C36*F9+D36*E9+E36*D9+F36*C9 -> 6 | G39: =C36*G9+D36*F9+E36*E9+F36*D9+G36*C9 -> 8
A40: Net charging profit per charger-year (blended DC/AC, from EV_Pilot) | B40: RM | C40: =EV_Pilot!$C$50 -> -7403.2012 | D40: =EV_Pilot!$C$50 -> -7403.2012 | E40: =EV_Pilot!$C$50 -> -7403.2012 | F40: =EV_Pilot!$C$50 -> -7403.2012 | G40: =EV_Pilot!$C$50 -> -7403.2012
A41: Residents' share of charging profit (their 50%, before the 70/10/10/10 split) | B41: RM | C41: =C39*EV_Pilot!$C$54 -> 0 | D41: =D39*EV_Pilot!$C$54 -> 0 | E41: =E39*EV_Pilot!$C$54 -> 0 | F41: =F39*EV_Pilot!$C$54 -> 0 | G41: =G39*EV_Pilot!$C$54 -> 0
A42: Payouts to residents (incl. usage top-up) | B42: RM | C42: =C68*EV_Pilot!$C$56+C69*EV_Pilot!$C$57+C39*EV_Pilot!$C$65 -> 1500 | D42: =D68*EV_Pilot!$C$56+D69*EV_Pilot!$C$57+D39*EV_Pilot!$C$65 -> 6000 | E42: =E68*EV_Pilot!$C$56+E69*EV_Pilot!$C$57+E39*EV_Pilot!$C$65 -> 12000 | F42: =F68*EV_Pilot!$C$56+F69*EV_Pilot!$C$57+F39*EV_Pilot!$C$65 -> 18000 | G42: =G68*EV_Pilot!$C$56+G69*EV_Pilot!$C$57+G39*EV_Pilot!$C$65 -> 24000
A43: Residents' EV money paid back | B43: RM | C43: =C37*C14 -> 2500 | D43: =C37*D14+D37*C14 -> 10000 | E43: =C37*E14+D37*D14+E37*C14 -> 20000 | F43: =C37*F14+D37*E14+E37*D14+F37*C14 -> 30000 | G43: =C37*G14+D37*F14+E37*E14+F37*D14+G37*C14 -> 40000
A44: All pools – totals for one SDP-size client
A45: Money raised from residents | B45: RM | C45: =C17+C26+C37 -> 2255000 | D45: =D17+D26+D37 -> 2490000 | E45: =E17+E26+E37 -> 2830000 | F45: =F17+F26+F37 -> 3470000 | G45: =G17+G26+G37 -> 3470000
A46: Residents' money still invested (average) | B46: RM | C46: =C18+C27+C38 -> 1126875 | D46: =D18+D27+D38 -> 3273127.8 | E46: =E18+E27+E38 -> 5213269.4 | F46: =F18+F27+F38 -> 7080758.5 | G46: =G18+G27+G38 -> 8663849.8
A47: Payouts to residents | B47: RM | C47: =C20+C30+C42 -> 278404.01 | D47: =D20+D30+D42 -> 873490.84 | E47: =E20+E30+E42 -> 1525600.2 | F47: =F20+F30+F42 -> 2215197 | G47: =G20+G30+G42 -> 2886758.8
A48: Spent at the developer's malls (incl. bonus) | B48: RM | C48: =C47*Assumptions!$B$8*(1+Assumptions!$B$9) -> 91873.324 | D48: =D47*Assumptions!$B$8*(1+Assumptions!$B$9) -> 288251.98 | E48: =E47*Assumptions!$B$8*(1+Assumptions!$B$9) -> 503448.07 | F48: =F47*Assumptions!$B$8*(1+Assumptions!$B$9) -> 731015.02 | G48: =G47*Assumptions!$B$8*(1+Assumptions!$B$9) -> 952630.39
A49: Resident investments made (count, at average ticket) | B49: count | C49: =C45/Assumptions!$B$7 -> 4510 | D49: =D45/Assumptions!$B$7 -> 4980 | E49: =E45/Assumptions!$B$7 -> 5660 | F49: =F45/Assumptions!$B$7 -> 6940 | G49: =G45/Assumptions!$B$7 -> 6940
A50: Residents' profit earned (after expected shop losses) | B50: RM | C50: =C18*Assumptions!$B$19+C27*Assumptions!$B$26-C59+C42-C43 -> 50465.897 | D50: =D18*Assumptions!$B$19+D27*Assumptions!$B$26-D59+D42-D43 -> 140973.89 | E50: =E18*Assumptions!$B$19+E27*Assumptions!$B$26-E59+E42-E43 -> 219193.59 | F50: =F18*Assumptions!$B$19+F27*Assumptions!$B$26-F59+F42-F43 -> 302787.27 | G50: =G18*Assumptions!$B$19+G27*Assumptions!$B$26-G59+G42-G43 -> 382758.04
A51: CO2 avoided by assets residents co-fund (solar + upgrades) | B51: tCO2e | C51: =C23+C34 -> 1460.848 | D51: =D23+D34 -> 4431.4427 | E51: =E23+E34 -> 7840.0881 | F51: =F23+F34 -> 12027.037 | G51: =G23+G34 -> 16554.24
A53: Note: timing factors are simple approximations (money raised mid-year; solar and upgrades repaid monthly; EV money returned from charging profit, not guaranteed).
A55: v2 – Guarantees, expected losses and certificates
A56: Repayment counted per shop-month (higher of actual or guaranteed saving × repay share) | B56: RM | C56: =MAX(Scenarios!$C$7,Assumptions!$B$72)*Assumptions!$B$25 -> 640 | D56: =MAX(Scenarios!$C$7,Assumptions!$B$72)*Assumptions!$B$25 -> 640 | E56: =MAX(Scenarios!$C$7,Assumptions!$B$72)*Assumptions!$B$25 -> 640 | F56: =MAX(Scenarios!$C$7,Assumptions!$B$72)*Assumptions!$B$25 -> 640 | G56: =MAX(Scenarios!$C$7,Assumptions!$B$72)*Assumptions!$B$25 -> 640
A57: Expected default loss per shop-year | B57: RM | C57: =Assumptions!$B$23*Scenarios!$C$13*Assumptions!$B$74 -> 1000 | D57: =Assumptions!$B$23*Scenarios!$C$13*Assumptions!$B$74 -> 1000 | E57: =Assumptions!$B$23*Scenarios!$C$13*Assumptions!$B$74 -> 1000 | F57: =Assumptions!$B$23*Scenarios!$C$13*Assumptions!$B$74 -> 1000 | G57: =Assumptions!$B$23*Scenarios!$C$13*Assumptions!$B$74 -> 1000
A58: Bad-debt reserve per shop-year (unused half of margin) | B58: RM | C58: =MAX(0,C31)*(1-Assumptions!$B$28) -> 162.11965 | D58: =MAX(0,D31)*(1-Assumptions!$B$28) -> 162.11965 | E58: =MAX(0,E31)*(1-Assumptions!$B$28) -> 162.11965 | F58: =MAX(0,F31)*(1-Assumptions!$B$28) -> 162.11965 | G58: =MAX(0,G31)*(1-Assumptions!$B$28) -> 162.11965
A59: Residents' uncovered loss on upgrades | B59: RM | C59: =C28*(MAX(0,C57-C58)+MAX(0,-C31)) -> 6284.1026 | D59: =D28*(MAX(0,D57-D58)+MAX(0,-D31)) -> 23041.709 | E59: =E28*(MAX(0,E57-E58)+MAX(0,-E31)) -> 37704.616 | F59: =F28*(MAX(0,F57-F58)+MAX(0,-F31)) -> 39799.316 | G59: =G28*(MAX(0,G57-G58)+MAX(0,-G31)) -> 31420.513
A60: v3: kWh sold per charger-day (after downtime) | B60: kWh | C60: =EV_Pilot!$C$9 -> 27 | D60: =EV_Pilot!$C$9 -> 27 | E60: =EV_Pilot!$C$9 -> 27 | F60: =EV_Pilot!$C$9 -> 27 | G60: =EV_Pilot!$C$9 -> 27
A61: v3: usage top-up per charger-year (after cap) | B61: RM | C61: =EV_Pilot!$C$65 -> 3000 | D61: =EV_Pilot!$C$65 -> 3000 | E61: =EV_Pilot!$C$65 -> 3000 | F61: =EV_Pilot!$C$65 -> 3000 | G61: =EV_Pilot!$C$65 -> 3000
A62: v3: usage top-up paid to residents (developer + platform + CPO) | B62: RM | C62: =C39*C61 -> 1500 | D62: =D39*D61 -> 6000 | E62: =E39*E61 -> 12000 | F62: =F39*F61 -> 18000 | G62: =G39*G61 -> 24000
A63: Solar MWh from the residents' share (for certificates) | B63: MWh | C63: =C22*Scenarios!$C$23 -> 375 | D63: =D22*Scenarios!$C$23 -> 1125 | E63: =E22*Scenarios!$C$23 -> 2000 | F63: =F22*Scenarios!$C$23 -> 3125 | G63: =G22*Scenarios!$C$23 -> 4375
A65: v3 – EV: who is paid while residents recover their money
A66: EV: charger-year factor while residents recover (by age) | C66: =C9*IF(C6-0.5<EV_Pilot!$C$73,1,0) -> 0.5 | D66: =D9*IF(D6-0.5<EV_Pilot!$C$73,1,0) -> 1 | E66: =E9*IF(E6-0.5<EV_Pilot!$C$73,1,0) -> 1 | F66: =F9*IF(F6-0.5<EV_Pilot!$C$73,1,0) -> 1 | G66: =G9*IF(G6-0.5<EV_Pilot!$C$73,1,0) -> 1
A67: EV: charger-year factor after residents recover (by age) | C67: =C9-C66 -> 0 | D67: =D9-D66 -> 0 | E67: =E9-E66 -> 0 | F67: =F9-F66 -> 0 | G67: =G9-G66 -> 0
A68: EV charger-years while residents recover | B68: chg-yrs | C68: =C36*C66 -> 0.5 | D68: =C36*D66+D36*C66 -> 2 | E68: =C36*E66+D36*D66+E36*C66 -> 4 | F68: =C36*F66+D36*E66+E36*D66+F36*C66 -> 6 | G68: =C36*G66+D36*F66+E36*E66+F36*D66+G36*C66 -> 8
A69: EV charger-years after residents recover | B69: chg-yrs | C69: =C36*C67 -> 0 | D69: =C36*D67+D36*C67 -> 0 | E69: =C36*E67+D36*D67+E36*C67 -> 0 | F69: =C36*F67+D36*E67+E36*D67+F36*C67 -> 0 | G69: =C36*G67+D36*F67+E36*E67+F36*D67+G36*C67 -> 0
A70: Developer's 10% share of residents' EV profit (paid after recovery if deferral is on) | B70: RM | C70: =IF(Assumptions!$B$135=1,C69,C39)*EV_Pilot!$C$58 -> 0 | D70: =IF(Assumptions!$B$135=1,D69,D39)*EV_Pilot!$C$58 -> 0 | E70: =IF(Assumptions!$B$135=1,E69,E39)*EV_Pilot!$C$58 -> 0 | F70: =IF(Assumptions!$B$135=1,F69,F39)*EV_Pilot!$C$58 -> 0 | G70: =IF(Assumptions!$B$135=1,G69,G39)*EV_Pilot!$C$58 -> 0
A71: Developer's part of the usage top-up | B71: RM | C71: =C39*EV_Pilot!$C$66 -> 495 | D71: =D39*EV_Pilot!$C$66 -> 1980 | E71: =E39*EV_Pilot!$C$66 -> 3960 | F71: =F39*EV_Pilot!$C$66 -> 5940 | G71: =G39*EV_Pilot!$C$66 -> 7920
A72: Platform's 10% share of residents' EV profit (paid after recovery if deferral is on) | B72: RM | C72: =IF(Assumptions!$B$135=1,C69,C39)*EV_Pilot!$C$59 -> 0 | D72: =IF(Assumptions!$B$135=1,D69,D39)*EV_Pilot!$C$59 -> 0 | E72: =IF(Assumptions!$B$135=1,E69,E39)*EV_Pilot!$C$59 -> 0 | F72: =IF(Assumptions!$B$135=1,F69,F39)*EV_Pilot!$C$59 -> 0 | G72: =IF(Assumptions!$B$135=1,G69,G39)*EV_Pilot!$C$59 -> 0
A73: Platform's part of the usage top-up | B73: RM | C73: =C39*EV_Pilot!$C$67 -> 495 | D73: =D39*EV_Pilot!$C$67 -> 1980 | E73: =E39*EV_Pilot!$C$67 -> 3960 | F73: =F39*EV_Pilot!$C$67 -> 5940 | G73: =G39*EV_Pilot!$C$67 -> 7920

Sheet C_Benefits
A1: 1) Benefits – value created for the developer (customer) – CONSERVATIVE scenario (inputs from Scenarios sheet)
A2: Top: one SDP-size client by its year on the platform. Bottom: all clients together by calendar year.
A4: Benefit | B4: How it is worked out | C4: Year 1 | D4: Year 2 | E4: Year 3 | F4: Year 4 | G4: Year 5
A5: One SDP-size client (by client's year)
A6: A. Cheaper money for solar | B6: Residents' solar money × ((8.5% − 5%) × developer's JV share + JV arrangement fee) | C6: =C_Pools!C18*((Assumptions!$B$21-Assumptions!$B$19)*Scenarios!$C$9+Assumptions!$B$70) -> 19680 | D6: =C_Pools!D18*((Assumptions!$B$21-Assumptions!$B$19)*Scenarios!$C$9+Assumptions!$B$70) -> 55478.416 | E6: =C_Pools!E18*((Assumptions!$B$21-Assumptions!$B$19)*Scenarios!$C$9+Assumptions!$B$70) -> 90535.585 | F6: =C_Pools!F18*((Assumptions!$B$21-Assumptions!$B$19)*Scenarios!$C$9+Assumptions!$B$70) -> 129859.25 | G6: =C_Pools!G18*((Assumptions!$B$21-Assumptions!$B$19)*Scenarios!$C$9+Assumptions!$B$70) -> 164072.34
A7: B. Fee from shop upgrades | B7: Shop-years × positive safety margin × developer's share | C7: =C_Pools!C28*MAX(0,C_Pools!C31)*Assumptions!$B$28 -> 1215.8974 | D7: =C_Pools!D28*MAX(0,C_Pools!D31)*Assumptions!$B$28 -> 4458.2905 | E7: =C_Pools!E28*MAX(0,C_Pools!E31)*Assumptions!$B$28 -> 7295.3845 | F7: =C_Pools!F28*MAX(0,C_Pools!F31)*Assumptions!$B$28 -> 7700.6836 | G7: =C_Pools!G28*MAX(0,C_Pools!G31)*Assumptions!$B$28 -> 6079.4871
A8: C. Developer's EV share, less its part of the usage top-up | B8: v3: 10% of residents' EV profit (paid after residents recover) − developer's 33% of any top-up | C8: =C_Pools!C70-C_Pools!C71 -> -495 | D8: =C_Pools!D70-C_Pools!D71 -> -1980 | E8: =C_Pools!E70-C_Pools!E71 -> -3960 | F8: =C_Pools!F70-C_Pools!F71 -> -5940 | G8: =C_Pools!G70-C_Pools!G71 -> -7920
A9: D. Extra mall rent | B9: Money spent at malls × turnover rent | C9: =C_Pools!C48*Assumptions!$B$10 -> 918.73324 | D9: =C_Pools!D48*Assumptions!$B$10 -> 2882.5198 | E9: =C_Pools!E48*Assumptions!$B$10 -> 5034.4807 | F9: =C_Pools!F48*Assumptions!$B$10 -> 7310.1502 | G9: =C_Pools!G48*Assumptions!$B$10 -> 9526.3039
A10: Cash benefits (A to D, plus F) | C10: =SUM(C6:C9)+C31 -> 22856.606 | D10: =SUM(D6:D9)+D31 -> 65450.151 | E10: =SUM(E6:E9)+E31 -> 107102.65 | F10: =SUM(F6:F9)+F31 -> 151738.21 | G10: =SUM(G6:G9)+G31 -> 189689.51
A11: E. Community-programme saving (actually achieved) | B11: Programme spend × saving rate × share achieved | C11: =Assumptions!$B$13*Yearly_Inputs!$B$8*Scenarios!$C$5 -> 0 | D11: =Assumptions!$B$13*Yearly_Inputs!$C$8*Scenarios!$C$5 -> 0 | E11: =Assumptions!$B$13*Yearly_Inputs!$D$8*Scenarios!$C$5 -> 0 | F11: =Assumptions!$B$13*Yearly_Inputs!$E$8*Scenarios!$C$5 -> 0 | G11: =Assumptions!$B$13*Yearly_Inputs!$F$8*Scenarios!$C$5 -> 0
A12: Total benefit for one SDP-size client | C12: =C10+C11 -> 22856.606 | D12: =D10+D11 -> 65450.151 | E12: =E10+E11 -> 107102.65 | F12: =F10+F11 -> 151738.21 | G12: =G10+G11 -> 189689.51
A14: Value to residents and shops (one SDP-size client, not counted in developer ROI)
A15: Residents' profit earned | B15: Payout profit on money invested, after expected shop losses | C15: =C_Pools!C50 -> 50465.897 | D15: =C_Pools!D50 -> 140973.89 | E15: =C_Pools!E50 -> 219193.59 | F15: =C_Pools!F50 -> 302787.27 | G15: =C_Pools!G50 -> 382758.04
A16: Savings shops keep | B16: 20% of savings during repayment | C16: =C_Pools!C32 -> 9000 | D16: =C_Pools!D32 -> 33000 | E16: =C_Pools!E32 -> 54000 | F16: =C_Pools!F32 -> 57000 | G16: =C_Pools!G32 -> 45000
A17: CO2 avoided (tCO2e) | B17: Solar + upgrades | C17: =C_Pools!C51 -> 1460.848 | D17: =C_Pools!D51 -> 4431.4427 | E17: =C_Pools!E51 -> 7840.0881 | F17: =C_Pools!F51 -> 12027.037 | G17: =C_Pools!G51 -> 16554.24
A19: All clients together (by calendar year)
A20: Developer clients on the platform | B20: Cumulative clients signed | C20: =Yearly_Inputs!$B$9 -> 1 | D20: =Yearly_Inputs!$B$9+Scenarios!$C$8 -> 2 | E20: =Yearly_Inputs!$B$9+Scenarios!$C$8+Yearly_Inputs!$D$9 -> 4 | F20: =Yearly_Inputs!$B$9+Scenarios!$C$8+Yearly_Inputs!$D$9+Yearly_Inputs!$E$9 -> 6 | G20: =Yearly_Inputs!$B$9+Scenarios!$C$8+Yearly_Inputs!$D$9+Yearly_Inputs!$E$9+Yearly_Inputs!$F$9 -> 8
A21: Cash benefits (A to D, plus F), all clients | C21: =Yearly_Inputs!$B$9*Yearly_Inputs!$B$10*C10 -> 22856.606 | D21: =Yearly_Inputs!$B$9*Yearly_Inputs!$B$10*D10+Scenarios!$C$8*Scenarios!$C$12*C10 -> 74592.794 | E21: =Yearly_Inputs!$B$9*Yearly_Inputs!$B$10*E10+Scenarios!$C$8*Scenarios!$C$12*D10+Yearly_Inputs!$D$9*Scenarios!$C$12*C10 -> 151567.99 | F21: =Yearly_Inputs!$B$9*Yearly_Inputs!$B$10*F10+Scenarios!$C$8*Scenarios!$C$12*E10+Yearly_Inputs!$D$9*Scenarios!$C$12*D10+Yearly_Inputs!$E$9*Scenarios!$C$12*C10 -> 265224.67 | G21: =Yearly_Inputs!$B$9*Yearly_Inputs!$B$10*G10+Scenarios!$C$8*Scenarios!$C$12*F10+Yearly_Inputs!$D$9*Scenarios!$C$12*E10+Yearly_Inputs!$E$9*Scenarios!$C$12*D10+Yearly_Inputs!$F$9*Scenarios!$C$12*C10 -> 406712.32
A22: Community-programme saving, all clients | C22: =Yearly_Inputs!$B$9*Yearly_Inputs!$B$10*C11 -> 0 | D22: =Yearly_Inputs!$B$9*Yearly_Inputs!$B$10*D11+Scenarios!$C$8*Scenarios!$C$12*C11 -> 0 | E22: =Yearly_Inputs!$B$9*Yearly_Inputs!$B$10*E11+Scenarios!$C$8*Scenarios!$C$12*D11+Yearly_Inputs!$D$9*Scenarios!$C$12*C11 -> 0 | F22: =Yearly_Inputs!$B$9*Yearly_Inputs!$B$10*F11+Scenarios!$C$8*Scenarios!$C$12*E11+Yearly_Inputs!$D$9*Scenarios!$C$12*D11+Yearly_Inputs!$E$9*Scenarios!$C$12*C11 -> 0 | G22: =Yearly_Inputs!$B$9*Yearly_Inputs!$B$10*G11+Scenarios!$C$8*Scenarios!$C$12*F11+Yearly_Inputs!$D$9*Scenarios!$C$12*E11+Yearly_Inputs!$E$9*Scenarios!$C$12*D11+Yearly_Inputs!$F$9*Scenarios!$C$12*C11 -> 0
A23: Total benefits, all clients | C23: =C21+C22 -> 22856.606 | D23: =D21+D22 -> 74592.794 | E23: =E21+E22 -> 151567.99 | F23: =F21+F22 -> 265224.67 | G23: =G21+G22 -> 406712.32
A24: Money raised from residents, all clients | C24: =Yearly_Inputs!$B$9*Yearly_Inputs!$B$10*C_Pools!C45 -> 2255000 | D24: =Yearly_Inputs!$B$9*Yearly_Inputs!$B$10*C_Pools!D45+Scenarios!$C$8*Scenarios!$C$12*C_Pools!C45 -> 3392000 | E24: =Yearly_Inputs!$B$9*Yearly_Inputs!$B$10*C_Pools!E45+Scenarios!$C$8*Scenarios!$C$12*C_Pools!D45+Yearly_Inputs!$D$9*Scenarios!$C$12*C_Pools!C45 -> 5630000 | F24: =Yearly_Inputs!$B$9*Yearly_Inputs!$B$10*C_Pools!F45+Scenarios!$C$8*Scenarios!$C$12*C_Pools!E45+Yearly_Inputs!$D$9*Scenarios!$C$12*C_Pools!D45+Yearly_Inputs!$E$9*Scenarios!$C$12*C_Pools!C45 -> 8398000 | G24: =Yearly_Inputs!$B$9*Yearly_Inputs!$B$10*C_Pools!G45+Scenarios!$C$8*Scenarios!$C$12*C_Pools!F45+Yearly_Inputs!$D$9*Scenarios!$C$12*C_Pools!E45+Yearly_Inputs!$E$9*Scenarios!$C$12*C_Pools!D45+Yearly_Inputs!$F$9*Scenarios!$C$12*C_Pools!C45 -> 10918000
A25: Resident investments made, all clients (count) | B25: count | C25: =Yearly_Inputs!$B$9*Yearly_Inputs!$B$10*C_Pools!C49 -> 4510 | D25: =Yearly_Inputs!$B$9*Yearly_Inputs!$B$10*C_Pools!D49+Scenarios!$C$8*Scenarios!$C$12*C_Pools!C49 -> 6784 | E25: =Yearly_Inputs!$B$9*Yearly_Inputs!$B$10*C_Pools!E49+Scenarios!$C$8*Scenarios!$C$12*C_Pools!D49+Yearly_Inputs!$D$9*Scenarios!$C$12*C_Pools!C49 -> 11260 | F25: =Yearly_Inputs!$B$9*Yearly_Inputs!$B$10*C_Pools!F49+Scenarios!$C$8*Scenarios!$C$12*C_Pools!E49+Yearly_Inputs!$D$9*Scenarios!$C$12*C_Pools!D49+Yearly_Inputs!$E$9*Scenarios!$C$12*C_Pools!C49 -> 16796 | G25: =Yearly_Inputs!$B$9*Yearly_Inputs!$B$10*C_Pools!G49+Scenarios!$C$8*Scenarios!$C$12*C_Pools!F49+Yearly_Inputs!$D$9*Scenarios!$C$12*C_Pools!E49+Yearly_Inputs!$E$9*Scenarios!$C$12*C_Pools!D49+Yearly_Inputs!$F$9*Scenarios!$C$12*C_Pools!C49 -> 21836
A26: Residents' profit, all clients | C26: =Yearly_Inputs!$B$9*Yearly_Inputs!$B$10*C_Pools!C50 -> 50465.897 | D26: =Yearly_Inputs!$B$9*Yearly_Inputs!$B$10*C_Pools!D50+Scenarios!$C$8*Scenarios!$C$12*C_Pools!C50 -> 161160.25 | E26: =Yearly_Inputs!$B$9*Yearly_Inputs!$B$10*C_Pools!E50+Scenarios!$C$8*Scenarios!$C$12*C_Pools!D50+Yearly_Inputs!$D$9*Scenarios!$C$12*C_Pools!C50 -> 315955.87 | F26: =Yearly_Inputs!$B$9*Yearly_Inputs!$B$10*C_Pools!F50+Scenarios!$C$8*Scenarios!$C$12*C_Pools!E50+Yearly_Inputs!$D$9*Scenarios!$C$12*C_Pools!D50+Yearly_Inputs!$E$9*Scenarios!$C$12*C_Pools!C50 -> 543616.54 | G26: =Yearly_Inputs!$B$9*Yearly_Inputs!$B$10*C_Pools!G50+Scenarios!$C$8*Scenarios!$C$12*C_Pools!F50+Yearly_Inputs!$D$9*Scenarios!$C$12*C_Pools!E50+Yearly_Inputs!$E$9*Scenarios!$C$12*C_Pools!D50+Yearly_Inputs!$F$9*Scenarios!$C$12*C_Pools!C50 -> 832379.65
A27: CO2 avoided, all clients (tCO2e) | C27: =Yearly_Inputs!$B$9*Yearly_Inputs!$B$10*C_Pools!C51 -> 1460.848 | D27: =Yearly_Inputs!$B$9*Yearly_Inputs!$B$10*C_Pools!D51+Scenarios!$C$8*Scenarios!$C$12*C_Pools!C51 -> 5015.7819 | E27: =Yearly_Inputs!$B$9*Yearly_Inputs!$B$10*C_Pools!E51+Scenarios!$C$8*Scenarios!$C$12*C_Pools!D51+Yearly_Inputs!$D$9*Scenarios!$C$12*C_Pools!C51 -> 10781.344 | F27: =Yearly_Inputs!$B$9*Yearly_Inputs!$B$10*C_Pools!F51+Scenarios!$C$8*Scenarios!$C$12*C_Pools!E51+Yearly_Inputs!$D$9*Scenarios!$C$12*C_Pools!D51+Yearly_Inputs!$E$9*Scenarios!$C$12*C_Pools!C51 -> 19876.905 | G27: =Yearly_Inputs!$B$9*Yearly_Inputs!$B$10*C_Pools!G51+Scenarios!$C$8*Scenarios!$C$12*C_Pools!F51+Yearly_Inputs!$D$9*Scenarios!$C$12*C_Pools!E51+Yearly_Inputs!$E$9*Scenarios!$C$12*C_Pools!D51+Yearly_Inputs!$F$9*Scenarios!$C$12*C_Pools!C51 -> 32350.958
A28: Benefit A only counts the residents' share of each solar asset and only the developer's assumed share of the JV. Benefit E is the least certain; v2 guarantees half of it in the contract (see Pricing_Income credit rows).
A30: v2 – Certificates and the community-saving guarantee (one SDP-size client)
A31: F. Renewable energy certificate (REC) sales, developer's share | B31: Residents' share of solar MWh × REC price × USD rate × JV share × (1 − our service fee) | C31: =C_Pools!C63*Assumptions!$B$78*Assumptions!$B$52*Scenarios!$C$9*(1-Assumptions!$B$79) -> 1536.975 | D31: =C_Pools!D63*Assumptions!$B$78*Assumptions!$B$52*Scenarios!$C$9*(1-Assumptions!$B$79) -> 4610.925 | E31: =C_Pools!E63*Assumptions!$B$78*Assumptions!$B$52*Scenarios!$C$9*(1-Assumptions!$B$79) -> 8197.2 | F31: =C_Pools!F63*Assumptions!$B$78*Assumptions!$B$52*Scenarios!$C$9*(1-Assumptions!$B$79) -> 12808.125 | G31: =C_Pools!G63*Assumptions!$B$78*Assumptions!$B$52*Scenarios!$C$9*(1-Assumptions!$B$79) -> 17931.375
A32: Community saving we guarantee in the contract | B32: Programme spend × saving rate × guaranteed share | C32: =Assumptions!$B$13*Yearly_Inputs!$B$8*Assumptions!$B$65 -> 52000 | D32: =Assumptions!$B$13*Yearly_Inputs!$C$8*Assumptions!$B$65 -> 104000 | E32: =Assumptions!$B$13*Yearly_Inputs!$D$8*Assumptions!$B$65 -> 104000 | F32: =Assumptions!$B$13*Yearly_Inputs!$E$8*Assumptions!$B$65 -> 104000 | G32: =Assumptions!$B$13*Yearly_Inputs!$F$8*Assumptions!$B$65 -> 104000
A33: Shortfall vs guarantee | B33: Guaranteed − achieved (if positive) | C33: =MAX(0,C32-C11) -> 52000 | D33: =MAX(0,D32-D11) -> 104000 | E33: =MAX(0,E32-E11) -> 104000 | F33: =MAX(0,F32-F11) -> 104000 | G33: =MAX(0,G32-G11) -> 104000

Sheet C_Pricing_Income
A1: 2) Pricing / Income – what clients pay = what we earn – CONSERVATIVE scenario (inputs from Scenarios sheet)
A2: Top: one client by its year on the platform. Bottom: all clients by calendar year. v2 credits refund part of our fees if the community saving falls short.
A4: Income line | B4: Who pays | C4: Year 1 | D4: Year 2 | E4: Year 3 | F4: Year 4 | G4: Year 5
A5: One client (by client's year). Fixed fees are the same for every client; usage fees scale with client size.
A6: Set-up fee (v2: split into Year 1 and Year 2 instalments) | B6: Developer | C6: =Assumptions!$B$60 -> 20000 | D6: =Assumptions!$B$61 -> 30000 | E6: =0 -> 0 | F6: =0 -> 0 | G6: =0 -> 0
A7: Platform fee (waived in Year 1 pilot; billed monthly) | B7: Developer | C7: =0 -> 0 | D7: =Assumptions!$B$39 -> 72000 | E7: =Assumptions!$B$39 -> 72000 | F7: =Assumptions!$B$39 -> 72000 | G7: =Assumptions!$B$39 -> 72000
A8: Fixed fees | C8: =C6+C7 -> 20000 | D8: =D6+D7 -> 102000 | E8: =E6+E7 -> 72000 | F8: =F6+F7 -> 72000 | G8: =G6+G7 -> 72000
A9: Success fee on money raised (v2: discounted in Year 1) | B9: Developer (from pool) | C9: =C_Pools!C45*Assumptions!$B$40*(1-Assumptions!$B$62) -> 0 | D9: =C_Pools!D45*Assumptions!$B$40 -> 18675 | E9: =C_Pools!E45*Assumptions!$B$40 -> 21225 | F9: =C_Pools!F45*Assumptions!$B$40 -> 26025 | G9: =C_Pools!G45*Assumptions!$B$40 -> 26025
A10: Fee on money still invested (from Year 2) | B10: Developer (from pool) | C10: =0 -> 0 | D10: =C_Pools!D46*Assumptions!$B$41 -> 16365.639 | E10: =C_Pools!E46*Assumptions!$B$41 -> 26066.347 | F10: =C_Pools!F46*Assumptions!$B$41 -> 35403.792 | G10: =C_Pools!G46*Assumptions!$B$41 -> 43319.249
A11: Usage fees paid by developer (SDP size) | C11: =C9+C10 -> 0 | D11: =D9+D10 -> 35040.639 | E11: =E9+E10 -> 47291.347 | F11: =F9+F10 -> 61428.792 | G11: =G9+G10 -> 69344.249
A12: Fee on mall redemptions (SDP size) | B12: Mall shops | C12: =C_Pools!C48*Assumptions!$B$42 -> 1837.4665 | D12: =C_Pools!D48*Assumptions!$B$42 -> 5765.0395 | E12: =C_Pools!E48*Assumptions!$B$42 -> 10068.961 | F12: =C_Pools!F48*Assumptions!$B$42 -> 14620.3 | G12: =C_Pools!G48*Assumptions!$B$42 -> 19052.608
A13: SDP pays us (fixed + usage − guarantee credit) | C13: =C8+C11-C25 -> 0 | D13: =D8+D11-D25 -> 102780.48 | E13: =E8+E11-E25 -> 89468.51 | F13: =F8+F11-F25 -> 100071.59 | G13: =G8+G11-G25 -> 106008.19
A15: All clients (by calendar year)
A16: Fixed fees (set-up + platform, pro rata to client size) | B16: Developers | C16: =Yearly_Inputs!$B$9*Yearly_Inputs!$B$10*C8 -> 20000 | D16: =Yearly_Inputs!$B$9*Yearly_Inputs!$B$10*D8+Scenarios!$C$8*Scenarios!$C$12*C8 -> 110000 | E16: =Yearly_Inputs!$B$9*Yearly_Inputs!$B$10*E8+Scenarios!$C$8*Scenarios!$C$12*D8+Yearly_Inputs!$D$9*Scenarios!$C$12*C8 -> 128800 | F16: =Yearly_Inputs!$B$9*Yearly_Inputs!$B$10*F8+Scenarios!$C$8*Scenarios!$C$12*E8+Yearly_Inputs!$D$9*Scenarios!$C$12*D8+Yearly_Inputs!$E$9*Scenarios!$C$12*C8 -> 198400 | G16: =Yearly_Inputs!$B$9*Yearly_Inputs!$B$10*G8+Scenarios!$C$8*Scenarios!$C$12*F8+Yearly_Inputs!$D$9*Scenarios!$C$12*E8+Yearly_Inputs!$E$9*Scenarios!$C$12*D8+Yearly_Inputs!$F$9*Scenarios!$C$12*C8 -> 256000
A17: Usage fees (success + invested money) | B17: Developers | C17: =Yearly_Inputs!$B$9*Yearly_Inputs!$B$10*C11 -> 0 | D17: =Yearly_Inputs!$B$9*Yearly_Inputs!$B$10*D11+Scenarios!$C$8*Scenarios!$C$12*C11 -> 35040.639 | E17: =Yearly_Inputs!$B$9*Yearly_Inputs!$B$10*E11+Scenarios!$C$8*Scenarios!$C$12*D11+Yearly_Inputs!$D$9*Scenarios!$C$12*C11 -> 61307.603 | F17: =Yearly_Inputs!$B$9*Yearly_Inputs!$B$10*F11+Scenarios!$C$8*Scenarios!$C$12*E11+Yearly_Inputs!$D$9*Scenarios!$C$12*D11+Yearly_Inputs!$E$9*Scenarios!$C$12*C11 -> 108377.84 | G17: =Yearly_Inputs!$B$9*Yearly_Inputs!$B$10*G11+Scenarios!$C$8*Scenarios!$C$12*F11+Yearly_Inputs!$D$9*Scenarios!$C$12*E11+Yearly_Inputs!$E$9*Scenarios!$C$12*D11+Yearly_Inputs!$F$9*Scenarios!$C$12*C11 -> 159781.35
A18: Paid by developers (after guarantee credits) | C18: =C16+C17-C37 -> 0 | D18: =D16+D17-D37 -> 102780.48 | E18: =E16+E17-E37 -> 130580.7 | F18: =F16+F17-F37 -> 218083.38 | G18: =G16+G17-G37 -> 299836.02
A19: Redemption fees | B19: Mall shops | C19: =Yearly_Inputs!$B$9*Yearly_Inputs!$B$10*C12 -> 1837.4665 | D19: =Yearly_Inputs!$B$9*Yearly_Inputs!$B$10*D12+Scenarios!$C$8*Scenarios!$C$12*C12 -> 6500.0261 | E19: =Yearly_Inputs!$B$9*Yearly_Inputs!$B$10*E12+Scenarios!$C$8*Scenarios!$C$12*D12+Yearly_Inputs!$D$9*Scenarios!$C$12*C12 -> 13844.95 | F19: =Yearly_Inputs!$B$9*Yearly_Inputs!$B$10*F12+Scenarios!$C$8*Scenarios!$C$12*E12+Yearly_Inputs!$D$9*Scenarios!$C$12*D12+Yearly_Inputs!$E$9*Scenarios!$C$12*C12 -> 24729.89 | G19: =Yearly_Inputs!$B$9*Yearly_Inputs!$B$10*G12+Scenarios!$C$8*Scenarios!$C$12*F12+Yearly_Inputs!$D$9*Scenarios!$C$12*E12+Yearly_Inputs!$E$9*Scenarios!$C$12*D12+Yearly_Inputs!$F$9*Scenarios!$C$12*C12 -> 39037.902
A20: Total income (incl. v2 and v3 income lines) | C20: =C18+C19+C38+C39+C40+C46 -> 18411.716 | D20: =D18+D19+D38+D39+D40+D46 -> 156137.96 | E20: =E18+E19+E38+E39+E40+E46 -> 223852.15 | F20: =F18+F19+F38+F39+F40+F46 -> 359589.02 | G20: =G18+G19+G38+G39+G40+G46 -> 490119.07
A23: v2 – Guarantee credits and new income lines (one client, by client's year)
A24: Credit cap (share of that year's developer fees) | C24: =Assumptions!$B$67 -> 1 | D24: =Assumptions!$B$68 -> 0.25 | E24: =Assumptions!$B$68 -> 0.25 | F24: =Assumptions!$B$68 -> 0.25 | G24: =Assumptions!$B$68 -> 0.25
A25: Guarantee credit to an SDP-size client | B25: Credit to developer | C25: =MIN(Assumptions!$B$66*C_Benefits!C33,C24*(C8+C11)) -> 20000 | D25: =MIN(Assumptions!$B$66*C_Benefits!D33,D24*(D8+D11)) -> 34260.16 | E25: =MIN(Assumptions!$B$66*C_Benefits!E33,E24*(E8+E11)) -> 29822.837 | F25: =MIN(Assumptions!$B$66*C_Benefits!F33,F24*(F8+F11)) -> 33357.198 | G25: =MIN(Assumptions!$B$66*C_Benefits!G33,G24*(G8+G11)) -> 35336.062
A26: Guarantee credit to a typical new client | B26: Credit to developer | C26: =MIN(Assumptions!$B$66*Scenarios!$C$12*C_Benefits!C33,C24*Scenarios!$C$12*(C8+C11)) -> 8000 | D26: =MIN(Assumptions!$B$66*Scenarios!$C$12*C_Benefits!D33,D24*Scenarios!$C$12*(D8+D11)) -> 13704.064 | E26: =MIN(Assumptions!$B$66*Scenarios!$C$12*C_Benefits!E33,E24*Scenarios!$C$12*(E8+E11)) -> 11929.135 | F26: =MIN(Assumptions!$B$66*Scenarios!$C$12*C_Benefits!F33,F24*Scenarios!$C$12*(F8+F11)) -> 13342.879 | G26: =MIN(Assumptions!$B$66*Scenarios!$C$12*C_Benefits!G33,G24*Scenarios!$C$12*(G8+G11)) -> 14134.425
A27: Featured offers in rewards catalogue (SDP size) | B27: Mall shops | C27: =Assumptions!$B$80*Assumptions!$B$81*12*C_Pools!C9 -> 12000 | D27: =Assumptions!$B$80*Assumptions!$B$81*12*C_Pools!D9 -> 24000 | E27: =Assumptions!$B$80*Assumptions!$B$81*12*C_Pools!E9 -> 24000 | F27: =Assumptions!$B$80*Assumptions!$B$81*12*C_Pools!F9 -> 24000 | G27: =Assumptions!$B$80*Assumptions!$B$81*12*C_Pools!G9 -> 24000
A28: Energy dashboard subscriptions (SDP size) | B28: Upgraded shops | C28: =C_Pools!C28*Assumptions!$B$82*12 -> 4500 | D28: =C_Pools!D28*Assumptions!$B$82*12 -> 16500 | E28: =C_Pools!E28*Assumptions!$B$82*12 -> 27000 | F28: =C_Pools!F28*Assumptions!$B$82*12 -> 28500 | G28: =C_Pools!G28*Assumptions!$B$82*12 -> 22500
A29: REC registration and sales service (SDP size) | B29: From REC proceeds | C29: =C_Pools!C63*Assumptions!$B$78*Assumptions!$B$52*Assumptions!$B$79 -> 569.25 | D29: =C_Pools!D63*Assumptions!$B$78*Assumptions!$B$52*Assumptions!$B$79 -> 1707.75 | E29: =C_Pools!E63*Assumptions!$B$78*Assumptions!$B$52*Assumptions!$B$79 -> 3036 | F29: =C_Pools!F63*Assumptions!$B$78*Assumptions!$B$52*Assumptions!$B$79 -> 4743.75 | G29: =C_Pools!G63*Assumptions!$B$78*Assumptions!$B$52*Assumptions!$B$79 -> 6641.25
A31: v2 – All clients (by calendar year)
A32: Guarantee credits – clients signed in Y1 | B32: Credit to developers | C32: =Yearly_Inputs!$B$9*MIN(Assumptions!$B$66*Yearly_Inputs!$B$10*C_Benefits!C33,C24*Yearly_Inputs!$B$10*(C8+C11)) -> 20000 | D32: =Yearly_Inputs!$B$9*MIN(Assumptions!$B$66*Yearly_Inputs!$B$10*C_Benefits!D33,D24*Yearly_Inputs!$B$10*(D8+D11)) -> 34260.16 | E32: =Yearly_Inputs!$B$9*MIN(Assumptions!$B$66*Yearly_Inputs!$B$10*C_Benefits!E33,E24*Yearly_Inputs!$B$10*(E8+E11)) -> 29822.837 | F32: =Yearly_Inputs!$B$9*MIN(Assumptions!$B$66*Yearly_Inputs!$B$10*C_Benefits!F33,F24*Yearly_Inputs!$B$10*(F8+F11)) -> 33357.198 | G32: =Yearly_Inputs!$B$9*MIN(Assumptions!$B$66*Yearly_Inputs!$B$10*C_Benefits!G33,G24*Yearly_Inputs!$B$10*(G8+G11)) -> 35336.062
A33: Guarantee credits – clients signed in Y2 | B33: Credit to developers | C33: =0 -> 0 | D33: =Scenarios!$C$8*MIN(Assumptions!$B$66*Scenarios!$C$12*C_Benefits!C33,C24*Scenarios!$C$12*(C8+C11)) -> 8000 | E33: =Scenarios!$C$8*MIN(Assumptions!$B$66*Scenarios!$C$12*C_Benefits!D33,D24*Scenarios!$C$12*(D8+D11)) -> 13704.064 | F33: =Scenarios!$C$8*MIN(Assumptions!$B$66*Scenarios!$C$12*C_Benefits!E33,E24*Scenarios!$C$12*(E8+E11)) -> 11929.135 | G33: =Scenarios!$C$8*MIN(Assumptions!$B$66*Scenarios!$C$12*C_Benefits!F33,F24*Scenarios!$C$12*(F8+F11)) -> 13342.879
A34: Guarantee credits – clients signed in Y3 | B34: Credit to developers | C34: =0 -> 0 | D34: =0 -> 0 | E34: =Yearly_Inputs!$D$9*MIN(Assumptions!$B$66*Scenarios!$C$12*C_Benefits!C33,C24*Scenarios!$C$12*(C8+C11)) -> 16000 | F34: =Yearly_Inputs!$D$9*MIN(Assumptions!$B$66*Scenarios!$C$12*C_Benefits!D33,D24*Scenarios!$C$12*(D8+D11)) -> 27408.128 | G34: =Yearly_Inputs!$D$9*MIN(Assumptions!$B$66*Scenarios!$C$12*C_Benefits!E33,E24*Scenarios!$C$12*(E8+E11)) -> 23858.269
A35: Guarantee credits – clients signed in Y4 | B35: Credit to developers | C35: =0 -> 0 | D35: =0 -> 0 | E35: =0 -> 0 | F35: =Yearly_Inputs!$E$9*MIN(Assumptions!$B$66*Scenarios!$C$12*C_Benefits!C33,C24*Scenarios!$C$12*(C8+C11)) -> 16000 | G35: =Yearly_Inputs!$E$9*MIN(Assumptions!$B$66*Scenarios!$C$12*C_Benefits!D33,D24*Scenarios!$C$12*(D8+D11)) -> 27408.128
A36: Guarantee credits – clients signed in Y5 | B36: Credit to developers | C36: =0 -> 0 | D36: =0 -> 0 | E36: =0 -> 0 | F36: =0 -> 0 | G36: =Yearly_Inputs!$F$9*MIN(Assumptions!$B$66*Scenarios!$C$12*C_Benefits!C33,C24*Scenarios!$C$12*(C8+C11)) -> 16000
A37: Guarantee credits, all clients | B37: Credit to developers | C37: =SUM(C32:C36) -> 20000 | D37: =SUM(D32:D36) -> 42260.16 | E37: =SUM(E32:E36) -> 59526.901 | F37: =SUM(F32:F36) -> 88694.461 | G37: =SUM(G32:G36) -> 115945.34
A38: Featured offers, all clients | B38: Mall shops | C38: =Yearly_Inputs!$B$9*Yearly_Inputs!$B$10*C27 -> 12000 | D38: =Yearly_Inputs!$B$9*Yearly_Inputs!$B$10*D27+Scenarios!$C$8*Scenarios!$C$12*C27 -> 28800 | E38: =Yearly_Inputs!$B$9*Yearly_Inputs!$B$10*E27+Scenarios!$C$8*Scenarios!$C$12*D27+Yearly_Inputs!$D$9*Scenarios!$C$12*C27 -> 43200 | F38: =Yearly_Inputs!$B$9*Yearly_Inputs!$B$10*F27+Scenarios!$C$8*Scenarios!$C$12*E27+Yearly_Inputs!$D$9*Scenarios!$C$12*D27+Yearly_Inputs!$E$9*Scenarios!$C$12*C27 -> 62400 | G38: =Yearly_Inputs!$B$9*Yearly_Inputs!$B$10*G27+Scenarios!$C$8*Scenarios!$C$12*F27+Yearly_Inputs!$D$9*Scenarios!$C$12*E27+Yearly_Inputs!$E$9*Scenarios!$C$12*D27+Yearly_Inputs!$F$9*Scenarios!$C$12*C27 -> 81600
A39: Energy dashboards, all clients | B39: Upgraded shops | C39: =Yearly_Inputs!$B$9*Yearly_Inputs!$B$10*C28 -> 4500 | D39: =Yearly_Inputs!$B$9*Yearly_Inputs!$B$10*D28+Scenarios!$C$8*Scenarios!$C$12*C28 -> 18300 | E39: =Yearly_Inputs!$B$9*Yearly_Inputs!$B$10*E28+Scenarios!$C$8*Scenarios!$C$12*D28+Yearly_Inputs!$D$9*Scenarios!$C$12*C28 -> 37200 | F39: =Yearly_Inputs!$B$9*Yearly_Inputs!$B$10*F28+Scenarios!$C$8*Scenarios!$C$12*E28+Yearly_Inputs!$D$9*Scenarios!$C$12*D28+Yearly_Inputs!$E$9*Scenarios!$C$12*C28 -> 56100 | G39: =Yearly_Inputs!$B$9*Yearly_Inputs!$B$10*G28+Scenarios!$C$8*Scenarios!$C$12*F28+Yearly_Inputs!$D$9*Scenarios!$C$12*E28+Yearly_Inputs!$E$9*Scenarios!$C$12*D28+Yearly_Inputs!$F$9*Scenarios!$C$12*C28 -> 72300
A40: REC service fees, all clients | B40: From REC proceeds | C40: =Yearly_Inputs!$B$9*Yearly_Inputs!$B$10*C29 -> 569.25 | D40: =Yearly_Inputs!$B$9*Yearly_Inputs!$B$10*D29+Scenarios!$C$8*Scenarios!$C$12*C29 -> 1935.45 | E40: =Yearly_Inputs!$B$9*Yearly_Inputs!$B$10*E29+Scenarios!$C$8*Scenarios!$C$12*D29+Yearly_Inputs!$D$9*Scenarios!$C$12*C29 -> 4174.5 | F40: =Yearly_Inputs!$B$9*Yearly_Inputs!$B$10*F29+Scenarios!$C$8*Scenarios!$C$12*E29+Yearly_Inputs!$D$9*Scenarios!$C$12*D29+Yearly_Inputs!$E$9*Scenarios!$C$12*C29 -> 7779.75 | G40: =Yearly_Inputs!$B$9*Yearly_Inputs!$B$10*G29+Scenarios!$C$8*Scenarios!$C$12*F29+Yearly_Inputs!$D$9*Scenarios!$C$12*E29+Yearly_Inputs!$E$9*Scenarios!$C$12*D29+Yearly_Inputs!$F$9*Scenarios!$C$12*C29 -> 12789.15
A42: v3 – EV: our 10% share and our part of the usage top-up
A43: EV: our 10% share of residents' charging profit (SDP size; after residents recover) | B43: From EV pool | C43: =C_Pools!C72 -> 0 | D43: =C_Pools!D72 -> 0 | E43: =C_Pools!E72 -> 0 | F43: =C_Pools!F72 -> 0 | G43: =C_Pools!G72 -> 0
A44: EV: our 33% part of the usage top-up (cost, SDP size) | B44: We pay | C44: =-C_Pools!C73 -> -495 | D44: =-C_Pools!D73 -> -1980 | E44: =-C_Pools!E73 -> -3960 | F44: =-C_Pools!F73 -> -5940 | G44: =-C_Pools!G73 -> -7920
A45: EV: net (SDP size) | C45: =C43+C44 -> -495 | D45: =D43+D44 -> -1980 | E45: =E43+E44 -> -3960 | F45: =F43+F44 -> -5940 | G45: =G43+G44 -> -7920
A46: EV: net, all clients (can be negative) | C46: =Yearly_Inputs!$B$9*Yearly_Inputs!$B$10*C45 -> -495 | D46: =Yearly_Inputs!$B$9*Yearly_Inputs!$B$10*D45+Scenarios!$C$8*Scenarios!$C$12*C45 -> -2178 | E46: =Yearly_Inputs!$B$9*Yearly_Inputs!$B$10*E45+Scenarios!$C$8*Scenarios!$C$12*D45+Yearly_Inputs!$D$9*Scenarios!$C$12*C45 -> -5148 | F46: =Yearly_Inputs!$B$9*Yearly_Inputs!$B$10*F45+Scenarios!$C$8*Scenarios!$C$12*E45+Yearly_Inputs!$D$9*Scenarios!$C$12*D45+Yearly_Inputs!$E$9*Scenarios!$C$12*C45 -> -9504 | G46: =Yearly_Inputs!$B$9*Yearly_Inputs!$B$10*G45+Scenarios!$C$8*Scenarios!$C$12*F45+Yearly_Inputs!$D$9*Scenarios!$C$12*E45+Yearly_Inputs!$E$9*Scenarios!$C$12*D45+Yearly_Inputs!$F$9*Scenarios!$C$12*C45 -> -15444

Sheet C_Customer_ROI
A1: Does the customer make money from Year 1? – CONSERVATIVE scenario (inputs from Scenarios sheet)
A2: Developer's benefit minus what the developer pays us (after any guarantee credit). Shops' fees are not counted (shops pay them).
A4: Item | C4: Year 1 | D4: Year 2 | E4: Year 3 | F4: Year 4 | G4: Year 5
A5: Sime Darby Property (first client, full size)
A6: Total benefit | C6: =C_Benefits!C12 -> 22856.606 | D6: =C_Benefits!D12 -> 65450.151 | E6: =C_Benefits!E12 -> 107102.65 | F6: =C_Benefits!F12 -> 151738.21 | G6: =C_Benefits!G12 -> 189689.51
A7: Paid to us (after guarantee credit) | C7: =C_Pricing_Income!C13 -> 0 | D7: =C_Pricing_Income!D13 -> 102780.48 | E7: =C_Pricing_Income!E13 -> 89468.51 | F7: =C_Pricing_Income!F13 -> 100071.59 | G7: =C_Pricing_Income!G13 -> 106008.19
A8: Net gain | C8: =C6-C7 -> 22856.606 | D8: =D6-D7 -> -37330.328 | E8: =E6-E7 -> 17634.14 | F8: =F6-F7 -> 51666.614 | G8: =G6-G7 -> 83681.324
A9: Cumulative net gain | C9: =C8 -> 22856.606 | D9: =C9+D8 -> -14473.723 | E9: =D9+E8 -> 3160.4171 | F9: =E9+F8 -> 54827.031 | G9: =F9+G8 -> 138508.35
A10: Net gain WITHOUT community-programme saving (cash only, after any credit) | C10: =C_Benefits!C10-C7 -> 22856.606 | D10: =C_Benefits!D10-D7 -> -37330.328 | E10: =C_Benefits!E10-E7 -> 17634.14 | F10: =C_Benefits!F10-F7 -> 51666.614 | G10: =C_Benefits!G10-G7 -> 83681.324
A11: Return on what SDP pays (benefit ÷ paid) | C11: =IF(C7<=0,"n/a",C6/C7) -> n/a | D11: =IF(D7<=0,"n/a",D6/D7) -> 0.63679554 | E11: =IF(E7<=0,"n/a",E6/E7) -> 1.1970988 | F11: =IF(F7<=0,"n/a",F6/F7) -> 1.5162965 | G11: =IF(G7<=0,"n/a",G6/G7) -> 1.7893855
A13: A typical new developer (smaller client)
A14: Total benefit | C14: =C_Benefits!C12*Scenarios!$C$12 -> 9142.6423 | D14: =C_Benefits!D12*Scenarios!$C$12 -> 26180.06 | E14: =C_Benefits!E12*Scenarios!$C$12 -> 42841.06 | F14: =C_Benefits!F12*Scenarios!$C$12 -> 60695.283 | G14: =C_Benefits!G12*Scenarios!$C$12 -> 75875.804
A15: Paid to us (after guarantee credit) | C15: =(C_Pricing_Income!C8+C_Pricing_Income!C11)*Scenarios!$C$12-C_Pricing_Income!C26 -> 0 | D15: =(C_Pricing_Income!D8+C_Pricing_Income!D11)*Scenarios!$C$12-C_Pricing_Income!D26 -> 41112.192 | E15: =(C_Pricing_Income!E8+C_Pricing_Income!E11)*Scenarios!$C$12-C_Pricing_Income!E26 -> 35787.404 | F15: =(C_Pricing_Income!F8+C_Pricing_Income!F11)*Scenarios!$C$12-C_Pricing_Income!F26 -> 40028.638 | G15: =(C_Pricing_Income!G8+C_Pricing_Income!G11)*Scenarios!$C$12-C_Pricing_Income!G26 -> 42403.275
A16: Net gain | C16: =C14-C15 -> 9142.6423 | D16: =D14-D15 -> -14932.131 | E16: =E14-E15 -> 7053.6559 | F16: =F14-F15 -> 20666.645 | G16: =G14-G15 -> 33472.53
A17: Net gain WITHOUT community-programme saving (cash only, after any credit) | C17: =C_Benefits!C10*Scenarios!$C$12-C15 -> 9142.6423 | D17: =C_Benefits!D10*Scenarios!$C$12-D15 -> -14932.131 | E17: =C_Benefits!E10*Scenarios!$C$12-E15 -> 7053.6559 | F17: =C_Benefits!F10*Scenarios!$C$12-F15 -> 20666.645 | G17: =C_Benefits!G10*Scenarios!$C$12-G15 -> 33472.53
A19: Checks
A20: SDP gains in Year 1? | C20: =IF(C8>0,"YES","NO") -> YES
A21: New developer gains in its Year 1? | C21: =IF(C16>0,"YES","NO") -> YES
A23: v2 – Contract view and extra checks
A24: Guarantee credit SDP receives | C24: =C_Pricing_Income!C25 -> 20000 | D24: =C_Pricing_Income!D25 -> 34260.16 | E24: =C_Pricing_Income!E25 -> 29822.837 | F24: =C_Pricing_Income!F25 -> 33357.198 | G24: =C_Pricing_Income!G25 -> 35336.062
A25: Net gain if community saving only reaches the guaranteed level | C25: =C_Benefits!C10+MIN(C_Benefits!C11,C_Benefits!C32)-C7 -> 22856.606 | D25: =C_Benefits!D10+MIN(C_Benefits!D11,C_Benefits!D32)-D7 -> -37330.328 | E25: =C_Benefits!E10+MIN(C_Benefits!E11,C_Benefits!E32)-E7 -> 17634.14 | F25: =C_Benefits!F10+MIN(C_Benefits!F11,C_Benefits!F32)-F7 -> 51666.614 | G25: =C_Benefits!G10+MIN(C_Benefits!G11,C_Benefits!G32)-G7 -> 83681.324
A26: Guarantee credit a new client receives | C26: =C_Pricing_Income!C26 -> 8000 | D26: =C_Pricing_Income!D26 -> 13704.064 | E26: =C_Pricing_Income!E26 -> 11929.135 | F26: =C_Pricing_Income!F26 -> 13342.879 | G26: =C_Pricing_Income!G26 -> 14134.425
A27: SDP cash-only net gain > 0 in Year 1? | C27: =IF(C10>0,"YES","NO") -> YES
A28: New developer cash-only net gain > 0 in its Year 1? | C28: =IF(C17>0,"YES","NO") -> YES

Sheet C_Spendings
A1: 3) Spendings – our own cost to build and run the platform (calendar year) – CONSERVATIVE scenario (inputs from Scenarios sheet)
A2: Lean team; cloud cost grows with each client. v2: part of Year 1 pay taken as equity.
A4: Cost line | B4: How it is worked out | C4: Year 1 | D4: Year 2 | E4: Year 3 | F4: Year 4 | G4: Year 5
A5: Clients on the platform | B5: From Benefits | C5: =C_Benefits!C20 -> 1 | D5: =C_Benefits!D20 -> 2 | E5: =C_Benefits!E20 -> 4 | F5: =C_Benefits!F20 -> 6 | G5: =C_Benefits!G20 -> 8
A6: Founders' pay (cash) | B6: People × salary × 12 × (1 + on-cost); Year 1 × cash share | C6: =Assumptions!$B$44*Assumptions!$B$45*12*(1+Assumptions!$B$46)*Assumptions!$B$84 -> 55176 | D6: =Assumptions!$B$44*Assumptions!$B$45*12*(1+Assumptions!$B$46) -> 110352 | E6: =Assumptions!$B$44*Assumptions!$B$45*12*(1+Assumptions!$B$46) -> 110352 | F6: =Assumptions!$B$44*Assumptions!$B$45*12*(1+Assumptions!$B$46) -> 110352 | G6: =Assumptions!$B$44*Assumptions!$B$45*12*(1+Assumptions!$B$46) -> 110352
A7: Contract developer (build Year 1, cash part) | B7: Months × monthly rate × cash share | C7: =Assumptions!$B$47*Assumptions!$B$48*Assumptions!$B$85 -> 29400 | D7: =0 -> 0 | E7: =0 -> 0 | F7: =0 -> 0 | G7: =0 -> 0
A8: Extra developers | B8: People × pay × 12 × (1 + on-cost) | C8: =Yearly_Inputs!$B$11*Assumptions!$B$48*12*(1+Assumptions!$B$46) -> 0 | D8: =Yearly_Inputs!$C$11*Assumptions!$B$48*12*(1+Assumptions!$B$46) -> 0 | E8: =Scenarios!$C$14*Assumptions!$B$48*12*(1+Assumptions!$B$46) -> 0 | F8: =Yearly_Inputs!$E$11*Assumptions!$B$48*12*(1+Assumptions!$B$46) -> 96558 | G8: =Yearly_Inputs!$F$11*Assumptions!$B$48*12*(1+Assumptions!$B$46) -> 193116
A9: Part-time support and operations | B9: From Yearly_Inputs | C9: =Yearly_Inputs!$B$12 -> 0 | D9: =Yearly_Inputs!$C$12 -> 18000 | E9: =Yearly_Inputs!$D$12 -> 36000 | F9: =Yearly_Inputs!$E$12 -> 36000 | G9: =Yearly_Inputs!$F$12 -> 48000
