Workbook

Sheet Summary
A1: Township Green Loop – Executive Summary
A3: SDP University Hackathon 2026 · Theme: Planet · We run the platform; township developers pay to use it; residents invest in three green pools.
A5: Vendor (us, the platform)
A6: Vendor ROI (5-yr) | C6: Vendor net profit (5-yr) | E6: Vendor NPV
A7: =ROI!C16 -> 1.171918 | C7: =ROI!H10 -> 1434165.2 | E7: =ROI!E31 -> 778498.7
A9: Customer (township developers, all clients)
A10: Customer ROI (5-yr) | C10: Customer net profit (5-yr) | E10: Customer NPV
A11: =ROI!C17 -> 1.9631463 | C11: =ROI!H13 -> 3553672.7 | E11: =ROI!C39 -> 2080179.5
A13: ="Discount rate "&TEXT(Assumptions!$B$58,"0%")&" · ROI = (gain − cost) ÷ cost · Customer = benefit to developers minus what they pay us (Customer_ROI has SDP alone)." -> Discount rate 15% · ROI = (gain − cost) ÷ cost · Customer = benefit to developers minus what they pay us (Customer_ROI has SDP alone).
A15: Investor (resident) view: see the Investor_View sheet (minimum and maximum investment for each pool).
A17: Key takeaways
A18: • SDP gains from Year 1 even on cash alone: Year 1 costs only a RM20,000 set-up instalment, and the JV passes a 1% fee on residents' solar money to SDP. Half of the community saving is guaranteed in the contract.
A19: • Residents earn from Year 1 on solar and upgrades; EV is variable with a minimum-usage top-up.
A20: • We lose money in Year 1 (covered by a RM120,000 grant) and earn from Year 2, even if only one new developer signs that year. See Conservative_Test.
A22: Core prices
A23: ="Set-up fee RM"&TEXT(Assumptions!$B$38,"#,##0")&" (RM"&TEXT(Assumptions!$B$60,"#,##0")&" in Year 1, RM"&TEXT(Assumptions!$B$61,"#,##0")&" in Year 2) · Platform fee RM"&TEXT(Assumptions!$B$39,"#,##0")&" a year from Year 2 · Success fee "&TEXT(Assumptions!$B$40,"0.00%")&" (waived in Year 1) · "&TEXT(Assumptions!$B$41,"0.0%")&" a year on money invested · "&TEXT(Assumptions!$B$42,"0%")&" on mall redemptions · smaller developers pay pro rata" -> Set-up fee RM50,000 (RM20,000 in Year 1, RM30,000 in Year 2) · Platform fee RM72,000 a year from Year 2 · Success fee 0.75% (waived in Year 1) · 0.5% a year on money invested · 2% on mall redemptions · smaller developers pay pro rata
A25: Normal vs conservative (live, from Conservative_Test)
A26: Check | C26: Normal | E26: Conservative | G26: Normal | H26: Conservative
A27: 1. Customer (SDP) net gain, Year 1 | C27: =Conservative_Test!B28 -> 126768.55 | E27: =Conservative_Test!C28 -> 5808.8056 | G27: =Conservative_Test!E28 -> PASS | H27: =Conservative_Test!F28 -> PASS
A28: 2. Customer cash-only net gain, Year 1 (no community saving) | C28: =Conservative_Test!B29 -> 22768.55 | E28: =Conservative_Test!C29 -> 5808.8056 | G28: =Conservative_Test!E29 -> PASS | H28: =Conservative_Test!F29 -> PASS
A29: 2b. New developer net gain, its Year 1 | C29: =Conservative_Test!B30 -> 76061.13 | E29: =Conservative_Test!C30 -> 2323.5223 | G29: =Conservative_Test!E30 -> PASS | H29: =Conservative_Test!F30 -> PASS
A30: 3. Residents' profit, Year 1 (all pools, SDP) | C30: =Conservative_Test!B31 -> 82163.299 | E30: =Conservative_Test!C31 -> 50465.897 | G30: =Conservative_Test!E31 -> PASS | H30: =Conservative_Test!F31 -> PASS
A31: 4a. Solar investor return, Year 1 | C31: =Conservative_Test!B32 -> 0.04547563 | E31: =Conservative_Test!C32 -> 0.04547563 | G31: =Conservative_Test!E32 -> PASS | H31: =Conservative_Test!F32 -> PASS
A32: 4b. Upgrade investor return, Year 1 | C32: =Conservative_Test!B33 -> 0.05484129 | E32: =Conservative_Test!C33 -> 0.012947272 | G32: =Conservative_Test!E33 -> PASS | H32: =Conservative_Test!F33 -> PASS
A33: 4c. EV investor loss over the 7-year payback period | C33: =Conservative_Test!B34 -> 0 | E33: =Conservative_Test!C34 -> 0.4 | G33: =Conservative_Test!E34 -> PASS | H33: =Conservative_Test!F34 -> PASS
A34: 5. Vendor net profit, Year 2 | C34: =Conservative_Test!B35 -> 92228.355 | E34: =Conservative_Test!C35 -> 5033.9555 | G34: =Conservative_Test!E35 -> PASS | H34: =Conservative_Test!F35 -> PASS
A35: 6. Vendor net profit, 5 years | C35: =Conservative_Test!B36 -> 1434165.2 | E35: =Conservative_Test!C36 -> 131171.91 | G35: =Conservative_Test!E36 -> PASS | H35: =Conservative_Test!F36 -> PASS
A36: 7. NPV of vendor cash flows | C36: =Conservative_Test!B37 -> 778498.7 | E36: =Conservative_Test!C37 -> 22817.907 | G36: =Conservative_Test!E37 -> PASS | H36: =Conservative_Test!F37 -> PASS
A37: 8. Lowest cash balance in 5 years (with grant) | C37: =Conservative_Test!B38 -> 33918.505 | E37: =Conservative_Test!C38 -> 12403.716 | G37: =Conservative_Test!E38 -> PASS | H37: =Conservative_Test!F38 -> PASS
A38: 9. Vendor lowest yearly net profit, Years 2–5 | C38: =Conservative_Test!B39 -> 92228.355 | E38: =Conservative_Test!C39 -> 5033.9555 | G38: =Conservative_Test!E39 -> PASS | H38: =Conservative_Test!F39 -> PASS
A39: All checks | G39: =Conservative_Test!E40 -> ALL PASS | H39: =Conservative_Test!F40 -> ALL PASS

Sheet Investor_View
A1: Investor_View – what a resident gets from each pool, at the minimum and maximum investment
A2: All numbers link to Investor_ROI and Assumptions. Change the limits in Assumptions rows 96–101.
A4: Per resident | B4: Solar pool (low risk) | D4: Upgrade pool (medium risk) | F4: EV pool (high risk)
B5: Minimum | C5: Maximum | D5: Minimum | E5: Maximum | F5: Minimum | G5: Maximum
A6: Invest | B6: =Assumptions!$B$96 -> 100 | C6: =Assumptions!$B$97 -> 2000 | D6: =Assumptions!$B$98 -> 100 | E6: =Assumptions!$B$99 -> 1000 | F6: =Assumptions!$B$100 -> 100 | G6: =Assumptions!$B$101 -> 500
A7: Investment rate (per year) | B7: =Investor_ROI!B6 -> 0.05 | C7: =Investor_ROI!B6 -> 0.05 | D7: =Investor_ROI!B15 -> 0.065 | E7: =Investor_ROI!B15 -> 0.065 | F7: =Investor_ROI!B57 -> 0.066187268 | G7: =Investor_ROI!B57 -> 0.066187268
A8: Rate type | B8: Fixed payout backed by tenant power payments (not roof leasing); minimum 4.5% | C8: Fixed payout backed by tenant power payments (not roof leasing); minimum 4.5% | D8: Fixed; installer guarantees shop savings | E8: Fixed; installer guarantees shop savings | F8: Variable, not guaranteed; partners top up to 60 kWh/day (capped) | G8: Variable, not guaranteed; partners top up to 60 kWh/day (capped)
A9: Money paid back over | B9: =Assumptions!$B$20&" years, monthly" -> 5 years, monthly | C9: =Assumptions!$B$20&" years, monthly" -> 5 years, monthly | D9: =Assumptions!$B$27&" years, monthly" -> 3 years, monthly | E9: =Assumptions!$B$27&" years, monthly" -> 3 years, monthly | F9: =Investor_ROI!B30&" years, from charging income" -> 7 years, from charging income | G9: =Investor_ROI!B30&" years, from charging income" -> 7 years, from charging income
A10: Normal case
A11: Total received | B11: =B6*(Investor_ROI!B46)/Investor_ROI!B45 -> 113.2274 | C11: =C6*(Investor_ROI!B46)/Investor_ROI!B45 -> 2264.548 | D11: =D6*((Investor_ROI!B50-Investor_ROI!B51))/Investor_ROI!B45 -> 110.33641 | E11: =E6*((Investor_ROI!B50-Investor_ROI!B51))/Investor_ROI!B45 -> 1103.3641 | F11: =F6*(Investor_ROI!B55)/Investor_ROI!B45 -> 128.70961 | G11: =G6*(Investor_ROI!B55)/Investor_ROI!B45 -> 643.54803
A12: Return over the payback period (RM) | B12: =B6*(Investor_ROI!B46)/Investor_ROI!B45-B6 -> 13.227402 | C12: =C6*(Investor_ROI!B46)/Investor_ROI!B45-C6 -> 264.54804 | D12: =D6*((Investor_ROI!B50-Investor_ROI!B51))/Investor_ROI!B45-D6 -> 10.33641 | E12: =E6*((Investor_ROI!B50-Investor_ROI!B51))/Investor_ROI!B45-E6 -> 103.3641 | F12: =F6*(Investor_ROI!B55)/Investor_ROI!B45-F6 -> 28.709607 | G12: =G6*(Investor_ROI!B55)/Investor_ROI!B45-G6 -> 143.54803
A13: Return over the payback period (%) | B13: =(Investor_ROI!B46)/Investor_ROI!B45-1 -> 0.13227402 | C13: =(Investor_ROI!B46)/Investor_ROI!B45-1 -> 0.13227402 | D13: =((Investor_ROI!B50-Investor_ROI!B51))/Investor_ROI!B45-1 -> 0.1033641 | E13: =((Investor_ROI!B50-Investor_ROI!B51))/Investor_ROI!B45-1 -> 0.1033641 | F13: =(Investor_ROI!B55)/Investor_ROI!B45-1 -> 0.28709607 | G13: =(Investor_ROI!B55)/Investor_ROI!B45-1 -> 0.28709607
A14: Conservative case (Pools_Scenarios sheet)
A15: Effective rate (per year) | B15: =Investor_ROI!C8 -> 0.05 | C15: =Investor_ROI!C8 -> 0.05 | D15: =Investor_ROI!C53 -> 0.032304876 | E15: =Investor_ROI!C53 -> 0.032304876 | F15: =Investor_ROI!C57 -> -0.11351477 | G15: =Investor_ROI!C57 -> -0.11351477
A16: Total received | B16: =B6*(Investor_ROI!C46)/Investor_ROI!C45 -> 113.2274 | C16: =C6*(Investor_ROI!C46)/Investor_ROI!C45 -> 2264.548 | D16: =D6*((Investor_ROI!C50-Investor_ROI!C51))/Investor_ROI!C45 -> 105.05843 | E16: =E6*((Investor_ROI!C50-Investor_ROI!C51))/Investor_ROI!C45 -> 1050.5843 | F16: =F6*(Investor_ROI!C55)/Investor_ROI!C45 -> 60 | G16: =G6*(Investor_ROI!C55)/Investor_ROI!C45 -> 300
A17: Return over the payback period (RM) | B17: =B6*(Investor_ROI!C46)/Investor_ROI!C45-B6 -> 13.227402 | C17: =C6*(Investor_ROI!C46)/Investor_ROI!C45-C6 -> 264.54804 | D17: =D6*((Investor_ROI!C50-Investor_ROI!C51))/Investor_ROI!C45-D6 -> 5.0584278 | E17: =E6*((Investor_ROI!C50-Investor_ROI!C51))/Investor_ROI!C45-E6 -> 50.584278 | F17: =F6*(Investor_ROI!C55)/Investor_ROI!C45-F6 -> -40 | G17: =G6*(Investor_ROI!C55)/Investor_ROI!C45-G6 -> -200
A18: Return over the payback period (%) | B18: =(Investor_ROI!C46)/Investor_ROI!C45-1 -> 0.13227402 | C18: =(Investor_ROI!C46)/Investor_ROI!C45-1 -> 0.13227402 | D18: =((Investor_ROI!C50-Investor_ROI!C51))/Investor_ROI!C45-1 -> 0.050584278 | E18: =((Investor_ROI!C50-Investor_ROI!C51))/Investor_ROI!C45-1 -> 0.050584278 | F18: =(Investor_ROI!C55)/Investor_ROI!C45-1 -> -0.4 | G18: =(Investor_ROI!C55)/Investor_ROI!C45-1 -> -0.4
A20: ="Most one resident can put in across all three pools: RM"&TEXT(Assumptions!$B$97+Assumptions!$B$99+Assumptions!$B$101,"#,##0")&". Smallest start: RM"&TEXT(MIN(Assumptions!$B$96,Assumptions!$B$98,Assumptions!$B$100),"#,##0")&" in any one pool." -> Most one resident can put in across all three pools: RM3,500. Smallest start: RM100 in any one pool.
A21: • Payback period: solar 5 years, upgrades 3 years, EV 7 years. Returns are over each pool's own payback period. The return % is the same at the minimum and the maximum; only the RM amount changes.
A22: • Solar: residents are funders, not roof landlords. The developer/JV owns and runs the panels; tenants, malls and factories pay for the power, and residents' payouts are paid first. Different from SDP's CREAM roof-leasing project in Elmina.
A23: • Upgrades: paid back monthly over 3 years. Totals are after expected shop defaults and the bad-debt reserve.
A24: • EV: the thinnest pool. A licensed charge point operator (CPO) co-invests half and runs the chargers. Payouts come only from charging profit; the developer and platform take their 10% shares only after residents get their money back. If usage falls below 60 kWh/day, partners top up (capped at RM3,000 per charger a year). Price wars, cost rises and a refused government grant are NOT covered: in the conservative case residents get back only about 60% of their money.
A25: • Risk disclosure: none of the pools is a deposit and none is covered by PIDM. Money is held by a licensed platform, never by us. Caps (RM2,000 / 1,000 / 500) sit well inside the retail limit of RM10,000 per issuer and RM50,000 a year [R17].

Sheet Business_Case
A1: Business_Case – who pays whom, investment rules, customers, stakeholders and competition
A2: Vendor = us (the platform company); SDP and other township developers are our customers. Green cells are live links to the model.
A4: 1. Business model – who pays whom
A5: Party | B5: Puts in | C5: Gets out | D5: Live number
A6: Residents (investors) | B6: From RM100 per pool through a licensed market operator (RMO). Caps: Solar RM2,000, Upgrades RM1,000, EV RM500. | C6: Monthly payouts to the app wallet; +10% when spent at SDP malls (shop-funded); green points and badges. Solar 5% fixed (minimum 4.5%), Upgrades 6.5% fixed, EV variable (~6.6% expected, not guaranteed). | D6: ="RM"&TEXT(Pools_Scenarios!C50,"#,##0;(#,##0)") -> RM82,163
A7: Shop tenants | B7: Nothing upfront. Pay for solar power about 15% below grid; repay upgrades from 80% of bill savings; installer guarantees at least RM800 a month saving. | C7: Lower bills now; keep 100% of the savings after 3 years; energy dashboard.
A8: EV drivers | B8: Pay RM1.40/kWh (DC 60 kW) or RM1.00/kWh (AC 22 kW); peak and off-peak prices; idle fee after 15 minutes. | C8: Charging at the mall while they shop.
A9: SDP and other developers (OUR CUSTOMERS) | B9: Roofs, malls, tenant relationships, community programme team. Pay us: set-up RM50,000 (RM20,000 in Year 1), platform fee RM72,000 a year from Year 2, usage fees. Bear 50% of the RMO fee. | C9: Cheaper money for solar, JV fee, upgrade fees, extra mall rent, REC sales, community-programme saving, ESG/carbon data for the sustainability report. | D9: ="RM"&TEXT(Customer_ROI!C8,"#,##0;(#,##0)") -> RM126,769
A10: Us – Township Green Loop (VENDOR) | B10: Build and run the app: wallet, points, bills, rewards, impact data, AI advisor. Lean team of 2 founders. | C10: Set-up and platform fees, 0.75% success fee (waived in Year 1), 0.5% a year on money invested, 2% on mall redemptions, shop featured offers and dashboards, REC service fee, 10% of residents' EV profit after they recover their money. | D10: ="Y1 "&TEXT(ROI!C10,"#,##0;(#,##0)")&" · Y2 "&TEXT(ROI!D10,"#,##0;(#,##0)") -> Y1 (86,081) · Y2 92,228
A11: Licensed platform (RMO), e.g. pitchIN or Ethis | B11: Holds residents' money in trust, KYC, regulatory compliance. We are the front end only. | C11: Success fee about 6% + SST of money raised, paid by the issuer (developer 50%, JV/SPV 50%) [R19].
A12: Charge point operator (ChargEV, Gentari, DC Handal, TNB Electron…) | B12: Co-funds 50% of each charger, applies for the MARii grant, runs operations, maintenance, SLA and customer service. | C12: 50% of charging profit plus the service fee; pays 34% of any usage top-up.
A13: SDP × GSPARX JV | B13: Owns and runs the solar assets; funds the 70% residents do not. | C13: Power sales to tenants; lower cost of capital (5% to residents vs 8.5% own money).
A15: 2. Investment rules
A16: Rule | B16: What | C16: Why / source | D16: Where enforced
A17: Who can invest | B17: Verified township residents, plus supporters: family of residents, people who work in the township, former residents. KYC through the RMO for both. | C17: Residents first, supporters welcome: keeps the township at the centre while widening the investor base to fill each raise | D17: RMO onboarding; profile role (resident / supporter)
A18: Resident priority | B18: Residents get the first 14 days of every raise and at least 70% of each pool | C18: Benefits stay local | D18: Raise schedule on each pool
A19: Minimum / caps | B19: From RM100. Per resident: Solar RM2,000, Upgrades RM1,000, EV RM500 | C19: Retail limit RM10,000 per issuer and RM50,000 per 12 months [R17] | D19: Database trigger (pools.min_invest / max_invest)
A20: 12-month limit | B20: RM50,000 in total across all pools in any 12 months | C20: SC retail limit [R17] | D20: Database trigger
A21: Risk statement | B21: Must read and accept each pool's risk statement before the first investment | C21: Investor education duty of the operator | D21: risk_acknowledgements table
A22: Who holds money | B22: SC-recognised market operator holds funds in trust; the app is the front end only | C22: We never touch investor money | D22: Contract with RMO
A23: Solar share | B23: Residents fund at most 30% of each solar asset (20% in the conservative test) | C23: Tenant power payments cover payouts about 1.6x at 30% | D23: Assumptions row 111
A24: Upgrade shops | B24: Only high-energy shops with 3+ years left on lease and a deposit SDP holds; installer guarantees a minimum saving | C24: Tenant credit risk | D24: Shop selection + installer contract
A25: EV exposure | B25: EV under ~10% of each raise; RM500 cap; 'capital can fall' warning; developer and platform shares wait until residents recover their money | C25: Highest-risk pool (EV_Pilot) | D25: Pool cap + app warning
A26: Release of funds | B26: Each asset's money is released only when that asset is ready | C26: No idle money; explains partial Year-1 payouts | D26: RMO escrow
A27: Payouts | B27: Monthly to the app wallet; withdraw, reinvest or spend at SDP malls with +10% | C27: Proposal | D27: wallet_transactions, spend_at_mall()
... A30: Disclosure | B30: Show risk rating, expected payout, total payback and carbon saved before every investment | C30: Investor education | D30: Invest page
A32: 3. Target customers
A33: Segment | B33: Who | C33: Hook | D33: Evidence
A34: Our customer – township developers | B34: SDP first (28 townships and developments [R5]); then other township developers at about 60% of SDP's size | C34: Gain from Year 1; ESG data; tenant retention; mall footfall | D34: ="RM"&TEXT(Customer_ROI!C8,"#,##0;(#,##0)") -> RM126,769
A35: End users – residents with savings | B35: Residents of SDP townships with savings to put to work | C35: 5–6.5% on low-risk pools vs a 12-month FD board rate of about 1.9% [R10]. EPF paid 6.15% for 2025 [R11], so we are a complement, not a replacement.
A36: Active mall shoppers | B36: Residents already using SDP malls | C36: +10% wallet bonus and points make the wallet worth keeping
A37: Supporters | B37: Family of residents (e.g. children working in other states), township workers, former residents | C37: Back the township they care about; same pools, rates and caps; spend points and mall credits when they visit
A38: Shop tenants (B2B) | B38: High-energy shops in KL East Mall, Elmina Lakeside Mall, KLGCC Mall | C38: Lower bills with no upfront cost
A39: Partners | B39: GSPARX/TNB (solar), charge point operator, licensed RMO | C39: Volume, co-branding, ESG story
A41: 4. Stakeholders – what we show each one
A42: Stakeholder | B42: What they care about | C42: What we show / ask | D42: Live number
A43: SDP leadership (our buyer) | B43: Cost, fees, footfall, ESG reporting | C43: Customer_ROI: SDP gains from Year 1; 5-year developer ROI; carbon data. Ask: Year-1 pilot at one township. | D43: ="RM"&TEXT(ROI!H13,"#,##0;(#,##0)") -> RM3,553,673
A44: Mall managers / leasing | B44: Tenant retention, rent | C44: Energy-upgrade pilot with 5–10 shops; extra sales earn only the turnover rent (about 1%), not average rent
A45: Shop tenants | B45: Lower bills, no capex | C45: Solar 15% below grid; 80:20 savings split, then 100% to the shop
A46: Residents | B46: Safe-ish return, local impact | C46: Investor_View: return over each pool's payback period at min and max, risk labels
A47: JV partner / RMO | B47: Volume and compliance | C47: Tranche roadmap; residents fund under 30% of solar; JV shares the RMO fee
A48: Investors in us (grant / pre-seed) | B48: Path to profit | C48: Vendor loses Year 1 (covered by grant), profitable from Year 2 | D48: =TEXT(ROI!C16,"0%")&" 5-yr ROI" -> 117% 5-yr ROI
A50: 5. Competition
A51: Alternative | B51: What it does | C51: Gap Green Loop fills
A52: Equity crowdfunding platforms (e.g. pitchIN, Ethis) | B52: SC-recognised platforms; retail investors up to RM10,000 per issuer and RM50,000 a year [R17] | C52: Start-up equity, not local green assets; no rewards or mall wallet
A53: Green SRI sukuk | B53: Funds large solar plants for institutional investors | C53: Not open to RM100 retail investors
A54: Mall loyalty apps (e.g. Sunway Pals, Pavilion Privileges) | B54: Points on spending | C54: Rewards spending only; nothing to invest in or earn payouts from
A55: Bank FD / EPF | B55: FD board rate ~1.9% [R10], promos higher; EPF 6.15% for 2025 [R11] | C55: Low engagement, no local impact; we add local green yield plus spending power
A56: SDP's own CREAM rooftop leasing (Elmina) | B56: Homeowners rent out roofs to SDP/GSPARX [R4][R4] | C56: We let any resident (incl. condo owners and renters) fund green assets – complements CREAM
A57: Our edge | B57: Invest + earn + spend inside one township app, backed by real SDP assets | C57: First to join all three; SDP owns the roofs, malls and tenant data

Sheet Assumptions
A1: Township Green Loop – Business Plan Assumptions
A2: Blue = input you can change · Yellow = key assumption to check · Black = formula. All money in RM. Yearly inputs (by client year) are in the table at the bottom.
A4: Input | B4: Value | C4: Unit | D4: Source / note
A5: General
A6: Model Year 1 (calendar year) | B6: 2028 | C6: year | D6: Platform goes live after the hackathon pilot.
A7: Average investment per resident | B7: 500 | C7: RM | D7: Assumption. Each pool has its own minimum and maximum (Assumptions rows 96–101).
A8: Share of resident payouts spent at the developer's malls | B8: 0.3 | C8: % | D8: Assumption. Not survey-validated.
A9: Mall redemption bonus (paid by participating shops as a promotion) | B9: 0.1 | C9: % | D9: Design choice. Shops fund it, so it costs the developer nothing.
A10: Turnover rent the mall earns on extra shop sales | B10: 0.01 | C10: % of sales | D10: Assumption: turnover rent of about 1% of gross sales on top of base rent; confirm with SDP leasing.
A11: Average electricity cost for shops (low-voltage commercial) | B11: =Assumptions!$B$102 -> 0.5068 | C11: RM/kWh | D11: Links to row 102: 50.7 sen/kWh low-voltage non-domestic tariff, 1 Jul 2025 – 31 Dec 2027 [R6].
A12: Grid emission factor, Peninsular Malaysia 2024 | B12: 0.74 | C12: tCO2e/MWh | D12: Energy Commission, Grid Emission Factor 2022–2024 (provisional) [R7].
A13: SDP yearly spend on community programmes and spaces | B13: 20800000 | C13: RM/yr | D13: SDP Integrated Report 2024 key highlights: 70,000+ beneficiaries of community programmes and spaces, RM20.8 million total economic spend [R3].
A14: Share of solar funding saving kept by the developer | B14: 0.5 | C14: % | D14: Assumption. Solar assets sit in the SDP × GSPARX joint venture [R1]; the split is not public, so 50% is used.
A15: Pool 1 – Rooftop solar (residents fund it; the developer/JV owns and runs it – not roof leasing)
A16: Installed solar cost | B16: 3200 | C16: RM/kWp | D16: Assumption: commercial rooftop system including SST, mounting and grid works. Confirm with installer quotes.
A17: Solar output per kWp | B17: 1250 | C17: kWh/kWp/yr | D17: Conservative assumption. An academic study of a 216 kWp grid-connected system in Malaysia implies about 1,450 kWh/kWp a year [R25].
A18: Share of each solar asset funded by residents | B18: =Assumptions!$B$111 -> 0.3 | C18: % | D18: Links to row 111 (30%); the conservative case uses row 112 (20%). At 30%, tenant power payments cover payouts about 1.6 times (Investor_ROI).
A19: Payout rate to residents (solar) | B19: 0.05 | C19: % a year | D19: Design choice. Above the 12-month FD board rate of about 1.9% [R10] and below EPF's 6.15% for 2025 [R11].
A20: Solar payout tenure | B20: 5 | C20: years | D20: Design choice.
A21: Return the JV would otherwise need on its own money | B21: 0.085 | C21: % a year | D21: Assumption: return the JV would need on its own money for a solar project.
A22: Pool 2 – Shop energy upgrades
A23: Upgrade cost per shop | B23: 20000 | C23: RM | D23: Assumption (efficient air-con, fridges, LED). Get supplier quotes.
A24: Bill saving per shop | B24: 1000 | C24: RM/month | D24: Assumption: about 25% of a RM4,000 monthly bill. Confirm with energy audits.
A25: Share of savings used to repay residents | B25: 0.8 | C25: % | D25: Malaysian ESCO shared-savings contracts use 80:20 and 75:25 splits (MAESCO) [R20].
A26: Payout rate to residents (upgrades) | B26: 0.065 | C26: % a year | D26: Design choice: higher than solar to reflect shop default risk.
A27: Upgrade payout tenure | B27: 3 | C27: years | D27: Design choice.
A28: Developer's share of the monthly safety margin | B28: 0.5 | C28: % | D28: Design choice. Other half kept as a bad-debt reserve.
A29: Pool 3 – EV charging (DC 60 kW + AC 22 kW, run by a licensed charge point operator)
A30: Installed cost per charger, blended DC/AC mix (before grant) | B30: =Assumptions!$B$115*Assumptions!$B$116+(1-Assumptions!$B$115)*Assumptions!$B$117 -> 62500 | C30: RM | D30: Formula = DC share × DC cost + AC share × AC cost (rows 115–117).
A31: Share of each charger's net cost funded by residents | B31: 0.5 | C31: % | D31: Design choice. The charge point operator (CPO) co-invests the other 50% and runs the chargers (operations, maintenance, SLA, customer service).
A32: DC 60 kW standard charging price | B32: 1.4 | C32: RM/kWh | D32: ChargEV at AEON Mall Cheras Selatan, Jul 2026: 60 kW DC RM1.40, 22 kW AC RM1.00, 180 kW DC RM1.60 per kWh [R24].
A33: Payment and app costs | B33: 0.03 | C33: % of charging revenue | D33: Assumption: payment gateway about 1.5–3% plus app costs.
A34: DC 60 kW maintenance and CPO service fee | B34: 10000 | C34: RM/yr | D34: Assumption: maintenance, warranty and the CPO's service (SLA, customer service), about 10% of installed cost a year.
A35: Energy sold per charger per day | B35: =Assumptions!$B$105*Assumptions!$B$106 -> 60 | C35: kWh/day | D35: Formula = sessions × kWh per session (rows 105–106). Usage is the biggest EV risk.
A36: Developer's share of residents' charging profit (site host) | B36: 0.1 | C36: % | D36: Split of residents' charging profit: residents 70% (row 132), developer 10%, platform 10% (row 133), O&M reserve 10% (row 134). Developer and platform shares wait until residents recover their money (row 135).
A37: Vendor pricing (what we charge each developer)
A38: Set-up fee (total, billed over client Years 1 and 2) | B38: =Assumptions!$B$60+Assumptions!$B$61 -> 50000 | C38: RM | D38: Formula = Year 1 instalment + Year 2 instalment (rows 60–61).
A39: Annual platform fee (from client's second year) | B39: 72000 | C39: RM/yr | D39: Our price for an SDP-size client (RM6,000 a month). Waived in the first year as a pilot. Smaller clients pay pro rata to size.
A40: Success fee on money raised through the platform | B40: 0.0075 | C40: % of raised | D40: Our price, separate from the licensed platform's fee (row 148). Waived in client Year 1 (row 62).
A41: Yearly fee on residents' money still invested | B41: 0.005 | C41: % a year | D41: Our price, from client's second year.
A42: Fee on mall redemptions (paid by shops) | B42: 0.02 | C42: % of redemptions | D42: Our price.
A43: Vendor costs
A44: Founders on payroll | B44: 2 | C44: people | D44: Lean team: product/tech lead + business lead.
A45: Founder salary | B45: 4000 | C45: RM/month | D45: Assumption: junior developer pay.
A46: Employer EPF + SOCSO + EIS | B46: 0.1495 | C46: % of salary | D46: Employer EPF 13% (wages up to RM5,000) + SOCSO 1.75% + EIS 0.2% [R12].
A47: Contract developer, Year 1 | B47: 6 | C47: months | D47: Help build the first version.
A48: Contract / extra developer pay | B48: 7000 | C48: RM/month | D48: Assumption: mid-level developer pay.
A49: Supabase Pro per client | B49: 25 | C49: USD/month | D49: Supabase Pro from US$25 a month per organisation; compute billed separately [R22].
A50: Vercel Pro per seat | B50: 20 | C50: USD/month | D50: Vercel Pro: US$20 a month per deploying seat [R23].
A51: Vercel seats | B51: 2 | C51: seats
A52: USD to RM | B52: 4.4 | C52: RM per USD | D52: Approximate rate; check before use.
A53: Security testing, Year 1 | B53: 15000 | C53: RM | D53: Assumption (penetration test before handling investor data).
A54: Security testing, later years | B54: 8000 | C54: RM/yr | D54: Assumption.
A55: Legal, PDPA and partner agreements, Year 1 | B55: 15000 | C55: RM | D55: Assumption (licensed platform and developer contracts).
A56: Legal and compliance, later years | B56: 5000 | C56: RM/yr | D56: Assumption.
A57: Sales and onboarding per new client | B57: 8000 | C57: RM | D57: Assumption. Used for Year 1 only; later years use row 82.
A58: Discount rate for NPV | B58: 0.15 | C58: % a year | D58: Common range for early-stage tech ventures is 15–20%.
A59: Launch terms (customer must gain in Year 1)
A60: Set-up fee, Year 1 instalment (50% at signing) | B60: 20000 | C60: RM | D60: Split set-up fee so the client pays less in Year 1. Price for an SDP-size client; smaller clients pay pro rata.
A61: Set-up fee, Year 2 instalment (at go-live of full rollout) | B61: 30000 | C61: RM | D61: Billed at go-live of the full rollout.
A62: Success-fee discount in client Year 1 | B62: 1 | C62: % off | D62: 100% = waived in Year 1, in exchange for a signed Year 2 platform-fee commitment.
A63: Community-saving guarantee (makes benefit E contractual)
A64: Community saving actually achieved (vs expected) | B64: 1 | C64: % | D64: Normal case 100%. The conservative test sets this to 0%.
A65: Saving we guarantee in the contract (share of expected) | B65: 0.5 | C65: % | D65: We only promise half of the expected saving.
A66: Share of any shortfall we credit back to the developer | B66: 0.5 | C66: % | D66: Credit against our fees.
A67: Credit cap in client Year 1 (share of that year's fees) | B67: 1 | C67: % | D67: In Year 1 the credit can cancel all fees.
A68: Credit cap from client Year 2 (share of that year's fees) | B68: 0.25 | C68: % | D68: Limits our downside.
A69: Investor protection
A70: JV arrangement fee passed to the developer | B70: 0.01 | C70: % a year of residents' solar money | D70: The JV shares part of its funding saving (8.5% − 5% = 3.5%) with the developer that brings the residents. To negotiate.
A71: Solar minimum payout rate (floor) | B71: 0.045 | C71: % a year | D71: Backed by the JV saving above; the contract rate stays 5%.
A72: Guaranteed minimum saving per shop (installer contract) | B72: 800 | C72: RM/month | D72: Contract term we require: the installer (ESCO) covers any shortfall below this saving.
A73: Shop default rate | B73: 0.02 | C73: % a year | D73: Assumption. The conservative test uses 10%.
A74: Loss when a shop defaults (after deposit and equipment recovery) | B74: 0.5 | C74: % of upgrade cost | D74: Assumption: SDP holds tenant deposits.
A75: EV minimum usage topped up to | B75: 60 | C75: kWh/day/charger | D75: Equal to normal usage, so no top-up in the normal case. If a charger sells less, partners pay residents for the missing kWh at the normal contract margin, up to the yearly cap (row 140).
A76: Share of the top-up paid by the developer | B76: 0.33 | C76: % | D76: Platform pays 33% (row 138) and the CPO 34% (row 139; it also covers its own downtime).
A77: New income lines (paid by shops or from certificate sales, not by the developer)
A78: Renewable energy certificate (REC) price | B78: 3.45 | C78: USD/MWh | D78: Malaysian solar I-REC, US$3.45/MWh, 24 Apr 2026 (S&P Global Platts) [R21].
A79: Our REC registration and sales service fee | B79: 0.1 | C79: % of REC sales | D79: Our price.
A80: Shops buying featured offers in the rewards catalogue | B80: 10 | C80: shops per SDP-size client | D80: Assumption.
A81: Featured-offer fee | B81: 200 | C81: RM/month per shop | D81: Our price.
A82: Energy dashboard subscription for upgraded shops | B82: 50 | C82: RM/month per shop | D82: Our price. Shops track their savings.
A83: Our cost and cash plan
A84: Founders' pay taken in cash in Year 1 | B84: 0.5 | C84: % of salary | D84: Rest taken as equity (non-cash).
A85: Contract developer paid in cash | B85: 0.7 | C85: % of pay | D85: Rest paid in equity.
A86: Onboarding per new client after Year 1 (standardised) | B86: 5000 | C86: RM | D86: Standard onboarding playbook.
A87: Year 1 grant / pre-seed funding | B87: 120000 | C87: RM | D87: Covers the Year 1 loss. Cradle CIP Spark offers up to RM150,000 (conditional grant) [R16].
A88: Solar cover check
A89: Tenant's avoided grid rate | B89: 0.4 | C89: RM/kWh | D89: Assumption: avoided energy cost for a mall on the medium-voltage tariff (energy charge 29.83 sen/kWh plus part of the demand charge) [R6].
A90: PPA discount vs grid | B90: 0.15 | C90: % | D90: Assumption: power sold about 15% below the grid rate.
A91: Solar O&M | B91: 0.01 | C91: % of capex a year | D91: Assumption.
A92: Solar insurance | B92: 0.003 | C92: % of capex a year | D92: Assumption.
A93: Asset management fee on solar revenue | B93: 0.05 | C93: % of revenue | D93: Assumption.
A94: Investment example and limits per resident
A95: Example investment per resident (Investor_ROI 5-year view) | B95: 1000 | C95: RM | D95: Illustration only.
A96: Solar pool: minimum investment | B96: 100 | C96: RM | D96: Low entry so more residents can join (inclusivity).
A97: Solar pool: maximum investment | B97: 2000 | C97: RM | D97: Inside the retail limit of RM10,000 per issuer [R17] and RM50,000 in 12 months [R18]; each pool is a separate issuer. Smaller caps spread each pool across more residents.
A98: Upgrade pool: minimum investment | B98: 100 | C98: RM | D98: Same entry level for all pools.
A99: Upgrade pool: maximum investment | B99: 1000 | C99: RM | D99: Lower than solar because shop default risk is higher.
A100: EV pool: minimum investment | B100: 100 | C100: RM | D100: Same entry level for all pools.
A101: EV pool: maximum investment | B101: 500 | C101: RM | D101: Smallest cap: capital is not guaranteed. In the worst case (EV_Pilot column M) a resident loses about 60%, about RM300 at this cap.
...

Sheet Pools_Scenarios
A1: Pools – what happens inside one client (SDP size), by the client's year on the platform
A2: Money raised, money still invested, payouts and impact for the three pools (other clients are scaled from this). Conservative stress inputs are in the table from row 81.
A4: Item | B4: Unit | C4: Year 1 | D4: Year 2 | E4: Year 3 | F4: Year 4 | G4: Year 5
A5: Timing factors (money is raised mid-year on average)
A6: Year since money was raised | C6: 1 | D6: 2 | E6: 3 | F6: 4 | G6: 5
A7: Solar: share of money still owed at year end | C7: =((1+Assumptions!$B$19)^Assumptions!$B$20-(1+Assumptions!$B$19)^C6)/((1+Assumptions!$B$19)^Assumptions!$B$20-1) -> 0.8190252 | D7: =((1+Assumptions!$B$19)^Assumptions!$B$20-(1+Assumptions!$B$19)^D6)/((1+Assumptions!$B$19)^Assumptions!$B$20-1) -> 0.62900166 | E7: =((1+Assumptions!$B$19)^Assumptions!$B$20-(1+Assumptions!$B$19)^E6)/((1+Assumptions!$B$19)^Assumptions!$B$20-1) -> 0.42947695 | F7: =((1+Assumptions!$B$19)^Assumptions!$B$20-(1+Assumptions!$B$19)^F6)/((1+Assumptions!$B$19)^Assumptions!$B$20-1) -> 0.219976 | G7: =((1+Assumptions!$B$19)^Assumptions!$B$20-(1+Assumptions!$B$19)^G6)/((1+Assumptions!$B$19)^Assumptions!$B$20-1) -> 0
A8: Solar: average share still invested | C8: =0.5 -> 0.5 | D8: =(1+C7)/2 -> 0.9095126 | E8: =(C7+D7)/2 -> 0.72401343 | F8: =(D7+E7)/2 -> 0.52923931 | G8: =(E7+F7)/2 -> 0.32472647
A9: Payout timing (half year in first year) | C9: =0.5 -> 0.5 | D9: =1 -> 1 | E9: =1 -> 1 | F9: =1 -> 1 | G9: =1 -> 1
A10: Upgrades: share still owed at year end | C10: =MAX(0,((1+Assumptions!$B$26)^Assumptions!$B$27-(1+Assumptions!$B$26)^C6)/((1+Assumptions!$B$26)^Assumptions!$B$27-1)) -> 0.6874243 | D10: =MAX(0,((1+Assumptions!$B$26)^Assumptions!$B$27-(1+Assumptions!$B$26)^D6)/((1+Assumptions!$B$26)^Assumptions!$B$27-1)) -> 0.35453118 | E10: =MAX(0,((1+Assumptions!$B$26)^Assumptions!$B$27-(1+Assumptions!$B$26)^E6)/((1+Assumptions!$B$26)^Assumptions!$B$27-1)) -> 0 | F10: =MAX(0,((1+Assumptions!$B$26)^Assumptions!$B$27-(1+Assumptions!$B$26)^F6)/((1+Assumptions!$B$26)^Assumptions!$B$27-1)) -> 0 | G10: =MAX(0,((1+Assumptions!$B$26)^Assumptions!$B$27-(1+Assumptions!$B$26)^G6)/((1+Assumptions!$B$26)^Assumptions!$B$27-1)) -> 0
A11: Upgrades: average share still invested | C11: =0.5 -> 0.5 | D11: =(1+C10)/2 -> 0.84371215 | E11: =(C10+D10)/2 -> 0.52097774 | F11: =(D10+E10)/2 -> 0.17726559 | G11: =(E10+F10)/2 -> 0
A12: Upgrades: share of year a shop is repaying | C12: =0.5 -> 0.5 | D12: =1 -> 1 | E12: =1 -> 1 | F12: =0.5 -> 0.5 | G12: =0 -> 0
A13: EV: average share still invested (paid back evenly over the EV payback period) | C13: =0.5*(1+(1-0.5/Assumptions!$B$137))/2 -> 0.48214286 | D13: =MAX(0,1-1/Assumptions!$B$137) -> 0.85714286 | E13: =MAX(0,1-2/Assumptions!$B$137) -> 0.71428571 | F13: =MAX(0,1-3/Assumptions!$B$137) -> 0.57142857 | G13: =MAX(0,1-4/Assumptions!$B$137) -> 0.42857143
A14: EV: share of money paid back in the year | C14: =0.5/Assumptions!$B$137 -> 0.071428571 | D14: =IF(2-0.5<=Assumptions!$B$137,1/Assumptions!$B$137,0) -> 0.14285714 | E14: =IF(3-0.5<=Assumptions!$B$137,1/Assumptions!$B$137,0) -> 0.14285714 | F14: =IF(4-0.5<=Assumptions!$B$137,1/Assumptions!$B$137,0) -> 0.14285714 | G14: =IF(5-0.5<=Assumptions!$B$137,1/Assumptions!$B$137,0) -> 0.14285714
A15: Pool 1 – Rooftop solar
A16: New solar capacity with resident share | B16: MW | C16: =Assumptions!$B$155 -> 3 | D16: =Assumptions!$C$155 -> 3 | E16: =Assumptions!$D$155 -> 4 | F16: =Assumptions!$E$155 -> 5 | G16: =Assumptions!$F$155 -> 5
A17: Money raised from residents | B17: RM | C17: =C16*1000*Assumptions!$B$16*Assumptions!$B$18 -> 2880000 | D17: =D16*1000*Assumptions!$B$16*Assumptions!$B$18 -> 2880000 | E17: =E16*1000*Assumptions!$B$16*Assumptions!$B$18 -> 3840000 | F17: =F16*1000*Assumptions!$B$16*Assumptions!$B$18 -> 4800000 | G17: =G16*1000*Assumptions!$B$16*Assumptions!$B$18 -> 4800000
A18: Residents' money still invested (average) | B18: RM | C18: =C17*C8 -> 1440000 | D18: =C17*D8+D17*C8 -> 4059396.3 | E18: =C17*E8+D17*D8+E17*C8 -> 6624555 | F18: =C17*F8+D17*E8+E17*D8+F17*C8 -> 9501896.3 | G18: =C17*G8+D17*F8+E17*E8+F17*D8+G17*C8 -> 12005294
A19: Yearly payment per RM1 raised | B19: factor | C19: =PMT(Assumptions!$B$19,Assumptions!$B$20,-1) -> 0.2309748 | D19: =PMT(Assumptions!$B$19,Assumptions!$B$20,-1) -> 0.2309748 | E19: =PMT(Assumptions!$B$19,Assumptions!$B$20,-1) -> 0.2309748 | F19: =PMT(Assumptions!$B$19,Assumptions!$B$20,-1) -> 0.2309748 | G19: =PMT(Assumptions!$B$19,Assumptions!$B$20,-1) -> 0.2309748
A20: Payouts to residents | B20: RM | C20: =(C17*C9)*C19 -> 332603.71 | D20: =(C17*D9+D17*C9)*D19 -> 997811.13 | E20: =(C17*E9+D17*D9+E17*C9)*E19 -> 1773886.4 | F20: =(C17*F9+D17*E9+E17*D9+F17*C9)*F19 -> 2771697.6 | G20: =(C17*G9+D17*F9+E17*E9+F17*D9+G17*C9)*G19 -> 3880376.6
A21: Solar capacity running (average) | B21: MW | C21: =C16*C9 -> 1.5 | D21: =C16*D9+D16*C9 -> 4.5 | E21: =C16*E9+D16*D9+E16*C9 -> 8 | F21: =C16*F9+D16*E9+E16*D9+F16*C9 -> 12.5 | G21: =C16*G9+D16*F9+E16*E9+F16*D9+G16*C9 -> 17.5
A22: Solar power produced | B22: MWh | C22: =C21*Assumptions!$B$17 -> 1875 | D22: =D21*Assumptions!$B$17 -> 5625 | E22: =E21*Assumptions!$B$17 -> 10000 | F22: =F21*Assumptions!$B$17 -> 15625 | G22: =G21*Assumptions!$B$17 -> 21875
A23: CO2 avoided by solar | B23: tCO2e | C23: =C22*Assumptions!$B$12 -> 1387.5 | D23: =D22*Assumptions!$B$12 -> 4162.5 | E23: =E22*Assumptions!$B$12 -> 7400 | F23: =F22*Assumptions!$B$12 -> 11562.5 | G23: =G22*Assumptions!$B$12 -> 16187.5
A24: Pool 2 – Shop energy upgrades
A25: New shops upgraded | B25: shops | C25: =Assumptions!$B$156 -> 15 | D25: =Assumptions!$C$156 -> 25 | E25: =Assumptions!$D$156 -> 10 | F25: =Assumptions!$E$156 -> 10 | G25: =Assumptions!$F$156 -> 10
A26: Money raised from residents | B26: RM | C26: =C25*Assumptions!$B$23 -> 300000 | D26: =D25*Assumptions!$B$23 -> 500000 | E26: =E25*Assumptions!$B$23 -> 200000 | F26: =F25*Assumptions!$B$23 -> 200000 | G26: =G25*Assumptions!$B$23 -> 200000
A27: Residents' money still invested (average) | B27: RM | C27: =C26*C11 -> 150000 | D27: =C26*D11+D26*C11 -> 503113.64 | E27: =C26*E11+D26*D11+E26*C11 -> 678149.4 | F27: =C26*F11+D26*E11+E26*D11+F26*C11 -> 582410.97 | G27: =C26*G11+D26*F11+E26*E11+F26*D11+G26*C11 -> 461570.77
A28: Shops repaying (shop-years) | B28: shop-yrs | C28: =C25*C12 -> 7.5 | D28: =C25*D12+D25*C12 -> 27.5 | E28: =C25*E12+D25*D12+E25*C12 -> 45 | F28: =C25*F12+D25*E12+E25*D12+F25*C12 -> 47.5 | G28: =C25*G12+D25*F12+E25*E12+F25*D12+G25*C12 -> 37.5
A29: Yearly payout per shop to residents | B29: RM | C29: =PMT(Assumptions!$B$26/12,Assumptions!$B$27*12,-Assumptions!$B$23)*12 -> 7355.7607 | D29: =PMT(Assumptions!$B$26/12,Assumptions!$B$27*12,-Assumptions!$B$23)*12 -> 7355.7607 | E29: =PMT(Assumptions!$B$26/12,Assumptions!$B$27*12,-Assumptions!$B$23)*12 -> 7355.7607 | F29: =PMT(Assumptions!$B$26/12,Assumptions!$B$27*12,-Assumptions!$B$23)*12 -> 7355.7607 | G29: =PMT(Assumptions!$B$26/12,Assumptions!$B$27*12,-Assumptions!$B$23)*12 -> 7355.7607
A30: Payouts to residents | B30: RM | C30: =C28*C29 -> 55168.205 | D30: =D28*D29 -> 202283.42 | E30: =E28*E29 -> 331009.23 | F30: =F28*F29 -> 349398.63 | G30: =G28*G29 -> 275841.03
A31: Safety margin per shop-year (repayment counted − payout) | B31: RM | C31: =C56*12-C29 -> 2244.2393 | D31: =D56*12-D29 -> 2244.2393 | E31: =E56*12-E29 -> 2244.2393 | F31: =F56*12-F29 -> 2244.2393 | G31: =G56*12-G29 -> 2244.2393
A32: Savings shops keep | B32: RM | C32: =C28*Assumptions!$B$24*12*(1-Assumptions!$B$25) -> 18000 | D32: =D28*Assumptions!$B$24*12*(1-Assumptions!$B$25) -> 66000 | E32: =E28*Assumptions!$B$24*12*(1-Assumptions!$B$25) -> 108000 | F32: =F28*Assumptions!$B$24*12*(1-Assumptions!$B$25) -> 114000 | G32: =G28*Assumptions!$B$24*12*(1-Assumptions!$B$25) -> 90000
A33: Electricity saved | B33: MWh | C33: =C28*Assumptions!$B$24*12/Assumptions!$B$11/1000 -> 177.58485 | D33: =D28*Assumptions!$B$24*12/Assumptions!$B$11/1000 -> 651.14444 | E33: =E28*Assumptions!$B$24*12/Assumptions!$B$11/1000 -> 1065.5091 | F33: =F28*Assumptions!$B$24*12/Assumptions!$B$11/1000 -> 1124.704 | G33: =G28*Assumptions!$B$24*12/Assumptions!$B$11/1000 -> 887.92423
A34: CO2 avoided by upgrades | B34: tCO2e | C34: =C33*Assumptions!$B$12 -> 131.41279 | D34: =D33*Assumptions!$B$12 -> 481.84688 | E34: =E33*Assumptions!$B$12 -> 788.47672 | F34: =F33*Assumptions!$B$12 -> 832.28098 | G34: =G33*Assumptions!$B$12 -> 657.06393
A35: Pool 3 – EV charging
A36: New EV chargers | B36: chargers | C36: =Assumptions!$B$157 -> 1 | D36: =Assumptions!$C$157 -> 2 | E36: =Assumptions!$D$157 -> 2 | F36: =Assumptions!$E$157 -> 2 | G36: =Assumptions!$F$157 -> 2
A37: Money raised from residents (net cost after grant × residents' share) | B37: RM | C37: =C36*EV_Pilot!$B$46*Assumptions!$B$31 -> 22500 | D37: =D36*EV_Pilot!$B$46*Assumptions!$B$31 -> 45000 | E37: =E36*EV_Pilot!$B$46*Assumptions!$B$31 -> 45000 | F37: =F36*EV_Pilot!$B$46*Assumptions!$B$31 -> 45000 | G37: =G36*EV_Pilot!$B$46*Assumptions!$B$31 -> 45000
A38: Residents' money still invested (average) | B38: RM | C38: =C37*C13 -> 10848.214 | D38: =C37*D13+D37*C13 -> 40982.143 | E38: =C37*E13+D37*D13+E37*C13 -> 76339.286 | F38: =C37*F13+D37*E13+E37*D13+F37*C13 -> 105267.86 | G38: =C37*G13+D37*F13+E37*E13+F37*D13+G37*C13 -> 127767.86
A39: Chargers running (charger-years) | B39: chg-yrs | C39: =C36*C9 -> 0.5 | D39: =C36*D9+D36*C9 -> 2 | E39: =C36*E9+D36*D9+E36*C9 -> 4 | F39: =C36*F9+D36*E9+E36*D9+F36*C9 -> 6 | G39: =C36*G9+D36*F9+E36*E9+F36*D9+G36*C9 -> 8
A40: Net charging profit per charger-year (blended DC/AC, from EV_Pilot) | B40: RM | C40: =EV_Pilot!$B$50 -> 8979.74 | D40: =EV_Pilot!$B$50 -> 8979.74 | E40: =EV_Pilot!$B$50 -> 8979.74 | F40: =EV_Pilot!$B$50 -> 8979.74 | G40: =EV_Pilot!$B$50 -> 8979.74
A41: Residents' share of charging profit (their 50%, before the 70/10/10/10 split) | B41: RM | C41: =C39*EV_Pilot!$B$54 -> 2244.935 | D41: =D39*EV_Pilot!$B$54 -> 8979.74 | E41: =E39*EV_Pilot!$B$54 -> 17959.48 | F41: =F39*EV_Pilot!$B$54 -> 26939.22 | G41: =G39*EV_Pilot!$B$54 -> 35918.96
A42: Payouts to residents (incl. usage top-up) | B42: RM | C42: =C68*EV_Pilot!$B$56+C69*EV_Pilot!$B$57+C39*EV_Pilot!$B$65 -> 2020.4415 | D42: =D68*EV_Pilot!$B$56+D69*EV_Pilot!$B$57+D39*EV_Pilot!$B$65 -> 8081.766 | E42: =E68*EV_Pilot!$B$56+E69*EV_Pilot!$B$57+E39*EV_Pilot!$B$65 -> 16163.532 | F42: =F68*EV_Pilot!$B$56+F69*EV_Pilot!$B$57+F39*EV_Pilot!$B$65 -> 24245.298 | G42: =G68*EV_Pilot!$B$56+G69*EV_Pilot!$B$57+G39*EV_Pilot!$B$65 -> 32327.064
A43: Residents' EV money paid back | B43: RM | C43: =C37*C14 -> 1607.1429 | D43: =C37*D14+D37*C14 -> 6428.5714 | E43: =C37*E14+D37*D14+E37*C14 -> 12857.143 | F43: =C37*F14+D37*E14+E37*D14+F37*C14 -> 19285.714 | G43: =C37*G14+D37*F14+E37*E14+F37*D14+G37*C14 -> 25714.286
A44: All pools – totals for one SDP-size client
A45: Money raised from residents | B45: RM | C45: =C17+C26+C37 -> 3202500 | D45: =D17+D26+D37 -> 3425000 | E45: =E17+E26+E37 -> 4085000 | F45: =F17+F26+F37 -> 5045000 | G45: =G17+G26+G37 -> 5045000
A46: Residents' money still invested (average) | B46: RM | C46: =C18+C27+C38 -> 1600848.2 | D46: =D18+D27+D38 -> 4603492.1 | E46: =E18+E27+E38 -> 7379043.7 | F46: =F18+F27+F38 -> 10189575 | G46: =G18+G27+G38 -> 12594632
A47: Payouts to residents | B47: RM | C47: =C20+C30+C42 -> 389792.36 | D47: =D20+D30+D42 -> 1208176.3 | E47: =E20+E30+E42 -> 2121059.2 | F47: =F20+F30+F42 -> 3145341.5 | G47: =G20+G30+G42 -> 4188544.7
A48: Spent at the developer's malls (incl. bonus) | B48: RM | C48: =C47*Assumptions!$B$8*(1+Assumptions!$B$9) -> 128631.48 | D48: =D47*Assumptions!$B$8*(1+Assumptions!$B$9) -> 398698.18 | E48: =E47*Assumptions!$B$8*(1+Assumptions!$B$9) -> 699949.54 | F48: =F47*Assumptions!$B$8*(1+Assumptions!$B$9) -> 1037962.7 | G48: =G47*Assumptions!$B$8*(1+Assumptions!$B$9) -> 1382219.8
A49: Resident investments made (count, at average ticket) | B49: count | C49: =C45/Assumptions!$B$7 -> 6405 | D49: =D45/Assumptions!$B$7 -> 6850 | E49: =E45/Assumptions!$B$7 -> 8170 | F49: =F45/Assumptions!$B$7 -> 10090 | G49: =G45/Assumptions!$B$7 -> 10090
A50: Residents' profit earned (after expected shop losses) | B50: RM | C50: =C18*Assumptions!$B$19+C27*Assumptions!$B$26-C59+C42-C43 -> 82163.299 | D50: =D18*Assumptions!$B$19+D27*Assumptions!$B$26-D59+D42-D43 -> 237325.4 | E50: =E18*Assumptions!$B$19+E27*Assumptions!$B$26-E59+E42-E43 -> 378613.85 | F50: =F18*Assumptions!$B$19+F27*Assumptions!$B$26-F59+F42-F43 -> 517911.11 | G50: =G18*Assumptions!$B$19+G27*Assumptions!$B$26-G59+G42-G43 -> 636879.55
A51: CO2 avoided by assets residents co-fund (solar + upgrades) | B51: tCO2e | C51: =C23+C34 -> 1518.9128 | D51: =D23+D34 -> 4644.3469 | E51: =E23+E34 -> 8188.4767 | F51: =F23+F34 -> 12394.781 | G51: =G23+G34 -> 16844.564
A53: Note: timing factors are simple approximations (money raised mid-year; solar and upgrades repaid monthly; EV money returned from charging profit, not guaranteed).
A55: Guarantees, expected losses and certificates
A56: Repayment counted per shop-month (higher of actual or guaranteed saving × repay share) | B56: RM | C56: =MAX(Assumptions!$B$24,Assumptions!$B$72)*Assumptions!$B$25 -> 800 | D56: =MAX(Assumptions!$B$24,Assumptions!$B$72)*Assumptions!$B$25 -> 800 | E56: =MAX(Assumptions!$B$24,Assumptions!$B$72)*Assumptions!$B$25 -> 800 | F56: =MAX(Assumptions!$B$24,Assumptions!$B$72)*Assumptions!$B$25 -> 800 | G56: =MAX(Assumptions!$B$24,Assumptions!$B$72)*Assumptions!$B$25 -> 800
A57: Expected default loss per shop-year | B57: RM | C57: =Assumptions!$B$23*Assumptions!$B$73*Assumptions!$B$74 -> 200 | D57: =Assumptions!$B$23*Assumptions!$B$73*Assumptions!$B$74 -> 200 | E57: =Assumptions!$B$23*Assumptions!$B$73*Assumptions!$B$74 -> 200 | F57: =Assumptions!$B$23*Assumptions!$B$73*Assumptions!$B$74 -> 200 | G57: =Assumptions!$B$23*Assumptions!$B$73*Assumptions!$B$74 -> 200
A58: Bad-debt reserve per shop-year (unused half of margin) | B58: RM | C58: =MAX(0,C31)*(1-Assumptions!$B$28) -> 1122.1197 | D58: =MAX(0,D31)*(1-Assumptions!$B$28) -> 1122.1197 | E58: =MAX(0,E31)*(1-Assumptions!$B$28) -> 1122.1197 | F58: =MAX(0,F31)*(1-Assumptions!$B$28) -> 1122.1197 | G58: =MAX(0,G31)*(1-Assumptions!$B$28) -> 1122.1197
A59: Residents' uncovered loss on upgrades | B59: RM | C59: =C28*(MAX(0,C57-C58)+MAX(0,-C31)) -> 0 | D59: =D28*(MAX(0,D57-D58)+MAX(0,-D31)) -> 0 | E59: =E28*(MAX(0,E57-E58)+MAX(0,-E31)) -> 0 | F59: =F28*(MAX(0,F57-F58)+MAX(0,-F31)) -> 0 | G59: =G28*(MAX(0,G57-G58)+MAX(0,-G31)) -> 0
A60: kWh sold per charger-day (after downtime) | B60: kWh | C60: =EV_Pilot!$B$9 -> 60 | D60: =EV_Pilot!$B$9 -> 60 | E60: =EV_Pilot!$B$9 -> 60 | F60: =EV_Pilot!$B$9 -> 60 | G60: =EV_Pilot!$B$9 -> 60
A61: usage top-up per charger-year (after cap) | B61: RM | C61: =EV_Pilot!$B$65 -> 0 | D61: =EV_Pilot!$B$65 -> 0 | E61: =EV_Pilot!$B$65 -> 0 | F61: =EV_Pilot!$B$65 -> 0 | G61: =EV_Pilot!$B$65 -> 0
A62: usage top-up paid to residents (developer + platform + CPO) | B62: RM | C62: =C39*C61 -> 0 | D62: =D39*D61 -> 0 | E62: =E39*E61 -> 0 | F62: =F39*F61 -> 0 | G62: =G39*G61 -> 0
A63: Solar MWh from the residents' share (for certificates) | B63: MWh | C63: =C22*Assumptions!$B$18 -> 562.5 | D63: =D22*Assumptions!$B$18 -> 1687.5 | E63: =E22*Assumptions!$B$18 -> 3000 | F63: =F22*Assumptions!$B$18 -> 4687.5 | G63: =G22*Assumptions!$B$18 -> 6562.5
A65: EV: who is paid while residents recover their money
A66: EV: charger-year factor while residents recover (by age) | C66: =C9*IF(C6-0.5<EV_Pilot!$B$73,1,0) -> 0.5 | D66: =D9*IF(D6-0.5<EV_Pilot!$B$73,1,0) -> 1 | E66: =E9*IF(E6-0.5<EV_Pilot!$B$73,1,0) -> 1 | F66: =F9*IF(F6-0.5<EV_Pilot!$B$73,1,0) -> 1 | G66: =G9*IF(G6-0.5<EV_Pilot!$B$73,1,0) -> 1
A67: EV: charger-year factor after residents recover (by age) | C67: =C9-C66 -> 0 | D67: =D9-D66 -> 0 | E67: =E9-E66 -> 0 | F67: =F9-F66 -> 0 | G67: =G9-G66 -> 0
A68: EV charger-years while residents recover | B68: chg-yrs | C68: =C36*C66 -> 0.5 | D68: =C36*D66+D36*C66 -> 2 | E68: =C36*E66+D36*D66+E36*C66 -> 4 | F68: =C36*F66+D36*E66+E36*D66+F36*C66 -> 6 | G68: =C36*G66+D36*F66+E36*E66+F36*D66+G36*C66 -> 8
A69: EV charger-years after residents recover | B69: chg-yrs | C69: =C36*C67 -> 0 | D69: =C36*D67+D36*C67 -> 0 | E69: =C36*E67+D36*D67+E36*C67 -> 0 | F69: =C36*F67+D36*E67+E36*D67+F36*C67 -> 0 | G69: =C36*G67+D36*F67+E36*E67+F36*D67+G36*C67 -> 0
A70: Developer's 10% share of residents' EV profit (paid after recovery if deferral is on) | B70: RM | C70: =IF(Assumptions!$B$135=1,C69,C39)*EV_Pilot!$B$58 -> 0 | D70: =IF(Assumptions!$B$135=1,D69,D39)*EV_Pilot!$B$58 -> 0 | E70: =IF(Assumptions!$B$135=1,E69,E39)*EV_Pilot!$B$58 -> 0 | F70: =IF(Assumptions!$B$135=1,F69,F39)*EV_Pilot!$B$58 -> 0 | G70: =IF(Assumptions!$B$135=1,G69,G39)*EV_Pilot!$B$58 -> 0
A71: Developer's part of the usage top-up | B71: RM | C71: =C39*EV_Pilot!$B$66 -> 0 | D71: =D39*EV_Pilot!$B$66 -> 0 | E71: =E39*EV_Pilot!$B$66 -> 0 | F71: =F39*EV_Pilot!$B$66 -> 0 | G71: =G39*EV_Pilot!$B$66 -> 0
A72: Platform's 10% share of residents' EV profit (paid after recovery if deferral is on) | B72: RM | C72: =IF(Assumptions!$B$135=1,C69,C39)*EV_Pilot!$B$59 -> 0 | D72: =IF(Assumptions!$B$135=1,D69,D39)*EV_Pilot!$B$59 -> 0 | E72: =IF(Assumptions!$B$135=1,E69,E39)*EV_Pilot!$B$59 -> 0 | F72: =IF(Assumptions!$B$135=1,F69,F39)*EV_Pilot!$B$59 -> 0 | G72: =IF(Assumptions!$B$135=1,G69,G39)*EV_Pilot!$B$59 -> 0
A73: Platform's part of the usage top-up | B73: RM | C73: =C39*EV_Pilot!$B$67 -> 0 | D73: =D39*EV_Pilot!$B$67 -> 0 | E73: =E39*EV_Pilot!$B$67 -> 0 | F73: =F39*EV_Pilot!$B$67 -> 0 | G73: =G39*EV_Pilot!$B$67 -> 0
A75: Licensed platform (RMO) fee, spread over the payout period
A76: Share of each raise's RMO fee counted in the year (by age) | C76: =0.5/Assumptions!$B$151 -> 0.1 | D76: =IF(2-0.5<=Assumptions!$B$151,1/Assumptions!$B$151,0) -> 0.2 | E76: =IF(3-0.5<=Assumptions!$B$151,1/Assumptions!$B$151,0) -> 0.2 | F76: =IF(4-0.5<=Assumptions!$B$151,1/Assumptions!$B$151,0) -> 0.2 | G76: =IF(5-0.5<=Assumptions!$B$151,1/Assumptions!$B$151,0) -> 0.2
A77: Money raised whose RMO fee is counted this year | B77: RM | C77: =C45*C76 -> 320250 | D77: =C45*D76+D45*C76 -> 983000 | E77: =C45*E76+D45*D76+E45*C76 -> 1734000 | F77: =C45*F76+D45*E76+E45*D76+F45*C76 -> 2647000 | G77: =C45*G76+D45*F76+E45*E76+F45*D76+G45*C76 -> 3656000
A78: RMO fee cost borne by the developer (spread) | B78: RM | C78: =C77*Assumptions!$B$148*(1+Assumptions!$B$149)*Assumptions!$B$150 -> 10376.1 | D78: =D77*Assumptions!$B$148*(1+Assumptions!$B$149)*Assumptions!$B$150 -> 31849.2 | E78: =E77*Assumptions!$B$148*(1+Assumptions!$B$149)*Assumptions!$B$150 -> 56181.6 | F78: =F77*Assumptions!$B$148*(1+Assumptions!$B$149)*Assumptions!$B$150 -> 85762.8 | G78: =G77*Assumptions!$B$148*(1+Assumptions!$B$149)*Assumptions!$B$150 -> 118454.4
A81: Conservative scenario – stress inputs (drive the hidden C_ sheets and the conservative checks on Summary)
A82: Stressed input | B82: Normal | C82: Conservative | D82: Change | E82: Why
A83: Community saving actually achieved | B83: =Assumptions!$B$64 -> 1 | C83: 0 | D83: =IF(B83=0,"",C83/B83-1) -> -1 | E83: Benefit E fails completely.
A84: EV energy sold per charger per day (kWh) = sessions × kWh per session | B84: =Assumptions!$B$35 -> 60 | C84: =C93*C94 -> 30 | D84: =IF(B84=0,"",C84/B84-1) -> -0.5 | E84: Half the normal usage (rows 93–94).
A85: Bill saving per shop (RM/month) | B85: =Assumptions!$B$24 -> 1000 | C85: 500 | D85: =IF(B85=0,"",C85/B85-1) -> -0.5 | E85: Upgrades save half as much.
A86: New developer clients signed in Year 2 | B86: =Assumptions!$C$159 -> 2 | C86: 1 | D86: =IF(B86=0,"",C86/B86-1) -> -0.5 | E86: Only one new client in Year 2.
A87: Developer's share of solar funding saving | B87: =Assumptions!$B$14 -> 0.5 | C87: 0.3 | D87: =IF(B87=0,"",C87/B87-1) -> -0.4 | E87: Weaker JV terms.
A88: Discount rate for NPV | B88: =Assumptions!$B$58 -> 0.15 | C88: 0.2 | D88: =IF(B88=0,"",C88/B88-1) -> 0.33333333 | E88: Higher required return.
A89: Competitor price drop (all charging prices) | B89: =0 -> 0 | C89: 0.2 | D89: =IF(B89=0,"",C89/B89-1) | E89: Price war: all prices 20% lower.
A90: Size of new clients vs SDP (Years 2–5) | B90: =Assumptions!$C$160 -> 0.6 | C90: 0.4 | D90: =IF(B90=0,"",C90/B90-1) -> -0.33333333 | E90: Smaller developers sign up.
A91: Shop default rate (a year) | B91: =Assumptions!$B$73 -> 0.02 | C91: 0.1 | D91: =IF(B91=0,"",C91/B91-1) -> 4 | E91: Five times more shop defaults.
A92: Extra developers hired in Year 3 (our response, not a stress) | B92: =Assumptions!$D$161 -> 1 | C92: 0 | D92: =IF(B92=0,"",C92/B92-1) -> -1 | E92: Delay the hire when fewer clients sign.
A93: EV: charging sessions per charger per day | B93: =Assumptions!$B$105 -> 2 | C93: 1.5 | D93: =IF(B93=0,"",C93/B93-1) -> -0.25 | E93: 1.5 sessions × 20 kWh = 30 kWh/day.
A94: EV: average kWh per session | B94: =Assumptions!$B$106 -> 30 | C94: 20 | D94: =IF(B94=0,"",C94/B94-1) -> -0.33333333 | E94: Smaller top-ups.
A95: EV: electricity cost increase | B95: =0 -> 0 | C95: 0.2 | D95: =IF(B95=0,"",C95/B95-1) | E95: Tariff or AFA surcharge up 20%.
A96: EV: maintenance cost increase | B96: =0 -> 0 | C96: 0.5 | D96: =IF(B96=0,"",C96/B96-1) | E96: Repairs and parts 50% dearer.
A97: EV: charger downtime | B97: =0 -> 0 | C97: 0.1 | D97: =IF(B97=0,"",C97/B97-1) | E97: Chargers out of service 10% of the time.
A98: EV: MARii grant approved (1 = yes, 0 = no) | B98: =1 -> 1 | C98: 0 | D98: =IF(B98=0,"",C98/B98-1) -> -1 | E98: Grant not approved; residents and CPO fund the full DC cost.
A99: EV: billed idle minutes per charger per day | B99: =Assumptions!$B$124 -> 10 | C99: 5 | D99: =IF(B99=0,"",C99/B99-1) -> -0.5 | E99: Half the idle-fee income.
A100: EV: paying members per charger | B100: =Assumptions!$B$126 -> 10 | C100: 5 | D100: =IF(B100=0,"",C100/B100-1) -> -0.5 | E100: Half the membership income.
A101: Solar: residents' share of each solar asset | B101: =Assumptions!$B$111 -> 0.3 | C101: =Assumptions!$B$112 -> 0.2 | D101: =IF(B101=0,"",C101/B101-1) -> -0.33333333 | E101: Assumptions row 112.
A102: RMO success fee on money raised | B102: =Assumptions!$B$148 -> 0.06 | C102: 0.07 | D102: =IF(B102=0,"",C102/B102-1) -> 0.16666667 | E102: Top of the pitchIN schedule (raises under RM3m).
A103: Share of the RMO fee borne by the developer | B103: =Assumptions!$B$150 -> 0.5 | C103: 1 | D103: =IF(B103=0,"",C103/B103-1) -> 1 | E103: JV refuses to share the fee.
A104: Charging price after drop (RM/kWh) | B104: =Assumptions!$B$32 -> 1.4 | C104: =Assumptions!$B$32*(1-Pools_Scenarios!$C$89) -> 1.12

Sheet EV_Pilot
A1: EV_Pilot – one charger's economics, who gets the money, and stress tests
A2: Each column is a case. B = normal, C = conservative (all stresses together, from Pools_Scenarios). D–K change one thing from normal. L removes the deferral, M is the worst case, N removes the top-up. Every cell is a formula.
A4: Item | B4: Normal | C4: Conservative (all stresses) | D4: Tariff +20% | E4: Maintenance +50% | F4: Downtime 10% | G4: Price −20% | H4: Grant not approved | I4: Usage 30 kWh/day | J4: No idle or membership fees | K4: Mall MV demand charge | L4: Normal, no deferral (70% split from day 1) | M4: WORST CASE: RM1.00/kWh, tariff +30%, 20 kWh/day, no grant, CPO exits | N4: Conservative, no top-up | O4: Unit / how
A5: Usage and prices
A6: Charging sessions per charger per day | B6: =Assumptions!$B$105 -> 2 | C6: =Pools_Scenarios!$C$93 -> 1.5 | D6: =Assumptions!$B$105 -> 2 | E6: =Assumptions!$B$105 -> 2 | F6: =Assumptions!$B$105 -> 2 | G6: =Assumptions!$B$105 -> 2 | H6: =Assumptions!$B$105 -> 2 | I6: =Pools_Scenarios!$C$93 -> 1.5 | J6: =Assumptions!$B$105 -> 2 | K6: =Assumptions!$B$105 -> 2 | L6: =Assumptions!$B$105 -> 2 | M6: =1 -> 1 | N6: =Pools_Scenarios!$C$93 -> 1.5 | O6: sessions
A7: Energy per session | B7: =Assumptions!$B$106 -> 30 | C7: =Pools_Scenarios!$C$94 -> 20 | D7: =Assumptions!$B$106 -> 30 | E7: =Assumptions!$B$106 -> 30 | F7: =Assumptions!$B$106 -> 30 | G7: =Assumptions!$B$106 -> 30 | H7: =Assumptions!$B$106 -> 30 | I7: =Pools_Scenarios!$C$94 -> 20 | J7: =Assumptions!$B$106 -> 30 | K7: =Assumptions!$B$106 -> 30 | L7: =Assumptions!$B$106 -> 30 | M7: =20 -> 20 | N7: =Pools_Scenarios!$C$94 -> 20 | O7: kWh
A8: Downtime | B8: =0 -> 0 | C8: =Pools_Scenarios!$C$97 -> 0.1 | D8: =0 -> 0 | E8: =0 -> 0 | F8: =Pools_Scenarios!$C$97 -> 0.1 | G8: =0 -> 0 | H8: =0 -> 0 | I8: =0 -> 0 | J8: =0 -> 0 | K8: =0 -> 0 | L8: =0 -> 0 | M8: =Pools_Scenarios!$C$97 -> 0.1 | N8: =Pools_Scenarios!$C$97 -> 0.1 | O8: % of time
A9: Energy sold per charger per day | B9: =B6*B7*(1-B8) -> 60 | C9: =C6*C7*(1-C8) -> 27 | D9: =D6*D7*(1-D8) -> 60 | E9: =E6*E7*(1-E8) -> 60 | F9: =F6*F7*(1-F8) -> 54 | G9: =G6*G7*(1-G8) -> 60 | H9: =H6*H7*(1-H8) -> 60 | I9: =I6*I7*(1-I8) -> 30 | ... N9: =N6*N7*(1-N8) -> 27 | O9: kWh/day
A10: Price level (1 − competitor price drop) | B10: =1-0 -> 1 | C10: =1-Pools_Scenarios!$C$89 -> 0.8 | D10: =1-0 -> 1 | E10: =1-0 -> 1 | F10: =1-0 -> 1 | G10: =1-Pools_Scenarios!$C$89 -> 0.8 | H10: =1-0 -> 1 | I10: =1-0 -> 1 | J10: =1-0 -> 1 | K10: =1-0 -> 1 | L10: =1-0 -> 1 | M10: =1-0 -> 1 | N10: =1-Pools_Scenarios!$C$89 -> 0.8
A11: DC average price (standard + peak) | B11: =IF(0=1,1,(Assumptions!$B$32*(1-Assumptions!$B$120)+Assumptions!$B$119*Assumptions!$B$120)*B10) -> 1.49 | C11: =IF(0=1,1,(Assumptions!$B$32*(1-Assumptions!$B$120)+Assumptions!$B$119*Assumptions!$B$120)*C10) -> 1.192 | D11: =IF(0=1,1,(Assumptions!$B$32*(1-Assumptions!$B$120)+Assumptions!$B$119*Assumptions!$B$120)*D10) -> 1.49 | E11: =IF(0=1,1,(Assumptions!$B$32*(1-Assumptions!$B$120)+Assumptions!$B$119*Assumptions!$B$120)*E10) -> 1.49 | F11: =IF(0=1,1,(Assumptions!$B$32*(1-Assumptions!$B$120)+Assumptions!$B$119*Assumptions!$B$120)*F10) -> 1.49 | G11: =IF(0=1,1,(Assumptions!$B$32*(1-Assumptions!$B$120)+Assumptions!$B$119*Assumptions!$B$120)*G10) -> 1.192 | H11: =IF(0=1,1,(Assumptions!$B$32*(1-Assumptions!$B$120)+Assumptions!$B$119*Assumptions!$B$120)*H10) -> 1.49 | I11: =IF(0=1,1,(Assumptions!$B$32*(1-Assumptions!$B$120)+Assumptions!$B$119*Assumptions!$B$120)*I10) -> 1.49 | ... L11: =IF(0=1,1,(Assumptions!$B$32*(1-Assumptions!$B$120)+Assumptions!$B$119*Assumptions!$B$120)*L10) -> 1.49 | M11: =IF(1=1,1,(Assumptions!$B$32*(1-Assumptions!$B$120)+Assumptions!$B$119*Assumptions!$B$120)*M10) -> 1 | N11: =IF(0=1,1,(Assumptions!$B$32*(1-Assumptions!$B$120)+Assumptions!$B$119*Assumptions!$B$120)*N10) -> 1.192 | O11: RM/kWh
A12: AC average price (standard + off-peak) | B12: =IF(0=1,1,(Assumptions!$B$118*(1-Assumptions!$B$122)+Assumptions!$B$121*Assumptions!$B$122)*B10) -> 0.95 | C12: =IF(0=1,1,(Assumptions!$B$118*(1-Assumptions!$B$122)+Assumptions!$B$121*Assumptions!$B$122)*C10) -> 0.76 | D12: =IF(0=1,1,(Assumptions!$B$118*(1-Assumptions!$B$122)+Assumptions!$B$121*Assumptions!$B$122)*D10) -> 0.95 | E12: =IF(0=1,1,(Assumptions!$B$118*(1-Assumptions!$B$122)+Assumptions!$B$121*Assumptions!$B$122)*E10) -> 0.95 | F12: =IF(0=1,1,(Assumptions!$B$118*(1-Assumptions!$B$122)+Assumptions!$B$121*Assumptions!$B$122)*F10) -> 0.95 | G12: =IF(0=1,1,(Assumptions!$B$118*(1-Assumptions!$B$122)+Assumptions!$B$121*Assumptions!$B$122)*G10) -> 0.76 | H12: =IF(0=1,1,(Assumptions!$B$118*(1-Assumptions!$B$122)+Assumptions!$B$121*Assumptions!$B$122)*H10) -> 0.95 | I12: =IF(0=1,1,(Assumptions!$B$118*(1-Assumptions!$B$122)+Assumptions!$B$121*Assumptions!$B$122)*I10) -> 0.95 | ... L12: =IF(0=1,1,(Assumptions!$B$118*(1-Assumptions!$B$122)+Assumptions!$B$121*Assumptions!$B$122)*L10) -> 0.95 | M12: =IF(1=1,1,(Assumptions!$B$118*(1-Assumptions!$B$122)+Assumptions!$B$121*Assumptions!$B$122)*M10) -> 1 | N12: =IF(0=1,1,(Assumptions!$B$118*(1-Assumptions!$B$122)+Assumptions!$B$121*Assumptions!$B$122)*N10) -> 0.76 | O12: RM/kWh
A13: Electricity cost per kWh (energy + capacity + network) | B13: =Assumptions!$B$102*(1+0) -> 0.5068 | C13: =Assumptions!$B$102*(1+Pools_Scenarios!$C$95) -> 0.60816 | D13: =Assumptions!$B$102*(1+Pools_Scenarios!$C$95) -> 0.60816 | E13: =Assumptions!$B$102*(1+0) -> 0.5068 | F13: =Assumptions!$B$102*(1+0) -> 0.5068 | G13: =Assumptions!$B$102*(1+0) -> 0.5068 | H13: =Assumptions!$B$102*(1+0) -> 0.5068 | I13: =Assumptions!$B$102*(1+0) -> 0.5068 | J13: =Assumptions!$B$102*(1+0) -> 0.5068 | K13: =Assumptions!$B$102*(1+0) -> 0.5068 | L13: =Assumptions!$B$102*(1+0) -> 0.5068 | M13: =Assumptions!$B$102*(1+0.3) -> 0.65884 | N13: =Assumptions!$B$102*(1+Pools_Scenarios!$C$95) -> 0.60816 | O13: RM/kWh
A14: of which capacity charge | B14: =Assumptions!$B$103*(1+0) -> 0.0883 | C14: =Assumptions!$B$103*(1+Pools_Scenarios!$C$95) -> 0.10596 | D14: =Assumptions!$B$103*(1+Pools_Scenarios!$C$95) -> 0.10596 | E14: =Assumptions!$B$103*(1+0) -> 0.0883 | F14: =Assumptions!$B$103*(1+0) -> 0.0883 | G14: =Assumptions!$B$103*(1+0) -> 0.0883 | H14: =Assumptions!$B$103*(1+0) -> 0.0883 | I14: =Assumptions!$B$103*(1+0) -> 0.0883 | J14: =Assumptions!$B$103*(1+0) -> 0.0883 | K14: =Assumptions!$B$103*(1+0) -> 0.0883 | L14: =Assumptions!$B$103*(1+0) -> 0.0883 | M14: =Assumptions!$B$103*(1+0.3) -> 0.11479 | N14: =Assumptions!$B$103*(1+Pools_Scenarios!$C$95) -> 0.10596 | O14: RM/kWh
A15: Maximum-demand charge per kW (only if the site is on the MV tariff) | B15: =0*Assumptions!$B$141 -> 0 | C15: =0*Assumptions!$B$141 -> 0 | D15: =0*Assumptions!$B$141 -> 0 | E15: =0*Assumptions!$B$141 -> 0 | F15: =0*Assumptions!$B$141 -> 0 | G15: =0*Assumptions!$B$141 -> 0 | H15: =0*Assumptions!$B$141 -> 0 | I15: =0*Assumptions!$B$141 -> 0 | J15: =0*Assumptions!$B$141 -> 0 | K15: =1*Assumptions!$B$141 -> 89.27 | L15: =0*Assumptions!$B$141 -> 0 | M15: =0*Assumptions!$B$141 -> 0 | N15: =0*Assumptions!$B$141 -> 0 | O15: RM/kW/month
A16: DC 60 kW charger (per year)
A17: Installed cost | B17: =Assumptions!$B$116 -> 100000 | C17: =Assumptions!$B$116 -> 100000 | D17: =Assumptions!$B$116 -> 100000 | E17: =Assumptions!$B$116 -> 100000 | F17: =Assumptions!$B$116 -> 100000 | G17: =Assumptions!$B$116 -> 100000 | H17: =Assumptions!$B$116 -> 100000 | I17: =Assumptions!$B$116 -> 100000 | ... N17: =Assumptions!$B$116 -> 100000 | O17: RM
A18: MARii grant (if approved) | B18: =MIN(Assumptions!$B$116*Assumptions!$B$104,Assumptions!$B$129)*1 -> 50000 | C18: =MIN(Assumptions!$B$116*Assumptions!$B$104,Assumptions!$B$129)*Pools_Scenarios!$C$98 -> 0 | D18: =MIN(Assumptions!$B$116*Assumptions!$B$104,Assumptions!$B$129)*1 -> 50000 | E18: =MIN(Assumptions!$B$116*Assumptions!$B$104,Assumptions!$B$129)*1 -> 50000 | F18: =MIN(Assumptions!$B$116*Assumptions!$B$104,Assumptions!$B$129)*1 -> 50000 | G18: =MIN(Assumptions!$B$116*Assumptions!$B$104,Assumptions!$B$129)*1 -> 50000 | H18: =MIN(Assumptions!$B$116*Assumptions!$B$104,Assumptions!$B$129)*Pools_Scenarios!$C$98 -> 0 | I18: =MIN(Assumptions!$B$116*Assumptions!$B$104,Assumptions!$B$129)*1 -> 50000 | J18: =MIN(Assumptions!$B$116*Assumptions!$B$104,Assumptions!$B$129)*1 -> 50000 | K18: =MIN(Assumptions!$B$116*Assumptions!$B$104,Assumptions!$B$129)*1 -> 50000 | L18: =MIN(Assumptions!$B$116*Assumptions!$B$104,Assumptions!$B$129)*1 -> 50000 | M18: =MIN(Assumptions!$B$116*Assumptions!$B$104,Assumptions!$B$129)*0 -> 0 | N18: =MIN(Assumptions!$B$116*Assumptions!$B$104,Assumptions!$B$129)*Pools_Scenarios!$C$98 -> 0 | O18: RM
A19: Compliance cost share (per site ÷ chargers per site) | B19: =Assumptions!$B$107/Assumptions!$B$128 -> 7500 | C19: =Assumptions!$B$107/Assumptions!$B$128 -> 7500 | D19: =Assumptions!$B$107/Assumptions!$B$128 -> 7500 | E19: =Assumptions!$B$107/Assumptions!$B$128 -> 7500 | F19: =Assumptions!$B$107/Assumptions!$B$128 -> 7500 | G19: =Assumptions!$B$107/Assumptions!$B$128 -> 7500 | H19: =Assumptions!$B$107/Assumptions!$B$128 -> 7500 | I19: =Assumptions!$B$107/Assumptions!$B$128 -> 7500 | ... N19: =Assumptions!$B$107/Assumptions!$B$128 -> 7500 | O19: RM
A20: Net installed cost | B20: =B17-B18+B19 -> 57500 | C20: =C17-C18+C19 -> 107500 | D20: =D17-D18+D19 -> 57500 | E20: =E17-E18+E19 -> 57500 | F20: =F17-F18+F19 -> 57500 | G20: =G17-G18+G19 -> 57500 | H20: =H17-H18+H19 -> 107500 | I20: =I17-I18+I19 -> 57500 | ... N20: =N17-N18+N19 -> 107500 | O20: RM
A21: Charging revenue | B21: =365*B9*B11 -> 32631 | C21: =365*C9*C11 -> 11747.16 | D21: =365*D9*D11 -> 32631 | E21: =365*E9*E11 -> 32631 | F21: =365*F9*F11 -> 29367.9 | G21: =365*G9*G11 -> 26104.8 | H21: =365*H9*H11 -> 32631 | I21: =365*I9*I11 -> 16315.5 | ... N21: =365*N9*N11 -> 11747.16 | O21: RM/yr
A22: Idle (occupancy) fees | B22: =365*Assumptions!$B$124*Assumptions!$B$123*(1-B8) -> 1460 | C22: =365*Pools_Scenarios!$C$99*Assumptions!$B$123*(1-C8) -> 657 | D22: =365*Assumptions!$B$124*Assumptions!$B$123*(1-D8) -> 1460 | E22: =365*Assumptions!$B$124*Assumptions!$B$123*(1-E8) -> 1460 | F22: =365*Assumptions!$B$124*Assumptions!$B$123*(1-F8) -> 1314 | G22: =365*Assumptions!$B$124*Assumptions!$B$123*(1-G8) -> 1460 | H22: =365*Assumptions!$B$124*Assumptions!$B$123*(1-H8) -> 1460 | I22: =365*Assumptions!$B$124*Assumptions!$B$123*(1-I8) -> 1460 | J22: =365*0*Assumptions!$B$123*(1-J8) -> 0 | K22: =365*Assumptions!$B$124*Assumptions!$B$123*(1-K8) -> 1460 | L22: =365*Assumptions!$B$124*Assumptions!$B$123*(1-L8) -> 1460 | M22: =365*0*Assumptions!$B$123*(1-M8) -> 0 | N22: =365*Pools_Scenarios!$C$99*Assumptions!$B$123*(1-N8) -> 657 | O22: RM/yr
A23: Membership fees | B23: =Assumptions!$B$126*Assumptions!$B$125*12 -> 1800 | C23: =Pools_Scenarios!$C$100*Assumptions!$B$125*12 -> 900 | D23: =Assumptions!$B$126*Assumptions!$B$125*12 -> 1800 | E23: =Assumptions!$B$126*Assumptions!$B$125*12 -> 1800 | F23: =Assumptions!$B$126*Assumptions!$B$125*12 -> 1800 | G23: =Assumptions!$B$126*Assumptions!$B$125*12 -> 1800 | H23: =Assumptions!$B$126*Assumptions!$B$125*12 -> 1800 | I23: =Assumptions!$B$126*Assumptions!$B$125*12 -> 1800 | J23: =0*Assumptions!$B$125*12 -> 0 | K23: =Assumptions!$B$126*Assumptions!$B$125*12 -> 1800 | L23: =Assumptions!$B$126*Assumptions!$B$125*12 -> 1800 | M23: =0*Assumptions!$B$125*12 -> 0 | N23: =Pools_Scenarios!$C$100*Assumptions!$B$125*12 -> 900 | O23: RM/yr
A24: Payment and app costs | B24: =-Assumptions!$B$33*(B21+B22+B23) -> -1076.73 | C24: =-Assumptions!$B$33*(C21+C22+C23) -> -399.1248 | D24: =-Assumptions!$B$33*(D21+D22+D23) -> -1076.73 | E24: =-Assumptions!$B$33*(E21+E22+E23) -> -1076.73 | F24: =-Assumptions!$B$33*(F21+F22+F23) -> -974.457 | G24: =-Assumptions!$B$33*(G21+G22+G23) -> -880.944 | H24: =-Assumptions!$B$33*(H21+H22+H23) -> -1076.73 | I24: =-Assumptions!$B$33*(I21+I22+I23) -> -587.265 | ... N24: =-Assumptions!$B$33*(N21+N22+N23) -> -399.1248 | O24: RM/yr
A25: Electricity (incl. capacity and network charges) | B25: =-365*B9*B13 -> -11098.92 | C25: =-365*C9*C13 -> -5993.4168 | D25: =-365*D9*D13 -> -13318.704 | E25: =-365*E9*E13 -> -11098.92 | F25: =-365*F9*F13 -> -9989.028 | G25: =-365*G9*G13 -> -11098.92 | H25: =-365*H9*H13 -> -11098.92 | I25: =-365*I9*I13 -> -5549.46 | ... N25: =-365*N9*N13 -> -5993.4168 | O25: RM/yr
A26: Maximum-demand charge (MV sites only) | B26: =-B15*Assumptions!$B$142*1*12 -> 0 | C26: =-C15*Assumptions!$B$142*1*12 -> 0 | D26: =-D15*Assumptions!$B$142*1*12 -> 0 | E26: =-E15*Assumptions!$B$142*1*12 -> 0 | F26: =-F15*Assumptions!$B$142*1*12 -> 0 | G26: =-G15*Assumptions!$B$142*1*12 -> 0 | H26: =-H15*Assumptions!$B$142*1*12 -> 0 | I26: =-I15*Assumptions!$B$142*1*12 -> 0 | ... N26: =-N15*Assumptions!$B$142*1*12 -> 0 | O26: RM/yr
A27: Maintenance and CPO service fee | B27: =-Assumptions!$B$34*(1+0) -> -10000 | C27: =-Assumptions!$B$34*(1+Pools_Scenarios!$C$96) -> -15000 | D27: =-Assumptions!$B$34*(1+0) -> -10000 | E27: =-Assumptions!$B$34*(1+Pools_Scenarios!$C$96) -> -15000 | F27: =-Assumptions!$B$34*(1+0) -> -10000 | G27: =-Assumptions!$B$34*(1+0) -> -10000 | H27: =-Assumptions!$B$34*(1+0) -> -10000 | I27: =-Assumptions!$B$34*(1+0) -> -10000 | J27: =-Assumptions!$B$34*(1+0) -> -10000 | K27: =-Assumptions!$B$34*(1+0) -> -10000 | L27: =-Assumptions!$B$34*(1+0) -> -10000 | M27: =-Assumptions!$B$34*(1+Pools_Scenarios!$C$96) -> -15000 | N27: =-Assumptions!$B$34*(1+Pools_Scenarios!$C$96) -> -15000 | O27: RM/yr
A28: Compliance audit share | B28: =-Assumptions!$B$108/Assumptions!$B$128 -> -2500 | C28: =-Assumptions!$B$108/Assumptions!$B$128 -> -2500 | D28: =-Assumptions!$B$108/Assumptions!$B$128 -> -2500 | E28: =-Assumptions!$B$108/Assumptions!$B$128 -> -2500 | F28: =-Assumptions!$B$108/Assumptions!$B$128 -> -2500 | G28: =-Assumptions!$B$108/Assumptions!$B$128 -> -2500 | H28: =-Assumptions!$B$108/Assumptions!$B$128 -> -2500 | I28: =-Assumptions!$B$108/Assumptions!$B$128 -> -2500 | ... N28: =-Assumptions!$B$108/Assumptions!$B$128 -> -2500 | O28: RM/yr
A29: Net charging profit | B29: =SUM(B21:B28) -> 11215.35 | C29: =SUM(C21:C28) -> -10588.382 | D29: =SUM(D21:D28) -> 8995.566 | E29: =SUM(E21:E28) -> 6215.35 | F29: =SUM(F21:F28) -> 9018.415 | G29: =SUM(G21:G28) -> 4884.936 | H29: =SUM(H21:H28) -> 11215.35 | I29: =SUM(I21:I28) -> 938.775 | ... N29: =SUM(N21:N28) -> -10588.382 | O29: RM/yr
A30: Revenue per charger per day | B30: =(B21+B22+B23)/365 -> 98.331507 | C30: =(C21+C22+C23)/365 -> 36.449753 | D30: =(D21+D22+D23)/365 -> 98.331507 | E30: =(E21+E22+E23)/365 -> 98.331507 | F30: =(F21+F22+F23)/365 -> 88.991507 | G30: =(G21+G22+G23)/365 -> 80.451507 | H30: =(H21+H22+H23)/365 -> 98.331507 | I30: =(I21+I22+I23)/365 -> 53.631507 | ... N30: =(N21+N22+N23)/365 -> 36.449753 | O30: RM/day
A31: AC 22 kW charger (per year)
A32: Installed cost | B32: =Assumptions!$B$117 -> 25000 | C32: =Assumptions!$B$117 -> 25000 | D32: =Assumptions!$B$117 -> 25000 | E32: =Assumptions!$B$117 -> 25000 | F32: =Assumptions!$B$117 -> 25000 | G32: =Assumptions!$B$117 -> 25000 | H32: =Assumptions!$B$117 -> 25000 | I32: =Assumptions!$B$117 -> 25000 | ... N32: =Assumptions!$B$117 -> 25000 | O32: RM
A33: Compliance cost share (per site ÷ chargers per site) | B33: =Assumptions!$B$107/Assumptions!$B$128 -> 7500 | C33: =Assumptions!$B$107/Assumptions!$B$128 -> 7500 | D33: =Assumptions!$B$107/Assumptions!$B$128 -> 7500 | E33: =Assumptions!$B$107/Assumptions!$B$128 -> 7500 | F33: =Assumptions!$B$107/Assumptions!$B$128 -> 7500 | G33: =Assumptions!$B$107/Assumptions!$B$128 -> 7500 | H33: =Assumptions!$B$107/Assumptions!$B$128 -> 7500 | I33: =Assumptions!$B$107/Assumptions!$B$128 -> 7500 | ... N33: =Assumptions!$B$107/Assumptions!$B$128 -> 7500 | O33: RM
A34: Net installed cost | B34: =B32+B33 -> 32500 | C34: =C32+C33 -> 32500 | D34: =D32+D33 -> 32500 | E34: =E32+E33 -> 32500 | F34: =F32+F33 -> 32500 | G34: =G32+G33 -> 32500 | H34: =H32+H33 -> 32500 | I34: =I32+I33 -> 32500 | ... N34: =N32+N33 -> 32500 | O34: RM
A35: Charging revenue | B35: =365*B9*B12 -> 20805 | C35: =365*C9*C12 -> 7489.8 | D35: =365*D9*D12 -> 20805 | E35: =365*E9*E12 -> 20805 | F35: =365*F9*F12 -> 18724.5 | G35: =365*G9*G12 -> 16644 | H35: =365*H9*H12 -> 20805 | I35: =365*I9*I12 -> 10402.5 | ... N35: =365*N9*N12 -> 7489.8 | O35: RM/yr
A36: Idle (occupancy) fees | B36: =365*Assumptions!$B$124*Assumptions!$B$123*(1-B8) -> 1460 | C36: =365*Pools_Scenarios!$C$99*Assumptions!$B$123*(1-C8) -> 657 | D36: =365*Assumptions!$B$124*Assumptions!$B$123*(1-D8) -> 1460 | E36: =365*Assumptions!$B$124*Assumptions!$B$123*(1-E8) -> 1460 | F36: =365*Assumptions!$B$124*Assumptions!$B$123*(1-F8) -> 1314 | G36: =365*Assumptions!$B$124*Assumptions!$B$123*(1-G8) -> 1460 | H36: =365*Assumptions!$B$124*Assumptions!$B$123*(1-H8) -> 1460 | I36: =365*Assumptions!$B$124*Assumptions!$B$123*(1-I8) -> 1460 | J36: =365*0*Assumptions!$B$123*(1-J8) -> 0 | K36: =365*Assumptions!$B$124*Assumptions!$B$123*(1-K8) -> 1460 | L36: =365*Assumptions!$B$124*Assumptions!$B$123*(1-L8) -> 1460 | M36: =365*0*Assumptions!$B$123*(1-M8) -> 0 | N36: =365*Pools_Scenarios!$C$99*Assumptions!$B$123*(1-N8) -> 657 | O36: RM/yr
A37: Membership fees | B37: =Assumptions!$B$126*Assumptions!$B$125*12 -> 1800 | C37: =Pools_Scenarios!$C$100*Assumptions!$B$125*12 -> 900 | D37: =Assumptions!$B$126*Assumptions!$B$125*12 -> 1800 | E37: =Assumptions!$B$126*Assumptions!$B$125*12 -> 1800 | F37: =Assumptions!$B$126*Assumptions!$B$125*12 -> 1800 | G37: =Assumptions!$B$126*Assumptions!$B$125*12 -> 1800 | H37: =Assumptions!$B$126*Assumptions!$B$125*12 -> 1800 | I37: =Assumptions!$B$126*Assumptions!$B$125*12 -> 1800 | J37: =0*Assumptions!$B$125*12 -> 0 | K37: =Assumptions!$B$126*Assumptions!$B$125*12 -> 1800 | L37: =Assumptions!$B$126*Assumptions!$B$125*12 -> 1800 | M37: =0*Assumptions!$B$125*12 -> 0 | N37: =Pools_Scenarios!$C$100*Assumptions!$B$125*12 -> 900 | O37: RM/yr
A38: Payment and app costs | B38: =-Assumptions!$B$33*(B35+B36+B37) -> -721.95 | C38: =-Assumptions!$B$33*(C35+C36+C37) -> -271.404 | D38: =-Assumptions!$B$33*(D35+D36+D37) -> -721.95 | E38: =-Assumptions!$B$33*(E35+E36+E37) -> -721.95 | F38: =-Assumptions!$B$33*(F35+F36+F37) -> -655.155 | G38: =-Assumptions!$B$33*(G35+G36+G37) -> -597.12 | H38: =-Assumptions!$B$33*(H35+H36+H37) -> -721.95 | I38: =-Assumptions!$B$33*(I35+I36+I37) -> -409.875 | ... N38: =-Assumptions!$B$33*(N35+N36+N37) -> -271.404 | O38: RM/yr
A39: Electricity (incl. capacity and network charges) | B39: =-365*B9*B13 -> -11098.92 | C39: =-365*C9*C13 -> -5993.4168 | D39: =-365*D9*D13 -> -13318.704 | E39: =-365*E9*E13 -> -11098.92 | F39: =-365*F9*F13 -> -9989.028 | G39: =-365*G9*G13 -> -11098.92 | H39: =-365*H9*H13 -> -11098.92 | I39: =-365*I9*I13 -> -5549.46 | ... N39: =-365*N9*N13 -> -5993.4168 | O39: RM/yr
A40: Maximum-demand charge (MV sites only) | B40: =-B15*Assumptions!$B$142*22/60*12 -> 0 | C40: =-C15*Assumptions!$B$142*22/60*12 -> 0 | D40: =-D15*Assumptions!$B$142*22/60*12 -> 0 | E40: =-E15*Assumptions!$B$142*22/60*12 -> 0 | F40: =-F15*Assumptions!$B$142*22/60*12 -> 0 | G40: =-G15*Assumptions!$B$142*22/60*12 -> 0 | H40: =-H15*Assumptions!$B$142*22/60*12 -> 0 | I40: =-I15*Assumptions!$B$142*22/60*12 -> 0 | ... N40: =-N15*Assumptions!$B$142*22/60*12 -> 0 | O40: RM/yr
A41: Maintenance and CPO service fee | B41: =-Assumptions!$B$127*(1+0) -> -3000 | C41: =-Assumptions!$B$127*(1+Pools_Scenarios!$C$96) -> -4500 | D41: =-Assumptions!$B$127*(1+0) -> -3000 | E41: =-Assumptions!$B$127*(1+Pools_Scenarios!$C$96) -> -4500 | F41: =-Assumptions!$B$127*(1+0) -> -3000 | G41: =-Assumptions!$B$127*(1+0) -> -3000 | H41: =-Assumptions!$B$127*(1+0) -> -3000 | I41: =-Assumptions!$B$127*(1+0) -> -3000 | J41: =-Assumptions!$B$127*(1+0) -> -3000 | K41: =-Assumptions!$B$127*(1+0) -> -3000 | L41: =-Assumptions!$B$127*(1+0) -> -3000 | M41: =-Assumptions!$B$127*(1+Pools_Scenarios!$C$96) -> -4500 | N41: =-Assumptions!$B$127*(1+Pools_Scenarios!$C$96) -> -4500 | O41: RM/yr
A42: Compliance audit share | B42: =-Assumptions!$B$108/Assumptions!$B$128 -> -2500 | C42: =-Assumptions!$B$108/Assumptions!$B$128 -> -2500 | D42: =-Assumptions!$B$108/Assumptions!$B$128 -> -2500 | E42: =-Assumptions!$B$108/Assumptions!$B$128 -> -2500 | F42: =-Assumptions!$B$108/Assumptions!$B$128 -> -2500 | G42: =-Assumptions!$B$108/Assumptions!$B$128 -> -2500 | H42: =-Assumptions!$B$108/Assumptions!$B$128 -> -2500 | I42: =-Assumptions!$B$108/Assumptions!$B$128 -> -2500 | ... N42: =-Assumptions!$B$108/Assumptions!$B$128 -> -2500 | O42: RM/yr
A43: Net charging profit | B43: =SUM(B35:B42) -> 6744.13 | C43: =SUM(C35:C42) -> -4218.0208 | D43: =SUM(D35:D42) -> 4524.346 | E43: =SUM(E35:E42) -> 5244.13 | F43: =SUM(F35:F42) -> 5694.317 | G43: =SUM(G35:G42) -> 2707.96 | H43: =SUM(H35:H42) -> 6744.13 | I43: =SUM(I35:I42) -> 2203.165 | ... N43: =SUM(N35:N42) -> -4218.0208 | O43: RM/yr
A44: Revenue per charger per day | B44: =(B35+B36+B37)/365 -> 65.931507 | C44: =(C35+C36+C37)/365 -> 24.785753 | D44: =(D35+D36+D37)/365 -> 65.931507 | E44: =(E35+E36+E37)/365 -> 65.931507 | F44: =(F35+F36+F37)/365 -> 59.831507 | G44: =(G35+G36+G37)/365 -> 54.531507 | H44: =(H35+H36+H37)/365 -> 65.931507 | I44: =(I35+I36+I37)/365 -> 37.431507 | ... N44: =(N35+N36+N37)/365 -> 24.785753 | O44: RM/day
A45: Blended charger (DC share × DC + AC share × AC)
A46: Net installed cost after grant | B46: =Assumptions!$B$115*B20+(1-Assumptions!$B$115)*B34 -> 45000 | C46: =Assumptions!$B$115*C20+(1-Assumptions!$B$115)*C34 -> 70000 | D46: =Assumptions!$B$115*D20+(1-Assumptions!$B$115)*D34 -> 45000 | E46: =Assumptions!$B$115*E20+(1-Assumptions!$B$115)*E34 -> 45000 | F46: =Assumptions!$B$115*F20+(1-Assumptions!$B$115)*F34 -> 45000 | G46: =Assumptions!$B$115*G20+(1-Assumptions!$B$115)*G34 -> 45000 | H46: =Assumptions!$B$115*H20+(1-Assumptions!$B$115)*H34 -> 70000 | I46: =Assumptions!$B$115*I20+(1-Assumptions!$B$115)*I34 -> 45000 | ... N46: =Assumptions!$B$115*N20+(1-Assumptions!$B$115)*N34 -> 70000 | O46: RM
A47: Government grant received | B47: =Assumptions!$B$115*B18 -> 25000 | C47: =Assumptions!$B$115*C18 -> 0 | D47: =Assumptions!$B$115*D18 -> 25000 | E47: =Assumptions!$B$115*E18 -> 25000 | F47: =Assumptions!$B$115*F18 -> 25000 | G47: =Assumptions!$B$115*G18 -> 25000 | H47: =Assumptions!$B$115*H18 -> 0 | I47: =Assumptions!$B$115*I18 -> 25000 | ... N47: =Assumptions!$B$115*N18 -> 0 | O47: RM
A48: Revenue per charger per day | B48: =Assumptions!$B$115*B30+(1-Assumptions!$B$115)*B44 -> 82.131507 | C48: =Assumptions!$B$115*C30+(1-Assumptions!$B$115)*C44 -> 30.617753 | D48: =Assumptions!$B$115*D30+(1-Assumptions!$B$115)*D44 -> 82.131507 | E48: =Assumptions!$B$115*E30+(1-Assumptions!$B$115)*E44 -> 82.131507 | F48: =Assumptions!$B$115*F30+(1-Assumptions!$B$115)*F44 -> 74.411507 | G48: =Assumptions!$B$115*G30+(1-Assumptions!$B$115)*G44 -> 67.491507 | H48: =Assumptions!$B$115*H30+(1-Assumptions!$B$115)*H44 -> 82.131507 | I48: =Assumptions!$B$115*I30+(1-Assumptions!$B$115)*I44 -> 45.531507 | ... N48: =Assumptions!$B$115*N30+(1-Assumptions!$B$115)*N44 -> 30.617753 | O48: RM/day
A49: Electricity cost per charger per day (incl. capacity charge and any MV demand charge) | B49: =-(Assumptions!$B$115*(B25+B26)+(1-Assumptions!$B$115)*(B39+B40))/365 -> 30.408 | C49: =-(Assumptions!$B$115*(C25+C26)+(1-Assumptions!$B$115)*(C39+C40))/365 -> 16.42032 | D49: =-(Assumptions!$B$115*(D25+D26)+(1-Assumptions!$B$115)*(D39+D40))/365 -> 36.4896 | E49: =-(Assumptions!$B$115*(E25+E26)+(1-Assumptions!$B$115)*(E39+E40))/365 -> 30.408 | F49: =-(Assumptions!$B$115*(F25+F26)+(1-Assumptions!$B$115)*(F39+F40))/365 -> 27.3672 | G49: =-(Assumptions!$B$115*(G25+G26)+(1-Assumptions!$B$115)*(G39+G40))/365 -> 30.408 | H49: =-(Assumptions!$B$115*(H25+H26)+(1-Assumptions!$B$115)*(H39+H40))/365 -> 30.408 | I49: =-(Assumptions!$B$115*(I25+I26)+(1-Assumptions!$B$115)*(I39+I40))/365 -> 15.204 | ... N49: =-(Assumptions!$B$115*(N25+N26)+(1-Assumptions!$B$115)*(N39+N40))/365 -> 16.42032 | O49: RM/day
A50: Net charging profit per charger | B50: =Assumptions!$B$115*B29+(1-Assumptions!$B$115)*B43 -> 8979.74 | C50: =Assumptions!$B$115*C29+(1-Assumptions!$B$115)*C43 -> -7403.2012 | D50: =Assumptions!$B$115*D29+(1-Assumptions!$B$115)*D43 -> 6759.956 | E50: =Assumptions!$B$115*E29+(1-Assumptions!$B$115)*E43 -> 5729.74 | F50: =Assumptions!$B$115*F29+(1-Assumptions!$B$115)*F43 -> 7356.366 | G50: =Assumptions!$B$115*G29+(1-Assumptions!$B$115)*G43 -> 3796.448 | H50: =Assumptions!$B$115*H29+(1-Assumptions!$B$115)*H43 -> 8979.74 | I50: =Assumptions!$B$115*I29+(1-Assumptions!$B$115)*I43 -> 1570.97 | ... N50: =Assumptions!$B$115*N29+(1-Assumptions!$B$115)*N43 -> -7403.2012 | O50: RM/yr
A51: Whole-charger payback | B51: =IF(B50<=0,"Never",B46/B50) -> 5.011281 | C51: =IF(C50<=0,"Never",C46/C50) -> Never | D51: =IF(D50<=0,"Never",D46/D50) -> 6.6568481 | E51: =IF(E50<=0,"Never",E46/E50) -> 7.8537595 | F51: =IF(F50<=0,"Never",F46/F50) -> 6.1171508 | G51: =IF(G50<=0,"Never",G46/G50) -> 11.853185 | H51: =IF(H50<=0,"Never",H46/H50) -> 7.7953259 | I51: =IF(I50<=0,"Never",I46/I50) -> 28.644723 | ... N51: =IF(N50<=0,"Never",N46/N50) -> Never | O51: years
A52: Who gets the profit (per charger per year)
A53: Residents' money in one charger | B53: =B46*Assumptions!$B$31 -> 22500 | C53: =C46*Assumptions!$B$31 -> 35000 | D53: =D46*Assumptions!$B$31 -> 22500 | E53: =E46*Assumptions!$B$31 -> 22500 | F53: =F46*Assumptions!$B$31 -> 22500 | G53: =G46*Assumptions!$B$31 -> 22500 | H53: =H46*Assumptions!$B$31 -> 35000 | I53: =I46*Assumptions!$B$31 -> 22500 | ... N53: =N46*Assumptions!$B$31 -> 35000 | O53: RM
A54: Residents' share of profit (their 50%) | B54: =MAX(0,B50)*Assumptions!$B$31 -> 4489.87 | C54: =MAX(0,C50)*Assumptions!$B$31 -> 0 | D54: =MAX(0,D50)*Assumptions!$B$31 -> 3379.978 | E54: =MAX(0,E50)*Assumptions!$B$31 -> 2864.87 | F54: =MAX(0,F50)*Assumptions!$B$31 -> 3678.183 | G54: =MAX(0,G50)*Assumptions!$B$31 -> 1898.224 | H54: =MAX(0,H50)*Assumptions!$B$31 -> 4489.87 | I54: =MAX(0,I50)*Assumptions!$B$31 -> 785.485 | ... N54: =MAX(0,N50)*Assumptions!$B$31 -> 0 | O54: RM/yr
A55: CPO's share of profit (its 50%; it also earns the service fee) | B55: =B50*(1-Assumptions!$B$31) -> 4489.87 | C55: =C50*(1-Assumptions!$B$31) -> -3701.6006 | D55: =D50*(1-Assumptions!$B$31) -> 3379.978 | E55: =E50*(1-Assumptions!$B$31) -> 2864.87 | F55: =F50*(1-Assumptions!$B$31) -> 3678.183 | G55: =G50*(1-Assumptions!$B$31) -> 1898.224 | H55: =H50*(1-Assumptions!$B$31) -> 4489.87 | I55: =I50*(1-Assumptions!$B$31) -> 785.485 | ... N55: =N50*(1-Assumptions!$B$31) -> -3701.6006 | O55: RM/yr
A56: To residents while they recover their money | B56: =B54*(Assumptions!$B$132+Assumptions!$B$135*(Assumptions!$B$36+Assumptions!$B$133)) -> 4040.883 | C56: =C54*(Assumptions!$B$132+Assumptions!$B$135*(Assumptions!$B$36+Assumptions!$B$133)) -> 0 | D56: =D54*(Assumptions!$B$132+Assumptions!$B$135*(Assumptions!$B$36+Assumptions!$B$133)) -> 3041.9802 | E56: =E54*(Assumptions!$B$132+Assumptions!$B$135*(Assumptions!$B$36+Assumptions!$B$133)) -> 2578.383 | F56: =F54*(Assumptions!$B$132+Assumptions!$B$135*(Assumptions!$B$36+Assumptions!$B$133)) -> 3310.3647 | G56: =G54*(Assumptions!$B$132+Assumptions!$B$135*(Assumptions!$B$36+Assumptions!$B$133)) -> 1708.4016 | H56: =H54*(Assumptions!$B$132+Assumptions!$B$135*(Assumptions!$B$36+Assumptions!$B$133)) -> 4040.883 | I56: =I54*(Assumptions!$B$132+Assumptions!$B$135*(Assumptions!$B$36+Assumptions!$B$133)) -> 706.9365 | ... K56: =K54*(Assumptions!$B$132+Assumptions!$B$135*(Assumptions!$B$36+Assumptions!$B$133)) -> 746.82 | L56: =L54*(Assumptions!$B$132+0*(Assumptions!$B$36+Assumptions!$B$133)) -> 3142.909 | M56: =M54*(Assumptions!$B$132+Assumptions!$B$135*(Assumptions!$B$36+Assumptions!$B$133)) -> 0 | N56: =N54*(Assumptions!$B$132+Assumptions!$B$135*(Assumptions!$B$36+Assumptions!$B$133)) -> 0 | O56: RM/yr
A57: To residents after they recover their money | B57: =B54*Assumptions!$B$132 -> 3142.909 | C57: =C54*Assumptions!$B$132 -> 0 | D57: =D54*Assumptions!$B$132 -> 2365.9846 | E57: =E54*Assumptions!$B$132 -> 2005.409 | F57: =F54*Assumptions!$B$132 -> 2574.7281 | G57: =G54*Assumptions!$B$132 -> 1328.7568 | H57: =H54*Assumptions!$B$132 -> 3142.909 | I57: =I54*Assumptions!$B$132 -> 549.8395 | ... N57: =N54*Assumptions!$B$132 -> 0 | O57: RM/yr
A58: Developer share (paid after recovery if deferral is on) | B58: =B54*Assumptions!$B$36 -> 448.987 | C58: =C54*Assumptions!$B$36 -> 0 | D58: =D54*Assumptions!$B$36 -> 337.9978 | E58: =E54*Assumptions!$B$36 -> 286.487 | F58: =F54*Assumptions!$B$36 -> 367.8183 | G58: =G54*Assumptions!$B$36 -> 189.8224 | H58: =H54*Assumptions!$B$36 -> 448.987 | I58: =I54*Assumptions!$B$36 -> 78.5485 | ... N58: =N54*Assumptions!$B$36 -> 0 | O58: RM/yr
A59: Platform share (paid after recovery if deferral is on) | B59: =B54*Assumptions!$B$133 -> 448.987 | C59: =C54*Assumptions!$B$133 -> 0 | D59: =D54*Assumptions!$B$133 -> 337.9978 | E59: =E54*Assumptions!$B$133 -> 286.487 | F59: =F54*Assumptions!$B$133 -> 367.8183 | G59: =G54*Assumptions!$B$133 -> 189.8224 | H59: =H54*Assumptions!$B$133 -> 448.987 | I59: =I54*Assumptions!$B$133 -> 78.5485 | ... N59: =N54*Assumptions!$B$133 -> 0 | O59: RM/yr
A60: O&M reserve | B60: =B54*Assumptions!$B$134 -> 448.987 | C60: =C54*Assumptions!$B$134 -> 0 | D60: =D54*Assumptions!$B$134 -> 337.9978 | E60: =E54*Assumptions!$B$134 -> 286.487 | F60: =F54*Assumptions!$B$134 -> 367.8183 | G60: =G54*Assumptions!$B$134 -> 189.8224 | H60: =H54*Assumptions!$B$134 -> 448.987 | I60: =I54*Assumptions!$B$134 -> 78.5485 | ... N60: =N54*Assumptions!$B$134 -> 0 | O60: RM/yr
A61: Usage top-up (partners pay for missing kWh below the minimum, up to a cap)
A62: Missing kWh per day below the minimum | B62: =MAX(0,Assumptions!$B$75-B9) -> 0 | C62: =MAX(0,Assumptions!$B$75-C9) -> 33 | D62: =MAX(0,Assumptions!$B$75-D9) -> 0 | E62: =MAX(0,Assumptions!$B$75-E9) -> 0 | F62: =MAX(0,Assumptions!$B$75-F9) -> 6 | G62: =MAX(0,Assumptions!$B$75-G9) -> 0 | H62: =MAX(0,Assumptions!$B$75-H9) -> 0 | I62: =MAX(0,Assumptions!$B$75-I9) -> 30 | ... N62: =MAX(0,Assumptions!$B$75-N9) -> 33 | O62: kWh/day
A63: Contract top-up rate (normal margin per kWh, fixed in contract) | B63: =Assumptions!$B$115*(($B$11)*(1-Assumptions!$B$33)-$B$13)+(1-Assumptions!$B$115)*(($B$12)*(1-Assumptions!$B$33)-$B$13) -> 0.6766 | C63: =Assumptions!$B$115*(($B$11)*(1-Assumptions!$B$33)-$B$13)+(1-Assumptions!$B$115)*(($B$12)*(1-Assumptions!$B$33)-$B$13) -> 0.6766 | D63: =Assumptions!$B$115*(($B$11)*(1-Assumptions!$B$33)-$B$13)+(1-Assumptions!$B$115)*(($B$12)*(1-Assumptions!$B$33)-$B$13) -> 0.6766 | E63: =Assumptions!$B$115*(($B$11)*(1-Assumptions!$B$33)-$B$13)+(1-Assumptions!$B$115)*(($B$12)*(1-Assumptions!$B$33)-$B$13) -> 0.6766 | F63: =Assumptions!$B$115*(($B$11)*(1-Assumptions!$B$33)-$B$13)+(1-Assumptions!$B$115)*(($B$12)*(1-Assumptions!$B$33)-$B$13) -> 0.6766 | G63: =Assumptions!$B$115*(($B$11)*(1-Assumptions!$B$33)-$B$13)+(1-Assumptions!$B$115)*(($B$12)*(1-Assumptions!$B$33)-$B$13) -> 0.6766 | H63: =Assumptions!$B$115*(($B$11)*(1-Assumptions!$B$33)-$B$13)+(1-Assumptions!$B$115)*(($B$12)*(1-Assumptions!$B$33)-$B$13) -> 0.6766 | I63: =Assumptions!$B$115*(($B$11)*(1-Assumptions!$B$33)-$B$13)+(1-Assumptions!$B$115)*(($B$12)*(1-Assumptions!$B$33)-$B$13) -> 0.6766 | ... N63: =Assumptions!$B$115*(($B$11)*(1-Assumptions!$B$33)-$B$13)+(1-Assumptions!$B$115)*(($B$12)*(1-Assumptions!$B$33)-$B$13) -> 0.6766 | O63: RM/kWh
A64: Top-up before cap (residents' part) | B64: =365*B62*B63*Assumptions!$B$31*(Assumptions!$B$132+Assumptions!$B$135*(Assumptions!$B$36+Assumptions!$B$133))*1 -> 0 | C64: =365*C62*C63*Assumptions!$B$31*(Assumptions!$B$132+Assumptions!$B$135*(Assumptions!$B$36+Assumptions!$B$133))*1 -> 3667.3411 | D64: =365*D62*D63*Assumptions!$B$31*(Assumptions!$B$132+Assumptions!$B$135*(Assumptions!$B$36+Assumptions!$B$133))*1 -> 0 | E64: =365*E62*E63*Assumptions!$B$31*(Assumptions!$B$132+Assumptions!$B$135*(Assumptions!$B$36+Assumptions!$B$133))*1 -> 0 | F64: =365*F62*F63*Assumptions!$B$31*(Assumptions!$B$132+Assumptions!$B$135*(Assumptions!$B$36+Assumptions!$B$133))*1 -> 666.7893 | G64: =365*G62*G63*Assumptions!$B$31*(Assumptions!$B$132+Assumptions!$B$135*(Assumptions!$B$36+Assumptions!$B$133))*1 -> 0 | H64: =365*H62*H63*Assumptions!$B$31*(Assumptions!$B$132+Assumptions!$B$135*(Assumptions!$B$36+Assumptions!$B$133))*1 -> 0 | I64: =365*I62*I63*Assumptions!$B$31*(Assumptions!$B$132+Assumptions!$B$135*(Assumptions!$B$36+Assumptions!$B$133))*1 -> 3333.9465 | ... K64: =365*K62*K63*Assumptions!$B$31*(Assumptions!$B$132+Assumptions!$B$135*(Assumptions!$B$36+Assumptions!$B$133))*1 -> 0 | L64: =365*L62*L63*Assumptions!$B$31*(Assumptions!$B$132+0*(Assumptions!$B$36+Assumptions!$B$133))*1 -> 0 | M64: =365*M62*M63*Assumptions!$B$31*(Assumptions!$B$132+Assumptions!$B$135*(Assumptions!$B$36+Assumptions!$B$133))*1 -> 4667.5251 | N64: =365*N62*N63*Assumptions!$B$31*(Assumptions!$B$132+Assumptions!$B$135*(Assumptions!$B$36+Assumptions!$B$133))*0 -> 0 | O64: RM/yr
A65: Top-up paid (after cap; CPO part missing if the CPO exits) | B65: =MIN(Assumptions!$B$140,B64)*(1-(1-1)*Assumptions!$B$139) -> 0 | C65: =MIN(Assumptions!$B$140,C64)*(1-(1-1)*Assumptions!$B$139) -> 3000 | D65: =MIN(Assumptions!$B$140,D64)*(1-(1-1)*Assumptions!$B$139) -> 0 | E65: =MIN(Assumptions!$B$140,E64)*(1-(1-1)*Assumptions!$B$139) -> 0 | F65: =MIN(Assumptions!$B$140,F64)*(1-(1-1)*Assumptions!$B$139) -> 666.7893 | G65: =MIN(Assumptions!$B$140,G64)*(1-(1-1)*Assumptions!$B$139) -> 0 | H65: =MIN(Assumptions!$B$140,H64)*(1-(1-1)*Assumptions!$B$139) -> 0 | I65: =MIN(Assumptions!$B$140,I64)*(1-(1-1)*Assumptions!$B$139) -> 3000 | ... L65: =MIN(Assumptions!$B$140,L64)*(1-(1-1)*Assumptions!$B$139) -> 0 | M65: =MIN(Assumptions!$B$140,M64)*(1-(1-0)*Assumptions!$B$139) -> 1980 | N65: =MIN(Assumptions!$B$140,N64)*(1-(1-1)*Assumptions!$B$139) -> 0 | O65: RM/yr
A66: paid by developer | B66: =MIN(Assumptions!$B$140,B64)*Assumptions!$B$76 -> 0 | C66: =MIN(Assumptions!$B$140,C64)*Assumptions!$B$76 -> 990 | D66: =MIN(Assumptions!$B$140,D64)*Assumptions!$B$76 -> 0 | E66: =MIN(Assumptions!$B$140,E64)*Assumptions!$B$76 -> 0 | F66: =MIN(Assumptions!$B$140,F64)*Assumptions!$B$76 -> 220.04047 | G66: =MIN(Assumptions!$B$140,G64)*Assumptions!$B$76 -> 0 | H66: =MIN(Assumptions!$B$140,H64)*Assumptions!$B$76 -> 0 | I66: =MIN(Assumptions!$B$140,I64)*Assumptions!$B$76 -> 990 | ... N66: =MIN(Assumptions!$B$140,N64)*Assumptions!$B$76 -> 0 | O66: RM/yr
A67: paid by platform (us) | B67: =MIN(Assumptions!$B$140,B64)*Assumptions!$B$138 -> 0 | C67: =MIN(Assumptions!$B$140,C64)*Assumptions!$B$138 -> 990 | D67: =MIN(Assumptions!$B$140,D64)*Assumptions!$B$138 -> 0 | E67: =MIN(Assumptions!$B$140,E64)*Assumptions!$B$138 -> 0 | F67: =MIN(Assumptions!$B$140,F64)*Assumptions!$B$138 -> 220.04047 | G67: =MIN(Assumptions!$B$140,G64)*Assumptions!$B$138 -> 0 | H67: =MIN(Assumptions!$B$140,H64)*Assumptions!$B$138 -> 0 | I67: =MIN(Assumptions!$B$140,I64)*Assumptions!$B$138 -> 990 | ... N67: =MIN(Assumptions!$B$140,N64)*Assumptions!$B$138 -> 0 | O67: RM/yr
A68: paid by CPO | B68: =MIN(Assumptions!$B$140,B64)*Assumptions!$B$139*1 -> 0 | C68: =MIN(Assumptions!$B$140,C64)*Assumptions!$B$139*1 -> 1020 | D68: =MIN(Assumptions!$B$140,D64)*Assumptions!$B$139*1 -> 0 | E68: =MIN(Assumptions!$B$140,E64)*Assumptions!$B$139*1 -> 0 | F68: =MIN(Assumptions!$B$140,F64)*Assumptions!$B$139*1 -> 226.70836 | G68: =MIN(Assumptions!$B$140,G64)*Assumptions!$B$139*1 -> 0 | H68: =MIN(Assumptions!$B$140,H64)*Assumptions!$B$139*1 -> 0 | I68: =MIN(Assumptions!$B$140,I64)*Assumptions!$B$139*1 -> 1020 | ... L68: =MIN(Assumptions!$B$140,L64)*Assumptions!$B$139*1 -> 0 | M68: =MIN(Assumptions!$B$140,M64)*Assumptions!$B$139*0 -> 0 | N68: =MIN(Assumptions!$B$140,N64)*Assumptions!$B$139*1 -> 0 | O68: RM/yr
A69: Residents: cash for every RM1,000 invested
A70: Cash a year while recovering money (incl. top-up) | B70: =(B56+B65)/B53*1000 -> 179.5948 | C70: =(C56+C65)/C53*1000 -> 85.714286 | D70: =(D56+D65)/D53*1000 -> 135.19912 | E70: =(E56+E65)/E53*1000 -> 114.5948 | F70: =(F56+F65)/F53*1000 -> 176.7624 | G70: =(G56+G65)/G53*1000 -> 75.92896 | H70: =(H56+H65)/H53*1000 -> 115.4538 | I70: =(I56+I65)/I53*1000 -> 164.75273 | ... N70: =(N56+N65)/N53*1000 -> 0 | O70: RM/yr
A71: Cash a year after recovering money (incl. top-up) | B71: =(B57+B65)/B53*1000 -> 139.68484 | C71: =(C57+C65)/C53*1000 -> 85.714286 | D71: =(D57+D65)/D53*1000 -> 105.15487 | E71: =(E57+E65)/E53*1000 -> 89.129289 | F71: =(F57+F65)/F53*1000 -> 144.06744 | G71: =(G57+G65)/G53*1000 -> 59.055858 | H71: =(H57+H65)/H53*1000 -> 89.7974 | I71: =(I57+I65)/I53*1000 -> 157.77064 | ... N71: =(N57+N65)/N53*1000 -> 0 | O71: RM/yr
A72: Reserve returned at the end | B72: =B60*Assumptions!$B$137*Assumptions!$B$136/B53*1000 -> 69.842422 | C72: =C60*Assumptions!$B$137*Assumptions!$B$136/C53*1000 -> 0 | D72: =D60*Assumptions!$B$137*Assumptions!$B$136/D53*1000 -> 52.577436 | E72: =E60*Assumptions!$B$137*Assumptions!$B$136/E53*1000 -> 44.564644 | F72: =F60*Assumptions!$B$137*Assumptions!$B$136/F53*1000 -> 57.21618 | G72: =G60*Assumptions!$B$137*Assumptions!$B$136/G53*1000 -> 29.527929 | H72: =H60*Assumptions!$B$137*Assumptions!$B$136/H53*1000 -> 44.8987 | I72: =I60*Assumptions!$B$137*Assumptions!$B$136/I53*1000 -> 12.218656 | ... N72: =N60*Assumptions!$B$137*Assumptions!$B$136/N53*1000 -> 0 | O72: RM
A73: Years to recover money | B73: =IF(B70<=0,99,1000/B70) -> 5.5680899 | C73: =IF(C70<=0,99,1000/C70) -> 11.666667 | D73: =IF(D70<=0,99,1000/D70) -> 7.3964978 | E73: =IF(E70<=0,99,1000/E70) -> 8.7263995 | F73: =IF(F70<=0,99,1000/F70) -> 5.6573117 | G73: =IF(G70<=0,99,1000/G70) -> 13.170205 | H73: =IF(H70<=0,99,1000/H70) -> 8.6614732 | I73: =IF(I70<=0,99,1000/I70) -> 6.069702 | ... N73: =IF(N70<=0,99,1000/N70) -> 99 | O73: years
A74: Year 0 (invest) | B74: =-1000 -> -1000 | C74: =-1000 -> -1000 | D74: =-1000 -> -1000 | E74: =-1000 -> -1000 | F74: =-1000 -> -1000 | G74: =-1000 -> -1000 | H74: =-1000 -> -1000 | I74: =-1000 -> -1000 | ... N74: =-1000 -> -1000
A75: Year 1 | B75: =IF(1>Assumptions!$B$137,0,IF(0<1000,B70,B71)+IF(1=Assumptions!$B$137,B72,0)) -> 179.5948 | C75: =IF(1>Assumptions!$B$137,0,IF(0<1000,C70,C71)+IF(1=Assumptions!$B$137,C72,0)) -> 85.714286 | D75: =IF(1>Assumptions!$B$137,0,IF(0<1000,D70,D71)+IF(1=Assumptions!$B$137,D72,0)) -> 135.19912 | E75: =IF(1>Assumptions!$B$137,0,IF(0<1000,E70,E71)+IF(1=Assumptions!$B$137,E72,0)) -> 114.5948 | F75: =IF(1>Assumptions!$B$137,0,IF(0<1000,F70,F71)+IF(1=Assumptions!$B$137,F72,0)) -> 176.7624 | G75: =IF(1>Assumptions!$B$137,0,IF(0<1000,G70,G71)+IF(1=Assumptions!$B$137,G72,0)) -> 75.92896 | H75: =IF(1>Assumptions!$B$137,0,IF(0<1000,H70,H71)+IF(1=Assumptions!$B$137,H72,0)) -> 115.4538 | I75: =IF(1>Assumptions!$B$137,0,IF(0<1000,I70,I71)+IF(1=Assumptions!$B$137,I72,0)) -> 164.75273 | ... N75: =IF(1>Assumptions!$B$137,0,IF(0<1000,N70,N71)+IF(1=Assumptions!$B$137,N72,0)) -> 0
A76: Year 2 | B76: =IF(2>Assumptions!$B$137,0,IF(SUM(B75:B75)<1000,B70,B71)+IF(2=Assumptions!$B$137,B72,0)) -> 179.5948 | C76: =IF(2>Assumptions!$B$137,0,IF(SUM(C75:C75)<1000,C70,C71)+IF(2=Assumptions!$B$137,C72,0)) -> 85.714286 | D76: =IF(2>Assumptions!$B$137,0,IF(SUM(D75:D75)<1000,D70,D71)+IF(2=Assumptions!$B$137,D72,0)) -> 135.19912 | E76: =IF(2>Assumptions!$B$137,0,IF(SUM(E75:E75)<1000,E70,E71)+IF(2=Assumptions!$B$137,E72,0)) -> 114.5948 | F76: =IF(2>Assumptions!$B$137,0,IF(SUM(F75:F75)<1000,F70,F71)+IF(2=Assumptions!$B$137,F72,0)) -> 176.7624 | G76: =IF(2>Assumptions!$B$137,0,IF(SUM(G75:G75)<1000,G70,G71)+IF(2=Assumptions!$B$137,G72,0)) -> 75.92896 | H76: =IF(2>Assumptions!$B$137,0,IF(SUM(H75:H75)<1000,H70,H71)+IF(2=Assumptions!$B$137,H72,0)) -> 115.4538 | I76: =IF(2>Assumptions!$B$137,0,IF(SUM(I75:I75)<1000,I70,I71)+IF(2=Assumptions!$B$137,I72,0)) -> 164.75273 | ... N76: =IF(2>Assumptions!$B$137,0,IF(SUM(N75:N75)<1000,N70,N71)+IF(2=Assumptions!$B$137,N72,0)) -> 0
A77: Year 3 | B77: =IF(3>Assumptions!$B$137,0,IF(SUM(B75:B76)<1000,B70,B71)+IF(3=Assumptions!$B$137,B72,0)) -> 179.5948 | C77: =IF(3>Assumptions!$B$137,0,IF(SUM(C75:C76)<1000,C70,C71)+IF(3=Assumptions!$B$137,C72,0)) -> 85.714286 | D77: =IF(3>Assumptions!$B$137,0,IF(SUM(D75:D76)<1000,D70,D71)+IF(3=Assumptions!$B$137,D72,0)) -> 135.19912 | E77: =IF(3>Assumptions!$B$137,0,IF(SUM(E75:E76)<1000,E70,E71)+IF(3=Assumptions!$B$137,E72,0)) -> 114.5948 | F77: =IF(3>Assumptions!$B$137,0,IF(SUM(F75:F76)<1000,F70,F71)+IF(3=Assumptions!$B$137,F72,0)) -> 176.7624 | G77: =IF(3>Assumptions!$B$137,0,IF(SUM(G75:G76)<1000,G70,G71)+IF(3=Assumptions!$B$137,G72,0)) -> 75.92896 | H77: =IF(3>Assumptions!$B$137,0,IF(SUM(H75:H76)<1000,H70,H71)+IF(3=Assumptions!$B$137,H72,0)) -> 115.4538 | I77: =IF(3>Assumptions!$B$137,0,IF(SUM(I75:I76)<1000,I70,I71)+IF(3=Assumptions!$B$137,I72,0)) -> 164.75273 | ... N77: =IF(3>Assumptions!$B$137,0,IF(SUM(N75:N76)<1000,N70,N71)+IF(3=Assumptions!$B$137,N72,0)) -> 0
A78: Year 4 | B78: =IF(4>Assumptions!$B$137,0,IF(SUM(B75:B77)<1000,B70,B71)+IF(4=Assumptions!$B$137,B72,0)) -> 179.5948 | C78: =IF(4>Assumptions!$B$137,0,IF(SUM(C75:C77)<1000,C70,C71)+IF(4=Assumptions!$B$137,C72,0)) -> 85.714286 | D78: =IF(4>Assumptions!$B$137,0,IF(SUM(D75:D77)<1000,D70,D71)+IF(4=Assumptions!$B$137,D72,0)) -> 135.19912 | E78: =IF(4>Assumptions!$B$137,0,IF(SUM(E75:E77)<1000,E70,E71)+IF(4=Assumptions!$B$137,E72,0)) -> 114.5948 | F78: =IF(4>Assumptions!$B$137,0,IF(SUM(F75:F77)<1000,F70,F71)+IF(4=Assumptions!$B$137,F72,0)) -> 176.7624 | G78: =IF(4>Assumptions!$B$137,0,IF(SUM(G75:G77)<1000,G70,G71)+IF(4=Assumptions!$B$137,G72,0)) -> 75.92896 | H78: =IF(4>Assumptions!$B$137,0,IF(SUM(H75:H77)<1000,H70,H71)+IF(4=Assumptions!$B$137,H72,0)) -> 115.4538 | I78: =IF(4>Assumptions!$B$137,0,IF(SUM(I75:I77)<1000,I70,I71)+IF(4=Assumptions!$B$137,I72,0)) -> 164.75273 | ... N78: =IF(4>Assumptions!$B$137,0,IF(SUM(N75:N77)<1000,N70,N71)+IF(4=Assumptions!$B$137,N72,0)) -> 0
A79: Year 5 | B79: =IF(5>Assumptions!$B$137,0,IF(SUM(B75:B78)<1000,B70,B71)+IF(5=Assumptions!$B$137,B72,0)) -> 179.5948 | C79: =IF(5>Assumptions!$B$137,0,IF(SUM(C75:C78)<1000,C70,C71)+IF(5=Assumptions!$B$137,C72,0)) -> 85.714286 | D79: =IF(5>Assumptions!$B$137,0,IF(SUM(D75:D78)<1000,D70,D71)+IF(5=Assumptions!$B$137,D72,0)) -> 135.19912 | E79: =IF(5>Assumptions!$B$137,0,IF(SUM(E75:E78)<1000,E70,E71)+IF(5=Assumptions!$B$137,E72,0)) -> 114.5948 | F79: =IF(5>Assumptions!$B$137,0,IF(SUM(F75:F78)<1000,F70,F71)+IF(5=Assumptions!$B$137,F72,0)) -> 176.7624 | G79: =IF(5>Assumptions!$B$137,0,IF(SUM(G75:G78)<1000,G70,G71)+IF(5=Assumptions!$B$137,G72,0)) -> 75.92896 | H79: =IF(5>Assumptions!$B$137,0,IF(SUM(H75:H78)<1000,H70,H71)+IF(5=Assumptions!$B$137,H72,0)) -> 115.4538 | I79: =IF(5>Assumptions!$B$137,0,IF(SUM(I75:I78)<1000,I70,I71)+IF(5=Assumptions!$B$137,I72,0)) -> 164.75273 | ... N79: =IF(5>Assumptions!$B$137,0,IF(SUM(N75:N78)<1000,N70,N71)+IF(5=Assumptions!$B$137,N72,0)) -> 0
A80: Year 6 | B80: =IF(6>Assumptions!$B$137,0,IF(SUM(B75:B79)<1000,B70,B71)+IF(6=Assumptions!$B$137,B72,0)) -> 179.5948 | C80: =IF(6>Assumptions!$B$137,0,IF(SUM(C75:C79)<1000,C70,C71)+IF(6=Assumptions!$B$137,C72,0)) -> 85.714286 | D80: =IF(6>Assumptions!$B$137,0,IF(SUM(D75:D79)<1000,D70,D71)+IF(6=Assumptions!$B$137,D72,0)) -> 135.19912 | E80: =IF(6>Assumptions!$B$137,0,IF(SUM(E75:E79)<1000,E70,E71)+IF(6=Assumptions!$B$137,E72,0)) -> 114.5948 | F80: =IF(6>Assumptions!$B$137,0,IF(SUM(F75:F79)<1000,F70,F71)+IF(6=Assumptions!$B$137,F72,0)) -> 176.7624 | G80: =IF(6>Assumptions!$B$137,0,IF(SUM(G75:G79)<1000,G70,G71)+IF(6=Assumptions!$B$137,G72,0)) -> 75.92896 | H80: =IF(6>Assumptions!$B$137,0,IF(SUM(H75:H79)<1000,H70,H71)+IF(6=Assumptions!$B$137,H72,0)) -> 115.4538 | I80: =IF(6>Assumptions!$B$137,0,IF(SUM(I75:I79)<1000,I70,I71)+IF(6=Assumptions!$B$137,I72,0)) -> 164.75273 | ... N80: =IF(6>Assumptions!$B$137,0,IF(SUM(N75:N79)<1000,N70,N71)+IF(6=Assumptions!$B$137,N72,0)) -> 0
A81: Year 7 | B81: =IF(7>Assumptions!$B$137,0,IF(SUM(B75:B80)<1000,B70,B71)+IF(7=Assumptions!$B$137,B72,0)) -> 209.52727 | C81: =IF(7>Assumptions!$B$137,0,IF(SUM(C75:C80)<1000,C70,C71)+IF(7=Assumptions!$B$137,C72,0)) -> 85.714286 | D81: =IF(7>Assumptions!$B$137,0,IF(SUM(D75:D80)<1000,D70,D71)+IF(7=Assumptions!$B$137,D72,0)) -> 187.77656 | E81: =IF(7>Assumptions!$B$137,0,IF(SUM(E75:E80)<1000,E70,E71)+IF(7=Assumptions!$B$137,E72,0)) -> 159.15944 | F81: =IF(7>Assumptions!$B$137,0,IF(SUM(F75:F80)<1000,F70,F71)+IF(7=Assumptions!$B$137,F72,0)) -> 201.28362 | G81: =IF(7>Assumptions!$B$137,0,IF(SUM(G75:G80)<1000,G70,G71)+IF(7=Assumptions!$B$137,G72,0)) -> 105.45689 | H81: =IF(7>Assumptions!$B$137,0,IF(SUM(H75:H80)<1000,H70,H71)+IF(7=Assumptions!$B$137,H72,0)) -> 160.3525 | I81: =IF(7>Assumptions!$B$137,0,IF(SUM(I75:I80)<1000,I70,I71)+IF(7=Assumptions!$B$137,I72,0)) -> 176.97139 | ... N81: =IF(7>Assumptions!$B$137,0,IF(SUM(N75:N80)<1000,N70,N71)+IF(7=Assumptions!$B$137,N72,0)) -> 0
A82: Year 8 | B82: =IF(8>Assumptions!$B$137,0,IF(SUM(B75:B81)<1000,B70,B71)+IF(8=Assumptions!$B$137,B72,0)) -> 0 | C82: =IF(8>Assumptions!$B$137,0,IF(SUM(C75:C81)<1000,C70,C71)+IF(8=Assumptions!$B$137,C72,0)) -> 0 | D82: =IF(8>Assumptions!$B$137,0,IF(SUM(D75:D81)<1000,D70,D71)+IF(8=Assumptions!$B$137,D72,0)) -> 0 | E82: =IF(8>Assumptions!$B$137,0,IF(SUM(E75:E81)<1000,E70,E71)+IF(8=Assumptions!$B$137,E72,0)) -> 0 | F82: =IF(8>Assumptions!$B$137,0,IF(SUM(F75:F81)<1000,F70,F71)+IF(8=Assumptions!$B$137,F72,0)) -> 0 | G82: =IF(8>Assumptions!$B$137,0,IF(SUM(G75:G81)<1000,G70,G71)+IF(8=Assumptions!$B$137,G72,0)) -> 0 | H82: =IF(8>Assumptions!$B$137,0,IF(SUM(H75:H81)<1000,H70,H71)+IF(8=Assumptions!$B$137,H72,0)) -> 0 | I82: =IF(8>Assumptions!$B$137,0,IF(SUM(I75:I81)<1000,I70,I71)+IF(8=Assumptions!$B$137,I72,0)) -> 0 | ... N82: =IF(8>Assumptions!$B$137,0,IF(SUM(N75:N81)<1000,N70,N71)+IF(8=Assumptions!$B$137,N72,0)) -> 0
A83: Year 9 | B83: =IF(9>Assumptions!$B$137,0,IF(SUM(B75:B82)<1000,B70,B71)+IF(9=Assumptions!$B$137,B72,0)) -> 0 | C83: =IF(9>Assumptions!$B$137,0,IF(SUM(C75:C82)<1000,C70,C71)+IF(9=Assumptions!$B$137,C72,0)) -> 0 | D83: =IF(9>Assumptions!$B$137,0,IF(SUM(D75:D82)<1000,D70,D71)+IF(9=Assumptions!$B$137,D72,0)) -> 0 | E83: =IF(9>Assumptions!$B$137,0,IF(SUM(E75:E82)<1000,E70,E71)+IF(9=Assumptions!$B$137,E72,0)) -> 0 | F83: =IF(9>Assumptions!$B$137,0,IF(SUM(F75:F82)<1000,F70,F71)+IF(9=Assumptions!$B$137,F72,0)) -> 0 | G83: =IF(9>Assumptions!$B$137,0,IF(SUM(G75:G82)<1000,G70,G71)+IF(9=Assumptions!$B$137,G72,0)) -> 0 | H83: =IF(9>Assumptions!$B$137,0,IF(SUM(H75:H82)<1000,H70,H71)+IF(9=Assumptions!$B$137,H72,0)) -> 0 | I83: =IF(9>Assumptions!$B$137,0,IF(SUM(I75:I82)<1000,I70,I71)+IF(9=Assumptions!$B$137,I72,0)) -> 0 | ... N83: =IF(9>Assumptions!$B$137,0,IF(SUM(N75:N82)<1000,N70,N71)+IF(9=Assumptions!$B$137,N72,0)) -> 0
A84: Year 10 | B84: =IF(10>Assumptions!$B$137,0,IF(SUM(B75:B83)<1000,B70,B71)+IF(10=Assumptions!$B$137,B72,0)) -> 0 | C84: =IF(10>Assumptions!$B$137,0,IF(SUM(C75:C83)<1000,C70,C71)+IF(10=Assumptions!$B$137,C72,0)) -> 0 | D84: =IF(10>Assumptions!$B$137,0,IF(SUM(D75:D83)<1000,D70,D71)+IF(10=Assumptions!$B$137,D72,0)) -> 0 | E84: =IF(10>Assumptions!$B$137,0,IF(SUM(E75:E83)<1000,E70,E71)+IF(10=Assumptions!$B$137,E72,0)) -> 0 | F84: =IF(10>Assumptions!$B$137,0,IF(SUM(F75:F83)<1000,F70,F71)+IF(10=Assumptions!$B$137,F72,0)) -> 0 | G84: =IF(10>Assumptions!$B$137,0,IF(SUM(G75:G83)<1000,G70,G71)+IF(10=Assumptions!$B$137,G72,0)) -> 0 | H84: =IF(10>Assumptions!$B$137,0,IF(SUM(H75:H83)<1000,H70,H71)+IF(10=Assumptions!$B$137,H72,0)) -> 0 | I84: =IF(10>Assumptions!$B$137,0,IF(SUM(I75:I83)<1000,I70,I71)+IF(10=Assumptions!$B$137,I72,0)) -> 0 | ... N84: =IF(10>Assumptions!$B$137,0,IF(SUM(N75:N83)<1000,N70,N71)+IF(10=Assumptions!$B$137,N72,0)) -> 0
A85: Total received over the payback period | B85: =SUM(B75:B84) -> 1287.0961 | C85: =SUM(C75:C84) -> 600 | D85: =SUM(D75:D84) -> 998.97128 | E85: =SUM(E75:E84) -> 846.72824 | F85: =SUM(F75:F84) -> 1261.858 | G85: =SUM(G75:G84) -> 561.03065 | H85: =SUM(H75:H84) -> 853.0753 | I85: =SUM(I75:I84) -> 1165.4878 | ... N85: =SUM(N75:N84) -> 0 | O85: RM
A86: Money back (share of what was invested) | B86: =B85/1000 -> 1.2870961 | C86: =C85/1000 -> 0.6 | D86: =D85/1000 -> 0.99897128 | E86: =E85/1000 -> 0.84672824 | F86: =F85/1000 -> 1.261858 | G86: =G85/1000 -> 0.56103065 | H86: =H85/1000 -> 0.8530753 | I86: =I85/1000 -> 1.1654878 | ... N86: =N85/1000 -> 0
A87: Loss over the payback period (target: no worse than 50%) | B87: =MAX(0,1-B86) -> 0 | C87: =MAX(0,1-C86) -> 0.4 | D87: =MAX(0,1-D86) -> 0.0010287244 | E87: =MAX(0,1-E86) -> 0.15327176 | F87: =MAX(0,1-F86) -> 0 | G87: =MAX(0,1-G86) -> 0.43896935 | H87: =MAX(0,1-H86) -> 0.1469247 | I87: =MAX(0,1-I86) -> 0 | ... N87: =MAX(0,1-N86) -> 1
A88: Residents' return a year (IRR) | B88: =IFERROR(IRR(B74:B84),-1) -> 0.066187268 | C88: =IFERROR(IRR(C74:C84),-1) -> -0.11351477 | D88: =IFERROR(IRR(D74:D84),-1) -> -0.00024748024 | E88: =IFERROR(IRR(E74:E84),-1) -> -0.038472292 | F88: =IFERROR(IRR(F74:F84),-1) -> 0.060849358 | G88: =IFERROR(IRR(G74:G84),-1) -> -0.12230207 | H88: =IFERROR(IRR(H74:H84),-1) -> -0.036808596 | I88: =IFERROR(IRR(I74:I84),-1) -> 0.039500305 | ... N88: =IFERROR(IRR(N74:N84),-1) -> -1
A89: Year-1 cash return (cash ÷ invested) | B89: =B70/1000 -> 0.1795948 | C89: =C70/1000 -> 0.085714286 | D89: =D70/1000 -> 0.13519912 | E89: =E70/1000 -> 0.1145948 | F89: =F70/1000 -> 0.1767624 | G89: =G70/1000 -> 0.07592896 | H89: =H70/1000 -> 0.1154538 | I89: =I70/1000 -> 0.16475273 | ... N89: =N70/1000 -> 0
A90: Developer, platform and CPO (per charger per year)
A91: Developer net while residents recover (share − top-up) | B91: =(1-Assumptions!$B$135)*B58-B66 -> 0 | C91: =(1-Assumptions!$B$135)*C58-C66 -> -990 | D91: =(1-Assumptions!$B$135)*D58-D66 -> 0 | E91: =(1-Assumptions!$B$135)*E58-E66 -> 0 | F91: =(1-Assumptions!$B$135)*F58-F66 -> -220.04047 | G91: =(1-Assumptions!$B$135)*G58-G66 -> 0 | H91: =(1-Assumptions!$B$135)*H58-H66 -> 0 | I91: =(1-Assumptions!$B$135)*I58-I66 -> -990 | ... K91: =(1-Assumptions!$B$135)*K58-K66 -> 0 | L91: =(1-0)*L58-L66 -> 448.987 | M91: =(1-Assumptions!$B$135)*M58-M66 -> -990 | N91: =(1-Assumptions!$B$135)*N58-N66 -> 0 | O91: RM/yr
A92: Developer net after residents recover | B92: =B58-B66 -> 448.987 | C92: =C58-C66 -> -990 | D92: =D58-D66 -> 337.9978 | E92: =E58-E66 -> 286.487 | F92: =F58-F66 -> 147.77783 | G92: =G58-G66 -> 189.8224 | H92: =H58-H66 -> 448.987 | I92: =I58-I66 -> -911.4515 | ... N92: =N58-N66 -> 0 | O92: RM/yr
A93: Platform net while residents recover (share − top-up) | B93: =(1-Assumptions!$B$135)*B59-B67 -> 0 | C93: =(1-Assumptions!$B$135)*C59-C67 -> -990 | D93: =(1-Assumptions!$B$135)*D59-D67 -> 0 | E93: =(1-Assumptions!$B$135)*E59-E67 -> 0 | F93: =(1-Assumptions!$B$135)*F59-F67 -> -220.04047 | G93: =(1-Assumptions!$B$135)*G59-G67 -> 0 | H93: =(1-Assumptions!$B$135)*H59-H67 -> 0 | I93: =(1-Assumptions!$B$135)*I59-I67 -> -990 | ... K93: =(1-Assumptions!$B$135)*K59-K67 -> 0 | L93: =(1-0)*L59-L67 -> 448.987 | M93: =(1-Assumptions!$B$135)*M59-M67 -> -990 | N93: =(1-Assumptions!$B$135)*N59-N67 -> 0 | O93: RM/yr
A94: Platform net after residents recover | B94: =B59-B67 -> 448.987 | C94: =C59-C67 -> -990 | D94: =D59-D67 -> 337.9978 | E94: =E59-E67 -> 286.487 | F94: =F59-F67 -> 147.77783 | G94: =G59-G67 -> 189.8224 | H94: =H59-H67 -> 448.987 | I94: =I59-I67 -> -911.4515 | ... N94: =N59-N67 -> 0 | O94: RM/yr
A95: CPO: profit share + service fee − top-up | B95: =B55+Assumptions!$B$115*Assumptions!$B$34*(1+0)+(1-Assumptions!$B$115)*Assumptions!$B$127*(1+0)-B68 -> 10989.87 | C95: =C55+Assumptions!$B$115*Assumptions!$B$34*(1+Pools_Scenarios!$C$96)+(1-Assumptions!$B$115)*Assumptions!$B$127*(1+Pools_Scenarios!$C$96)-C68 -> 5028.3994 | D95: =D55+Assumptions!$B$115*Assumptions!$B$34*(1+0)+(1-Assumptions!$B$115)*Assumptions!$B$127*(1+0)-D68 -> 9879.978 | E95: =E55+Assumptions!$B$115*Assumptions!$B$34*(1+Pools_Scenarios!$C$96)+(1-Assumptions!$B$115)*Assumptions!$B$127*(1+Pools_Scenarios!$C$96)-E68 -> 12614.87 | F95: =F55+Assumptions!$B$115*Assumptions!$B$34*(1+0)+(1-Assumptions!$B$115)*Assumptions!$B$127*(1+0)-F68 -> 9951.4746 | G95: =G55+Assumptions!$B$115*Assumptions!$B$34*(1+0)+(1-Assumptions!$B$115)*Assumptions!$B$127*(1+0)-G68 -> 8398.224 | H95: =H55+Assumptions!$B$115*Assumptions!$B$34*(1+0)+(1-Assumptions!$B$115)*Assumptions!$B$127*(1+0)-H68 -> 10989.87 | I95: =I55+Assumptions!$B$115*Assumptions!$B$34*(1+0)+(1-Assumptions!$B$115)*Assumptions!$B$127*(1+0)-I68 -> 6265.485 | J95: =J55+Assumptions!$B$115*Assumptions!$B$34*(1+0)+(1-Assumptions!$B$115)*Assumptions!$B$127*(1+0)-J68 -> 9408.77 | K95: =K55+Assumptions!$B$115*Assumptions!$B$34*(1+0)+(1-Assumptions!$B$115)*Assumptions!$B$127*(1+0)-K68 -> 7329.8 | L95: =L55+Assumptions!$B$115*Assumptions!$B$34*(1+0)+(1-Assumptions!$B$115)*Assumptions!$B$127*(1+0)-L68 -> 10989.87 | M95: =M55+Assumptions!$B$115*Assumptions!$B$34*(1+Pools_Scenarios!$C$96)+(1-Assumptions!$B$115)*Assumptions!$B$127*(1+Pools_Scenarios!$C$96)-M68 -> 4647.1606 | N95: =N55+Assumptions!$B$115*Assumptions!$B$34*(1+Pools_Scenarios!$C$96)+(1-Assumptions!$B$115)*Assumptions!$B$127*(1+Pools_Scenarios!$C$96)-N68 -> 6048.3994 | O95: RM/yr
A96: CPO earns the service fee to cover its own crews and parts; shown for context | B96: ="" | C96: ="" | D96: ="" | E96: ="" | F96: ="" | G96: ="" | H96: ="" | I96: ="" | ... N96: =""
A98: How to read: a charger costs about RM45,000 after the grant; residents fund half and the CPO funds half. Profit is shared 50/50 by funding, then residents' half is split 70/10/10/10.
A99: Normal: the whole charger pays back in about 5 years, so a 7-year resident payback gives a single-digit return. EV is the thinnest pool: keep it small (RM500 cap per resident, 1–2 chargers a year).
A100: Top-up: if a charger sells less than 60 kWh/day, the developer (33%), platform (33%) and CPO (34%) pay residents for the missing kWh at the normal contract margin, capped at RM3,000 per charger a year. It does not cover price wars or cost rises.
A101: Losses: payouts never go below zero. Operating losses stay with the asset; a charger that keeps losing money should be moved or switched off by the CPO.
A102: WORST CASE (column M): loss is above 50%. This is why the EV pool is capped at RM500 per resident: the most a resident can lose is about RM300. If the CPO exits, a replacement operator is assumed to keep the chargers running; the CPO's 34% of the top-up is lost.
...

Sheet Benefits
A1: 1) Benefits – value created for the developer (customer)
A2: Top: one SDP-size client by its year on the platform. Bottom: all clients together by calendar year.
A4: Benefit | B4: How it is worked out | C4: Year 1 | D4: Year 2 | E4: Year 3 | F4: Year 4 | G4: Year 5
A5: One SDP-size client (by client's year)
A6: A. Cheaper money for solar | B6: Residents' solar money × ((8.5% − 5%) × developer's JV share + JV arrangement fee) | C6: =Pools_Scenarios!C18*((Assumptions!$B$21-Assumptions!$B$19)*Assumptions!$B$14+Assumptions!$B$70) -> 39600 | D6: =Pools_Scenarios!D18*((Assumptions!$B$21-Assumptions!$B$19)*Assumptions!$B$14+Assumptions!$B$70) -> 111633.4 | E6: =Pools_Scenarios!E18*((Assumptions!$B$21-Assumptions!$B$19)*Assumptions!$B$14+Assumptions!$B$70) -> 182175.26 | F6: =Pools_Scenarios!F18*((Assumptions!$B$21-Assumptions!$B$19)*Assumptions!$B$14+Assumptions!$B$70) -> 261302.15 | G6: =Pools_Scenarios!G18*((Assumptions!$B$21-Assumptions!$B$19)*Assumptions!$B$14+Assumptions!$B$70) -> 330145.57
A7: B. Fee from shop upgrades | B7: Shop-years × positive safety margin × developer's share | C7: =Pools_Scenarios!C28*MAX(0,Pools_Scenarios!C31)*Assumptions!$B$28 -> 8415.8974 | D7: =Pools_Scenarios!D28*MAX(0,Pools_Scenarios!D31)*Assumptions!$B$28 -> 30858.291 | E7: =Pools_Scenarios!E28*MAX(0,Pools_Scenarios!E31)*Assumptions!$B$28 -> 50495.384 | F7: =Pools_Scenarios!F28*MAX(0,Pools_Scenarios!F31)*Assumptions!$B$28 -> 53300.684 | G7: =Pools_Scenarios!G28*MAX(0,Pools_Scenarios!G31)*Assumptions!$B$28 -> 42079.487
A8: C. Developer's EV share, less its part of the usage top-up | B8: 10% of residents' EV profit (paid after residents recover) − developer's 33% of any top-up | C8: =Pools_Scenarios!C70-Pools_Scenarios!C71 -> 0 | D8: =Pools_Scenarios!D70-Pools_Scenarios!D71 -> 0 | E8: =Pools_Scenarios!E70-Pools_Scenarios!E71 -> 0 | F8: =Pools_Scenarios!F70-Pools_Scenarios!F71 -> 0 | G8: =Pools_Scenarios!G70-Pools_Scenarios!G71 -> 0
A9: D. Extra mall rent | B9: Money spent at malls × turnover rent | C9: =Pools_Scenarios!C48*Assumptions!$B$10 -> 1286.3148 | D9: =Pools_Scenarios!D48*Assumptions!$B$10 -> 3986.9818 | E9: =Pools_Scenarios!E48*Assumptions!$B$10 -> 6999.4954 | F9: =Pools_Scenarios!F48*Assumptions!$B$10 -> 10379.627 | G9: =Pools_Scenarios!G48*Assumptions!$B$10 -> 13822.198
A10: Cash benefits (A to D, plus F, less G) | C10: =SUM(C6:C9)+C31+C34 -> 42768.55 | D10: =SUM(D6:D9)+D31+D34 -> 126156.78 | E10: =SUM(E6:E9)+E31+E34 -> 203981.54 | F10: =SUM(F6:F9)+F31+F34 -> 271239.97 | G10: =SUM(G6:G9)+G31+G34 -> 312421.29
A11: E. Community-programme saving (actually achieved) | B11: Programme spend × saving rate × share achieved | C11: =Assumptions!$B$13*Assumptions!$B$158*Assumptions!$B$64 -> 104000 | D11: =Assumptions!$B$13*Assumptions!$C$158*Assumptions!$B$64 -> 208000 | E11: =Assumptions!$B$13*Assumptions!$D$158*Assumptions!$B$64 -> 208000 | F11: =Assumptions!$B$13*Assumptions!$E$158*Assumptions!$B$64 -> 208000 | G11: =Assumptions!$B$13*Assumptions!$F$158*Assumptions!$B$64 -> 208000
A12: Total benefit for one SDP-size client | C12: =C10+C11 -> 146768.55 | D12: =D10+D11 -> 334156.78 | E12: =E10+E11 -> 411981.54 | F12: =F10+F11 -> 479239.97 | G12: =G10+G11 -> 520421.29
A14: Value to residents and shops (one SDP-size client, not counted in developer ROI)
A15: Residents' profit earned | B15: Payout profit on money invested, after expected shop losses | C15: =Pools_Scenarios!C50 -> 82163.299 | D15: =Pools_Scenarios!D50 -> 237325.4 | E15: =Pools_Scenarios!E50 -> 378613.85 | F15: =Pools_Scenarios!F50 -> 517911.11 | G15: =Pools_Scenarios!G50 -> 636879.55
A16: Savings shops keep | B16: 20% of savings during repayment | C16: =Pools_Scenarios!C32 -> 18000 | D16: =Pools_Scenarios!D32 -> 66000 | E16: =Pools_Scenarios!E32 -> 108000 | F16: =Pools_Scenarios!F32 -> 114000 | G16: =Pools_Scenarios!G32 -> 90000
A17: CO2 avoided (tCO2e) | B17: Solar + upgrades | C17: =Pools_Scenarios!C51 -> 1518.9128 | D17: =Pools_Scenarios!D51 -> 4644.3469 | E17: =Pools_Scenarios!E51 -> 8188.4767 | F17: =Pools_Scenarios!F51 -> 12394.781 | G17: =Pools_Scenarios!G51 -> 16844.564
A19: All clients together (by calendar year)
A20: Developer clients on the platform | B20: Cumulative clients signed | C20: =Assumptions!$B$159 -> 1 | D20: =Assumptions!$B$159+Assumptions!$C$159 -> 3 | E20: =Assumptions!$B$159+Assumptions!$C$159+Assumptions!$D$159 -> 5 | F20: =Assumptions!$B$159+Assumptions!$C$159+Assumptions!$D$159+Assumptions!$E$159 -> 7 | G20: =Assumptions!$B$159+Assumptions!$C$159+Assumptions!$D$159+Assumptions!$E$159+Assumptions!$F$159 -> 9
A21: Cash benefits (A to D, plus F), all clients | C21: =Assumptions!$B$159*Assumptions!$B$160*C10 -> 42768.55 | D21: =Assumptions!$B$159*Assumptions!$B$160*D10+Assumptions!$C$159*Assumptions!$C$160*C10 -> 177479.04 | E21: =Assumptions!$B$159*Assumptions!$B$160*E10+Assumptions!$C$159*Assumptions!$C$160*D10+Assumptions!$D$159*Assumptions!$D$160*C10 -> 406691.94 | F21: =Assumptions!$B$159*Assumptions!$B$160*F10+Assumptions!$C$159*Assumptions!$C$160*E10+Assumptions!$D$159*Assumptions!$D$160*D10+Assumptions!$E$159*Assumptions!$E$160*C10 -> 718728.22 | G21: =Assumptions!$B$159*Assumptions!$B$160*G10+Assumptions!$C$159*Assumptions!$C$160*F10+Assumptions!$D$159*Assumptions!$D$160*E10+Assumptions!$E$159*Assumptions!$E$160*D10+Assumptions!$F$159*Assumptions!$F$160*C10 -> 1085397.5
A22: Community-programme saving, all clients | C22: =Assumptions!$B$159*Assumptions!$B$160*C11 -> 104000 | D22: =Assumptions!$B$159*Assumptions!$B$160*D11+Assumptions!$C$159*Assumptions!$C$160*C11 -> 332800 | E22: =Assumptions!$B$159*Assumptions!$B$160*E11+Assumptions!$C$159*Assumptions!$C$160*D11+Assumptions!$D$159*Assumptions!$D$160*C11 -> 582400 | F22: =Assumptions!$B$159*Assumptions!$B$160*F11+Assumptions!$C$159*Assumptions!$C$160*E11+Assumptions!$D$159*Assumptions!$D$160*D11+Assumptions!$E$159*Assumptions!$E$160*C11 -> 832000 | G22: =Assumptions!$B$159*Assumptions!$B$160*G11+Assumptions!$C$159*Assumptions!$C$160*F11+Assumptions!$D$159*Assumptions!$D$160*E11+Assumptions!$E$159*Assumptions!$E$160*D11+Assumptions!$F$159*Assumptions!$F$160*C11 -> 1081600
A23: Total benefits, all clients | C23: =C21+C22 -> 146768.55 | D23: =D21+D22 -> 510279.04 | E23: =E21+E22 -> 989091.94 | F23: =F21+F22 -> 1550728.2 | G23: =G21+G22 -> 2166997.5
A24: Money raised from residents, all clients | C24: =Assumptions!$B$159*Assumptions!$B$160*Pools_Scenarios!C45 -> 3202500 | D24: =Assumptions!$B$159*Assumptions!$B$160*Pools_Scenarios!D45+Assumptions!$C$159*Assumptions!$C$160*Pools_Scenarios!C45 -> 7268000 | E24: =Assumptions!$B$159*Assumptions!$B$160*Pools_Scenarios!E45+Assumptions!$C$159*Assumptions!$C$160*Pools_Scenarios!D45+Assumptions!$D$159*Assumptions!$D$160*Pools_Scenarios!C45 -> 12038000 | F24: =Assumptions!$B$159*Assumptions!$B$160*Pools_Scenarios!F45+Assumptions!$C$159*Assumptions!$C$160*Pools_Scenarios!E45+Assumptions!$D$159*Assumptions!$D$160*Pools_Scenarios!D45+Assumptions!$E$159*Assumptions!$E$160*Pools_Scenarios!C45 -> 17900000 | G24: =Assumptions!$B$159*Assumptions!$B$160*Pools_Scenarios!G45+Assumptions!$C$159*Assumptions!$C$160*Pools_Scenarios!F45+Assumptions!$D$159*Assumptions!$D$160*Pools_Scenarios!E45+Assumptions!$E$159*Assumptions!$E$160*Pools_Scenarios!D45+Assumptions!$F$159*Assumptions!$F$160*Pools_Scenarios!C45 -> 23954000
A25: Resident investments made, all clients (count) | B25: count | C25: =Assumptions!$B$159*Assumptions!$B$160*Pools_Scenarios!C49 -> 6405 | D25: =Assumptions!$B$159*Assumptions!$B$160*Pools_Scenarios!D49+Assumptions!$C$159*Assumptions!$C$160*Pools_Scenarios!C49 -> 14536 | E25: =Assumptions!$B$159*Assumptions!$B$160*Pools_Scenarios!E49+Assumptions!$C$159*Assumptions!$C$160*Pools_Scenarios!D49+Assumptions!$D$159*Assumptions!$D$160*Pools_Scenarios!C49 -> 24076 | F25: =Assumptions!$B$159*Assumptions!$B$160*Pools_Scenarios!F49+Assumptions!$C$159*Assumptions!$C$160*Pools_Scenarios!E49+Assumptions!$D$159*Assumptions!$D$160*Pools_Scenarios!D49+Assumptions!$E$159*Assumptions!$E$160*Pools_Scenarios!C49 -> 35800 | G25: =Assumptions!$B$159*Assumptions!$B$160*Pools_Scenarios!G49+Assumptions!$C$159*Assumptions!$C$160*Pools_Scenarios!F49+Assumptions!$D$159*Assumptions!$D$160*Pools_Scenarios!E49+Assumptions!$E$159*Assumptions!$E$160*Pools_Scenarios!D49+Assumptions!$F$159*Assumptions!$F$160*Pools_Scenarios!C49 -> 47908
A26: Residents' profit, all clients | C26: =Assumptions!$B$159*Assumptions!$B$160*Pools_Scenarios!C50 -> 82163.299 | D26: =Assumptions!$B$159*Assumptions!$B$160*Pools_Scenarios!D50+Assumptions!$C$159*Assumptions!$C$160*Pools_Scenarios!C50 -> 335921.35 | E26: =Assumptions!$B$159*Assumptions!$B$160*Pools_Scenarios!E50+Assumptions!$C$159*Assumptions!$C$160*Pools_Scenarios!D50+Assumptions!$D$159*Assumptions!$D$160*Pools_Scenarios!C50 -> 762000.28 | F26: =Assumptions!$B$159*Assumptions!$B$160*Pools_Scenarios!F50+Assumptions!$C$159*Assumptions!$C$160*Pools_Scenarios!E50+Assumptions!$D$159*Assumptions!$D$160*Pools_Scenarios!D50+Assumptions!$E$159*Assumptions!$E$160*Pools_Scenarios!C50 -> 1355634.2 | G26: =Assumptions!$B$159*Assumptions!$B$160*Pools_Scenarios!G50+Assumptions!$C$159*Assumptions!$C$160*Pools_Scenarios!F50+Assumptions!$D$159*Assumptions!$D$160*Pools_Scenarios!E50+Assumptions!$E$159*Assumptions!$E$160*Pools_Scenarios!D50+Assumptions!$F$159*Assumptions!$F$160*Pools_Scenarios!C50 -> 2096095.9
A27: CO2 avoided, all clients (tCO2e) | C27: =Assumptions!$B$159*Assumptions!$B$160*Pools_Scenarios!C51 -> 1518.9128 | D27: =Assumptions!$B$159*Assumptions!$B$160*Pools_Scenarios!D51+Assumptions!$C$159*Assumptions!$C$160*Pools_Scenarios!C51 -> 6467.0422 | E27: =Assumptions!$B$159*Assumptions!$B$160*Pools_Scenarios!E51+Assumptions!$C$159*Assumptions!$C$160*Pools_Scenarios!D51+Assumptions!$D$159*Assumptions!$D$160*Pools_Scenarios!C51 -> 15584.388 | F27: =Assumptions!$B$159*Assumptions!$B$160*Pools_Scenarios!F51+Assumptions!$C$159*Assumptions!$C$160*Pools_Scenarios!E51+Assumptions!$D$159*Assumptions!$D$160*Pools_Scenarios!D51+Assumptions!$E$159*Assumptions!$E$160*Pools_Scenarios!C51 -> 29616.865 | G27: =Assumptions!$B$159*Assumptions!$B$160*Pools_Scenarios!G51+Assumptions!$C$159*Assumptions!$C$160*Pools_Scenarios!F51+Assumptions!$D$159*Assumptions!$D$160*Pools_Scenarios!E51+Assumptions!$E$159*Assumptions!$E$160*Pools_Scenarios!D51+Assumptions!$F$159*Assumptions!$F$160*Pools_Scenarios!C51 -> 48940.385
A28: Benefit A only counts the residents' share of each solar asset and only the developer's assumed share of the JV. Benefit E is the least certain; guarantees half of it in the contract (see Pricing_Income credit rows).
A30: Certificates and the community-saving guarantee (one SDP-size client)
A31: F. Renewable energy certificate (REC) sales, developer's share | B31: Residents' share of solar MWh × REC price × USD rate × JV share × (1 − our service fee) | C31: =Pools_Scenarios!C63*Assumptions!$B$78*Assumptions!$B$52*Assumptions!$B$14*(1-Assumptions!$B$79) -> 3842.4375 | D31: =Pools_Scenarios!D63*Assumptions!$B$78*Assumptions!$B$52*Assumptions!$B$14*(1-Assumptions!$B$79) -> 11527.313 | E31: =Pools_Scenarios!E63*Assumptions!$B$78*Assumptions!$B$52*Assumptions!$B$14*(1-Assumptions!$B$79) -> 20493 | F31: =Pools_Scenarios!F63*Assumptions!$B$78*Assumptions!$B$52*Assumptions!$B$14*(1-Assumptions!$B$79) -> 32020.312 | G31: =Pools_Scenarios!G63*Assumptions!$B$78*Assumptions!$B$52*Assumptions!$B$14*(1-Assumptions!$B$79) -> 44828.438
A32: Community saving we guarantee in the contract | B32: Programme spend × saving rate × guaranteed share | C32: =Assumptions!$B$13*Assumptions!$B$158*Assumptions!$B$65 -> 52000 | D32: =Assumptions!$B$13*Assumptions!$C$158*Assumptions!$B$65 -> 104000 | E32: =Assumptions!$B$13*Assumptions!$D$158*Assumptions!$B$65 -> 104000 | F32: =Assumptions!$B$13*Assumptions!$E$158*Assumptions!$B$65 -> 104000 | G32: =Assumptions!$B$13*Assumptions!$F$158*Assumptions!$B$65 -> 104000
A33: Shortfall vs guarantee | B33: Guaranteed − achieved (if positive) | C33: =MAX(0,C32-C11) -> 0 | D33: =MAX(0,D32-D11) -> 0 | E33: =MAX(0,E32-E11) -> 0 | F33: =MAX(0,F32-F11) -> 0 | G33: =MAX(0,G32-G11) -> 0
A34: G. Licensed platform (RMO) fee, developer's share (cost) | B34: − raised × RMO fee × (1 + SST) × developer's share, spread over the payout period | C34: =-Pools_Scenarios!C78 -> -10376.1 | D34: =-Pools_Scenarios!D78 -> -31849.2 | E34: =-Pools_Scenarios!E78 -> -56181.6 | F34: =-Pools_Scenarios!F78 -> -85762.8 | G34: =-Pools_Scenarios!G78 -> -118454.4

Sheet Pricing_Income
A1: 2) Pricing / Income – what clients pay = what we earn
A2: Top: one client by its year on the platform. Bottom: all clients by calendar year. credits refund part of our fees if the community saving falls short.
A4: Income line | B4: Who pays | C4: Year 1 | D4: Year 2 | E4: Year 3 | F4: Year 4 | G4: Year 5
A5: One client (by client's year). Fixed fees are the same for every client; usage fees scale with client size.
A6: Set-up fee (split into Year 1 and Year 2 instalments) | B6: Developer | C6: =Assumptions!$B$60 -> 20000 | D6: =Assumptions!$B$61 -> 30000 | E6: =0 -> 0 | F6: =0 -> 0 | G6: =0 -> 0
A7: Platform fee (waived in Year 1 pilot; billed monthly) | B7: Developer | C7: =0 -> 0 | D7: =Assumptions!$B$39 -> 72000 | E7: =Assumptions!$B$39 -> 72000 | F7: =Assumptions!$B$39 -> 72000 | G7: =Assumptions!$B$39 -> 72000
A8: Fixed fees | C8: =C6+C7 -> 20000 | D8: =D6+D7 -> 102000 | E8: =E6+E7 -> 72000 | F8: =F6+F7 -> 72000 | G8: =G6+G7 -> 72000
A9: Success fee on money raised (waived in Year 1) | B9: Developer (from pool) | C9: =Pools_Scenarios!C45*Assumptions!$B$40*(1-Assumptions!$B$62) -> 0 | D9: =Pools_Scenarios!D45*Assumptions!$B$40 -> 25687.5 | E9: =Pools_Scenarios!E45*Assumptions!$B$40 -> 30637.5 | F9: =Pools_Scenarios!F45*Assumptions!$B$40 -> 37837.5 | G9: =Pools_Scenarios!G45*Assumptions!$B$40 -> 37837.5
A10: Fee on money still invested (from Year 2) | B10: Developer (from pool) | C10: =0 -> 0 | D10: =Pools_Scenarios!D46*Assumptions!$B$41 -> 23017.46 | E10: =Pools_Scenarios!E46*Assumptions!$B$41 -> 36895.218 | F10: =Pools_Scenarios!F46*Assumptions!$B$41 -> 50947.876 | G10: =Pools_Scenarios!G46*Assumptions!$B$41 -> 62973.161
A11: Usage fees paid by developer (SDP size) | C11: =C9+C10 -> 0 | D11: =D9+D10 -> 48704.96 | E11: =E9+E10 -> 67532.718 | F11: =F9+F10 -> 88785.376 | G11: =G9+G10 -> 100810.66
A12: Fee on mall redemptions (SDP size) | B12: Mall shops | C12: =Pools_Scenarios!C48*Assumptions!$B$42 -> 2572.6295 | D12: =Pools_Scenarios!D48*Assumptions!$B$42 -> 7973.9637 | E12: =Pools_Scenarios!E48*Assumptions!$B$42 -> 13998.991 | F12: =Pools_Scenarios!F48*Assumptions!$B$42 -> 20759.254 | G12: =Pools_Scenarios!G48*Assumptions!$B$42 -> 27644.395
A13: SDP pays us (fixed + usage − guarantee credit) | C13: =C8+C11-C25 -> 20000 | D13: =D8+D11-D25 -> 150704.96 | E13: =E8+E11-E25 -> 139532.72 | F13: =F8+F11-F25 -> 160785.38 | G13: =G8+G11-G25 -> 172810.66
A15: All clients (by calendar year)
A16: Fixed fees (set-up + platform, pro rata to client size) | B16: Developers | C16: =Assumptions!$B$159*Assumptions!$B$160*C8 -> 20000 | D16: =Assumptions!$B$159*Assumptions!$B$160*D8+Assumptions!$C$159*Assumptions!$C$160*C8 -> 126000 | E16: =Assumptions!$B$159*Assumptions!$B$160*E8+Assumptions!$C$159*Assumptions!$C$160*D8+Assumptions!$D$159*Assumptions!$D$160*C8 -> 218400 | F16: =Assumptions!$B$159*Assumptions!$B$160*F8+Assumptions!$C$159*Assumptions!$C$160*E8+Assumptions!$D$159*Assumptions!$D$160*D8+Assumptions!$E$159*Assumptions!$E$160*C8 -> 304800 | G16: =Assumptions!$B$159*Assumptions!$B$160*G8+Assumptions!$C$159*Assumptions!$C$160*F8+Assumptions!$D$159*Assumptions!$D$160*E8+Assumptions!$E$159*Assumptions!$E$160*D8+Assumptions!$F$159*Assumptions!$F$160*C8 -> 391200
A17: Usage fees (success + invested money) | B17: Developers | C17: =Assumptions!$B$159*Assumptions!$B$160*C11 -> 0 | D17: =Assumptions!$B$159*Assumptions!$B$160*D11+Assumptions!$C$159*Assumptions!$C$160*C11 -> 48704.96 | E17: =Assumptions!$B$159*Assumptions!$B$160*E11+Assumptions!$C$159*Assumptions!$C$160*D11+Assumptions!$D$159*Assumptions!$D$160*C11 -> 125978.67 | F17: =Assumptions!$B$159*Assumptions!$B$160*F11+Assumptions!$C$159*Assumptions!$C$160*E11+Assumptions!$D$159*Assumptions!$D$160*D11+Assumptions!$E$159*Assumptions!$E$160*C11 -> 228270.59 | G17: =Assumptions!$B$159*Assumptions!$B$160*G11+Assumptions!$C$159*Assumptions!$C$160*F11+Assumptions!$D$159*Assumptions!$D$160*E11+Assumptions!$E$159*Assumptions!$E$160*D11+Assumptions!$F$159*Assumptions!$F$160*C11 -> 346838.33
A18: Paid by developers (after guarantee credits) | C18: =C16+C17-C37 -> 20000 | D18: =D16+D17-D37 -> 174704.96 | E18: =E16+E17-E37 -> 344378.67 | F18: =F16+F17-F37 -> 533070.59 | G18: =G16+G17-G37 -> 738038.33
A19: Redemption fees | B19: Mall shops | C19: =Assumptions!$B$159*Assumptions!$B$160*C12 -> 2572.6295 | D19: =Assumptions!$B$159*Assumptions!$B$160*D12+Assumptions!$C$159*Assumptions!$C$160*C12 -> 11061.119 | E19: =Assumptions!$B$159*Assumptions!$B$160*E12+Assumptions!$C$159*Assumptions!$C$160*D12+Assumptions!$D$159*Assumptions!$D$160*C12 -> 26654.903 | F19: =Assumptions!$B$159*Assumptions!$B$160*F12+Assumptions!$C$159*Assumptions!$C$160*E12+Assumptions!$D$159*Assumptions!$D$160*D12+Assumptions!$E$159*Assumptions!$E$160*C12 -> 50213.955 | G19: =Assumptions!$B$159*Assumptions!$B$160*G12+Assumptions!$C$159*Assumptions!$C$160*F12+Assumptions!$D$159*Assumptions!$D$160*E12+Assumptions!$E$159*Assumptions!$E$160*D12+Assumptions!$F$159*Assumptions!$F$160*C12 -> 82010.201
A20: Total income (all income lines) | C20: =C18+C19+C38+C39+C40+C46 -> 39926.505 | D20: =D18+D19+D38+D39+D40+D46 -> 249652.35 | E20: =E18+E19+E38+E39+E40+E46 -> 499086.17 | F20: =F18+F19+F38+F39+F40+F46 -> 782063.57 | G20: =G18+G19+G38+G39+G40+G46 -> 1087212.6
A23: Guarantee credits and new income lines (one client, by client's year)
A24: Credit cap (share of that year's developer fees) | C24: =Assumptions!$B$67 -> 1 | D24: =Assumptions!$B$68 -> 0.25 | E24: =Assumptions!$B$68 -> 0.25 | F24: =Assumptions!$B$68 -> 0.25 | G24: =Assumptions!$B$68 -> 0.25
A25: Guarantee credit to an SDP-size client | B25: Credit to developer | C25: =MIN(Assumptions!$B$66*Benefits!C33,C24*(C8+C11)) -> 0 | D25: =MIN(Assumptions!$B$66*Benefits!D33,D24*(D8+D11)) -> 0 | E25: =MIN(Assumptions!$B$66*Benefits!E33,E24*(E8+E11)) -> 0 | F25: =MIN(Assumptions!$B$66*Benefits!F33,F24*(F8+F11)) -> 0 | G25: =MIN(Assumptions!$B$66*Benefits!G33,G24*(G8+G11)) -> 0
A26: Guarantee credit to a typical new client | B26: Credit to developer | C26: =MIN(Assumptions!$B$66*Assumptions!$C$160*Benefits!C33,C24*Assumptions!$C$160*(C8+C11)) -> 0 | D26: =MIN(Assumptions!$B$66*Assumptions!$C$160*Benefits!D33,D24*Assumptions!$C$160*(D8+D11)) -> 0 | E26: =MIN(Assumptions!$B$66*Assumptions!$C$160*Benefits!E33,E24*Assumptions!$C$160*(E8+E11)) -> 0 | F26: =MIN(Assumptions!$B$66*Assumptions!$C$160*Benefits!F33,F24*Assumptions!$C$160*(F8+F11)) -> 0 | G26: =MIN(Assumptions!$B$66*Assumptions!$C$160*Benefits!G33,G24*Assumptions!$C$160*(G8+G11)) -> 0
A27: Featured offers in rewards catalogue (SDP size) | B27: Mall shops | C27: =Assumptions!$B$80*Assumptions!$B$81*12*Pools_Scenarios!C9 -> 12000 | D27: =Assumptions!$B$80*Assumptions!$B$81*12*Pools_Scenarios!D9 -> 24000 | E27: =Assumptions!$B$80*Assumptions!$B$81*12*Pools_Scenarios!E9 -> 24000 | F27: =Assumptions!$B$80*Assumptions!$B$81*12*Pools_Scenarios!F9 -> 24000 | G27: =Assumptions!$B$80*Assumptions!$B$81*12*Pools_Scenarios!G9 -> 24000
A28: Energy dashboard subscriptions (SDP size) | B28: Upgraded shops | C28: =Pools_Scenarios!C28*Assumptions!$B$82*12 -> 4500 | D28: =Pools_Scenarios!D28*Assumptions!$B$82*12 -> 16500 | E28: =Pools_Scenarios!E28*Assumptions!$B$82*12 -> 27000 | F28: =Pools_Scenarios!F28*Assumptions!$B$82*12 -> 28500 | G28: =Pools_Scenarios!G28*Assumptions!$B$82*12 -> 22500
A29: REC registration and sales service (SDP size) | B29: From REC proceeds | C29: =Pools_Scenarios!C63*Assumptions!$B$78*Assumptions!$B$52*Assumptions!$B$79 -> 853.875 | D29: =Pools_Scenarios!D63*Assumptions!$B$78*Assumptions!$B$52*Assumptions!$B$79 -> 2561.625 | E29: =Pools_Scenarios!E63*Assumptions!$B$78*Assumptions!$B$52*Assumptions!$B$79 -> 4554 | F29: =Pools_Scenarios!F63*Assumptions!$B$78*Assumptions!$B$52*Assumptions!$B$79 -> 7115.625 | G29: =Pools_Scenarios!G63*Assumptions!$B$78*Assumptions!$B$52*Assumptions!$B$79 -> 9961.875
A31: All clients (by calendar year)
A32: Guarantee credits – clients signed in Y1 | B32: Credit to developers | C32: =Assumptions!$B$159*MIN(Assumptions!$B$66*Assumptions!$B$160*Benefits!C33,C24*Assumptions!$B$160*(C8+C11)) -> 0 | D32: =Assumptions!$B$159*MIN(Assumptions!$B$66*Assumptions!$B$160*Benefits!D33,D24*Assumptions!$B$160*(D8+D11)) -> 0 | E32: =Assumptions!$B$159*MIN(Assumptions!$B$66*Assumptions!$B$160*Benefits!E33,E24*Assumptions!$B$160*(E8+E11)) -> 0 | F32: =Assumptions!$B$159*MIN(Assumptions!$B$66*Assumptions!$B$160*Benefits!F33,F24*Assumptions!$B$160*(F8+F11)) -> 0 | G32: =Assumptions!$B$159*MIN(Assumptions!$B$66*Assumptions!$B$160*Benefits!G33,G24*Assumptions!$B$160*(G8+G11)) -> 0
A33: Guarantee credits – clients signed in Y2 | B33: Credit to developers | C33: =0 -> 0 | D33: =Assumptions!$C$159*MIN(Assumptions!$B$66*Assumptions!$C$160*Benefits!C33,C24*Assumptions!$C$160*(C8+C11)) -> 0 | E33: =Assumptions!$C$159*MIN(Assumptions!$B$66*Assumptions!$C$160*Benefits!D33,D24*Assumptions!$C$160*(D8+D11)) -> 0 | F33: =Assumptions!$C$159*MIN(Assumptions!$B$66*Assumptions!$C$160*Benefits!E33,E24*Assumptions!$C$160*(E8+E11)) -> 0 | G33: =Assumptions!$C$159*MIN(Assumptions!$B$66*Assumptions!$C$160*Benefits!F33,F24*Assumptions!$C$160*(F8+F11)) -> 0
A34: Guarantee credits – clients signed in Y3 | B34: Credit to developers | C34: =0 -> 0 | D34: =0 -> 0 | E34: =Assumptions!$D$159*MIN(Assumptions!$B$66*Assumptions!$D$160*Benefits!C33,C24*Assumptions!$D$160*(C8+C11)) -> 0 | F34: =Assumptions!$D$159*MIN(Assumptions!$B$66*Assumptions!$D$160*Benefits!D33,D24*Assumptions!$D$160*(D8+D11)) -> 0 | G34: =Assumptions!$D$159*MIN(Assumptions!$B$66*Assumptions!$D$160*Benefits!E33,E24*Assumptions!$D$160*(E8+E11)) -> 0
A35: Guarantee credits – clients signed in Y4 | B35: Credit to developers | C35: =0 -> 0 | D35: =0 -> 0 | E35: =0 -> 0 | F35: =Assumptions!$E$159*MIN(Assumptions!$B$66*Assumptions!$E$160*Benefits!C33,C24*Assumptions!$E$160*(C8+C11)) -> 0 | G35: =Assumptions!$E$159*MIN(Assumptions!$B$66*Assumptions!$E$160*Benefits!D33,D24*Assumptions!$E$160*(D8+D11)) -> 0
A36: Guarantee credits – clients signed in Y5 | B36: Credit to developers | C36: =0 -> 0 | D36: =0 -> 0 | E36: =0 -> 0 | F36: =0 -> 0 | G36: =Assumptions!$F$159*MIN(Assumptions!$B$66*Assumptions!$F$160*Benefits!C33,C24*Assumptions!$F$160*(C8+C11)) -> 0
A37: Guarantee credits, all clients | B37: Credit to developers | C37: =SUM(C32:C36) -> 0 | D37: =SUM(D32:D36) -> 0 | E37: =SUM(E32:E36) -> 0 | F37: =SUM(F32:F36) -> 0 | G37: =SUM(G32:G36) -> 0
A38: Featured offers, all clients | B38: Mall shops | C38: =Assumptions!$B$159*Assumptions!$B$160*C27 -> 12000 | D38: =Assumptions!$B$159*Assumptions!$B$160*D27+Assumptions!$C$159*Assumptions!$C$160*C27 -> 38400 | E38: =Assumptions!$B$159*Assumptions!$B$160*E27+Assumptions!$C$159*Assumptions!$C$160*D27+Assumptions!$D$159*Assumptions!$D$160*C27 -> 67200 | F38: =Assumptions!$B$159*Assumptions!$B$160*F27+Assumptions!$C$159*Assumptions!$C$160*E27+Assumptions!$D$159*Assumptions!$D$160*D27+Assumptions!$E$159*Assumptions!$E$160*C27 -> 96000 | G38: =Assumptions!$B$159*Assumptions!$B$160*G27+Assumptions!$C$159*Assumptions!$C$160*F27+Assumptions!$D$159*Assumptions!$D$160*E27+Assumptions!$E$159*Assumptions!$E$160*D27+Assumptions!$F$159*Assumptions!$F$160*C27 -> 124800
A39: Energy dashboards, all clients | B39: Upgraded shops | C39: =Assumptions!$B$159*Assumptions!$B$160*C28 -> 4500 | D39: =Assumptions!$B$159*Assumptions!$B$160*D28+Assumptions!$C$159*Assumptions!$C$160*C28 -> 21900 | E39: =Assumptions!$B$159*Assumptions!$B$160*E28+Assumptions!$C$159*Assumptions!$C$160*D28+Assumptions!$D$159*Assumptions!$D$160*C28 -> 52200 | F39: =Assumptions!$B$159*Assumptions!$B$160*F28+Assumptions!$C$159*Assumptions!$C$160*E28+Assumptions!$D$159*Assumptions!$D$160*D28+Assumptions!$E$159*Assumptions!$E$160*C28 -> 86100 | G39: =Assumptions!$B$159*Assumptions!$B$160*G28+Assumptions!$C$159*Assumptions!$C$160*F28+Assumptions!$D$159*Assumptions!$D$160*E28+Assumptions!$E$159*Assumptions!$E$160*D28+Assumptions!$F$159*Assumptions!$F$160*C28 -> 114300
A40: REC service fees, all clients | B40: From REC proceeds | C40: =Assumptions!$B$159*Assumptions!$B$160*C29 -> 853.875 | D40: =Assumptions!$B$159*Assumptions!$B$160*D29+Assumptions!$C$159*Assumptions!$C$160*C29 -> 3586.275 | E40: =Assumptions!$B$159*Assumptions!$B$160*E29+Assumptions!$C$159*Assumptions!$C$160*D29+Assumptions!$D$159*Assumptions!$D$160*C29 -> 8652.6 | F40: =Assumptions!$B$159*Assumptions!$B$160*F29+Assumptions!$C$159*Assumptions!$C$160*E29+Assumptions!$D$159*Assumptions!$D$160*D29+Assumptions!$E$159*Assumptions!$E$160*C29 -> 16679.025 | G40: =Assumptions!$B$159*Assumptions!$B$160*G29+Assumptions!$C$159*Assumptions!$C$160*F29+Assumptions!$D$159*Assumptions!$D$160*E29+Assumptions!$E$159*Assumptions!$E$160*D29+Assumptions!$F$159*Assumptions!$F$160*C29 -> 28064.025
A42: EV: our 10% share and our part of the usage top-up
A43: EV: our 10% share of residents' charging profit (SDP size; after residents recover) | B43: From EV pool | C43: =Pools_Scenarios!C72 -> 0 | D43: =Pools_Scenarios!D72 -> 0 | E43: =Pools_Scenarios!E72 -> 0 | F43: =Pools_Scenarios!F72 -> 0 | G43: =Pools_Scenarios!G72 -> 0
A44: EV: our 33% part of the usage top-up (cost, SDP size) | B44: We pay | C44: =-Pools_Scenarios!C73 -> 0 | D44: =-Pools_Scenarios!D73 -> 0 | E44: =-Pools_Scenarios!E73 -> 0 | F44: =-Pools_Scenarios!F73 -> 0 | G44: =-Pools_Scenarios!G73 -> 0
A45: EV: net (SDP size) | C45: =C43+C44 -> 0 | D45: =D43+D44 -> 0 | E45: =E43+E44 -> 0 | F45: =F43+F44 -> 0 | G45: =G43+G44 -> 0
A46: EV: net, all clients (can be negative) | C46: =Assumptions!$B$159*Assumptions!$B$160*C45 -> 0 | D46: =Assumptions!$B$159*Assumptions!$B$160*D45+Assumptions!$C$159*Assumptions!$C$160*C45 -> 0 | E46: =Assumptions!$B$159*Assumptions!$B$160*E45+Assumptions!$C$159*Assumptions!$C$160*D45+Assumptions!$D$159*Assumptions!$D$160*C45 -> 0 | F46: =Assumptions!$B$159*Assumptions!$B$160*F45+Assumptions!$C$159*Assumptions!$C$160*E45+Assumptions!$D$159*Assumptions!$D$160*D45+Assumptions!$E$159*Assumptions!$E$160*C45 -> 0 | G46: =Assumptions!$B$159*Assumptions!$B$160*G45+Assumptions!$C$159*Assumptions!$C$160*F45+Assumptions!$D$159*Assumptions!$D$160*E45+Assumptions!$E$159*Assumptions!$E$160*D45+Assumptions!$F$159*Assumptions!$F$160*C45 -> 0

Sheet Customer_ROI
A1: Customer ROI
A2: Developer's benefit minus what the developer pays us (after any guarantee credit). Shops' fees are not counted (shops pay them).
A4: Item | C4: Year 1 | D4: Year 2 | E4: Year 3 | F4: Year 4 | G4: Year 5
A5: Sime Darby Property (first client, full size)
A6: Total benefit | C6: =Benefits!C12 -> 146768.55 | D6: =Benefits!D12 -> 334156.78 | E6: =Benefits!E12 -> 411981.54 | F6: =Benefits!F12 -> 479239.97 | G6: =Benefits!G12 -> 520421.29
A7: Paid to us (after guarantee credit) | C7: =Pricing_Income!C13 -> 20000 | D7: =Pricing_Income!D13 -> 150704.96 | E7: =Pricing_Income!E13 -> 139532.72 | F7: =Pricing_Income!F13 -> 160785.38 | G7: =Pricing_Income!G13 -> 172810.66
A8: Net gain | C8: =C6-C7 -> 126768.55 | D8: =D6-D7 -> 183451.82 | E8: =E6-E7 -> 272448.82 | F8: =F6-F7 -> 318454.6 | G8: =G6-G7 -> 347610.63
A9: Cumulative net gain | C9: =C8 -> 126768.55 | D9: =C9+D8 -> 310220.37 | E9: =D9+E8 -> 582669.2 | F9: =E9+F8 -> 901123.79 | G9: =F9+G8 -> 1248734.4
A10: Net gain WITHOUT community-programme saving (cash only, after any credit) | C10: =Benefits!C10-C7 -> 22768.55 | D10: =Benefits!D10-D7 -> -24548.178 | E10: =Benefits!E10-E7 -> 64448.823 | F10: =Benefits!F10-F7 -> 110454.6 | G10: =Benefits!G10-G7 -> 139610.63
A11: Return on what SDP pays (benefit ÷ paid) | C11: =IF(C7<=0,"n/a",C6/C7) -> 7.3384275 | D11: =IF(D7<=0,"n/a",D6/D7) -> 2.2172912 | E11: =IF(E7<=0,"n/a",E6/E7) -> 2.9525802 | F11: =IF(F7<=0,"n/a",F6/F7) -> 2.9806192 | G11: =IF(G7<=0,"n/a",G6/G7) -> 3.0115115
A13: A typical new developer (smaller client)
A14: Total benefit | C14: =Benefits!C12*Assumptions!$C$160 -> 88061.13 | D14: =Benefits!D12*Assumptions!$C$160 -> 200494.07 | E14: =Benefits!E12*Assumptions!$C$160 -> 247188.93 | F14: =Benefits!F12*Assumptions!$C$160 -> 287543.98 | G14: =Benefits!G12*Assumptions!$C$160 -> 312252.78
A15: Paid to us (after guarantee credit) | C15: =(Pricing_Income!C8+Pricing_Income!C11)*Assumptions!$C$160-Pricing_Income!C26 -> 12000 | D15: =(Pricing_Income!D8+Pricing_Income!D11)*Assumptions!$C$160-Pricing_Income!D26 -> 90422.976 | E15: =(Pricing_Income!E8+Pricing_Income!E11)*Assumptions!$C$160-Pricing_Income!E26 -> 83719.631 | F15: =(Pricing_Income!F8+Pricing_Income!F11)*Assumptions!$C$160-Pricing_Income!F26 -> 96471.225 | G15: =(Pricing_Income!G8+Pricing_Income!G11)*Assumptions!$C$160-Pricing_Income!G26 -> 103686.4
A16: Net gain | C16: =C14-C15 -> 76061.13 | D16: =D14-D15 -> 110071.09 | E16: =E14-E15 -> 163469.29 | F16: =F14-F15 -> 191072.76 | G16: =G14-G15 -> 208566.38
A17: Net gain WITHOUT community-programme saving (cash only, after any credit) | C17: =Benefits!C10*Assumptions!$C$160-C15 -> 13661.13 | D17: =Benefits!D10*Assumptions!$C$160-D15 -> -14728.907 | E17: =Benefits!E10*Assumptions!$C$160-E15 -> 38669.294 | F17: =Benefits!F10*Assumptions!$C$160-F15 -> 66272.757 | G17: =Benefits!G10*Assumptions!$C$160-G15 -> 83766.38
A19: Checks
A20: SDP gains in Year 1? | C20: =IF(C8>0,"YES","NO") -> YES
A21: New developer gains in its Year 1? | C21: =IF(C16>0,"YES","NO") -> YES
A23: Contract view and extra checks
A24: Guarantee credit SDP receives | C24: =Pricing_Income!C25 -> 0 | D24: =Pricing_Income!D25 -> 0 | E24: =Pricing_Income!E25 -> 0 | F24: =Pricing_Income!F25 -> 0 | G24: =Pricing_Income!G25 -> 0
A25: Net gain if community saving only reaches the guaranteed level | C25: =Benefits!C10+MIN(Benefits!C11,Benefits!C32)-C7 -> 74768.55 | D25: =Benefits!D10+MIN(Benefits!D11,Benefits!D32)-D7 -> 79451.822 | E25: =Benefits!E10+MIN(Benefits!E11,Benefits!E32)-E7 -> 168448.82 | F25: =Benefits!F10+MIN(Benefits!F11,Benefits!F32)-F7 -> 214454.6 | G25: =Benefits!G10+MIN(Benefits!G11,Benefits!G32)-G7 -> 243610.63
A26: Guarantee credit a new client receives | C26: =Pricing_Income!C26 -> 0 | D26: =Pricing_Income!D26 -> 0 | E26: =Pricing_Income!E26 -> 0 | F26: =Pricing_Income!F26 -> 0 | G26: =Pricing_Income!G26 -> 0
A27: SDP cash-only net gain > 0 in Year 1? | C27: =IF(C10>0,"YES","NO") -> YES
A28: New developer cash-only net gain > 0 in its Year 1? | C28: =IF(C17>0,"YES","NO") -> YES
A29: info: SDP net gain if the RMO fee were paid upfront in cash (not spread) | C29: =C8-Benefits!C34-Pools_Scenarios!C45*Assumptions!$B$148*(1+Assumptions!$B$149)*Assumptions!$B$150 -> 33383.65 | D29: =D8-Benefits!D34-Pools_Scenarios!D45*Assumptions!$B$148*(1+Assumptions!$B$149)*Assumptions!$B$150 -> 104331.02 | E29: =E8-Benefits!E34-Pools_Scenarios!E45*Assumptions!$B$148*(1+Assumptions!$B$149)*Assumptions!$B$150 -> 196276.42 | F29: =F8-Benefits!F34-Pools_Scenarios!F45*Assumptions!$B$148*(1+Assumptions!$B$149)*Assumptions!$B$150 -> 240759.4 | G29: =G8-Benefits!G34-Pools_Scenarios!G45*Assumptions!$B$148*(1+Assumptions!$B$149)*Assumptions!$B$150 -> 302607.03

Sheet Investor_ROI
A1: Investor_ROI – what one resident gets in Year 1, per RM1,000 invested
A2: Normal uses Assumptions; Conservative uses the Pools_Scenarios sheet. Money is held by a licensed platform, never by us. Payouts are monthly.
A4: Item | B4: Normal | C4: Conservative | D4: Note
A5: Pool 1 – Rooftop solar (low risk): fixed payout backed by tenant power payments, not roof leasing
A6: Contract payout rate | B6: =Assumptions!$B$19 -> 0.05 | C6: =Assumptions!$B$19 -> 0.05
A7: Minimum payout rate (floor, backed by JV saving) | B7: =Assumptions!$B$71 -> 0.045 | C7: =Assumptions!$B$71 -> 0.045
A8: Rate paid in Year 1 | B8: =MAX(B6,B7) -> 0.05 | C8: =MAX(C6,C7) -> 0.05
A9: Average share of money still invested in first 12 months | B9: =(1+((1+Assumptions!$B$19)^Assumptions!$B$20-(1+Assumptions!$B$19))/((1+Assumptions!$B$19)^Assumptions!$B$20-1))/2 -> 0.9095126 | C9: =(1+((1+Assumptions!$B$19)^Assumptions!$B$20-(1+Assumptions!$B$19))/((1+Assumptions!$B$19)^Assumptions!$B$20-1))/2 -> 0.9095126 | D9: Money is paid back monthly, so less is invested by year end.
A10: Year-1 profit per RM1,000 | B10: =1000*B8*B9 -> 45.47563 | C10: =1000*C8*C9 -> 45.47563
A11: Year-1 return | B11: =B10/1000 -> 0.04547563 | C11: =C10/1000 -> 0.04547563
A12: Solar cover: tenant power payments ÷ payouts to residents | B12: =(Assumptions!$B$17*1000*Assumptions!$B$89*(1-Assumptions!$B$90)*(1-Assumptions!$B$93)-Assumptions!$B$16*1000*(Assumptions!$B$91+Assumptions!$B$92))/(Assumptions!$B$16*1000*Assumptions!$B$18*PMT(Assumptions!$B$19,Assumptions!$B$20,-1)) -> 1.63325 | C12: =(Assumptions!$B$17*1000*Assumptions!$B$89*(1-Assumptions!$B$90)*(1-Assumptions!$B$93)-Assumptions!$B$16*1000*(Assumptions!$B$91+Assumptions!$B$92))/(Assumptions!$B$16*1000*Pools_Scenarios!$C$101*PMT(Assumptions!$B$19,Assumptions!$B$20,-1)) -> 2.449875 | D12: Above 1.3x is comfortable. Per MW, first year.
A14: Pool 2 – Shop energy upgrades (medium risk)
A15: Contract payout rate | B15: =Assumptions!$B$26 -> 0.065 | C15: =Assumptions!$B$26 -> 0.065
A16: Average share of money still invested in first 12 months | B16: =(1+((1+Assumptions!$B$26)^Assumptions!$B$27-(1+Assumptions!$B$26))/((1+Assumptions!$B$26)^Assumptions!$B$27-1))/2 -> 0.84371215 | C16: =(1+((1+Assumptions!$B$26)^Assumptions!$B$27-(1+Assumptions!$B$26))/((1+Assumptions!$B$26)^Assumptions!$B$27-1))/2 -> 0.84371215
A17: Year-1 profit per RM1,000 before losses | B17: =1000*B15*B16 -> 54.84129 | C17: =1000*C15*C16 -> 54.84129
A18: Repayment counted per shop-month (higher of actual or guaranteed saving × 80%) | B18: =MAX(Assumptions!$B$24,Assumptions!$B$72)*Assumptions!$B$25 -> 800 | C18: =MAX(Pools_Scenarios!$C$85,Assumptions!$B$72)*Assumptions!$B$25 -> 640 | D18: Installer guarantees a minimum saving.
A19: Payout due per shop-year | B19: =PMT(Assumptions!$B$26/12,Assumptions!$B$27*12,-Assumptions!$B$23)*12 -> 7355.7607 | C19: =PMT(Assumptions!$B$26/12,Assumptions!$B$27*12,-Assumptions!$B$23)*12 -> 7355.7607
A20: Safety margin per shop-year | B20: =B18*12-B19 -> 2244.2393 | C20: =C18*12-C19 -> 324.23931
A21: Bad-debt reserve per shop-year | B21: =MAX(0,B20)*(1-Assumptions!$B$28) -> 1122.1197 | C21: =MAX(0,C20)*(1-Assumptions!$B$28) -> 162.11965
A22: Expected default loss per shop-year | B22: =Assumptions!$B$23*Assumptions!$B$73*Assumptions!$B$74 -> 200 | C22: =Assumptions!$B$23*Pools_Scenarios!$C$91*Assumptions!$B$74 -> 1000
A23: Uncovered loss per RM1,000 | B23: =(MAX(0,B22-B21)+MAX(0,-B20))/Assumptions!$B$23*1000 -> 0 | C23: =(MAX(0,C22-C21)+MAX(0,-C20))/Assumptions!$B$23*1000 -> 41.894017
A24: Year-1 profit per RM1,000 after expected losses | B24: =B17-B23 -> 54.84129 | C24: =C17-C23 -> 12.947272
A25: Year-1 return | B25: =B24/1000 -> 0.05484129 | C25: =C24/1000 -> 0.012947272
A27: Pool 3 – EV charging (high risk, not capital-guaranteed; CPO partner runs the chargers)
A28: kWh sold per charger per day (after downtime) | B28: =EV_Pilot!B9 -> 60 | C28: =EV_Pilot!C9 -> 27
A29: Usage top-up per charger per year (after cap) | B29: =EV_Pilot!B65 -> 0 | C29: =EV_Pilot!C65 -> 3000 | D29: Developer 33%, platform 33%, CPO 34%; cap RM3,000.
A30: EV payback period | B30: =Assumptions!$B$137 -> 7 | C30: =Assumptions!$B$137 -> 7 | D30: Residents are repaid over 7 years.
A31: Cash per RM1,000 a year WITHOUT top-up (while recovering money) | B31: =EV_Pilot!B56/EV_Pilot!B53*1000 -> 179.5948 | C31: =EV_Pilot!C56/EV_Pilot!C53*1000 -> 0 | D31: Shown for transparency.
A32: Cash per RM1,000 a year WITH top-up (while recovering money) | B32: =EV_Pilot!B70 -> 179.5948 | C32: =EV_Pilot!C70 -> 85.714286
A33: Year-1 profit per RM1,000 (cash − money paid back) | B33: =B32-1000/B30 -> 36.737657 | C33: =C32-1000/C30 -> -57.142857
A34: Year-1 return | B34: =B33/1000 -> 0.036737657 | C34: =C33/1000 -> -0.057142857
A35: Money back over the payback period (share of RM invested) | B35: =EV_Pilot!B86 -> 1.2870961 | C35: =EV_Pilot!C86 -> 0.6
A36: Loss over the payback period (if any) | B36: =MAX(0,1-B35) -> 0 | C36: =MAX(0,1-C35) -> 0.4
A37: Money back without the protection (B: no deferral; C: no top-up) | B37: =EV_Pilot!L86 -> 1.0476363 | C37: =EV_Pilot!N86 -> 0 | D37: Shows what the protections are worth.
A39: Checks
A40: Solar Year-1 return > 0? | B40: =IF(B11>0,"YES","NO") -> YES | C40: =IF(C11>0,"YES","NO") -> YES
A41: Upgrades Year-1 return > 0? | B41: =IF(B25>0,"YES","NO") -> YES | C41: =IF(C25>0,"YES","NO") -> YES
A42: EV loss over the payback period no worse than 50%? | B42: =IF(B36<=0.5,"YES","NO") -> YES | C42: =IF(C36<=0.5,"YES","NO") -> YES
A44: 5-year view per example investment (used on Summary)
A45: Example investment | B45: =Assumptions!$B$95 -> 1000 | C45: =Assumptions!$B$95 -> 1000
A46: Solar: total received over tenure | B46: =PMT(Assumptions!$B$19/12,Assumptions!$B$20*12,-Assumptions!$B$95)*Assumptions!$B$20*12 -> 1132.274 | C46: =PMT(Assumptions!$B$19/12,Assumptions!$B$20*12,-Assumptions!$B$95)*Assumptions!$B$20*12 -> 1132.274
A47: Solar: 5-year profit | B47: =B46-B45 -> 132.27402 | C47: =C46-C45 -> 132.27402
A48: Upgrades: share still owed after year 1 | B48: =((1+Assumptions!$B$26)^Assumptions!$B$27-(1+Assumptions!$B$26))/((1+Assumptions!$B$26)^Assumptions!$B$27-1) -> 0.6874243 | C48: =((1+Assumptions!$B$26)^Assumptions!$B$27-(1+Assumptions!$B$26))/((1+Assumptions!$B$26)^Assumptions!$B$27-1) -> 0.6874243
A49: Upgrades: share still owed after year 2 | B49: =MAX(0,((1+Assumptions!$B$26)^Assumptions!$B$27-(1+Assumptions!$B$26)^2)/((1+Assumptions!$B$26)^Assumptions!$B$27-1)) -> 0.35453118 | C49: =MAX(0,((1+Assumptions!$B$26)^Assumptions!$B$27-(1+Assumptions!$B$26)^2)/((1+Assumptions!$B$26)^Assumptions!$B$27-1)) -> 0.35453118
A50: Upgrades: total received over tenure | B50: =PMT(Assumptions!$B$26/12,Assumptions!$B$27*12,-Assumptions!$B$95)*Assumptions!$B$27*12 -> 1103.3641 | C50: =PMT(Assumptions!$B$26/12,Assumptions!$B$27*12,-Assumptions!$B$95)*Assumptions!$B$27*12 -> 1103.3641
A51: Upgrades: expected uncovered loss over tenure | B51: =MAX(0,B45*Assumptions!$B$73*Assumptions!$B$74*(0.5+B48+B49)-B45/Assumptions!$B$23*B21*Assumptions!$B$27)+MAX(0,-B20)/Assumptions!$B$23*B45*Assumptions!$B$27 -> 0 | C51: =MAX(0,C45*Pools_Scenarios!$C$91*Assumptions!$B$74*(0.5+C48+C49)-C45/Assumptions!$B$23*C21*Assumptions!$B$27)+MAX(0,-C20)/Assumptions!$B$23*C45*Assumptions!$B$27 -> 52.779825 | D51: Defaults on money still owed, after the bad-debt reserve.
A52: Upgrades: 5-year profit after expected losses | B52: =B50-B45-B51 -> 103.3641 | C52: =C50-C45-C51 -> 50.584278
A53: Upgrades: rate after expected losses | B53: =RATE(Assumptions!$B$27*12,(B50-B51)/(Assumptions!$B$27*12),-B45)*12 -> 0.065 | C53: =RATE(Assumptions!$B$27*12,(C50-C51)/(Assumptions!$B$27*12),-C45)*12 -> 0.032304876
A54: EV: cash received in Year 1 (with top-up) | B54: =B32*B45/1000 -> 179.5948 | C54: =C32*C45/1000 -> 85.714286
A55: EV: total received over the payback period (7 years) | B55: =EV_Pilot!B85*B45/1000 -> 1287.0961 | C55: =EV_Pilot!C85*C45/1000 -> 600
A56: EV: profit / (loss) over the payback period | B56: =B55-B45 -> 287.09607 | C56: =C55-C45 -> -400
A57: EV: expected rate (IRR, from EV_Pilot) | B57: =EV_Pilot!B88 -> 0.066187268 | C57: =EV_Pilot!C88 -> -0.11351477 | D57: Variable, not guaranteed.

Sheet Spendings
A1: 3) Spendings – our own cost to build and run the platform (calendar year)
A2: Lean team; cloud cost grows with each client. part of Year 1 pay taken as equity.
A4: Cost line | B4: How it is worked out | C4: Year 1 | D4: Year 2 | E4: Year 3 | F4: Year 4 | G4: Year 5
A5: Clients on the platform | B5: From Benefits | C5: =Benefits!C20 -> 1 | D5: =Benefits!D20 -> 3 | E5: =Benefits!E20 -> 5 | F5: =Benefits!F20 -> 7 | G5: =Benefits!G20 -> 9
A6: Founders' pay (cash) | B6: People × salary × 12 × (1 + on-cost); Year 1 × cash share | C6: =Assumptions!$B$44*Assumptions!$B$45*12*(1+Assumptions!$B$46)*Assumptions!$B$84 -> 55176 | D6: =Assumptions!$B$44*Assumptions!$B$45*12*(1+Assumptions!$B$46) -> 110352 | E6: =Assumptions!$B$44*Assumptions!$B$45*12*(1+Assumptions!$B$46) -> 110352 | F6: =Assumptions!$B$44*Assumptions!$B$45*12*(1+Assumptions!$B$46) -> 110352 | G6: =Assumptions!$B$44*Assumptions!$B$45*12*(1+Assumptions!$B$46) -> 110352
A7: Contract developer (build Year 1, cash part) | B7: Months × monthly rate × cash share | C7: =Assumptions!$B$47*Assumptions!$B$48*Assumptions!$B$85 -> 29400 | D7: =0 -> 0 | E7: =0 -> 0 | F7: =0 -> 0 | G7: =0 -> 0
A8: Extra developers | B8: People × pay × 12 × (1 + on-cost) | C8: =Assumptions!$B$161*Assumptions!$B$48*12*(1+Assumptions!$B$46) -> 0 | D8: =Assumptions!$C$161*Assumptions!$B$48*12*(1+Assumptions!$B$46) -> 0 | E8: =Assumptions!$D$161*Assumptions!$B$48*12*(1+Assumptions!$B$46) -> 96558 | F8: =Assumptions!$E$161*Assumptions!$B$48*12*(1+Assumptions!$B$46) -> 96558 | G8: =Assumptions!$F$161*Assumptions!$B$48*12*(1+Assumptions!$B$46) -> 193116
A9: Part-time support and operations | B9: From Assumptions (yearly table) | C9: =Assumptions!$B$162 -> 0 | D9: =Assumptions!$C$162 -> 18000 | E9: =Assumptions!$D$162 -> 36000 | F9: =Assumptions!$E$162 -> 36000 | G9: =Assumptions!$F$162 -> 48000
A10: Cloud (Supabase + Vercel) | B10: (Clients × Supabase + seats × Vercel) × 12 × USD rate | C10: =(C5*Assumptions!$B$49+Assumptions!$B$51*Assumptions!$B$50)*12*Assumptions!$B$52 -> 3432 | D10: =(D5*Assumptions!$B$49+Assumptions!$B$51*Assumptions!$B$50)*12*Assumptions!$B$52 -> 6072 | E10: =(E5*Assumptions!$B$49+Assumptions!$B$51*Assumptions!$B$50)*12*Assumptions!$B$52 -> 8712 | F10: =(F5*Assumptions!$B$49+Assumptions!$B$51*Assumptions!$B$50)*12*Assumptions!$B$52 -> 11352 | G10: =(G5*Assumptions!$B$49+Assumptions!$B$51*Assumptions!$B$50)*12*Assumptions!$B$52 -> 13992
A11: Security testing | B11: Year 1 full test, then yearly retest | C11: =Assumptions!$B$53 -> 15000 | D11: =Assumptions!$B$54 -> 8000 | E11: =Assumptions!$B$54 -> 8000 | F11: =Assumptions!$B$54 -> 8000 | G11: =Assumptions!$B$54 -> 8000
A12: Legal, PDPA and partner agreements | B12: Year 1 set-up, then yearly | C12: =Assumptions!$B$55 -> 15000 | D12: =Assumptions!$B$56 -> 5000 | E12: =Assumptions!$B$56 -> 5000 | F12: =Assumptions!$B$56 -> 5000 | G12: =Assumptions!$B$56 -> 5000
A13: Sales and onboarding | B13: New clients × cost per client (standardised from Year 2) | C13: =Assumptions!$B$159*Assumptions!$B$57 -> 8000 | D13: =Assumptions!$C$159*Assumptions!$B$86 -> 10000 | E13: =Assumptions!$D$159*Assumptions!$B$86 -> 10000 | F13: =Assumptions!$E$159*Assumptions!$B$86 -> 10000 | G13: =Assumptions!$F$159*Assumptions!$B$86 -> 10000
A14: Total spend | C14: =SUM(C6:C13) -> 126008 | D14: =SUM(D6:D13) -> 157424 | E14: =SUM(E6:E13) -> 274622 | F14: =SUM(F6:F13) -> 277262 | G14: =SUM(G6:G13) -> 388460
A16: Non-cash pay taken as equity (not in total spend)
A17: Founders' pay taken as equity | B17: Year 1 salary × (1 − cash share) | C17: =Assumptions!$B$44*Assumptions!$B$45*12*(1-Assumptions!$B$84) -> 48000 | D17: =0 -> 0 | E17: =0 -> 0 | F17: =0 -> 0 | G17: =0 -> 0
A18: Contract pay taken as equity | B18: Contract pay × (1 − cash share) | C18: =Assumptions!$B$47*Assumptions!$B$48*(1-Assumptions!$B$85) -> 12600 | D18: =0 -> 0 | E18: =0 -> 0 | F18: =0 -> 0 | G18: =0 -> 0

Sheet ROI
A1: ROI – year by year and 5-year summary (calendar years, all clients)
A4: Item | C4: Y1 | D4: Y2 | E4: Y3 | F4: Y4 | G4: Y5 | H4: 5-year total
A5: Number of customer (How Many?) | C5: =Benefits!C20 -> 1 | D5: =Benefits!D20 -> 3 | E5: =Benefits!E20 -> 5 | F5: =Benefits!F20 -> 7 | G5: =Benefits!G20 -> 9
A6: Total benefits for customer | C6: =Benefits!C23 -> 146768.55 | D6: =Benefits!D23 -> 510279.04 | E6: =Benefits!E23 -> 989091.94 | F6: =Benefits!F23 -> 1550728.2 | G6: =Benefits!G23 -> 2166997.5 | H6: =SUM(C6:G6) -> 5363865.3
A7: Paid by customer to us (after credits) | C7: =Pricing_Income!C18 -> 20000 | D7: =Pricing_Income!D18 -> 174704.96 | E7: =Pricing_Income!E18 -> 344378.67 | F7: =Pricing_Income!F18 -> 533070.59 | G7: =Pricing_Income!G18 -> 738038.33 | H7: =SUM(C7:G7) -> 1810192.5
A8: Vendor total income (incl. shop and REC fees) | C8: =Pricing_Income!C20 -> 39926.505 | D8: =Pricing_Income!D20 -> 249652.35 | E8: =Pricing_Income!E20 -> 499086.17 | F8: =Pricing_Income!F20 -> 782063.57 | G8: =Pricing_Income!G20 -> 1087212.6 | H8: =SUM(C8:G8) -> 2657941.2
A9: Vendor total spend | C9: =Spendings!C14 -> 126008 | D9: =Spendings!D14 -> 157424 | E9: =Spendings!E14 -> 274622 | F9: =Spendings!F14 -> 277262 | G9: =Spendings!G14 -> 388460 | H9: =SUM(C9:G9) -> 1223776
A10: Vendor net profit / (loss) | C10: =C8-C9 -> -86081.495 | D10: =D8-D9 -> 92228.355 | E10: =E8-E9 -> 224464.17 | F10: =F8-F9 -> 504801.57 | G10: =G8-G9 -> 698752.55 | H10: =SUM(C10:G10) -> 1434165.2
A11: Vendor cumulative net | C11: =C10 -> -86081.495 | D11: =C11+D10 -> 6146.8591 | E11: =D11+E10 -> 230611.03 | F11: =E11+F10 -> 735412.6 | G11: =F11+G10 -> 1434165.2
A12: Vendor profit margin | C12: =IF(C8<=0,"n/a",C10/C8) -> -2.1559988 | D12: =IF(D8<=0,"n/a",D10/D8) -> 0.36942714 | E12: =IF(E8<=0,"n/a",E10/E8) -> 0.44975033 | F12: =IF(F8<=0,"n/a",F10/F8) -> 0.64547383 | G12: =IF(G8<=0,"n/a",G10/G8) -> 0.64270096
A13: Customer's net gain (benefit − paid) | C13: =C6-C7 -> 126768.55 | D13: =D6-D7 -> 335574.08 | E13: =E6-E7 -> 644713.27 | F13: =F6-F7 -> 1017657.6 | G13: =G6-G7 -> 1428959.2 | H13: =SUM(C13:G13) -> 3553672.7
A15: 5-year summary
A16: Vendor ROI = (income − spend) ÷ spend | C16: =(H8-H9)/H9 -> 1.171918 | D16: Vendor return on every RM spent over 5 years.
A17: Customer ROI = (benefit − paid) ÷ paid | C17: =(H6-H7)/H7 -> 1.9631463 | D17: What customers get back for every RM paid to the vendor.
A18: Vendor first profitable year | C18: =IF(C10>0,"Y1",IF(D10>0,"Y2",IF(E10>0,"Y3",IF(F10>0,"Y4",IF(G10>0,"Y5","Not in 5 yrs"))))) -> Y2
A19: Customer first profitable year | C19: =IF(C13>0,"Y1",IF(D13>0,"Y2",IF(E13>0,"Y3",IF(F13>0,"Y4",IF(G13>0,"Y5","Not in 5 yrs"))))) -> Y1
A20: Target: Vendor lose money in Y1? | C20: =IF(C10<0,"YES","NO") -> YES
A21: Target: Vendor make money from Y2? | C21: =IF(AND(D10>0,E10>0,F10>0,G10>0),"YES","NO") -> YES
A22: Target: Customer (SDP) gains in its Y1? | C22: =Customer_ROI!C20 -> YES
A24: Net present value (NPV) Vendor cash flows
A25: Year | C25: Net cash flow | D25: Discount factor | E25: Present value
A26: Y1 | C26: =C10 -> -86081.495 | D26: =1/(1+Assumptions!$B$58)^1 -> 0.86956522 | E26: =C26*D26 -> -74853.474
A27: Y2 | C27: =D10 -> 92228.355 | D27: =1/(1+Assumptions!$B$58)^2 -> 0.75614367 | E27: =C27*D27 -> 69737.886
A28: Y3 | C28: =E10 -> 224464.17 | D28: =1/(1+Assumptions!$B$58)^3 -> 0.65751623 | E28: =C28*D28 -> 147588.84
A29: Y4 | C29: =F10 -> 504801.57 | D29: =1/(1+Assumptions!$B$58)^4 -> 0.57175325 | E29: =C29*D29 -> 288621.94
A30: Y5 | C30: =G10 -> 698752.55 | D30: =1/(1+Assumptions!$B$58)^5 -> 0.49717674 | E30: =C30*D30 -> 347403.51
A31: NPV | E31: =SUM(E26:E30) -> 778498.7
A33: NPV brings each year's profit or loss back to today's value using the discount rate on Assumptions (Pools_Scenarios for the conservative copy).
A35: Cash plan (grant covers the Year 1 loss)
A36: Grant / pre-seed funding received | C36: =Assumptions!$B$87 -> 120000 | D36: =0 -> 0 | E36: =0 -> 0 | F36: =0 -> 0 | G36: =0 -> 0 | H36: =SUM(C36:G36) -> 120000
A37: Cash balance at year end | C37: =C10+C36 -> 33918.505 | D37: =C37+D10+D36 -> 126146.86 | E37: =D37+E10+E36 -> 350611.03 | F37: =E37+F10+F36 -> 855412.6 | G37: =F37+G10+G36 -> 1554165.2
A38: Cash stays positive in all 5 years? | C38: =IF(MIN(C37:G37)>=0,"YES","NO") -> YES
A39: Developers' NPV of net gain (all clients) | C39: =NPV(Assumptions!$B$58,C13:G13) -> 2080179.5 | D39: Same discount rate as the vendor NPV.

Sheet Dashboard
A1: Township Green Loop – 5-Year Financial Projection
A2: Charts link to ROI, C_ROI and Customer_ROI and update when inputs change.
A3: Year | B3: Vendor income | C3: Vendor spend | D3: Vendor cumulative net | E3: SDP benefit | F3: SDP pays us | G3: Vendor Net (normal) | H3: Vendor Net (conservative)
A4: Y1 | B4: =ROI!C8 -> 39926.505 | C4: =ROI!C9 -> 126008 | D4: =ROI!C11 -> -86081.495 | E4: =Customer_ROI!C6 -> 146768.55 | F4: =Customer_ROI!C7 -> 20000 | G4: =ROI!C10 -> -86081.495 | H4: =C_ROI!C10 -> -107596.28
A5: Y2 | B5: =ROI!D8 -> 249652.35 | C5: =ROI!D9 -> 157424 | D5: =ROI!D11 -> 6146.8591 | E5: =Customer_ROI!D6 -> 334156.78 | F5: =Customer_ROI!D7 -> 150704.96 | G5: =ROI!D10 -> 92228.355 | H5: =C_ROI!D10 -> 5033.9555
A6: Y3 | B6: =ROI!E8 -> 499086.17 | C6: =ROI!E9 -> 274622 | D6: =ROI!E11 -> 230611.03 | E6: =Customer_ROI!E6 -> 411981.54 | F6: =Customer_ROI!E7 -> 139532.72 | G6: =ROI!E10 -> 224464.17 | H6: =C_ROI!E10 -> 47108.152
A7: Y4 | B7: =ROI!F8 -> 782063.57 | C7: =ROI!F9 -> 277262 | D7: =ROI!F11 -> 735412.6 | E7: =Customer_ROI!F6 -> 479239.97 | F7: =Customer_ROI!F7 -> 160785.38 | G7: =ROI!F10 -> 504801.57 | H7: =C_ROI!F10 -> 83647.022
A8: Y5 | B8: =ROI!G8 -> 1087212.6 | C8: =ROI!G9 -> 388460 | D8: =ROI!G11 -> 1434165.2 | E8: =Customer_ROI!G6 -> 520421.29 | F8: =Customer_ROI!G7 -> 172810.66 | G8: =ROI!G10 -> 698752.55 | H8: =C_ROI!G10 -> 102979.07

Sheet References
A1: References
A2: Numbers in [Rn] across the workbook point here. Official sources (government, regulator, company) wherever one exists. Checked October 2026.
A4: Ref | B4: What it supports | C4: Link
A5: R1 | B5: Sime Darby Property press release, 11 Jul 2024 – joint venture with TNB's GSPARX: 14 assets, up to 4.5 MW initially, 20 MW in 5 years, 50 MW in 15 years | C5: https://www.simedarbyproperty.com/sites/default/files/2024-07/20240711-For%20Immediate%20Release-%20Sime%20Darby%20Property%20and%20TNB%20Launch%20Joint%20Venture%20to%20Empower%20Sustainability%20Agenda%20in%20Malaysia.pdf
A6: R2 | B6: Sime Darby Property press release, 23 Jan 2025 – KLGCC Mall, the company's third wholly-owned mall after KL East Mall and Elmina Lakeside Mall; 80+ tenants | C6: https://simedarbyproperty.com/sites/default/files/2025-01/20250123%20-%20For%20Immediate%20Release%20-%20Sime%20Darby%20Property%20Welcomes%20Anchor%20Tenants%20to%20New%20KLGCC%20Mall.pdf
A7: R3 | B7: Sime Darby Property – Integrated Report 2024 key highlights (70,000+ beneficiaries; RM20.8 million total economic spend on community programmes and spaces) | C7: https://simedarbyproperty.com/annualreport2024/download/sdp-ir2024-key-highlights.pdf
A8: R4 | B8: Sime Darby Property press release, 28 Apr 2025 – first LEGA under CREAM: leases residential rooftops in City of Elmina with TNB's GSPARX | C8: https://simedarbyproperty.com/sites/default/files/2025-04/20250428%20-%20For%20Immediate%20Release%20-%20Sime%20Darby%20Property%20Leads%20Nation%E2%80%99s%20First%20Community%20Solar%20Rollout%20Under%20NETR%20with%20TNB.pdf
A9: R5 | B9: Sime Darby Property press release, 12 Aug 2026 – Kanopi Residences topping-off; company operates 28 townships and developments | C9: https://www.simedarbyproperty.com/node/1811
A10: R6 | B10: Energy Commission (Suruhanjaya Tenaga) – TNB tariff schedule, 1 Jul 2025 to 31 Dec 2027: LV non-domestic energy 27.03, capacity 8.83, network 14.82 sen/kWh; MV general energy 29.83 sen/kWh, capacity RM29.43/kW, network RM59.84/kW | C10: https://myenergystats.st.gov.my/documents/d/guest/tariff-tnb-pdf-1
A11: R7 | B11: Energy Commission – Grid Emission Factor in Malaysia 2022–2024 (provisional) | C11: https://myenergystats.st.gov.my/documents/d/guest/grid-emission-factor-gef-in-malaysia-2022-2024-provisional-
A12: R8 | B12: Energy Commission media release – CREAM community access charge cut from 15 to 9 sen/kWh | C12: https://www.st.gov.my/contents/2025/CREAM/siaran_mediaeng.pdf
A13: R9 | B13: Energy Commission – Guidelines on Electric Vehicle Charging System (EVCS), 17 Mar 2025 (download listing) | C13: https://www.st.gov.my/eng/web/download/listing/150
A14: R10 | B14: Association of Banks in Malaysia – fixed deposit board rates as at 15 Aug 2026 | C14: https://www.abm.org.my/wp-content/uploads/2026/08/website-FD-Rates-as-at-15-Aug-2026.pdf
A15: R11 | B15: RTM (Radio Televisyen Malaysia) – KWSP declares 6.15% dividend for conventional and Shariah savings for 2025 | C15: https://berita.rtm.gov.my/niaga/senarai-berita-niaga/senarai-artikel/kwsp-umum-dividen-6-15-untuk-simpanan-konvensional-dan-shariah/
... A32: R28 | B32: National Energy Transition Roadmap (NETR): renewable energy share target of 70% by 2050 — market tailwinds | C32: https://www.mida.gov.my/national-energy-transition-roadmap-netr-charting-a-path-to-a-sustainable-energy-landscape/

Sheet Conservative_Test
A1: Conservative_Test – do the three targets hold under stress?
A2: Normal = original sheets. Conservative = C_ sheets, driven by the Pools_Scenarios sheet. Every number is a live formula.
A4: Stressed input | B4: Normal | C4: Conservative
A5: Community saving actually achieved | B5: =Pools_Scenarios!B83 -> 1 | C5: =Pools_Scenarios!C83 -> 0
A6: EV energy sold per charger per day (kWh) = sessions × kWh per session | B6: =Pools_Scenarios!B84 -> 60 | C6: =Pools_Scenarios!C84 -> 30
A7: Bill saving per shop (RM/month) | B7: =Pools_Scenarios!B85 -> 1000 | C7: =Pools_Scenarios!C85 -> 500
A8: New developer clients signed in Year 2 | B8: =Pools_Scenarios!B86 -> 2 | C8: =Pools_Scenarios!C86 -> 1
A9: Developer's share of solar funding saving | B9: =Pools_Scenarios!B87 -> 0.5 | C9: =Pools_Scenarios!C87 -> 0.3
A10: Discount rate for NPV | B10: =Pools_Scenarios!B88 -> 0.15 | C10: =Pools_Scenarios!C88 -> 0.2
A11: Competitor price drop (all charging prices) | B11: =Pools_Scenarios!B89 -> 0 | C11: =Pools_Scenarios!C89 -> 0.2
A12: Size of new clients vs SDP (Years 2–5) | B12: =Pools_Scenarios!B90 -> 0.6 | C12: =Pools_Scenarios!C90 -> 0.4
A13: Shop default rate (a year) | B13: =Pools_Scenarios!B91 -> 0.02 | C13: =Pools_Scenarios!C91 -> 0.1
A14: Extra developers hired in Year 3 (our response, not a stress) | B14: =Pools_Scenarios!B92 -> 1 | C14: =Pools_Scenarios!C92 -> 0
A15: EV: charging sessions per charger per day | B15: =Pools_Scenarios!B93 -> 2 | C15: =Pools_Scenarios!C93 -> 1.5
A16: EV: average kWh per session | B16: =Pools_Scenarios!B94 -> 30 | C16: =Pools_Scenarios!C94 -> 20
... A25: Share of the RMO fee borne by the developer | B25: =Pools_Scenarios!B103 -> 0.5 | C25: =Pools_Scenarios!C103 -> 1
A27: Check | B27: Normal | C27: Conservative | D27: Target | E27: Pass (normal) | F27: Pass (conservative)
A28: 1. Customer (SDP) net gain, Year 1 | B28: =Customer_ROI!C8 -> 126768.55 | C28: =C_Customer_ROI!C8 -> 5808.8056 | D28: >0 | E28: =IF(B28>0,"PASS","FAIL") -> PASS | F28: =IF(C28>0,"PASS","FAIL") -> PASS
A29: 2. Customer cash-only net gain, Year 1 (no community saving) | B29: =Customer_ROI!C10 -> 22768.55 | C29: =C_Customer_ROI!C10 -> 5808.8056 | D29: >0 | E29: =IF(B29>0,"PASS","FAIL") -> PASS | F29: =IF(C29>0,"PASS","FAIL") -> PASS
A30: 2b. New developer net gain, its Year 1 | B30: =Customer_ROI!C16 -> 76061.13 | C30: =C_Customer_ROI!C16 -> 2323.5223 | D30: >0 | E30: =IF(B30>0,"PASS","FAIL") -> PASS | F30: =IF(C30>0,"PASS","FAIL") -> PASS
A31: 3. Residents' profit, Year 1 (all pools, SDP) | B31: =Pools_Scenarios!C50 -> 82163.299 | C31: =C_Pools!C50 -> 50465.897 | D31: >0 | E31: =IF(B31>0,"PASS","FAIL") -> PASS | F31: =IF(C31>0,"PASS","FAIL") -> PASS
A32: 4a. Solar investor return, Year 1 | B32: =Investor_ROI!B11 -> 0.04547563 | C32: =Investor_ROI!C11 -> 0.04547563 | D32: >0 | E32: =IF(B32>0,"PASS","FAIL") -> PASS | F32: =IF(C32>0,"PASS","FAIL") -> PASS
A33: 4b. Upgrade investor return, Year 1 | B33: =Investor_ROI!B25 -> 0.05484129 | C33: =Investor_ROI!C25 -> 0.012947272 | D33: >0 | E33: =IF(B33>0,"PASS","FAIL") -> PASS | F33: =IF(C33>0,"PASS","FAIL") -> PASS
A34: 4c. EV investor loss over the 7-year payback period | B34: =Investor_ROI!B36 -> 0 | C34: =Investor_ROI!C36 -> 0.4 | D34: <=50% | E34: =IF(B34<=0.5,"PASS","FAIL") -> PASS | F34: =IF(C34<=0.5,"PASS","FAIL") -> PASS
A35: 5. Vendor net profit, Year 2 | B35: =ROI!D10 -> 92228.355 | C35: =C_ROI!D10 -> 5033.9555 | D35: >0 | E35: =IF(B35>0,"PASS","FAIL") -> PASS | F35: =IF(C35>0,"PASS","FAIL") -> PASS
A36: 6. Vendor net profit, 5 years | B36: =ROI!H10 -> 1434165.2 | C36: =C_ROI!H10 -> 131171.91 | D36: >0 | E36: =IF(B36>0,"PASS","FAIL") -> PASS | F36: =IF(C36>0,"PASS","FAIL") -> PASS
A37: 7. NPV of vendor cash flows | B37: =ROI!E31 -> 778498.7 | C37: =C_ROI!E31 -> 22817.907 | D37: >0 | E37: =IF(B37>0,"PASS","FAIL") -> PASS | F37: =IF(C37>0,"PASS","FAIL") -> PASS
A38: 8. Lowest cash balance in 5 years (with grant) | B38: =MIN(ROI!C37:G37) -> 33918.505 | C38: =MIN(C_ROI!C37:G37) -> 12403.716 | D38: >=0 | E38: =IF(B38>=0,"PASS","FAIL") -> PASS | F38: =IF(C38>=0,"PASS","FAIL") -> PASS
A39: 9. Vendor lowest yearly net profit, Years 2–5 | B39: =MIN(ROI!D10:G10) -> 92228.355 | C39: =MIN(C_ROI!D10:G10) -> 5033.9555 | D39: >0 | E39: =IF(B39>0,"PASS","FAIL") -> PASS | F39: =IF(C39>0,"PASS","FAIL") -> PASS
A40: All checks pass? | E40: =IF(COUNTIF(E28:E39,"FAIL")=0,"ALL PASS","SOME FAIL") -> ALL PASS | F40: =IF(COUNTIF(F28:F39,"FAIL")=0,"ALL PASS","SOME FAIL") -> ALL PASS
A42: Minimum changes that make the conservative case pass (already built into the inputs):
A43: • Year 1: set-up fee RM20,000 only; success fee waived; platform fee waived (Assumptions rows 38–40, 60–62).
A44: • Community saving made contractual: we guarantee 50% of the expected saving and credit back 50% of any shortfall (cap 100% of fees in Year 1, 25% later).
A45: • JV passes a 1% a year arrangement fee to the developer on residents' solar money (row 70).
A46: • Shop upgrades need an installer contract with a minimum-savings clause (RM800 a month) (row 72).
A47: • EV: partners top up to 60 kWh/day (developer 33%, platform 33%, CPO 34%), capped at RM3,000 per charger a year (Assumptions rows 75–76, 138–140).
A48: • EV: developer and platform 10% shares wait until residents recover their money (row 135); without this the normal EV return is about 1% a year.
A49: • EV: start with 1–2 chargers a year and an RM500 cap per resident, so a weak EV pool cannot hurt the customer or vendor targets.
A50: • New shop-paid income: featured offers and energy dashboards; REC service fee. None is paid by the developer.
A51: • Our Year 1 cost: founders take half pay in cash, contract developer 70% cash; a RM120,000 grant covers the Year 1 loss (RM100,000 leaves conservative cash slightly negative).
A52: • Clients: sign letters of intent in Year 1 so at least one new client starts in Year 2 (two is the safety margin).
A53: • If only one new client signs in Year 2, delay the Year 3 developer hire by a year (Pools_Scenarios row 14).
A54: • Fixed fees are pro rata to client size, so smaller developers are not priced out.

Sheet C_Pools
A1: Pools – what happens inside one client (SDP size), by the client's year on the platform – CONSERVATIVE scenario (inputs from Pools_Scenarios sheet)
A2: Money raised, money still invested, payouts and impact for the three pools (other clients are scaled from this).
A4: Item | B4: Unit | C4: Year 1 | D4: Year 2 | E4: Year 3 | F4: Year 4 | G4: Year 5
A5: Timing factors (money is raised mid-year on average)
A6: Year since money was raised | C6: 1 | D6: 2 | E6: 3 | F6: 4 | G6: 5
A7: Solar: share of money still owed at year end | C7: =((1+Assumptions!$B$19)^Assumptions!$B$20-(1+Assumptions!$B$19)^C6)/((1+Assumptions!$B$19)^Assumptions!$B$20-1) -> 0.8190252 | D7: =((1+Assumptions!$B$19)^Assumptions!$B$20-(1+Assumptions!$B$19)^D6)/((1+Assumptions!$B$19)^Assumptions!$B$20-1) -> 0.62900166 | E7: =((1+Assumptions!$B$19)^Assumptions!$B$20-(1+Assumptions!$B$19)^E6)/((1+Assumptions!$B$19)^Assumptions!$B$20-1) -> 0.42947695 | F7: =((1+Assumptions!$B$19)^Assumptions!$B$20-(1+Assumptions!$B$19)^F6)/((1+Assumptions!$B$19)^Assumptions!$B$20-1) -> 0.219976 | G7: =((1+Assumptions!$B$19)^Assumptions!$B$20-(1+Assumptions!$B$19)^G6)/((1+Assumptions!$B$19)^Assumptions!$B$20-1) -> 0
A8: Solar: average share still invested | C8: =0.5 -> 0.5 | D8: =(1+C7)/2 -> 0.9095126 | E8: =(C7+D7)/2 -> 0.72401343 | F8: =(D7+E7)/2 -> 0.52923931 | G8: =(E7+F7)/2 -> 0.32472647
A9: Payout timing (half year in first year) | C9: =0.5 -> 0.5 | D9: =1 -> 1 | E9: =1 -> 1 | F9: =1 -> 1 | G9: =1 -> 1
A10: Upgrades: share still owed at year end | C10: =MAX(0,((1+Assumptions!$B$26)^Assumptions!$B$27-(1+Assumptions!$B$26)^C6)/((1+Assumptions!$B$26)^Assumptions!$B$27-1)) -> 0.6874243 | D10: =MAX(0,((1+Assumptions!$B$26)^Assumptions!$B$27-(1+Assumptions!$B$26)^D6)/((1+Assumptions!$B$26)^Assumptions!$B$27-1)) -> 0.35453118 | E10: =MAX(0,((1+Assumptions!$B$26)^Assumptions!$B$27-(1+Assumptions!$B$26)^E6)/((1+Assumptions!$B$26)^Assumptions!$B$27-1)) -> 0 | F10: =MAX(0,((1+Assumptions!$B$26)^Assumptions!$B$27-(1+Assumptions!$B$26)^F6)/((1+Assumptions!$B$26)^Assumptions!$B$27-1)) -> 0 | G10: =MAX(0,((1+Assumptions!$B$26)^Assumptions!$B$27-(1+Assumptions!$B$26)^G6)/((1+Assumptions!$B$26)^Assumptions!$B$27-1)) -> 0
A11: Upgrades: average share still invested | C11: =0.5 -> 0.5 | D11: =(1+C10)/2 -> 0.84371215 | E11: =(C10+D10)/2 -> 0.52097774 | F11: =(D10+E10)/2 -> 0.17726559 | G11: =(E10+F10)/2 -> 0
A12: Upgrades: share of year a shop is repaying | C12: =0.5 -> 0.5 | D12: =1 -> 1 | E12: =1 -> 1 | F12: =0.5 -> 0.5 | G12: =0 -> 0
A13: EV: average share still invested (paid back evenly over the EV payback period) | C13: =0.5*(1+(1-0.5/Assumptions!$B$137))/2 -> 0.48214286 | D13: =MAX(0,1-1/Assumptions!$B$137) -> 0.85714286 | E13: =MAX(0,1-2/Assumptions!$B$137) -> 0.71428571 | F13: =MAX(0,1-3/Assumptions!$B$137) -> 0.57142857 | G13: =MAX(0,1-4/Assumptions!$B$137) -> 0.42857143
A14: EV: share of money paid back in the year | C14: =0.5/Assumptions!$B$137 -> 0.071428571 | D14: =IF(2-0.5<=Assumptions!$B$137,1/Assumptions!$B$137,0) -> 0.14285714 | E14: =IF(3-0.5<=Assumptions!$B$137,1/Assumptions!$B$137,0) -> 0.14285714 | F14: =IF(4-0.5<=Assumptions!$B$137,1/Assumptions!$B$137,0) -> 0.14285714 | G14: =IF(5-0.5<=Assumptions!$B$137,1/Assumptions!$B$137,0) -> 0.14285714
A15: Pool 1 – Rooftop solar
A16: New solar capacity with resident share | B16: MW | C16: =Assumptions!$B$155 -> 3 | D16: =Assumptions!$C$155 -> 3 | E16: =Assumptions!$D$155 -> 4 | F16: =Assumptions!$E$155 -> 5 | G16: =Assumptions!$F$155 -> 5
A17: Money raised from residents | B17: RM | C17: =C16*1000*Assumptions!$B$16*Pools_Scenarios!$C$101 -> 1920000 | D17: =D16*1000*Assumptions!$B$16*Pools_Scenarios!$C$101 -> 1920000 | E17: =E16*1000*Assumptions!$B$16*Pools_Scenarios!$C$101 -> 2560000 | F17: =F16*1000*Assumptions!$B$16*Pools_Scenarios!$C$101 -> 3200000 | G17: =G16*1000*Assumptions!$B$16*Pools_Scenarios!$C$101 -> 3200000
A18: Residents' money still invested (average) | B18: RM | C18: =C17*C8 -> 960000 | D18: =C17*D8+D17*C8 -> 2706264.2 | E18: =C17*E8+D17*D8+E17*C8 -> 4416370 | F18: =C17*F8+D17*E8+E17*D8+F17*C8 -> 6334597.5 | G18: =C17*G8+D17*F8+E17*E8+F17*D8+G17*C8 -> 8003529
A19: Yearly payment per RM1 raised | B19: factor | C19: =PMT(Assumptions!$B$19,Assumptions!$B$20,-1) -> 0.2309748 | D19: =PMT(Assumptions!$B$19,Assumptions!$B$20,-1) -> 0.2309748 | E19: =PMT(Assumptions!$B$19,Assumptions!$B$20,-1) -> 0.2309748 | F19: =PMT(Assumptions!$B$19,Assumptions!$B$20,-1) -> 0.2309748 | G19: =PMT(Assumptions!$B$19,Assumptions!$B$20,-1) -> 0.2309748
A20: Payouts to residents | B20: RM | C20: =(C17*C9)*C19 -> 221735.81 | D20: =(C17*D9+D17*C9)*D19 -> 665207.42 | E20: =(C17*E9+D17*D9+E17*C9)*E19 -> 1182591 | F20: =(C17*F9+D17*E9+E17*D9+F17*C9)*F19 -> 1847798.4 | G20: =(C17*G9+D17*F9+E17*E9+F17*D9+G17*C9)*G19 -> 2586917.7
A21: Solar capacity running (average) | B21: MW | C21: =C16*C9 -> 1.5 | D21: =C16*D9+D16*C9 -> 4.5 | E21: =C16*E9+D16*D9+E16*C9 -> 8 | F21: =C16*F9+D16*E9+E16*D9+F16*C9 -> 12.5 | G21: =C16*G9+D16*F9+E16*E9+F16*D9+G16*C9 -> 17.5
A22: Solar power produced | B22: MWh | C22: =C21*Assumptions!$B$17 -> 1875 | D22: =D21*Assumptions!$B$17 -> 5625 | E22: =E21*Assumptions!$B$17 -> 10000 | F22: =F21*Assumptions!$B$17 -> 15625 | G22: =G21*Assumptions!$B$17 -> 21875
A23: CO2 avoided by solar | B23: tCO2e | C23: =C22*Assumptions!$B$12 -> 1387.5 | D23: =D22*Assumptions!$B$12 -> 4162.5 | E23: =E22*Assumptions!$B$12 -> 7400 | F23: =F22*Assumptions!$B$12 -> 11562.5 | G23: =G22*Assumptions!$B$12 -> 16187.5
A24: Pool 2 – Shop energy upgrades
A25: New shops upgraded | B25: shops | C25: =Assumptions!$B$156 -> 15 | D25: =Assumptions!$C$156 -> 25 | E25: =Assumptions!$D$156 -> 10 | F25: =Assumptions!$E$156 -> 10 | G25: =Assumptions!$F$156 -> 10
A26: Money raised from residents | B26: RM | C26: =C25*Assumptions!$B$23 -> 300000 | D26: =D25*Assumptions!$B$23 -> 500000 | E26: =E25*Assumptions!$B$23 -> 200000 | F26: =F25*Assumptions!$B$23 -> 200000 | G26: =G25*Assumptions!$B$23 -> 200000
A27: Residents' money still invested (average) | B27: RM | C27: =C26*C11 -> 150000 | D27: =C26*D11+D26*C11 -> 503113.64 | E27: =C26*E11+D26*D11+E26*C11 -> 678149.4 | F27: =C26*F11+D26*E11+E26*D11+F26*C11 -> 582410.97 | G27: =C26*G11+D26*F11+E26*E11+F26*D11+G26*C11 -> 461570.77
A28: Shops repaying (shop-years) | B28: shop-yrs | C28: =C25*C12 -> 7.5 | D28: =C25*D12+D25*C12 -> 27.5 | E28: =C25*E12+D25*D12+E25*C12 -> 45 | F28: =C25*F12+D25*E12+E25*D12+F25*C12 -> 47.5 | G28: =C25*G12+D25*F12+E25*E12+F25*D12+G25*C12 -> 37.5
A29: Yearly payout per shop to residents | B29: RM | C29: =PMT(Assumptions!$B$26/12,Assumptions!$B$27*12,-Assumptions!$B$23)*12 -> 7355.7607 | D29: =PMT(Assumptions!$B$26/12,Assumptions!$B$27*12,-Assumptions!$B$23)*12 -> 7355.7607 | E29: =PMT(Assumptions!$B$26/12,Assumptions!$B$27*12,-Assumptions!$B$23)*12 -> 7355.7607 | F29: =PMT(Assumptions!$B$26/12,Assumptions!$B$27*12,-Assumptions!$B$23)*12 -> 7355.7607 | G29: =PMT(Assumptions!$B$26/12,Assumptions!$B$27*12,-Assumptions!$B$23)*12 -> 7355.7607
A30: Payouts to residents | B30: RM | C30: =C28*C29 -> 55168.205 | D30: =D28*D29 -> 202283.42 | E30: =E28*E29 -> 331009.23 | F30: =F28*F29 -> 349398.63 | G30: =G28*G29 -> 275841.03
A31: Safety margin per shop-year (repayment counted − payout) | B31: RM | C31: =C56*12-C29 -> 324.23931 | D31: =D56*12-D29 -> 324.23931 | E31: =E56*12-E29 -> 324.23931 | F31: =F56*12-F29 -> 324.23931 | G31: =G56*12-G29 -> 324.23931
A32: Savings shops keep | B32: RM | C32: =C28*Pools_Scenarios!$C$85*12*(1-Assumptions!$B$25) -> 9000 | D32: =D28*Pools_Scenarios!$C$85*12*(1-Assumptions!$B$25) -> 33000 | E32: =E28*Pools_Scenarios!$C$85*12*(1-Assumptions!$B$25) -> 54000 | F32: =F28*Pools_Scenarios!$C$85*12*(1-Assumptions!$B$25) -> 57000 | G32: =G28*Pools_Scenarios!$C$85*12*(1-Assumptions!$B$25) -> 45000
A33: Electricity saved | B33: MWh | C33: =C28*Pools_Scenarios!$C$85*12/Assumptions!$B$11/1000 -> 88.792423 | D33: =D28*Pools_Scenarios!$C$85*12/Assumptions!$B$11/1000 -> 325.57222 | E33: =E28*Pools_Scenarios!$C$85*12/Assumptions!$B$11/1000 -> 532.75454 | F33: =F28*Pools_Scenarios!$C$85*12/Assumptions!$B$11/1000 -> 562.35201 | G33: =G28*Pools_Scenarios!$C$85*12/Assumptions!$B$11/1000 -> 443.96212
A34: CO2 avoided by upgrades | B34: tCO2e | C34: =C33*Assumptions!$B$12 -> 65.706393 | D34: =D33*Assumptions!$B$12 -> 240.92344 | E34: =E33*Assumptions!$B$12 -> 394.23836 | F34: =F33*Assumptions!$B$12 -> 416.14049 | G34: =G33*Assumptions!$B$12 -> 328.53197
A35: Pool 3 – EV charging
A36: New EV chargers | B36: chargers | C36: =Assumptions!$B$157 -> 1 | D36: =Assumptions!$C$157 -> 2 | E36: =Assumptions!$D$157 -> 2 | F36: =Assumptions!$E$157 -> 2 | G36: =Assumptions!$F$157 -> 2
A37: Money raised from residents (net cost after grant × residents' share) | B37: RM | C37: =C36*EV_Pilot!$C$46*Assumptions!$B$31 -> 35000 | D37: =D36*EV_Pilot!$C$46*Assumptions!$B$31 -> 70000 | E37: =E36*EV_Pilot!$C$46*Assumptions!$B$31 -> 70000 | F37: =F36*EV_Pilot!$C$46*Assumptions!$B$31 -> 70000 | G37: =G36*EV_Pilot!$C$46*Assumptions!$B$31 -> 70000
A38: Residents' money still invested (average) | B38: RM | C38: =C37*C13 -> 16875 | D38: =C37*D13+D37*C13 -> 63750 | E38: =C37*E13+D37*D13+E37*C13 -> 118750 | F38: =C37*F13+D37*E13+E37*D13+F37*C13 -> 163750 | G38: =C37*G13+D37*F13+E37*E13+F37*D13+G37*C13 -> 198750
A39: Chargers running (charger-years) | B39: chg-yrs | C39: =C36*C9 -> 0.5 | D39: =C36*D9+D36*C9 -> 2 | E39: =C36*E9+D36*D9+E36*C9 -> 4 | F39: =C36*F9+D36*E9+E36*D9+F36*C9 -> 6 | G39: =C36*G9+D36*F9+E36*E9+F36*D9+G36*C9 -> 8
A40: Net charging profit per charger-year (blended DC/AC, from EV_Pilot) | B40: RM | C40: =EV_Pilot!$C$50 -> -7403.2012 | D40: =EV_Pilot!$C$50 -> -7403.2012 | E40: =EV_Pilot!$C$50 -> -7403.2012 | F40: =EV_Pilot!$C$50 -> -7403.2012 | G40: =EV_Pilot!$C$50 -> -7403.2012
A41: Residents' share of charging profit (their 50%, before the 70/10/10/10 split) | B41: RM | C41: =C39*EV_Pilot!$C$54 -> 0 | D41: =D39*EV_Pilot!$C$54 -> 0 | E41: =E39*EV_Pilot!$C$54 -> 0 | F41: =F39*EV_Pilot!$C$54 -> 0 | G41: =G39*EV_Pilot!$C$54 -> 0
A42: Payouts to residents (incl. usage top-up) | B42: RM | C42: =C68*EV_Pilot!$C$56+C69*EV_Pilot!$C$57+C39*EV_Pilot!$C$65 -> 1500 | D42: =D68*EV_Pilot!$C$56+D69*EV_Pilot!$C$57+D39*EV_Pilot!$C$65 -> 6000 | E42: =E68*EV_Pilot!$C$56+E69*EV_Pilot!$C$57+E39*EV_Pilot!$C$65 -> 12000 | F42: =F68*EV_Pilot!$C$56+F69*EV_Pilot!$C$57+F39*EV_Pilot!$C$65 -> 18000 | G42: =G68*EV_Pilot!$C$56+G69*EV_Pilot!$C$57+G39*EV_Pilot!$C$65 -> 24000
A43: Residents' EV money paid back | B43: RM | C43: =C37*C14 -> 2500 | D43: =C37*D14+D37*C14 -> 10000 | E43: =C37*E14+D37*D14+E37*C14 -> 20000 | F43: =C37*F14+D37*E14+E37*D14+F37*C14 -> 30000 | G43: =C37*G14+D37*F14+E37*E14+F37*D14+G37*C14 -> 40000
A44: All pools – totals for one SDP-size client
A45: Money raised from residents | B45: RM | C45: =C17+C26+C37 -> 2255000 | D45: =D17+D26+D37 -> 2490000 | E45: =E17+E26+E37 -> 2830000 | F45: =F17+F26+F37 -> 3470000 | G45: =G17+G26+G37 -> 3470000
A46: Residents' money still invested (average) | B46: RM | C46: =C18+C27+C38 -> 1126875 | D46: =D18+D27+D38 -> 3273127.8 | E46: =E18+E27+E38 -> 5213269.4 | F46: =F18+F27+F38 -> 7080758.5 | G46: =G18+G27+G38 -> 8663849.8
A47: Payouts to residents | B47: RM | C47: =C20+C30+C42 -> 278404.01 | D47: =D20+D30+D42 -> 873490.84 | E47: =E20+E30+E42 -> 1525600.2 | F47: =F20+F30+F42 -> 2215197 | G47: =G20+G30+G42 -> 2886758.8
A48: Spent at the developer's malls (incl. bonus) | B48: RM | C48: =C47*Assumptions!$B$8*(1+Assumptions!$B$9) -> 91873.324 | D48: =D47*Assumptions!$B$8*(1+Assumptions!$B$9) -> 288251.98 | E48: =E47*Assumptions!$B$8*(1+Assumptions!$B$9) -> 503448.07 | F48: =F47*Assumptions!$B$8*(1+Assumptions!$B$9) -> 731015.02 | G48: =G47*Assumptions!$B$8*(1+Assumptions!$B$9) -> 952630.39
A49: Resident investments made (count, at average ticket) | B49: count | C49: =C45/Assumptions!$B$7 -> 4510 | D49: =D45/Assumptions!$B$7 -> 4980 | E49: =E45/Assumptions!$B$7 -> 5660 | F49: =F45/Assumptions!$B$7 -> 6940 | G49: =G45/Assumptions!$B$7 -> 6940
A50: Residents' profit earned (after expected shop losses) | B50: RM | C50: =C18*Assumptions!$B$19+C27*Assumptions!$B$26-C59+C42-C43 -> 50465.897 | D50: =D18*Assumptions!$B$19+D27*Assumptions!$B$26-D59+D42-D43 -> 140973.89 | E50: =E18*Assumptions!$B$19+E27*Assumptions!$B$26-E59+E42-E43 -> 219193.59 | F50: =F18*Assumptions!$B$19+F27*Assumptions!$B$26-F59+F42-F43 -> 302787.27 | G50: =G18*Assumptions!$B$19+G27*Assumptions!$B$26-G59+G42-G43 -> 382758.04
A51: CO2 avoided by assets residents co-fund (solar + upgrades) | B51: tCO2e | C51: =C23+C34 -> 1453.2064 | D51: =D23+D34 -> 4403.4234 | E51: =E23+E34 -> 7794.2384 | F51: =F23+F34 -> 11978.64 | G51: =G23+G34 -> 16516.032
A53: Note: timing factors are simple approximations (money raised mid-year; solar and upgrades repaid monthly; EV money returned from charging profit, not guaranteed).
A55: Guarantees, expected losses and certificates
A56: Repayment counted per shop-month (higher of actual or guaranteed saving × repay share) | B56: RM | C56: =MAX(Pools_Scenarios!$C$85,Assumptions!$B$72)*Assumptions!$B$25 -> 640 | D56: =MAX(Pools_Scenarios!$C$85,Assumptions!$B$72)*Assumptions!$B$25 -> 640 | E56: =MAX(Pools_Scenarios!$C$85,Assumptions!$B$72)*Assumptions!$B$25 -> 640 | F56: =MAX(Pools_Scenarios!$C$85,Assumptions!$B$72)*Assumptions!$B$25 -> 640 | G56: =MAX(Pools_Scenarios!$C$85,Assumptions!$B$72)*Assumptions!$B$25 -> 640
A57: Expected default loss per shop-year | B57: RM | C57: =Assumptions!$B$23*Pools_Scenarios!$C$91*Assumptions!$B$74 -> 1000 | D57: =Assumptions!$B$23*Pools_Scenarios!$C$91*Assumptions!$B$74 -> 1000 | E57: =Assumptions!$B$23*Pools_Scenarios!$C$91*Assumptions!$B$74 -> 1000 | F57: =Assumptions!$B$23*Pools_Scenarios!$C$91*Assumptions!$B$74 -> 1000 | G57: =Assumptions!$B$23*Pools_Scenarios!$C$91*Assumptions!$B$74 -> 1000
A58: Bad-debt reserve per shop-year (unused half of margin) | B58: RM | C58: =MAX(0,C31)*(1-Assumptions!$B$28) -> 162.11965 | D58: =MAX(0,D31)*(1-Assumptions!$B$28) -> 162.11965 | E58: =MAX(0,E31)*(1-Assumptions!$B$28) -> 162.11965 | F58: =MAX(0,F31)*(1-Assumptions!$B$28) -> 162.11965 | G58: =MAX(0,G31)*(1-Assumptions!$B$28) -> 162.11965
A59: Residents' uncovered loss on upgrades | B59: RM | C59: =C28*(MAX(0,C57-C58)+MAX(0,-C31)) -> 6284.1026 | D59: =D28*(MAX(0,D57-D58)+MAX(0,-D31)) -> 23041.709 | E59: =E28*(MAX(0,E57-E58)+MAX(0,-E31)) -> 37704.616 | F59: =F28*(MAX(0,F57-F58)+MAX(0,-F31)) -> 39799.316 | G59: =G28*(MAX(0,G57-G58)+MAX(0,-G31)) -> 31420.513
A60: kWh sold per charger-day (after downtime) | B60: kWh | C60: =EV_Pilot!$C$9 -> 27 | D60: =EV_Pilot!$C$9 -> 27 | E60: =EV_Pilot!$C$9 -> 27 | F60: =EV_Pilot!$C$9 -> 27 | G60: =EV_Pilot!$C$9 -> 27
A61: usage top-up per charger-year (after cap) | B61: RM | C61: =EV_Pilot!$C$65 -> 3000 | D61: =EV_Pilot!$C$65 -> 3000 | E61: =EV_Pilot!$C$65 -> 3000 | F61: =EV_Pilot!$C$65 -> 3000 | G61: =EV_Pilot!$C$65 -> 3000
A62: usage top-up paid to residents (developer + platform + CPO) | B62: RM | C62: =C39*C61 -> 1500 | D62: =D39*D61 -> 6000 | E62: =E39*E61 -> 12000 | F62: =F39*F61 -> 18000 | G62: =G39*G61 -> 24000
A63: Solar MWh from the residents' share (for certificates) | B63: MWh | C63: =C22*Pools_Scenarios!$C$101 -> 375 | D63: =D22*Pools_Scenarios!$C$101 -> 1125 | E63: =E22*Pools_Scenarios!$C$101 -> 2000 | F63: =F22*Pools_Scenarios!$C$101 -> 3125 | G63: =G22*Pools_Scenarios!$C$101 -> 4375
A65: EV: who is paid while residents recover their money
A66: EV: charger-year factor while residents recover (by age) | C66: =C9*IF(C6-0.5<EV_Pilot!$C$73,1,0) -> 0.5 | D66: =D9*IF(D6-0.5<EV_Pilot!$C$73,1,0) -> 1 | E66: =E9*IF(E6-0.5<EV_Pilot!$C$73,1,0) -> 1 | F66: =F9*IF(F6-0.5<EV_Pilot!$C$73,1,0) -> 1 | G66: =G9*IF(G6-0.5<EV_Pilot!$C$73,1,0) -> 1
A67: EV: charger-year factor after residents recover (by age) | C67: =C9-C66 -> 0 | D67: =D9-D66 -> 0 | E67: =E9-E66 -> 0 | F67: =F9-F66 -> 0 | G67: =G9-G66 -> 0
A68: EV charger-years while residents recover | B68: chg-yrs | C68: =C36*C66 -> 0.5 | D68: =C36*D66+D36*C66 -> 2 | E68: =C36*E66+D36*D66+E36*C66 -> 4 | F68: =C36*F66+D36*E66+E36*D66+F36*C66 -> 6 | G68: =C36*G66+D36*F66+E36*E66+F36*D66+G36*C66 -> 8
A69: EV charger-years after residents recover | B69: chg-yrs | C69: =C36*C67 -> 0 | D69: =C36*D67+D36*C67 -> 0 | E69: =C36*E67+D36*D67+E36*C67 -> 0 | F69: =C36*F67+D36*E67+E36*D67+F36*C67 -> 0 | G69: =C36*G67+D36*F67+E36*E67+F36*D67+G36*C67 -> 0
A70: Developer's 10% share of residents' EV profit (paid after recovery if deferral is on) | B70: RM | C70: =IF(Assumptions!$B$135=1,C69,C39)*EV_Pilot!$C$58 -> 0 | D70: =IF(Assumptions!$B$135=1,D69,D39)*EV_Pilot!$C$58 -> 0 | E70: =IF(Assumptions!$B$135=1,E69,E39)*EV_Pilot!$C$58 -> 0 | F70: =IF(Assumptions!$B$135=1,F69,F39)*EV_Pilot!$C$58 -> 0 | G70: =IF(Assumptions!$B$135=1,G69,G39)*EV_Pilot!$C$58 -> 0
A71: Developer's part of the usage top-up | B71: RM | C71: =C39*EV_Pilot!$C$66 -> 495 | D71: =D39*EV_Pilot!$C$66 -> 1980 | E71: =E39*EV_Pilot!$C$66 -> 3960 | F71: =F39*EV_Pilot!$C$66 -> 5940 | G71: =G39*EV_Pilot!$C$66 -> 7920
A72: Platform's 10% share of residents' EV profit (paid after recovery if deferral is on) | B72: RM | C72: =IF(Assumptions!$B$135=1,C69,C39)*EV_Pilot!$C$59 -> 0 | D72: =IF(Assumptions!$B$135=1,D69,D39)*EV_Pilot!$C$59 -> 0 | E72: =IF(Assumptions!$B$135=1,E69,E39)*EV_Pilot!$C$59 -> 0 | F72: =IF(Assumptions!$B$135=1,F69,F39)*EV_Pilot!$C$59 -> 0 | G72: =IF(Assumptions!$B$135=1,G69,G39)*EV_Pilot!$C$59 -> 0
A73: Platform's part of the usage top-up | B73: RM | C73: =C39*EV_Pilot!$C$67 -> 495 | D73: =D39*EV_Pilot!$C$67 -> 1980 | E73: =E39*EV_Pilot!$C$67 -> 3960 | F73: =F39*EV_Pilot!$C$67 -> 5940 | G73: =G39*EV_Pilot!$C$67 -> 7920
A75: Licensed platform (RMO) fee, spread over the payout period
A76: Share of each raise's RMO fee counted in the year (by age) | C76: =0.5/Assumptions!$B$151 -> 0.1 | D76: =IF(2-0.5<=Assumptions!$B$151,1/Assumptions!$B$151,0) -> 0.2 | E76: =IF(3-0.5<=Assumptions!$B$151,1/Assumptions!$B$151,0) -> 0.2 | F76: =IF(4-0.5<=Assumptions!$B$151,1/Assumptions!$B$151,0) -> 0.2 | G76: =IF(5-0.5<=Assumptions!$B$151,1/Assumptions!$B$151,0) -> 0.2
A77: Money raised whose RMO fee is counted this year | B77: RM | C77: =C45*C76 -> 225500 | D77: =C45*D76+D45*C76 -> 700000 | E77: =C45*E76+D45*D76+E45*C76 -> 1232000 | F77: =C45*F76+D45*E76+E45*D76+F45*C76 -> 1862000 | G77: =C45*G76+D45*F76+E45*E76+F45*D76+G45*C76 -> 2556000
A78: RMO fee cost borne by the developer (spread) | B78: RM | C78: =C77*Pools_Scenarios!$C$102*(1+Assumptions!$B$149)*Pools_Scenarios!$C$103 -> 17047.8 | D78: =D77*Pools_Scenarios!$C$102*(1+Assumptions!$B$149)*Pools_Scenarios!$C$103 -> 52920 | E78: =E77*Pools_Scenarios!$C$102*(1+Assumptions!$B$149)*Pools_Scenarios!$C$103 -> 93139.2 | F78: =F77*Pools_Scenarios!$C$102*(1+Assumptions!$B$149)*Pools_Scenarios!$C$103 -> 140767.2 | G78: =G77*Pools_Scenarios!$C$102*(1+Assumptions!$B$149)*Pools_Scenarios!$C$103 -> 193233.6

Sheet C_Benefits
A1: 1) Benefits – value created for the developer (customer) – CONSERVATIVE scenario (inputs from Pools_Scenarios sheet)
A2: Top: one SDP-size client by its year on the platform. Bottom: all clients together by calendar year.
A4: Benefit | B4: How it is worked out | C4: Year 1 | D4: Year 2 | E4: Year 3 | F4: Year 4 | G4: Year 5
A5: One SDP-size client (by client's year)
A6: A. Cheaper money for solar | B6: Residents' solar money × ((8.5% − 5%) × developer's JV share + JV arrangement fee) | C6: =C_Pools!C18*((Assumptions!$B$21-Assumptions!$B$19)*Pools_Scenarios!$C$87+Assumptions!$B$70) -> 19680 | D6: =C_Pools!D18*((Assumptions!$B$21-Assumptions!$B$19)*Pools_Scenarios!$C$87+Assumptions!$B$70) -> 55478.416 | E6: =C_Pools!E18*((Assumptions!$B$21-Assumptions!$B$19)*Pools_Scenarios!$C$87+Assumptions!$B$70) -> 90535.585 | F6: =C_Pools!F18*((Assumptions!$B$21-Assumptions!$B$19)*Pools_Scenarios!$C$87+Assumptions!$B$70) -> 129859.25 | G6: =C_Pools!G18*((Assumptions!$B$21-Assumptions!$B$19)*Pools_Scenarios!$C$87+Assumptions!$B$70) -> 164072.34
A7: B. Fee from shop upgrades | B7: Shop-years × positive safety margin × developer's share | C7: =C_Pools!C28*MAX(0,C_Pools!C31)*Assumptions!$B$28 -> 1215.8974 | D7: =C_Pools!D28*MAX(0,C_Pools!D31)*Assumptions!$B$28 -> 4458.2905 | E7: =C_Pools!E28*MAX(0,C_Pools!E31)*Assumptions!$B$28 -> 7295.3845 | F7: =C_Pools!F28*MAX(0,C_Pools!F31)*Assumptions!$B$28 -> 7700.6836 | G7: =C_Pools!G28*MAX(0,C_Pools!G31)*Assumptions!$B$28 -> 6079.4871
A8: C. Developer's EV share, less its part of the usage top-up | B8: 10% of residents' EV profit (paid after residents recover) − developer's 33% of any top-up | C8: =C_Pools!C70-C_Pools!C71 -> -495 | D8: =C_Pools!D70-C_Pools!D71 -> -1980 | E8: =C_Pools!E70-C_Pools!E71 -> -3960 | F8: =C_Pools!F70-C_Pools!F71 -> -5940 | G8: =C_Pools!G70-C_Pools!G71 -> -7920
A9: D. Extra mall rent | B9: Money spent at malls × turnover rent | C9: =C_Pools!C48*Assumptions!$B$10 -> 918.73324 | D9: =C_Pools!D48*Assumptions!$B$10 -> 2882.5198 | E9: =C_Pools!E48*Assumptions!$B$10 -> 5034.4807 | F9: =C_Pools!F48*Assumptions!$B$10 -> 7310.1502 | G9: =C_Pools!G48*Assumptions!$B$10 -> 9526.3039
A10: Cash benefits (A to D, plus F, less G) | C10: =SUM(C6:C9)+C31+C34 -> 5808.8056 | D10: =SUM(D6:D9)+D31+D34 -> 12530.151 | E10: =SUM(E6:E9)+E31+E34 -> 13963.45 | F10: =SUM(F6:F9)+F31+F34 -> 10971.008 | G10: =SUM(G6:G9)+G31+G34 -> -3544.0893
A11: E. Community-programme saving (actually achieved) | B11: Programme spend × saving rate × share achieved | C11: =Assumptions!$B$13*Assumptions!$B$158*Pools_Scenarios!$C$83 -> 0 | D11: =Assumptions!$B$13*Assumptions!$C$158*Pools_Scenarios!$C$83 -> 0 | E11: =Assumptions!$B$13*Assumptions!$D$158*Pools_Scenarios!$C$83 -> 0 | F11: =Assumptions!$B$13*Assumptions!$E$158*Pools_Scenarios!$C$83 -> 0 | G11: =Assumptions!$B$13*Assumptions!$F$158*Pools_Scenarios!$C$83 -> 0
A12: Total benefit for one SDP-size client | C12: =C10+C11 -> 5808.8056 | D12: =D10+D11 -> 12530.151 | E12: =E10+E11 -> 13963.45 | F12: =F10+F11 -> 10971.008 | G12: =G10+G11 -> -3544.0893
A14: Value to residents and shops (one SDP-size client, not counted in developer ROI)
A15: Residents' profit earned | B15: Payout profit on money invested, after expected shop losses | C15: =C_Pools!C50 -> 50465.897 | D15: =C_Pools!D50 -> 140973.89 | E15: =C_Pools!E50 -> 219193.59 | F15: =C_Pools!F50 -> 302787.27 | G15: =C_Pools!G50 -> 382758.04
A16: Savings shops keep | B16: 20% of savings during repayment | C16: =C_Pools!C32 -> 9000 | D16: =C_Pools!D32 -> 33000 | E16: =C_Pools!E32 -> 54000 | F16: =C_Pools!F32 -> 57000 | G16: =C_Pools!G32 -> 45000
A17: CO2 avoided (tCO2e) | B17: Solar + upgrades | C17: =C_Pools!C51 -> 1453.2064 | D17: =C_Pools!D51 -> 4403.4234 | E17: =C_Pools!E51 -> 7794.2384 | F17: =C_Pools!F51 -> 11978.64 | G17: =C_Pools!G51 -> 16516.032
A19: All clients together (by calendar year)
A20: Developer clients on the platform | B20: Cumulative clients signed | C20: =Assumptions!$B$159 -> 1 | D20: =Assumptions!$B$159+Pools_Scenarios!$C$86 -> 2 | E20: =Assumptions!$B$159+Pools_Scenarios!$C$86+Assumptions!$D$159 -> 4 | F20: =Assumptions!$B$159+Pools_Scenarios!$C$86+Assumptions!$D$159+Assumptions!$E$159 -> 6 | G20: =Assumptions!$B$159+Pools_Scenarios!$C$86+Assumptions!$D$159+Assumptions!$E$159+Assumptions!$F$159 -> 8
A21: Cash benefits (A to D, plus F), all clients | C21: =Assumptions!$B$159*Assumptions!$B$160*C10 -> 5808.8056 | D21: =Assumptions!$B$159*Assumptions!$B$160*D10+Pools_Scenarios!$C$86*Pools_Scenarios!$C$90*C10 -> 14853.674 | E21: =Assumptions!$B$159*Assumptions!$B$160*E10+Pools_Scenarios!$C$86*Pools_Scenarios!$C$90*D10+Assumptions!$D$159*Pools_Scenarios!$C$90*C10 -> 23622.555 | F21: =Assumptions!$B$159*Assumptions!$B$160*F10+Pools_Scenarios!$C$86*Pools_Scenarios!$C$90*E10+Assumptions!$D$159*Pools_Scenarios!$C$90*D10+Assumptions!$E$159*Pools_Scenarios!$C$90*C10 -> 31227.553 | G21: =Assumptions!$B$159*Assumptions!$B$160*G10+Pools_Scenarios!$C$86*Pools_Scenarios!$C$90*F10+Assumptions!$D$159*Pools_Scenarios!$C$90*E10+Assumptions!$E$159*Pools_Scenarios!$C$90*D10+Assumptions!$F$159*Pools_Scenarios!$C$90*C10 -> 26686.239
A22: Community-programme saving, all clients | C22: =Assumptions!$B$159*Assumptions!$B$160*C11 -> 0 | D22: =Assumptions!$B$159*Assumptions!$B$160*D11+Pools_Scenarios!$C$86*Pools_Scenarios!$C$90*C11 -> 0 | E22: =Assumptions!$B$159*Assumptions!$B$160*E11+Pools_Scenarios!$C$86*Pools_Scenarios!$C$90*D11+Assumptions!$D$159*Pools_Scenarios!$C$90*C11 -> 0 | F22: =Assumptions!$B$159*Assumptions!$B$160*F11+Pools_Scenarios!$C$86*Pools_Scenarios!$C$90*E11+Assumptions!$D$159*Pools_Scenarios!$C$90*D11+Assumptions!$E$159*Pools_Scenarios!$C$90*C11 -> 0 | G22: =Assumptions!$B$159*Assumptions!$B$160*G11+Pools_Scenarios!$C$86*Pools_Scenarios!$C$90*F11+Assumptions!$D$159*Pools_Scenarios!$C$90*E11+Assumptions!$E$159*Pools_Scenarios!$C$90*D11+Assumptions!$F$159*Pools_Scenarios!$C$90*C11 -> 0
A23: Total benefits, all clients | C23: =C21+C22 -> 5808.8056 | D23: =D21+D22 -> 14853.674 | E23: =E21+E22 -> 23622.555 | F23: =F21+F22 -> 31227.553 | G23: =G21+G22 -> 26686.239
A24: Money raised from residents, all clients | C24: =Assumptions!$B$159*Assumptions!$B$160*C_Pools!C45 -> 2255000 | D24: =Assumptions!$B$159*Assumptions!$B$160*C_Pools!D45+Pools_Scenarios!$C$86*Pools_Scenarios!$C$90*C_Pools!C45 -> 3392000 | E24: =Assumptions!$B$159*Assumptions!$B$160*C_Pools!E45+Pools_Scenarios!$C$86*Pools_Scenarios!$C$90*C_Pools!D45+Assumptions!$D$159*Pools_Scenarios!$C$90*C_Pools!C45 -> 5630000 | F24: =Assumptions!$B$159*Assumptions!$B$160*C_Pools!F45+Pools_Scenarios!$C$86*Pools_Scenarios!$C$90*C_Pools!E45+Assumptions!$D$159*Pools_Scenarios!$C$90*C_Pools!D45+Assumptions!$E$159*Pools_Scenarios!$C$90*C_Pools!C45 -> 8398000 | G24: =Assumptions!$B$159*Assumptions!$B$160*C_Pools!G45+Pools_Scenarios!$C$86*Pools_Scenarios!$C$90*C_Pools!F45+Assumptions!$D$159*Pools_Scenarios!$C$90*C_Pools!E45+Assumptions!$E$159*Pools_Scenarios!$C$90*C_Pools!D45+Assumptions!$F$159*Pools_Scenarios!$C$90*C_Pools!C45 -> 10918000
A25: Resident investments made, all clients (count) | B25: count | C25: =Assumptions!$B$159*Assumptions!$B$160*C_Pools!C49 -> 4510 | D25: =Assumptions!$B$159*Assumptions!$B$160*C_Pools!D49+Pools_Scenarios!$C$86*Pools_Scenarios!$C$90*C_Pools!C49 -> 6784 | E25: =Assumptions!$B$159*Assumptions!$B$160*C_Pools!E49+Pools_Scenarios!$C$86*Pools_Scenarios!$C$90*C_Pools!D49+Assumptions!$D$159*Pools_Scenarios!$C$90*C_Pools!C49 -> 11260 | F25: =Assumptions!$B$159*Assumptions!$B$160*C_Pools!F49+Pools_Scenarios!$C$86*Pools_Scenarios!$C$90*C_Pools!E49+Assumptions!$D$159*Pools_Scenarios!$C$90*C_Pools!D49+Assumptions!$E$159*Pools_Scenarios!$C$90*C_Pools!C49 -> 16796 | G25: =Assumptions!$B$159*Assumptions!$B$160*C_Pools!G49+Pools_Scenarios!$C$86*Pools_Scenarios!$C$90*C_Pools!F49+Assumptions!$D$159*Pools_Scenarios!$C$90*C_Pools!E49+Assumptions!$E$159*Pools_Scenarios!$C$90*C_Pools!D49+Assumptions!$F$159*Pools_Scenarios!$C$90*C_Pools!C49 -> 21836
A26: Residents' profit, all clients | C26: =Assumptions!$B$159*Assumptions!$B$160*C_Pools!C50 -> 50465.897 | D26: =Assumptions!$B$159*Assumptions!$B$160*C_Pools!D50+Pools_Scenarios!$C$86*Pools_Scenarios!$C$90*C_Pools!C50 -> 161160.25 | E26: =Assumptions!$B$159*Assumptions!$B$160*C_Pools!E50+Pools_Scenarios!$C$86*Pools_Scenarios!$C$90*C_Pools!D50+Assumptions!$D$159*Pools_Scenarios!$C$90*C_Pools!C50 -> 315955.87 | F26: =Assumptions!$B$159*Assumptions!$B$160*C_Pools!F50+Pools_Scenarios!$C$86*Pools_Scenarios!$C$90*C_Pools!E50+Assumptions!$D$159*Pools_Scenarios!$C$90*C_Pools!D50+Assumptions!$E$159*Pools_Scenarios!$C$90*C_Pools!C50 -> 543616.54 | G26: =Assumptions!$B$159*Assumptions!$B$160*C_Pools!G50+Pools_Scenarios!$C$86*Pools_Scenarios!$C$90*C_Pools!F50+Assumptions!$D$159*Pools_Scenarios!$C$90*C_Pools!E50+Assumptions!$E$159*Pools_Scenarios!$C$90*C_Pools!D50+Assumptions!$F$159*Pools_Scenarios!$C$90*C_Pools!C50 -> 832379.65
A27: CO2 avoided, all clients (tCO2e) | C27: =Assumptions!$B$159*Assumptions!$B$160*C_Pools!C51 -> 1453.2064 | D27: =Assumptions!$B$159*Assumptions!$B$160*C_Pools!D51+Pools_Scenarios!$C$86*Pools_Scenarios!$C$90*C_Pools!C51 -> 4984.706 | E27: =Assumptions!$B$159*Assumptions!$B$160*C_Pools!E51+Pools_Scenarios!$C$86*Pools_Scenarios!$C$90*C_Pools!D51+Assumptions!$D$159*Pools_Scenarios!$C$90*C_Pools!C51 -> 10718.173 | F27: =Assumptions!$B$159*Assumptions!$B$160*C_Pools!F51+Pools_Scenarios!$C$86*Pools_Scenarios!$C$90*C_Pools!E51+Assumptions!$D$159*Pools_Scenarios!$C$90*C_Pools!D51+Assumptions!$E$159*Pools_Scenarios!$C$90*C_Pools!C51 -> 19781.64 | G27: =Assumptions!$B$159*Assumptions!$B$160*C_Pools!G51+Pools_Scenarios!$C$86*Pools_Scenarios!$C$90*C_Pools!F51+Assumptions!$D$159*Pools_Scenarios!$C$90*C_Pools!E51+Assumptions!$E$159*Pools_Scenarios!$C$90*C_Pools!D51+Assumptions!$F$159*Pools_Scenarios!$C$90*C_Pools!C51 -> 32228.183
A28: Benefit A only counts the residents' share of each solar asset and only the developer's assumed share of the JV. Benefit E is the least certain; guarantees half of it in the contract (see Pricing_Income credit rows).
A30: Certificates and the community-saving guarantee (one SDP-size client)
A31: F. Renewable energy certificate (REC) sales, developer's share | B31: Residents' share of solar MWh × REC price × USD rate × JV share × (1 − our service fee) | C31: =C_Pools!C63*Assumptions!$B$78*Assumptions!$B$52*Pools_Scenarios!$C$87*(1-Assumptions!$B$79) -> 1536.975 | D31: =C_Pools!D63*Assumptions!$B$78*Assumptions!$B$52*Pools_Scenarios!$C$87*(1-Assumptions!$B$79) -> 4610.925 | E31: =C_Pools!E63*Assumptions!$B$78*Assumptions!$B$52*Pools_Scenarios!$C$87*(1-Assumptions!$B$79) -> 8197.2 | F31: =C_Pools!F63*Assumptions!$B$78*Assumptions!$B$52*Pools_Scenarios!$C$87*(1-Assumptions!$B$79) -> 12808.125 | G31: =C_Pools!G63*Assumptions!$B$78*Assumptions!$B$52*Pools_Scenarios!$C$87*(1-Assumptions!$B$79) -> 17931.375
A32: Community saving we guarantee in the contract | B32: Programme spend × saving rate × guaranteed share | C32: =Assumptions!$B$13*Assumptions!$B$158*Assumptions!$B$65 -> 52000 | D32: =Assumptions!$B$13*Assumptions!$C$158*Assumptions!$B$65 -> 104000 | E32: =Assumptions!$B$13*Assumptions!$D$158*Assumptions!$B$65 -> 104000 | F32: =Assumptions!$B$13*Assumptions!$E$158*Assumptions!$B$65 -> 104000 | G32: =Assumptions!$B$13*Assumptions!$F$158*Assumptions!$B$65 -> 104000
A33: Shortfall vs guarantee | B33: Guaranteed − achieved (if positive) | C33: =MAX(0,C32-C11) -> 52000 | D33: =MAX(0,D32-D11) -> 104000 | E33: =MAX(0,E32-E11) -> 104000 | F33: =MAX(0,F32-F11) -> 104000 | G33: =MAX(0,G32-G11) -> 104000
A34: G. Licensed platform (RMO) fee, developer's share (cost) | B34: − raised × RMO fee × (1 + SST) × developer's share, spread over the payout period | C34: =-C_Pools!C78 -> -17047.8 | D34: =-C_Pools!D78 -> -52920 | E34: =-C_Pools!E78 -> -93139.2 | F34: =-C_Pools!F78 -> -140767.2 | G34: =-C_Pools!G78 -> -193233.6

Sheet C_Pricing_Income
A1: 2) Pricing / Income – what clients pay = what we earn – CONSERVATIVE scenario (inputs from Pools_Scenarios sheet)
A2: Top: one client by its year on the platform. Bottom: all clients by calendar year. credits refund part of our fees if the community saving falls short.
A4: Income line | B4: Who pays | C4: Year 1 | D4: Year 2 | E4: Year 3 | F4: Year 4 | G4: Year 5
A5: One client (by client's year). Fixed fees are the same for every client; usage fees scale with client size.
A6: Set-up fee (split into Year 1 and Year 2 instalments) | B6: Developer | C6: =Assumptions!$B$60 -> 20000 | D6: =Assumptions!$B$61 -> 30000 | E6: =0 -> 0 | F6: =0 -> 0 | G6: =0 -> 0
